Workbook

Sheet Reporte_Proyecto
A1: RESUMEN DE COBRANZAS
A4: Proyecto | B4: Precio Venta | C4: Cobrado | D4: Por Cobrar | E4: Vencido | F4: Tasa Morosidad | G4: Cantidad de Clientes Morosos | H4: Días de Atraso Promedio
A5: Beyond | B5: 21736300 | C5: 4849364.2 | D5: 8479306.6 | E5: 8403829.2 | F5: 0.38662648 | G5: 31 | H5: 134 | I5: =IF(ROUND(B5,0)=ROUND(C5+D5+E5,0),"OK","REVISAR")
A6: Prada | B6: 26220000 | C6: 23425730 | D6: 34989.8 | E6: 2759280 | F6: 0.1052357 | G6: 12 | H6: 74 | I6: =IF(ROUND(B6,0)=ROUND(C6+D6+E6,0),"OK","REVISAR")
A7: Venecia | B7: 8984700 | C7: 4670086.7 | D7: 2410647.4 | E7: 1903965.9 | F7: 0.21191202 | G7: 10 | H7: 43 | I7: =IF(ROUND(B7,0)=ROUND(C7+D7+E7,0),"OK","REVISAR")
A8: TOTAL | B8: 56941000 | C8: 32945181 | D8: 10924944 | E8: 13067075 | F8: 0.22948447 | G8: 53 | H8: 61 | I8: =IF(ROUND(B8,0)=ROUND(C8+D8+E8,0),"OK","REVISAR")

Sheet Reporte_General
A1: REPORTE DE COBRANZAS
C4: DEUDA TOTAL | G4: CLIENTES CON DEUDA
C5: 13067075 | G5: 53
A7: PRADA | F7: DEUDA TOTAL | H7: 2759280 | J7: CLIENTE | L7: 12
A8: Rank | B8: Cliente | F8: Unidad | G8: Financiamiento | H8: Precio Venta | I8: Monto Cobrado | J8: Monto Deuda | L8: Tasa de Morosidad | M8: Días de atraso
A9: 1 | B9: katherine Neyra Alor Neyra | F9: Dpto 405, Estc E 35 - D 27 | G9: Crédito Hipotecario | H9: 535000 | I9: 3000 | J9: 532000 | L9: 0.99439252 | M9: 93
A10: 2 | B10: RODRIGO SANDRO CARDENAS BULLON | F10: Dpto 402, Estc E 46 - D 35 | G10: Ahorro | H10: 512000 | I10: 36200 | J10: 475800 | L10: 0.92929688 | M10: 6
A11: 3 | B11: STEPHANIE LIZETH AQUINO HERRERA | F11: Dpto 1005 | G11: Crédito Hipotecario | H11: 480000 | I11: 24000 | J11: 456000 | L11: 0.95 | M11: 77
A12: 4 | B12: Sussan Yassmine Rubin Domínguez | F12: Dpto 805 | G12: Ahorro | H12: 470500 | I12: 42000 | J12: 428500 | L12: 0.91073326 | M12: 214
A13: 5 | B13: Marita Angeles Milla | F13: Dpto 1004 | G13: Ahorro | H13: 417700 | I13: 23770 | J13: 393930 | L13: 0.94309313 | M13: 46
A14: 6 | B14: PATROCINIO HUAMANI CUEVAS | F14: Dpto 503 | G14: Crédito Directo | H14: 660000 | I14: 500000 | J14: 160000 | L14: 0.24242424 | M14: 184
A15: 7 | B15: Gisella Isabel Martinez Andrade | F15: Dpto 304, Estc E 27 - D 21 | G15: Crédito Hipotecario | H15: 486500 | I15: 378650 | J15: 107850 | L15: 0.22168551 | M15: 58
A16: 8 | B16: PATROCINIO HUAMANI CUEVAS | F16: Estc E 17 - D 12 | G16: Crédito Directo | H16: 52500 | I16: 5000 | J16: 47500 | L16: 0.9047619 | M16: 30
A17: 9 | B17: Lizet Lopez Paucar | F17: Estc E 22 | G17: Crédito Directo | H17: 47500 | I17: 3000 | J17: 44500 | L17: 0.93684211 | M17: 38
A18: 10 | B18: Elmo Calatayud Chumbes | F18: Estc E 13 - D 10 | G18: Crédito Directo | H18: 57800 | I18: 20000 | J18: 37800 | L18: 0.65397924 | M18: 31
A19: 11 | B19: Luis Alberto Ovalle Huamanguilla | F19: Estc E 37 - D 28 | G19: Crédito Directo | H19: 52000 | I19: 17000 | J19: 35000 | L19: 0.67307692 | M19: 61
A20: 12 | B20: Karina Cabanillas Correa | F20: Estc E 09 - D 06 | G20: Crédito Directo | H20: 52000 | I20: 31600 | J20: 20400 | L20: 0.39230769 | M20: 92
A21: 13 | B21: Gersom Juver Gonzalez Alfaro | F21: Estc E 25 - D 19 | G21: Crédito Directo | H21: 60400 | I21: 20400 | J21: 20000 | L21: 0.33112583 | M21: 0
A24: BEYOND | F24: DEUDA TOTAL | H24: 8403829.2 | J24: CLIENTE | L24: 31
A25: Rank | B25: Cliente | F25: Unidad | G25: Financiamiento | H25: Precio Venta | I25: Monto Cobrado | J25: Monto Deuda | L25: Tasa de Morosidad | M25: Días de atraso
A26: 1 | B26: RONALD ANTONIO TICONA ARONES | F26: Dpto 703, Dpto 704 | G26: Crédito Hipotecario | H26: 942700 | I26: 94270 | J26: 848430 | L26: 0.9 | M26: 123
A27: 2 | B27: Tania Jackeline Valladares Timana | F27: Dpto 1001 | G27: Ahorro | H27: 518500 | I27: 39725 | J27: 478775 | L27: 0.92338476 | M27: 242
A28: 3 | B28: Jimmy Luis Andrade Morveli | F28: Dpto 601 | G28: Crédito Hipotecario | H28: 470000 | I28: 3000 | J28: 467000 | L28: 0.99361702 | M28: 199
A29: 4 | B29: Tania Milagros Cotrina Vara | F29: Dpto 205 | G29: Ahorro | H29: 577000 | I29: 120000 | J29: 457000 | L29: 0.79202773 | M29: 61
A30: 5 | B30: Leidy Lucero Espíritu Zabarburu | F30: Dpto 303 | G30: Ahorro | H30: 458000 | I30: 22900 | J30: 435100 | L30: 0.95 | M30: 31
A31: 6 | B31: Francesca Giuliana Ramos Ortiz | F31: Dpto 501, Estc E 14 - D 12 | G31: Ahorro | H31: 524500 | I31: 104900 | J31: 419600 | L31: 0.8 | M31: 61
A32: 7 | B32: Dolores Lissett Castillo Diaz | F32: Dpto 701, Estc E 17 | G32: Ahorro | H32: 521800 | I32: 104360 | J32: 417440 | L32: 0.8 | M32: 67
A33: 8 | B33: Juana Mercedes Moran Peralta | F33: Dpto 404 | G33: Ahorro | H33: 460000 | I33: 46000 | J33: 414000 | L33: 0.9 | M33: 13
A34: 9 | B34: Ronald José Claudio Ramírez | F34: Dpto 504, Estc E 07 | G34: Ahorro | H34: 510000 | I34: 102000 | J34: 408000 | L34: 0.8 | M34: 0
A35: 10 | B35: Jhoully Kattherine Moreno Saavedra | F35: Dpto 204 | G35: Crédito Hipotecario | H35: 450000 | I35: 45000 | J35: 405000 | L35: 0.9 | M35: 92
A36: 11 | B36: ERICK RAUL BEDOYA BACA | F36: Dpto 503 | G36: Crédito Hipotecario | H36: 470000 | I36: 70500 | J36: 399500 | L36: 0.85 | M36: 183
A37: 12 | B37: Mayra Andrea Montenegro Gomez | F37: Dpto 605 | G37: Crédito Hipotecario | H37: 495000 | I37: 99000 | J37: 396000 | L37: 0.8 | M37: 61
... A61: 36 | B61: Elizabeth Bertha Fierro Cancho | F61: Estc E 26 - D 17 | G61: Crédito Directo | H61: 51000 | I61: 19000 | J61: 3000 | L61: 0.058823529 | M61: 0
A64: VENECIA | F64: DEUDA TOTAL | H64: 1903965.9 | J64: CLIENTE | L64: 10
A65: Rank | B65: Cliente | F65: Unidad | G65: Financiamiento | H65: Precio Venta | I65: Monto Cobrado | J65: Monto Deuda | L65: Tasa de Morosidad | M65: Días de atraso
A66: 1 | B66: Ubaldo Yovera Puruguay | F66: Dpto 402 | G66: Ahorro | H66: 623000 | I66: 10000 | J66: 613000 | L66: 0.98394864 | M66: 36
A67: 2 | B67: Irma Paulina Palomino Huaman | F67: Dpto 701 | G67: Ahorro | H67: 561000 | I67: 21900 | J67: 539100 | L67: 0.96096257 | M67: 30
A68: 3 | B68: Mariela Gabriela Zapata Santivañez | F68: Dpto 205, Estc E 20 | G68: Crédito Hipotecario | H68: 432800 | I68: 86560 | J68: 346240 | L68: 0.8 | M68: 31
A69: 4 | B69: Rocio Chuquimango Valencia | F69: Dpto 602, Estc E 24 - D 5 | G69: Crédito Directo | H69: 624000 | I69: 79800 | J69: 180200.01 | L69: 0.28878207 | M69: 46
A70: 5 | B70: Carlos La Cruz Crespo | F70: Dpto 204, Estc E 14 - D 4 | G70: Crédito Directo | H70: 485800 | I70: 387320 | J70: 98480 | L70: 0.20271717 | M70: 0
A71: 6 | B71: Patricia Salazar Aparcana | F71: Dpto 302 | G71: Ahorro | H71: 600000 | I71: 20000 | J71: 40000 | L71: 0.066666667 | M71: 62
A72: 7 | B72: Norma Luz Tello Contreras | F72: Dpto 601, Estc E 11 | G72: Crédito Directo | H72: 595800 | I72: 285800 | J72: 36000 | L72: 0.060422961 | M72: 77
A73: 8 | B73: Luis Miguel Montero Monteza | F73: Dpto 104 | G73: Ahorro | H73: 497000 | I73: 25100 | J73: 24600 | L73: 0.049496982 | M73: 0
A74: 9 | B74: Petronila Tisnado Meneses | F74: Dpto 405, Estc E 29 - D 13 | G74: Crédito Directo | H74: 435000 | I74: 377800 | J74: 14300 | L74: 0.032873563 | M74: 0
A75: 10 | B75: Patricia Salazar Aparcana | F75: Estc E 25 - D 8 | G75: Crédito Directo | H75: 50800 | I75: 3000 | J75: 10105.88 | L75: 0.19893465 | M75: 36
A76: 11 | B76: Evelyn Arciela Leon Estela | F76: Estc E 04 | G76: Crédito Directo | H76: 48500 | I76: 40740 | J76: 1940 | L76: 0.04 | M76: 0

Sheet Reporte_Cliente
A1: REPORTE DE COBRANZAS POR CLIENTE
A4: Rank | B4: Cliente | E4: Proyecto | G4: Tipo de Financiamiento | I4: Monto Vendido | K4: Deuda | M4: Días Atrasados | N4: Unidad Inmobiliaria | O4: Tasa de Morosidad
A5: 1 | B5: RONALD ANTONIO TICONA ARONES | E5: Beyond | G5: Crédito Hipotecario | I5: 942700 | K5: 848430 | M5: 123 | N5: Dpto 703, Dpto 704 | O5: 0.9
A6: 2 | B6: Ubaldo Yovera Puruguay | E6: Venecia | G6: Ahorro | I6: 623000 | K6: 613000 | M6: 36 | N6: Dpto 402 | O6: 0.98394864
A7: 3 | B7: Irma Paulina Palomino Huaman | E7: Venecia | G7: Ahorro | I7: 561000 | K7: 539100 | M7: 30 | N7: Dpto 701 | O7: 0.96096257
A8: 4 | B8: katherine Neyra Alor Neyra | E8: Prada | G8: Crédito Hipotecario | I8: 535000 | K8: 532000 | M8: 93 | N8: Dpto 405, Estc E 35 - D 27 | O8: 0.99439252
A9: 5 | B9: Tania Jackeline Valladares Timana | E9: Beyond | G9: Ahorro | I9: 518500 | K9: 478775 | M9: 242 | N9: Dpto 1001 | O9: 0.92338476
A10: 6 | B10: RODRIGO SANDRO CARDENAS BULLON | E10: Prada | G10: Ahorro | I10: 512000 | K10: 475800 | M10: 6 | N10: Dpto 402, Estc E 46 - D 35 | O10: 0.92929688
A11: 7 | B11: Jimmy Luis Andrade Morveli | E11: Beyond | G11: Crédito Hipotecario | I11: 470000 | K11: 467000 | M11: 199 | N11: Dpto 601 | O11: 0.99361702
A12: 8 | B12: Tania Milagros Cotrina Vara | E12: Beyond | G12: Ahorro | I12: 577000 | K12: 457000 | M12: 61 | N12: Dpto 205 | O12: 0.79202773
A13: 9 | B13: STEPHANIE LIZETH AQUINO HERRERA | E13: Prada | G13: Crédito Hipotecario | I13: 480000 | K13: 456000 | M13: 77 | N13: Dpto 1005 | O13: 0.95
A14: 10 | B14: Leidy Lucero Espíritu Zabarburu | E14: Beyond | G14: Ahorro | I14: 458000 | K14: 435100 | M14: 31 | N14: Dpto 303 | O14: 0.95
A15: 11 | B15: Sussan Yassmine Rubin Domínguez | E15: Prada | G15: Ahorro | I15: 470500 | K15: 428500 | M15: 214 | N15: Dpto 805 | O15: 0.91073326
A16: 12 | B16: Francesca Giuliana Ramos Ortiz | E16: Beyond | G16: Ahorro | I16: 524500 | K16: 419600 | M16: 61 | N16: Dpto 501, Estc E 14 - D 12 | O16: 0.8
... A64: 60 | B64: Evelyn Arciela Leon Estela | E64: Venecia | G64: Crédito Directo | I64: 48500 | K64: 1940 | M64: 0 | N64: Estc E 04 | O64: 0.04

Sheet Base_Cobranzas
A1: Proyecto | B1: Etapa | C1: Tipo_Construccion_1 | D1: Nombre_Tipo_Construccion_1 | E1: TipoInmueble_1 | F1: NroInmueble_1 | G1: PrecioLista_1 | H1: PrecioVenta_1 | I1: Tipo_Construccion_2 | J1: Nombre_Tipo_Construccion_2 | K1: TipoInmueble_2 | L1: NroInmueble_2 | M1: PrecioLista_2 | N1: PrecioVenta_2 | O1: Tipo_Construccion_3 | P1: Nombre_Tipo_Construccion_3 | Q1: TipoInmueble_3 | R1: NroInmueble_3 | S1: PrecioLista_3 | T1: PrecioVenta_3 | U1: Tipo_Construccion_4 | V1: Nombre_Tipo_Construccion_4 | W1: TipoInmueble_4 | X1: NroInmueble_4 | Y1: PrecioLista_4 | Z1: PrecioVenta_4 | AA1: Nombres_Titular | AB1: NroDocumento | AC1: Direccion | AD1: TelefonoCasa | AE1: TelefonoCelular | AF1: CorreoElectronico | AG1: Provincia | AH1: Distrito | AI1: Fecha_Programada | AJ1: FechaPago | AK1: Tipo_Cuota | AL1: Nro_Cuota | AM1: Capital | AN1: Intereses | AO1: GastosAdministrativos | AP1: Monto_Cuota | AQ1: Monto_Cuota_Pagado | AR1: SaldoPorPagarCuota | AS1: MontoMora | AT1: TipoFinanciamiento | AU1: Entidad_Financiera | AV1: Nro_Cuenta | AW1: Medio_Pago | AX1: Nro_Documento | AY1: Nro_Operacion | AZ1: Verificado | BA1: OrigenFondo | BB1: TipoCambio | BC1: Estado | BD1: Estado_Letra | BE1: Ubicación_Letra | BF1: Casuistica_Cuota | BG1: Accio_Cuota | BH1: FechaPromesa | BI1: ValorCompromiso | BJ1: Porcentaje | BK1: Comentario_Cuota | BL1: Fecha_Modificiacion_Seguimiento | BM1: Usuario_Modificiacion_Seguimiento | BN1: Doc_Adjunto | BO1: FechaOperacionComercial | BP1: Asesor_Comercial | BQ1: Asesor_Banco | BR1: Correlativo | BS1: Fecha_Registro_Pago_Cargado | BT1: ComisionPago | BU1: IdCotizacion | BV1: Doc_Contable | BW1: Monto_EstadoCuenta | BX1: Archivo_Origen | BY1: Anio_Descarga | BZ1: Fecha_Inicio_Reporte | CA1: Fecha_Fin_Reporte
A2: RESIDENCIAL PRADA | B2: Etapa 1 | C2: Edificio | D2: A | E2: Estacionamiento | F2: E 14 - D 11 | G2: 56300 | H2: 56300 | AA2: Ayleen Katia Messarina Rios | AB2: 70512701 | AC2: Departamento 101 Urbanización Santa Rosa de Surco etapa 2 Mz D Lt 23 | AD2: 978722675 | AE2: 978722675 | AF2: ayleen30mr@gmail.com | AG2: LIMA | AH2: SANTIAGO DE SURCO | AI2: 45628 | AJ2: 45628 | AK2: SEPARACION | AL2: 1 | AM2: 3000 | AN2: 0 | AO2: 0 | AP2: 3000 | AQ2: 3000 | AR2: 0 | AS2: 0 | AT2: Crédito Directo | AU2: Scotiabank Perú | AV2: 000-2768484 | AW2: TRANSFERENCIA BANCARIA | AY2: 000001100000012 | AZ2: Si | BB2: 4 | BC2: CANCELADO | BN2: Si | BO2: 45748.63 | BP2: Magaly Guevara Perez | BR2: 56 | BS2: 28/06/2026 21:22 | BT2: 0 | BX2: Cobranzas_2024.csv | BY2: 2024 | BZ2: 01/01/2024 | CA2: 30/09/2031
A3: RESIDENCIAL PRADA | B3: Etapa 1 | C3: Edificio | D3: A | E3: Estacionamiento | F3: E 14 - D 11 | G3: 56300 | H3: 56300 | AA3: Ayleen Katia Messarina Rios | AB3: 70512701 | AC3: Departamento 101 Urbanización Santa Rosa de Surco etapa 2 Mz D Lt 23 | AD3: 978722675 | AE3: 978722675 | AF3: ayleen30mr@gmail.com | AG3: LIMA | AH3: SANTIAGO DE SURCO | AI3: 45628 | AJ3: 45628 | AK3: CUOTA INICIAL | AL3: 1 | AM3: 7000 | AN3: 0 | AO3: 0 | AP3: 7000 | AQ3: 7000 | AR3: 0 | AS3: 0 | AT3: Crédito Directo | AU3: Scotiabank Perú | AV3: 000-2768484 | AW3: TRANSFERENCIA BANCARIA | AY3: 000001100000012 | AZ3: Si | BB3: 4 | BC3: CANCELADO | BN3: Si | BO3: 45748.63 | BP3: Magaly Guevara Perez | BR3: 56 | BS3: 28/06/2026 21:22 | BT3: 0 | BX3: Cobranzas_2024.csv | BY3: 2024 | BZ3: 01/01/2024 | CA3: 30/09/2031
A4: RESIDENCIAL PRADA | B4: Etapa 1 | C4: Edificio | D4: A | E4: Departamento | F4: 302 | G4: 435500 | H4: 435500 | AA4: Cristhiam Ortiz Angeles | AB4: 45110882 | AC4: Av. Olavegoya 1879 departamento 301 | AD4: 992532732 | AE4: 992532732 | AF4: Cristhian4520@gmail.com | AG4: LIMA | AH4: JESUS MARIA | AI4: 45473 | AJ4: 45473 | AK4: SEPARACION | AL4: 1 | AM4: 3000 | AN4: 0 | AO4: 0 | AP4: 3000 | AQ4: 3000 | AR4: 0 | AS4: 0 | AT4: Crédito Hipotecario | AU4: Scotiabank Perú | AV4: 000-2768484 | AW4: TRANSFERENCIA BANCARIA | AX4: 45110882 | AY4: 01226077 | AZ4: No | BA4: NO PRECISA | BB4: 4 | BC4: CANCELADO | BN4: Si | BO4: 45499.613 | BP4: Kenny Salazar S | BR4: 34 | BS4: 02/06/2026 15:34 | BT4: 0 | BX4: Cobranzas_2024.csv | BY4: 2024 | BZ4: 01/01/2024 | CA4: 30/09/2031
A5: RESIDENCIAL PRADA | B5: Etapa 1 | C5: Edificio | D5: A | E5: Departamento | F5: 302 | G5: 435500 | H5: 435500 | AA5: Cristhiam Ortiz Angeles | AB5: 45110882 | AC5: Av. Olavegoya 1879 departamento 301 | AD5: 992532732 | AE5: 992532732 | AF5: Cristhian4520@gmail.com | AG5: LIMA | AH5: JESUS MARIA | AI5: 45499 | AJ5: 45499 | AK5: CUOTA INICIAL | AL5: 1 | AM5: 20000 | AN5: 0 | AO5: 0 | AP5: 20000 | AQ5: 20000 | AR5: 0 | AS5: 0 | AT5: Crédito Hipotecario | AU5: Scotiabank Perú | AV5: 000-2768484 | AW5: CHEQUE DE GERENCIA | AX5: 45110882 | AY5: 162515191002194000000022290 | AZ5: Si | BA5: NO PRECISA | BB5: 4 | BC5: CANCELADO | BN5: Si | BO5: 45499.613 | BP5: Kenny Salazar S | BR5: 34 | BS5: 04/06/2026 14:01 | BT5: 0 | BX5: Cobranzas_2024.csv | BY5: 2024 | BZ5: 01/01/2024 | CA5: 30/09/2031
A6: RESIDENCIAL PRADA | B6: Etapa 1 | C6: Edificio | D6: A | E6: Departamento | F6: 302 | G6: 435500 | H6: 435500 | AA6: Cristhiam Ortiz Angeles | AB6: 45110882 | AC6: Av. Olavegoya 1879 departamento 301 | AD6: 992532732 | AE6: 992532732 | AF6: Cristhian4520@gmail.com | AG6: LIMA | AH6: JESUS MARIA | AI6: 45534 | AJ6: 45538 | AK6: CUOTA INICIAL | AL6: 2 | AM6: 8775 | AN6: 0 | AO6: 0 | AP6: 8775 | AQ6: 8775 | AR6: 0 | AS6: 0 | AT6: Crédito Hipotecario | AU6: Scotiabank Perú | AV6: 000-2768484 | AW6: TRANSFERENCIA BANCARIA | AY6: U26966 | AZ6: No | BB6: 4 | BC6: CANCELADO | BN6: Si | BO6: 45499.613 | BP6: Kenny Salazar S | BR6: 34 | BS6: 07/07/2026 08:47 | BT6: 0 | BX6: Cobranzas_2024.csv | BY6: 2024 | BZ6: 01/01/2024 | CA6: 30/09/2031
A7: RESIDENCIAL PRADA | B7: Etapa 1 | C7: Edificio | D7: A | E7: Departamento | F7: 302 | G7: 435500 | H7: 435500 | AA7: Cristhiam Ortiz Angeles | AB7: 45110882 | AC7: Av. Olavegoya 1879 departamento 301 | AD7: 992532732 | AE7: 992532732 | AF7: Cristhian4520@gmail.com | AG7: LIMA | AH7: JESUS MARIA | AI7: 45565 | AJ7: 45538 | AK7: CUOTA INICIAL | AL7: 3 | AM7: 0 | AN7: 0 | AO7: 0 | AP7: 11775 | AQ7: 1225 | AR7: 0 | AS7: 0 | AT7: Crédito Hipotecario | AU7: Scotiabank Perú | AV7: 000-2768484 | AW7: TRANSFERENCIA BANCARIA | AY7: U26966 | AZ7: No | BB7: 4 | BC7: CANCELADO | BN7: Si | BO7: 45499.613 | BP7: Kenny Salazar S | BR7: 34 | BS7: 07/07/2026 08:47 | BT7: 0 | BX7: Cobranzas_2024.csv | BY7: 2024 | BZ7: 01/01/2024 | CA7: 30/09/2031
A8: RESIDENCIAL PRADA | B8: Etapa 1 | C8: Edificio | D8: A | E8: Departamento | F8: 302 | G8: 435500 | H8: 435500 | AA8: Cristhiam Ortiz Angeles | AB8: 45110882 | AC8: Av. Olavegoya 1879 departamento 301 | AD8: 992532732 | AE8: 992532732 | AF8: Cristhian4520@gmail.com | AG8: LIMA | AH8: JESUS MARIA | AI8: 45565 | AJ8: 45569 | AK8: CUOTA INICIAL | AL8: 3 | AM8: 0 | AN8: 0 | AO8: 0 | AP8: 0 | AQ8: 10000 | AR8: 0 | AS8: 0 | AT8: Crédito Hipotecario | AU8: Scotiabank Perú | AV8: 000-2768484 | AW8: TRANSFERENCIA BANCARIA | AY8: U27618 | AZ8: No | BB8: 4 | BC8: CANCELADO | BN8: Si | BO8: 45499.613 | BP8: Kenny Salazar S | BR8: 34 | BS8: 07/07/2026 08:52 | BT8: 0 | BX8: Cobranzas_2024.csv | BY8: 2024 | BZ8: 01/01/2024 | CA8: 30/09/2031
A9: RESIDENCIAL PRADA | B9: Etapa 1 | C9: Edificio | D9: A | E9: Departamento | F9: 302 | G9: 435500 | H9: 435500 | AA9: Cristhiam Ortiz Angeles | AB9: 45110882 | AC9: Av. Olavegoya 1879 departamento 301 | AD9: 992532732 | AE9: 992532732 | AF9: Cristhian4520@gmail.com | AG9: LIMA | AH9: JESUS MARIA | AI9: 45565 | AJ9: 45693 | AK9: CUOTA INICIAL | AL9: 3 | AM9: 11775 | AN9: 0 | AO9: 0 | AP9: 0 | AQ9: 550 | AR9: 0 | AS9: 0 | AT9: Crédito Hipotecario | AU9: Scotiabank Perú | AV9: 000-2768484 | AW9: TRANSFERENCIA BANCARIA | AY9: U28731 | AZ9: No | BB9: 4 | BC9: CANCELADO | BN9: Si | BO9: 45499.613 | BP9: Kenny Salazar S | BR9: 34 | BS9: 07/07/2026 08:56 | BT9: 0 | BX9: Cobranzas_2024.csv | BY9: 2024 | BZ9: 01/01/2024 | CA9: 30/09/2031
A10: RESIDENCIAL PRADA | B10: Etapa 1 | C10: Edificio | D10: A | E10: Departamento | F10: 302 | G10: 435500 | H10: 435500 | AA10: Cristhiam Ortiz Angeles | AB10: 45110882 | AC10: Av. Olavegoya 1879 departamento 301 | AD10: 992532732 | AE10: 992532732 | AF10: Cristhian4520@gmail.com | AG10: LIMA | AH10: JESUS MARIA | AI10: 45656 | AJ10: 45693 | AK10: CUOTA INICIAL | AL10: 4 | AM10: 21000 | AN10: 0 | AO10: 0 | AP10: 21000 | AQ10: 21000 | AR10: 0 | AS10: 0 | AT10: Crédito Hipotecario | AU10: Scotiabank Perú | AV10: 000-2768484 | AW10: TRANSFERENCIA BANCARIA | AY10: U28731 | AZ10: No | BB10: 4 | BC10: CANCELADO | BN10: Si | BO10: 45499.613 | BP10: Kenny Salazar S | BR10: 34 | BS10: 07/07/2026 08:56 | BT10: 0 | BX10: Cobranzas_2024.csv | BY10: 2024 | BZ10: 01/01/2024 | CA10: 30/09/2031
A11: RESIDENCIAL BEYOND | B11: Etapa 1 | C11: Edificio | D11: A | E11: Departamento | F11: 505 | G11: 532100 | H11: 500000 | I11: Edificio | J11: A | K11: Estacionamiento | L11: E 05 | M11: 45600 | N11: 45600 | O11: Edificio | P11: A | Q11: Depósito | R11: D 05 | S11: 15900 | T11: 15900 | AA11: Dante Enrique Segura Florian | AB11: 45587286 | AC11: 1845 San Andres Dr Pitsburg CA 94565 - San Francisco | AD11: 0 | AE11: +15103330517 | AF11: d.segura@uaa.edu | AI11: 45368 | AJ11: 45368 | AK11: SEPARACION | AL11: 1 | AM11: 3000 | AN11: 0 | AO11: 0 | AP11: 3000 | AQ11: 3000 | AR11: 0 | AS11: 0 | AT11: Crédito Directo | AU11: Banco de Credito del Perú | AV11: 194-7325779-0-65 | AW11: TRANSFERENCIA BANCARIA | AY11: 7844655595634 | AZ11: No | BB11: 4 | BC11: CANCELADO | BN11: Si | BO11: 45386.403 | BP11: Carla Michue M | BR11: 35 | BS11: 25/05/2026 17:28 | BT11: 0 | BX11: Cobranzas_2024.csv | BY11: 2024 | BZ11: 01/01/2024 | CA11: 30/09/2031
A12: RESIDENCIAL PRADA | B12: Etapa 1 | C12: Edificio | D12: A | E12: Departamento | F12: 703 | G12: 654000 | H12: 654000 | I12: Edificio | J12: A | K12: Estacionamiento | L12: E 06 - D 04 | M12: 57500 | N12: 57500 | AA12: David Edgar Valencia Cordova | AB12: 41844906 | AC12: P. Joven Año Nuevo Jr. Montero Rosas 860 | AD12: 991846561 | AE12: 991846561 | AF12: davico29@gmail.com | AG12: LIMA | AH12: COMAS | AI12: 45655 | AJ12: 45655 | AK12: SEPARACION | AL12: 1 | AM12: 3000 | AN12: 0 | AO12: 0 | AP12: 3000 | AQ12: 3000 | AR12: 0 | AS12: 0 | AT12: Crédito Hipotecario | AU12: Scotiabank Perú | AV12: 000-2768484 | AW12: TRANSFERENCIA BANCARIA | AX12: 41844906 | AY12: 00000082000000000 | AZ12: No | BA12: NO PRECISA | BB12: 4 | BC12: CANCELADO | BN12: Si | BO12: 45687.617 | BP12: Carla Michue M | BR12: 38 | BS12: 02/06/2026 18:05 | BT12: 0 | BX12: Cobranzas_2024.csv | BY12: 2024 | BZ12: 01/01/2024 | CA12: 30/09/2031
A13: RESIDENCIAL PRADA | B13: Etapa 1 | C13: Edificio | D13: A | E13: Departamento | F13: 205 | G13: 490000 | H13: 490000 | AA13: Elizabeth Rocio Urbina Ñañez | AB13: 71404863 | AC13: Av. Arequipa 2651 | AE13: 943921218 | AF13: elizabethurbina9624@gmail.com | AG13: LIMA | AH13: LINCE | AI13: 45620 | AJ13: 45620 | AK13: SEPARACION | AL13: 1 | AM13: 2000 | AN13: 0 | AO13: 0 | AP13: 2000 | AQ13: 2000 | AR13: 0 | AS13: 0 | AT13: Crédito Hipotecario | AU13: Scotiabank Perú | AV13: 000-2768484 | AW13: TRANSFERENCIA BANCARIA | AY13: FD893378 | AZ13: No | BB13: 4 | BC13: CANCELADO | BN13: Si | BO13: 45750.733 | BP13: Carla Michue M | BR13: 5 | BS13: 29/06/2026 21:44 | BT13: 0 | BX13: Cobranzas_2024.csv | BY13: 2024 | BZ13: 01/01/2024 | CA13: 30/09/2031
A14: RESIDENCIAL PRADA | B14: Etapa 1 | C14: Edificio | D14: A | E14: Departamento | F14: 101 | G14: 637000 | H14: 637000 | AA14: Elmo Calatayud Chumbes | AB14: 15580131 | AC14: Avenida Tomas Valles 1530 Block 14 departamento 204 | AD14: 955600933 | AE14: 955600933 | AF14: ec.calatayud@gmail.com | AG14: LIMA | AH14: LOS OLIVOS | AI14: 45595 | AJ14: 45595 | AK14: SEPARACION | AL14: 1 | AM14: 3000 | AN14: 0 | AO14: 0 | AP14: 3000 | AQ14: 3000 | AR14: 0 | AS14: 0 | AT14: Crédito Hipotecario | AU14: Scotiabank Perú | AV14: 000-2768484 | AW14: TRANSFERENCIA BANCARIA | AY14: 04797111 | AZ14: No | BB14: 4 | BC14: CANCELADO | BN14: Si | BO14: 45626.65 | BP14: Carla Michue M | BR14: 25 | BS14: 26/06/2026 14:52 | BT14: 0 | BX14: Cobranzas_2024.csv | BY14: 2024 | BZ14: 01/01/2024 | CA14: 30/09/2031
A15: RESIDENCIAL PRADA | B15: Etapa 1 | C15: Edificio | D15: A | E15: Departamento | F15: 101 | G15: 637000 | H15: 637000 | AA15: Elmo Calatayud Chumbes | AB15: 15580131 | AC15: Avenida Tomas Valles 1530 Block 14 departamento 204 | AD15: 955600933 | AE15: 955600933 | AF15: ec.calatayud@gmail.com | AG15: LIMA | AH15: LOS OLIVOS | AI15: 45626 | AJ15: 45626 | AK15: CUOTA INICIAL | AL15: 1 | AM15: 27000 | AN15: 0 | AO15: 0 | AP15: 27000 | AQ15: 27000 | AR15: 0 | AS15: 0 | AT15: Crédito Hipotecario | AU15: Scotiabank Perú | AV15: 000-2768484 | AW15: TRANSFERENCIA BANCARIA | AY15: 78446555266223 | AZ15: No | BB15: 4 | BC15: CANCELADO | BN15: Si | BO15: 45626.65 | BP15: Carla Michue M | BR15: 25 | BS15: 26/06/2026 14:53 | BT15: 0 | BX15: Cobranzas_2024.csv | BY15: 2024 | BZ15: 01/01/2024 | CA15: 30/09/2031
A16: RESIDENCIAL PRADA | B16: Etapa 1 | C16: Edificio | D16: A | E16: Departamento | F16: 101 | G16: 637000 | H16: 637000 | AA16: Elmo Calatayud Chumbes | AB16: 15580131 | AC16: Avenida Tomas Valles 1530 Block 14 departamento 204 | AD16: 955600933 | AE16: 955600933 | AF16: ec.calatayud@gmail.com | AG16: LIMA | AH16: LOS OLIVOS | AI16: 45626 | AJ16: 45626 | AK16: CUOTA INICIAL | AL16: 2 | AM16: 3000 | AN16: 0 | AO16: 0 | AP16: 3000 | AQ16: 3000 | AR16: 0 | AS16: 0 | AT16: Crédito Hipotecario | AU16: Scotiabank Perú | AV16: 000-2768484 | AW16: TRANSFERENCIA BANCARIA | AY16: 7844655544194 | AZ16: No | BB16: 4 | BC16: CANCELADO | BN16: Si | BO16: 45626.65 | BP16: Carla Michue M | BR16: 25 | BS16: 26/06/2026 14:53 | BT16: 0 | BX16: Cobranzas_2024.csv | BY16: 2024 | BZ16: 01/01/2024 | CA16: 30/09/2031
A17: RESIDENCIAL PRADA | B17: Etapa 1 | C17: Edificio | D17: A | E17: Departamento | F17: 101 | G17: 637000 | H17: 637000 | AA17: Elmo Calatayud Chumbes | AB17: 15580131 | AC17: Avenida Tomas Valles 1530 Block 14 departamento 204 | AD17: 955600933 | AE17: 955600933 | AF17: ec.calatayud@gmail.com | AG17: LIMA | AH17: LOS OLIVOS | AI17: 45656 | AJ17: 45656 | AK17: CUOTA INICIAL | AL17: 3 | AM17: 0 | AN17: 0 | AO17: 0 | AP17: 30700 | AQ17: 30000 | AR17: 0 | AS17: 0 | AT17: Crédito Hipotecario | AU17: Scotiabank Perú | AV17: 000-2768484 | AW17: TRANSFERENCIA BANCARIA | AY17: 7844655610530 | AZ17: No | BB17: 4 | BC17: CANCELADO | BN17: Si | BO17: 45626.65 | BP17: Carla Michue M | BR17: 25 | BS17: 26/06/2026 14:55 | BT17: 0 | BX17: Cobranzas_2024.csv | BY17: 2024 | BZ17: 01/01/2024 | CA17: 30/09/2031
A18: RESIDENCIAL PRADA | B18: Etapa 1 | C18: Edificio | D18: A | E18: Departamento | F18: 101 | G18: 637000 | H18: 637000 | AA18: Elmo Calatayud Chumbes | AB18: 15580131 | AC18: Avenida Tomas Valles 1530 Block 14 departamento 204 | AD18: 955600933 | AE18: 955600933 | AF18: ec.calatayud@gmail.com | AG18: LIMA | AH18: LOS OLIVOS | AI18: 45656 | AJ18: 45656 | AK18: CUOTA INICIAL | AL18: 3 | AM18: 30700 | AN18: 0 | AO18: 0 | AP18: 0 | AQ18: 700 | AR18: 0 | AS18: 0 | AT18: Crédito Hipotecario | AU18: Scotiabank Perú | AV18: 000-2768484 | AW18: TRANSFERENCIA BANCARIA | AY18: 7844655610860 | AZ18: No | BB18: 4 | BC18: CANCELADO | BN18: Si | BO18: 45626.65 | BP18: Carla Michue M | BR18: 25 | BS18: 26/06/2026 14:56 | BT18: 0 | BX18: Cobranzas_2024.csv | BY18: 2024 | BZ18: 01/01/2024 | CA18: 30/09/2031
A19: RESIDENCIAL PRADA | B19: Etapa 1 | C19: Edificio | D19: A | E19: Departamento | F19: 203 | G19: 654000 | H19: 654000 | I19: Edificio | J19: A | K19: Estacionamiento | L19: E 12 - D 09 | M19: 56300 | N19: 56300 | AA19: Gilberto Videla Flores | AB19: 06571347 | AC19: Mz D Lt 7 Urb. La Estrella | AE19: 969742622 | AF19: gvidelaf@gmail.com | AG19: LIMA | AH19: LOS OLIVOS | AI19: 45535 | AJ19: 45535 | AK19: SEPARACION | AL19: 1 | AM19: 3000 | AN19: 0 | AO19: 0 | AP19: 3000 | AQ19: 3000 | AR19: 0 | AS19: 0 | AT19: Crédito Directo | AU19: Scotiabank Perú | AV19: 000-2768484 | AW19: POS VISA | AX19: 06571347 | AY19: 0059 | AZ19: No | BA19: NO PRECISA | BB19: 1 | BC19: CANCELADO | BN19: Si | BO19: 45539.381 | BP19: Carla Michue M | BR19: 24 | BS19: 29/05/2026 12:21 | BT19: 0 | BX19: Cobranzas_2024.csv | BY19: 2024 | BZ19: 01/01/2024 | CA19: 30/09/2031
A20: RESIDENCIAL PRADA | B20: Etapa 1 | C20: Edificio | D20: A | E20: Departamento | F20: 203 | G20: 654000 | H20: 654000 | I20: Edificio | J20: A | K20: Estacionamiento | L20: E 12 - D 09 | M20: 56300 | N20: 56300 | AA20: Gilberto Videla Flores | AB20: 06571347 | AC20: Mz D Lt 7 Urb. La Estrella | AE20: 969742622 | AF20: gvidelaf@gmail.com | AG20: LIMA | AH20: LOS OLIVOS | AI20: 45539 | AJ20: 45539 | AK20: CUOTA INICIAL | AL20: 2 | AM20: 281120 | AN20: 0 | AO20: 0 | AP20: 281120 | AQ20: 281120 | AR20: 0 | AS20: 0 | AT20: Crédito Directo | AU20: Scotiabank Perú | AV20: 000-2768484 | AW20: TRANSFERENCIA BANCARIA | AY20: 0953413 | AZ20: No | BB20: 4 | BC20: CANCELADO | BN20: Si | BO20: 45539.381 | BP20: Carla Michue M | BR20: 24 | BS20: 30/06/2026 16:33 | BT20: 0 | BX20: Cobranzas_2024.csv | BY20: 2024 | BZ20: 01/01/2024 | CA20: 30/09/2031
A21: RESIDENCIAL PRADA | B21: Etapa 1 | C21: Edificio | D21: A | E21: Departamento | F21: 203 | G21: 654000 | H21: 654000 | I21: Edificio | J21: A | K21: Estacionamiento | L21: E 12 - D 09 | M21: 56300 | N21: 56300 | AA21: Gilberto Videla Flores | AB21: 06571347 | AC21: Mz D Lt 7 Urb. La Estrella | AE21: 969742622 | AF21: gvidelaf@gmail.com | AG21: LIMA | AH21: LOS OLIVOS | AI21: 45559 | AJ21: 45559 | AK21: SALDO FINANCIAR | AL21: 3 | AM21: 248605 | AN21: 0 | AO21: 0 | AP21: 248605 | AQ21: 248605 | AR21: 0 | AS21: 0 | AT21: Crédito Directo | AU21: Scotiabank Perú | AV21: 000-2768484 | AW21: TRANSFERENCIA BANCARIA | AY21: 0036913 | AZ21: No | BB21: 4 | BC21: CANCELADO | BN21: Si | BO21: 45539.381 | BP21: Carla Michue M | BR21: 24 | BS21: 30/06/2026 16:48 | BT21: 0 | BX21: Cobranzas_2024.csv | BY21: 2024 | BZ21: 01/01/2024 | CA21: 30/09/2031
A22: RESIDENCIAL PRADA | B22: Etapa 1 | C22: Edificio | D22: A | E22: Departamento | F22: 104 | G22: 609100 | H22: 609100 | I22: Edificio | J22: A | K22: Estacionamiento | L22: E 26 - D 20 | M22: 64600 | N22: 64600 | AA22: Gilda Victoria Sampi González | AB22: 43636501 | AC22: Av. Brasil 863 departamento 702-A | AD22: 966422784 | AE22: 966422784 | AF22: victoria.sampi@gmail.com | AG22: LIMA | AH22: JESUS MARIA | AI22: 45494 | AJ22: 45494 | AK22: SEPARACION | AL22: 1 | AM22: 3000 | AN22: 0 | AO22: 0 | AP22: 3000 | AQ22: 3000 | AR22: 0 | AS22: 0 | AT22: Crédito Hipotecario | AU22: Scotiabank Perú | AV22: 000-2768484 | AW22: TRANSFERENCIA BANCARIA | AX22: 43636501 | AY22: 00998929 | AZ22: No | BA22: NO PRECISA | BB22: 4 | BC22: CANCELADO | BN22: Si | BO22: 45537.593 | BP22: Kenny Salazar S | BR22: 32 | BS22: 02/06/2026 14:50 | BT22: 0 | BX22: Cobranzas_2024.csv | BY22: 2024 | BZ22: 01/01/2024 | CA22: 30/09/2031
A23: RESIDENCIAL PRADA | B23: Etapa 1 | C23: Edificio | D23: A | E23: Departamento | F23: 104 | G23: 609100 | H23: 609100 | I23: Edificio | J23: A | K23: Estacionamiento | L23: E 26 - D 20 | M23: 64600 | N23: 64600 | AA23: Gilda Victoria Sampi González | AB23: 43636501 | AC23: Av. Brasil 863 departamento 702-A | AD23: 966422784 | AE23: 966422784 | AF23: victoria.sampi@gmail.com | AG23: LIMA | AH23: JESUS MARIA | AI23: 45537 | AJ23: 45537 | AK23: CUOTA INICIAL | AL23: 1 | AM23: 134740 | AN23: 0 | AO23: 0 | AP23: 134740 | AQ23: 134740 | AR23: 0 | AS23: 0 | AT23: Crédito Hipotecario | AU23: Scotiabank Perú | AV23: 000-2768484 | AW23: TRANSFERENCIA BANCARIA | AX23: 43636501 | AY23: 009107870 | AZ23: No | BA23: NO PRECISA | BB23: 4 | BC23: CANCELADO | BN23: Si | BO23: 45537.593 | BP23: Kenny Salazar S | BR23: 32 | BS23: 04/06/2026 09:52 | BT23: 0 | BX23: Cobranzas_2024.csv | BY23: 2024 | BZ23: 01/01/2024 | CA23: 30/09/2031
A24: RESIDENCIAL PRADA | B24: Etapa 1 | C24: Edificio | D24: A | E24: Departamento | F24: 605 | G24: 501000 | H24: 501000 | I24: Edificio | J24: A | K24: Estacionamiento | L24: E 07 - D 05 | M24: 57300 | N24: 57300 | AA24: Jose Humberto Pehovaz Diez | AB24: 49073756 | AC24: - | AE24: 952256518 | AF24: josehp99@gmail.com | AG24: LIMA | AH24: MAGDALENA DEL MAR | AI24: 45338 | AJ24: 45698 | AK24: SEPARACION | AL24: 1 | AM24: 3000 | AN24: 0 | AO24: 0 | AP24: 3000 | AQ24: 3000 | AR24: 0 | AS24: 0 | AT24: Crédito Hipotecario | AU24: Scotiabank Perú | AV24: 000-2768484 | AW24: TRANSFERENCIA BANCARIA | AX24: 49073756 | AY24: 7844655534521 | AZ24: No | BA24: NO PRECISA | BB24: 1 | BC24: CANCELADO | BN24: Si | BO24: 45709.697 | BP24: Carla Michue M | BR24: 10 | BS24: 29/05/2026 12:21 | BT24: 0 | BX24: Cobranzas_2024.csv | BY24: 2024 | BZ24: 01/01/2024 | CA24: 30/09/2031
A25: RESIDENCIAL PRADA | B25: Etapa 1 | C25: Edificio | D25: A | E25: Departamento | F25: 201 | G25: 622500 | H25: 622500 | AA25: Joseluis Gaspar Zapata Flores | AB25: 46730672 | AC25: Jr. Los Clavles 141 P. J El Progreso 1er Sector | AE25: 948041027 | AF25: jlzapata91@gmail.com | AG25: LIMA | AH25: CARABAYLLO | AI25: 45479 | AJ25: 45479 | AK25: CUOTA INICIAL | AL25: 1 | AM25: 3000 | AN25: 0 | AO25: 0 | AP25: 3000 | AQ25: 3000 | AR25: 0 | AS25: 0 | AT25: Ahorro | AU25: Scotiabank Perú | AV25: 000-2768484 | AW25: TRANSFERENCIA BANCARIA | AY25: 03343387 | AZ25: Si | BB25: 4 | BC25: CANCELADO | BN25: Si | BO25: 45488.655 | BP25: Carla Michue M | BR25: 6 | BS25: 29/06/2026 01:05 | BT25: 0 | BX25: Cobranzas_2024.csv | BY25: 2024 | BZ25: 01/01/2024 | CA25: 30/09/2031
A26: RESIDENCIAL PRADA | B26: Etapa 1 | C26: Edificio | D26: A | E26: Departamento | F26: 201 | G26: 622500 | H26: 622500 | AA26: Joseluis Gaspar Zapata Flores | AB26: 46730672 | AC26: Jr. Los Clavles 141 P. J El Progreso 1er Sector | AE26: 948041027 | AF26: jlzapata91@gmail.com | AG26: LIMA | AH26: CARABAYLLO | AI26: 45488 | AJ26: 45488 | AK26: CUOTA INICIAL | AL26: 2 | AM26: 20000 | AN26: 0 | AO26: 0 | AP26: 20000 | AQ26: 20000 | AR26: 0 | AS26: 0 | AT26: Ahorro | AU26: Scotiabank Perú | AV26: 000-2768484 | AW26: TRANSFERENCIA BANCARIA | AY26: 7844655656315 | AZ26: No | BB26: 4 | BC26: CANCELADO | BN26: Si | BO26: 45488.655 | BP26: Carla Michue M | BR26: 6 | BS26: 29/06/2026 01:06 | BT26: 0 | BX26: Cobranzas_2024.csv | BY26: 2024 | BZ26: 01/01/2024 | CA26: 30/09/2031
A27: RESIDENCIAL PRADA | B27: Etapa 1 | C27: Edificio | D27: A | E27: Departamento | F27: 201 | G27: 622500 | H27: 622500 | AA27: Joseluis Gaspar Zapata Flores | AB27: 46730672 | AC27: Jr. Los Clavles 141 P. J El Progreso 1er Sector | AE27: 948041027 | AF27: jlzapata91@gmail.com | AG27: LIMA | AH27: CARABAYLLO | AI27: 45656 | AJ27: 45722 | AK27: CUOTA INICIAL | AL27: 3 | AM27: 0 | AN27: 0 | AO27: 0 | AP27: 67000 | AQ27: 65000 | AR27: 0 | AS27: 0 | AT27: Ahorro | AU27: Scotiabank Perú | AV27: 000-2768484 | AW27: TRANSFERENCIA BANCARIA | AY27: u26563 | AZ27: No | BB27: 4 | BC27: CANCELADO | BN27: Si | BO27: 45488.655 | BP27: Carla Michue M | BR27: 6 | BS27: 29/06/2026 01:07 | BT27: 0 | BX27: Cobranzas_2024.csv | BY27: 2024 | BZ27: 01/01/2024 | CA27: 30/09/2031
A28: RESIDENCIAL PRADA | B28: Etapa 1 | C28: Edificio | D28: A | E28: Departamento | F28: 201 | G28: 622500 | H28: 622500 | AA28: Joseluis Gaspar Zapata Flores | AB28: 46730672 | AC28: Jr. Los Clavles 141 P. J El Progreso 1er Sector | AE28: 948041027 | AF28: jlzapata91@gmail.com | AG28: LIMA | AH28: CARABAYLLO | AI28: 45656 | AJ28: 45722 | AK28: CUOTA INICIAL | AL28: 3 | AM28: 67000 | AN28: 0 | AO28: 0 | AP28: 0 | AQ28: 2000 | AR28: 0 | AS28: 0 | AT28: Ahorro | AU28: Scotiabank Perú | AV28: 000-2768484 | AW28: TRANSFERENCIA BANCARIA | AY28: 7844655541508 | AZ28: No | BB28: 4 | BC28: CANCELADO | BN28: Si | BO28: 45488.655 | BP28: Carla Michue M | BR28: 6 | BS28: 29/06/2026 01:08 | BT28: 0 | BX28: Cobranzas_2024.csv | BY28: 2024 | BZ28: 01/01/2024 | CA28: 30/09/2031
A29: RESIDENCIAL PRADA | B29: Etapa 1 | C29: Edificio | D29: A | E29: Departamento | F29: 501 | G29: 612000 | H29: 612000 | AA29: Juan Carlos Ángeles Milla | AB29: 32403305 | AC29: Av. Miraflores 218 | AE29: 942097700 | AF29: Vidang72@hotmail.com | AG29: HUAYLAS | AH29: HUAYLAS | AI29: 45520 | AJ29: 45520 | AK29: SEPARACION | AL29: 1 | AM29: 3000 | AN29: 0 | AO29: 0 | AP29: 3000 | AQ29: 3000 | AR29: 0 | AS29: 0 | AT29: Ahorro | AU29: Scotiabank Perú | AV29: 000-2768484 | AW29: TRANSFERENCIA BANCARIA | AX29: 32403305 | AY29: 02431073 | AZ29: No | BA29: NO PRECISA | BB29: 1 | BC29: CANCELADO | BN29: Si | BO29: 45541.594 | BP29: Carla Michue M | BR29: 21 | BS29: 29/05/2026 12:21 | BT29: 0 | BX29: Cobranzas_2024.csv | BY29: 2024 | BZ29: 01/01/2024 | CA29: 30/09/2031
A30: RESIDENCIAL PRADA | B30: Etapa 1 | C30: Edificio | D30: A | E30: Departamento | F30: 501 | G30: 612000 | H30: 612000 | AA30: Juan Carlos Ángeles Milla | AB30: 32403305 | AC30: Av. Miraflores 218 | AE30: 942097700 | AF30: Vidang72@hotmail.com | AG30: HUAYLAS | AH30: HUAYLAS | AI30: 45541 | AJ30: 45541 | AK30: CUOTA INICIAL | AL30: 2 | AM30: 29500 | AN30: 0 | AO30: 0 | AP30: 29500 | AQ30: 29500 | AR30: 0 | AS30: 0 | AT30: Ahorro | AU30: Scotiabank Perú | AV30: 000-2768484 | AW30: TRANSFERENCIA BANCARIA | AX30: 32403305 | AY30: 0500010059 | AZ30: No | BA30: NO PRECISA | BB30: 1 | BC30: CANCELADO | BN30: Si | BO30: 45541.594 | BP30: Carla Michue M | BR30: 21 | BS30: 29/05/2026 12:21 | BT30: 0 | BX30: Cobranzas_2024.csv | BY30: 2024 | BZ30: 01/01/2024 | CA30: 30/09/2031
A31: RESIDENCIAL PRADA | B31: Etapa 1 | C31: Edificio | D31: A | E31: Departamento | F31: 403 | G31: 654000 | H31: 654000 | AA31: Liliana Lucila Luciano Claros | AB31: 15764694 | AC31: MZ M5 – Lt. 7 urb. Paseo del Mar | AE31: 982406857 | AF31: liliana31_micaela@hotmail.com | AG31: SANTA | AH31: NUEVO CHIMBOTE | AI31: 45586 | AJ31: 45586 | AK31: SEPARACION | AL31: 1 | AM31: 3000 | AN31: 0 | AO31: 0 | AP31: 3000 | AQ31: 3000 | AR31: 0 | AS31: 0 | AT31: Crédito Hipotecario | AU31: Scotiabank Perú | AV31: 000-2768484 | AW31: EFECTIVO | AX31: 15764694 | AY31: 0500010056 | AZ31: No | BA31: NO PRECISA | BB31: 1 | BC31: CANCELADO | BN31: Si | BO31: 45619.386 | BP31: Carla Michue M | BR31: 1 | BS31: 29/05/2026 12:20 | BT31: 0 | BX31: Cobranzas_2024.csv | BY31: 2024 | BZ31: 01/01/2024 | CA31: 30/09/2031
A32: RESIDENCIAL PRADA | B32: Etapa 1 | C32: Edificio | D32: A | E32: Departamento | F32: 403 | G32: 654000 | H32: 654000 | AA32: Liliana Lucila Luciano Claros | AB32: 15764694 | AC32: MZ M5 – Lt. 7 urb. Paseo del Mar | AE32: 982406857 | AF32: liliana31_micaela@hotmail.com | AG32: SANTA | AH32: NUEVO CHIMBOTE | AI32: 45619 | AJ32: 45619 | AK32: CUOTA INICIAL | AL32: 2 | AM32: 97800 | AN32: 0 | AO32: 0 | AP32: 97800 | AQ32: 97800 | AR32: 0 | AS32: 0 | AT32: Crédito Hipotecario | AU32: Scotiabank Perú | AV32: 000-2768484 | AW32: TRANSFERENCIA BANCARIA | AY32: 12007725 | AZ32: No | BB32: 4 | BC32: CANCELADO | BN32: Si | BO32: 45619.386 | BP32: Carla Michue M | BR32: 1 | BS32: 07/07/2026 09:30 | BT32: 0 | BX32: Cobranzas_2024.csv | BY32: 2024 | BZ32: 01/01/2024 | CA32: 30/09/2031
A33: RESIDENCIAL PRADA | B33: Etapa 1 | C33: Edificio | D33: A | E33: Departamento | F33: 403 | G33: 654000 | H33: 654000 | AA33: Liliana Lucila Luciano Claros | AB33: 15764694 | AC33: MZ M5 – Lt. 7 urb. Paseo del Mar | AE33: 982406857 | AF33: liliana31_micaela@hotmail.com | AG33: SANTA | AH33: NUEVO CHIMBOTE | AI33: 45631 | AJ33: 45631 | AK33: CUOTA INICIAL | AL33: 3 | AM33: 30000 | AN33: 0 | AO33: 0 | AP33: 30000 | AQ33: 30000 | AR33: 0 | AS33: 0 | AT33: Crédito Hipotecario | AU33: Scotiabank Perú | AV33: 000-2768484 | AW33: DEPOSITO EN CUENTA | AX33: 15764694 | AY33: 05000010069 | AZ33: No | BA33: NO PRECISA | BB33: 1 | BC33: CANCELADO | BN33: Si | BO33: 45619.386 | BP33: Carla Michue M | BR33: 1 | BS33: 29/05/2026 12:20 | BT33: 0 | BX33: Cobranzas_2024.csv | BY33: 2024 | BZ33: 01/01/2024 | CA33: 30/09/2031
A34: RESIDENCIAL PRADA | B34: Etapa 1 | C34: Edificio | D34: A | E34: Departamento | F34: 403 | G34: 654000 | H34: 654000 | AA34: Liliana Lucila Luciano Claros | AB34: 15764694 | AC34: MZ M5 – Lt. 7 urb. Paseo del Mar | AE34: 982406857 | AF34: liliana31_micaela@hotmail.com | AG34: SANTA | AH34: NUEVO CHIMBOTE | AI34: 45657 | AJ34: 45723 | AK34: SALDO FINANCIAR | AL34: 4 | AM34: 523200 | AN34: 0 | AO34: 0 | AP34: 523200 | AQ34: 523200 | AR34: 0 | AS34: 0 | AT34: Crédito Hipotecario | AU34: Scotiabank Perú | AV34: 000-2768484 | AW34: TRANSFERENCIA BANCARIA | AY34: 07032025 | AZ34: Si | BB34: 4 | BC34: CANCELADO | BN34: Si | BO34: 45619.386 | BP34: Carla Michue M | BR34: 1 | BS34: 07/07/2026 09:31 | BT34: 0 | BX34: Cobranzas_2024.csv | BY34: 2024 | BZ34: 01/01/2024 | CA34: 30/09/2031
A35: RESIDENCIAL PRADA | B35: Etapa 1 | C35: Edificio | D35: A | E35: Departamento | F35: 603 | G35: 654000 | H35: 654000 | AA35: Luis Alberto Ovalle Huamanguilla | AB35: 43953371 | AC35: JR. NAPO NRO. 821 | AE35: 992764943 | AF35: aovalle2212@gmail.com | AG35: LIMA | AH35: BREÑA | AI35: 45477 | AJ35: 45477 | AK35: SEPARACION | AL35: 1 | AM35: 3000 | AN35: 0 | AO35: 0 | AP35: 3000 | AQ35: 3000 | AR35: 0 | AS35: 0 | AT35: Ahorro | AU35: Scotiabank Perú | AV35: 000-2768484 | AW35: TRANSFERENCIA BANCARIA | AY35: 901866 | AZ35: No | BB35: 4 | BC35: CANCELADO | BN35: Si | BO35: 45567.694 | BP35: Carla Michue M | BR35: 11 | BS35: 07/07/2026 10:58 | BT35: 0 | BX35: Cobranzas_2024.csv | BY35: 2024 | BZ35: 01/01/2024 | CA35: 30/09/2031
A36: RESIDENCIAL PRADA | B36: Etapa 1 | C36: Edificio | D36: A | E36: Departamento | F36: 603 | G36: 654000 | H36: 654000 | AA36: Luis Alberto Ovalle Huamanguilla | AB36: 43953371 | AC36: JR. NAPO NRO. 821 | AE36: 992764943 | AF36: aovalle2212@gmail.com | AG36: LIMA | AH36: BREÑA | AI36: 45656 | AJ36: 45567 | AK36: SEPARACION | AL36: 5 | AM36: 5000 | AN36: 0 | AO36: 0 | AP36: 5000 | AQ36: 5000 | AR36: 0 | AS36: 0 | AT36: Ahorro | AU36: Scotiabank Perú | AV36: 000-2768484 | AW36: TRANSFERENCIA BANCARIA | AY36: 06056215 | AZ36: No | BB36: 4 | BC36: CANCELADO | BN36: Si | BO36: 45567.694 | BP36: Carla Michue M | BR36: 11 | BS36: 07/07/2026 11:03 | BT36: 0 | BX36: Cobranzas_2024.csv | BY36: 2024 | BZ36: 01/01/2024 | CA36: 30/09/2031
A37: RESIDENCIAL PRADA | B37: Etapa 1 | C37: Edificio | D37: A | E37: Departamento | F37: 603 | G37: 654000 | H37: 654000 | AA37: Luis Alberto Ovalle Huamanguilla | AB37: 43953371 | AC37: JR. NAPO NRO. 821 | AE37: 992764943 | AF37: aovalle2212@gmail.com | AG37: LIMA | AH37: BREÑA | AI37: 45656 | AJ37: 45567 | AK37: CUOTA INICIAL | AL37: 1 | AM37: 57400 | AN37: 0 | AO37: 0 | AP37: 57400 | AQ37: 20000 | AR37: 0 | AS37: 0 | AT37: Ahorro | AU37: Scotiabank Perú | AV37: 000-2768484 | AW37: TRANSFERENCIA BANCARIA | AY37: 06056215 | AZ37: No | BB37: 4 | BC37: CANCELADO | BN37: Si | BO37: 45567.694 | BP37: Carla Michue M | BR37: 11 | BS37: 07/07/2026 11:03 | BT37: 0 | BX37: Cobranzas_2024.csv | BY37: 2024 | BZ37: 01/01/2024 | CA37: 30/09/2031
A38: RESIDENCIAL PRADA | B38: Etapa 1 | C38: Edificio | D38: A | E38: Departamento | F38: 603 | G38: 654000 | H38: 654000 | AA38: Luis Alberto Ovalle Huamanguilla | AB38: 43953371 | AC38: JR. NAPO NRO. 821 | AE38: 992764943 | AF38: aovalle2212@gmail.com | AG38: LIMA | AH38: BREÑA | AI38: 45656 | AJ38: 45723 | AK38: CUOTA INICIAL | AL38: 1 | AM38: 0 | AN38: 0 | AO38: 0 | AP38: 0 | AQ38: 37400 | AR38: 0 | AS38: 0 | AT38: Ahorro | AU38: Scotiabank Perú | AV38: 000-2768484 | AW38: TRANSFERENCIA BANCARIA | AY38: U26926 | AZ38: No | BB38: 4 | BC38: CANCELADO | BN38: Si | BO38: 45567.694 | BP38: Carla Michue M | BR38: 11 | BS38: 07/07/2026 11:04 | BT38: 0 | BX38: Cobranzas_2024.csv | BY38: 2024 | BZ38: 01/01/2024 | CA38: 30/09/2031
A39: RESIDENCIAL PRADA | B39: Etapa 1 | C39: Edificio | D39: A | E39: Departamento | F39: 103 | G39: 520400 | H39: 520400 | AA39: Luis Eduardo Herrera Arrasco | AB39: 70656236 | AC39: Podesta Pescheira 273 - Pueblo Libre | AE39: 987782194 | AF39: luisherrarra19@gmail.com | AI39: 45578 | AJ39: 45578 | AK39: SEPARACION | AL39: 1 | AM39: 3000 | AN39: 0 | AO39: 0 | AP39: 3000 | AQ39: 3000 | AR39: 0 | AS39: 0 | AT39: Crédito Hipotecario | AU39: Scotiabank Perú | AV39: 000-2768484 | AW39: TRANSFERENCIA BANCARIA | AY39: 01871075 | AZ39: No | BB39: 4 | BC39: CANCELADO | BN39: Si | BO39: 45663.588 | BP39: Kenny Salazar S | BR39: 31 | BS39: 26/06/2026 17:22 | BT39: 0 | BX39: Cobranzas_2024.csv | BY39: 2024 | BZ39: 01/01/2024 | CA39: 30/09/2031
A40: RESIDENCIAL PRADA | B40: Etapa 1 | C40: Edificio | D40: A | E40: Departamento | F40: 202 | G40: 446900 | H40: 446900 | AA40: María Cristina Collazos Romero | AB40: 31676885 | AC40: Jr. Huandoy 242 | AD40: 969870030 | AE40: 969870030 | AF40: gerenciasnacks1@gmail.com | AG40: HUARAZ | AH40: HUARAZ | AI40: 45526 | AJ40: 45526 | AK40: SEPARACION | AL40: 1 | AM40: 3000 | AN40: 0 | AO40: 0 | AP40: 3000 | AQ40: 3000 | AR40: 0 | AS40: 0 | AT40: Crédito Hipotecario | AU40: Scotiabank Perú | AV40: 000-2768484 | AW40: TRANSFERENCIA BANCARIA | AX40: 31676885 | AY40: 0500010101 | AZ40: No | BA40: NO PRECISA | BB40: 4 | BC40: CANCELADO | BN40: Si | BO40: 45911.607 | BP40: Kenny Salazar S | BR40: 33 | BS40: 02/06/2026 15:10 | BT40: 0 | BX40: Cobranzas_2024.csv | BY40: 2024 | BZ40: 01/01/2024 | CA40: 30/09/2031
A41: RESIDENCIAL PRADA | B41: Etapa 1 | C41: Edificio | D41: A | E41: Departamento | F41: 505 | G41: 490000 | H41: 490000 | AA41: Marina Francisca Vasquez Samaniego | AB41: 19907001 | AC41: Huandoy 887 | AD41: 964247615 | AE41: 964247615 | AF41: francisca4547@hotmail.com | AG41: LIMA | AH41: SAN MIGUEL | AI41: 45617 | AJ41: 45617 | AK41: SEPARACION | AL41: 1 | AM41: 3000 | AN41: 0 | AO41: 0 | AP41: 3000 | AQ41: 3000 | AR41: 0 | AS41: 0 | AT41: Crédito Hipotecario | AU41: Scotiabank Perú | AV41: 000-2768484 | AW41: TRANSFERENCIA BANCARIA | AX41: 19907001 | AY41: 00951165 | AZ41: No | BA41: NO PRECISA | BB41: 4 | BC41: CANCELADO | BN41: Si | BO41: 45652.617 | BP41: Carla Michue M | BR41: 37 | BS41: 02/06/2026 17:25 | BT41: 0 | BX41: Cobranzas_2024.csv | BY41: 2024 | BZ41: 01/01/2024 | CA41: 30/09/2031
A42: RESIDENCIAL PRADA | B42: Etapa 1 | C42: Edificio | D42: A | E42: Departamento | F42: 505 | G42: 490000 | H42: 490000 | AA42: Marina Francisca Vasquez Samaniego | AB42: 19907001 | AC42: Huandoy 887 | AD42: 964247615 | AE42: 964247615 | AF42: francisca4547@hotmail.com | AG42: LIMA | AH42: SAN MIGUEL | AI42: 45652 | AJ42: 45652 | AK42: CUOTA INICIAL | AL42: 1 | AM42: 20000 | AN42: 0 | AO42: 0 | AP42: 20000 | AQ42: 20000 | AR42: 0 | AS42: 0 | AT42: Crédito Hipotecario | AU42: Scotiabank Perú | AV42: 000-2768484 | AW42: TRANSFERENCIA BANCARIA | AY42: 6204304 | AZ42: No | BB42: 4 | BC42: CANCELADO | BN42: Si | BO42: 45652.617 | BP42: Carla Michue M | BR42: 37 | BS42: 07/07/2026 10:35 | BT42: 0 | BX42: Cobranzas_2024.csv | BY42: 2024 | BZ42: 01/01/2024 | CA42: 30/09/2031
A43: RESIDENCIAL PRADA | B43: Etapa 1 | C43: Edificio | D43: A | E43: Departamento | F43: 701 | G43: 592500 | H43: 592500 | AA43: Richard Humberto Lima Garcia | AB43: 10606793 | AC43: Mz E2 lote 10 Urb Coovitiomar - Ancón | AE43: 940170759 | AF43: richard_13_312@hotmail.com | AG43: LIMA | AH43: SANTA ROSA | AI43: 45593 | AJ43: 45593 | AK43: SEPARACION | AL43: 1 | AM43: 3000 | AN43: 0 | AO43: 0 | AP43: 3000 | AQ43: 3000 | AR43: 0 | AS43: 0 | AT43: Crédito Hipotecario | AU43: Scotiabank Perú | AV43: 000-2768484 | AW43: TRANSFERENCIA BANCARIA | AX43: 10606793 | AY43: 01525977 | AZ43: No | BA43: NO PRECISA | BB43: 1 | BC43: CANCELADO | BN43: Si | BO43: 45638.388 | BP43: Carla Michue M | BR43: 3 | BS43: 29/05/2026 12:21 | BT43: 0 | BX43: Cobranzas_2024.csv | BY43: 2024 | BZ43: 01/01/2024 | CA43: 30/09/2031
A44: RESIDENCIAL PRADA | B44: Etapa 1 | C44: Edificio | D44: A | E44: Departamento | F44: 701 | G44: 592500 | H44: 592500 | AA44: Richard Humberto Lima Garcia | AB44: 10606793 | AC44: Mz E2 lote 10 Urb Coovitiomar - Ancón | AE44: 940170759 | AF44: richard_13_312@hotmail.com | AG44: LIMA | AH44: SANTA ROSA | AI44: 45618 | AJ44: 45618 | AK44: CUOTA INICIAL | AL44: 2 | AM44: 48000 | AN44: 0 | AO44: 0 | AP44: 48000 | AQ44: 48000 | AR44: 0 | AS44: 0 | AT44: Crédito Hipotecario | AU44: Scotiabank Perú | AV44: 000-2768484 | AW44: TRANSFERENCIA BANCARIA | AY44: 0144739 | AZ44: No | BB44: 4 | BC44: CANCELADO | BN44: Si | BO44: 45638.388 | BP44: Carla Michue M | BR44: 3 | BS44: 14/07/2026 09:05 | BT44: 0 | BX44: Cobranzas_2024.csv | BY44: 2024 | BZ44: 01/01/2024 | CA44: 30/09/2031
A45: RESIDENCIAL PRADA | B45: Etapa 1 | C45: Edificio | D45: A | E45: Departamento | F45: 701 | G45: 592500 | H45: 592500 | AA45: Richard Humberto Lima Garcia | AB45: 10606793 | AC45: Mz E2 lote 10 Urb Coovitiomar - Ancón | AE45: 940170759 | AF45: richard_13_312@hotmail.com | AG45: LIMA | AH45: SANTA ROSA | AI45: 45638 | AJ45: 45638 | AK45: CUOTA INICIAL | AL45: 3 | AM45: 8250 | AN45: 0 | AO45: 0 | AP45: 8250 | AQ45: 8250 | AR45: 0 | AS45: 0 | AT45: Crédito Hipotecario | AU45: Scotiabank Perú | AV45: 000-2768484 | AW45: TRANSFERENCIA BANCARIA | AX45: 10606793 | AY45: 02209753 | AZ45: No | BA45: NO PRECISA | BB45: 1 | BC45: CANCELADO | BN45: Si | BO45: 45638.388 | BP45: Carla Michue M | BR45: 3 | BS45: 29/05/2026 12:21 | BT45: 0 | BX45: Cobranzas_2024.csv | BY45: 2024 | BZ45: 01/01/2024 | CA45: 30/09/2031
A46: RESIDENCIAL PRADA | B46: Etapa 1 | C46: Edificio | D46: A | E46: Departamento | F46: 705 | G46: 496000 | H46: 496000 | AA46: Sthefany Carolina Rodriguez Huamán | AB46: 70270427 | AC46: - | AE46: 989492681 | AF46: sthefany.rodriguez2207@gmail.com | AG46: LIMA | AH46: CERCADO DE LIMA | AI46: 45586 | AJ46: 45586 | AK46: SEPARACION | AL46: 1 | AM46: 200 | AN46: 0 | AO46: 0 | AP46: 200 | AQ46: 200 | AR46: 0 | AS46: 0 | AT46: Ahorro | AU46: Scotiabank Perú | AV46: 000-2768484 | AW46: TRANSFERENCIA BANCARIA | AX46: 70270427 | AY46: 7844655610334 | AZ46: No | BA46: NO PRECISA | BB46: 1 | BC46: CANCELADO | BN46: Si | BO46: 45829.39 | BP46: Carla Michue M | BR46: 2 | BS46: 29/05/2026 12:20 | BT46: 0 | BX46: Cobranzas_2024.csv | BY46: 2024 | BZ46: 01/01/2024 | CA46: 30/09/2031
A47: RESIDENCIAL PRADA | B47: Etapa 1 | C47: Edificio | D47: A | E47: Departamento | F47: 705 | G47: 496000 | H47: 496000 | AA47: Sthefany Carolina Rodriguez Huamán | AB47: 70270427 | AC47: - | AE47: 989492681 | AF47: sthefany.rodriguez2207@gmail.com | AG47: LIMA | AH47: CERCADO DE LIMA | AI47: 45587 | AJ47: 45587 | AK47: SEPARACION | AL47: 2 | AM47: 2800 | AN47: 0 | AO47: 0 | AP47: 2800 | AQ47: 2800 | AR47: 0 | AS47: 0 | AT47: Ahorro | AU47: Scotiabank Perú | AV47: 000-2768484 | AW47: EFECTIVO | AX47: 70270427 | AY47: 0500010021 | AZ47: No | BA47: NO PRECISA | BB47: 1 | BC47: CANCELADO | BN47: Si | BO47: 45829.39 | BP47: Carla Michue M | BR47: 2 | BS47: 29/05/2026 12:20 | BT47: 0 | BX47: Cobranzas_2024.csv | BY47: 2024 | BZ47: 01/01/2024 | CA47: 30/09/2031
A48: RESIDENCIAL BEYOND | B48: Etapa 1 | C48: Edificio | D48: A | E48: Departamento | F48: 205 | G48: 587000 | H48: 577000 | AA48: Tania Milagros Cotrina Vara | AB48: 10140034 | AC48: Av. Arnaldo Marquez 1526 Dpto. 26 | AD48: 0 | AE48: 941461159 | AF48: tamicov@hotmail.com | AG48: LIMA | AH48: JESUS MARIA | AI48: 45641 | AJ48: 45641 | AK48: SEPARACION | AL48: 1 | AM48: 3000 | AN48: 0 | AO48: 0 | AP48: 3000 | AQ48: 3000 | AR48: 0 | AS48: 0 | AT48: Ahorro | AU48: Banco de Credito del Perú | AV48: 194-7325779-0-65 | AW48: POS VISA | AX48: 10140034 | AY48: 594693007 | AZ48: Si | BA48: NO PRECISA | BB48: 4 | BC48: CANCELADO | BN48: Si | BO48: 45918.416 | BP48: Magaly Guevara Perez | BR48: 4 | BS48: 01/05/2026 11:00 | BT48: 0 | BX48: Cobranzas_2024.csv | BY48: 2024 | BZ48: 01/01/2024 | CA48: 30/09/2031
A49: RESIDENCIAL PRADA | B49: Etapa 1 | C49: Edificio | D49: A | E49: Departamento | F49: 301 | G49: 630000 | H49: 630000 | AA49: Alejandro Jose Navarrete Maldonado | AB49: 46304395 | AC49: Calle Jose Mariano Arce 139 – Dpto. 202 | AE49: 956466496 | AF49: anavarrete@nmabogados.com.pe | AG49: LIMA | AH49: PUEBLO LIBRE | AI49: 45754 | AJ49: 45754 | AK49: SEPARACION | AL49: 1 | AM49: 3000 | AN49: 0 | AO49: 0 | AP49: 3000 | AQ49: 3000 | AR49: 0 | AS49: 0 | AT49: Crédito Hipotecario | AU49: Scotiabank Perú | AV49: 000-2768484 | AW49: TRANSFERENCIA BANCARIA | AX49: 46304395 | AY49: 2715 | AZ49: No | BA49: NO PRECISA | BB49: 1 | BC49: CANCELADO | BN49: Si | BO49: 45775.391 | BP49: Carla Michue M | BR49: 8 | BS49: 29/05/2026 12:21 | BT49: 0 | BX49: Cobranzas_2025.csv | BY49: 2025 | BZ49: 01/01/2024 | CA49: 30/09/2031
A50: RESIDENCIAL PRADA | B50: Etapa 1 | C50: Edificio | D50: A | E50: Departamento | F50: 301 | G50: 630000 | H50: 630000 | AA50: Alejandro Jose Navarrete Maldonado | AB50: 46304395 | AC50: Calle Jose Mariano Arce 139 – Dpto. 202 | AE50: 956466496 | AF50: anavarrete@nmabogados.com.pe | AG50: LIMA | AH50: PUEBLO LIBRE | AI50: 45775 | AJ50: 45775 | AK50: SEPARACION | AL50: 6 | AM50: 10000 | AN50: 0 | AO50: 0 | AP50: 10000 | AQ50: 10000 | AR50: 0 | AS50: 0 | AT50: Crédito Hipotecario | AU50: Scotiabank Perú | AV50: 000-2768484 | AW50: TRANSFERENCIA BANCARIA | AY50: 8240169 | AZ50: No | BB50: 4 | BC50: CANCELADO | BN50: Si | BO50: 45775.391 | BP50: Carla Michue M | BR50: 8 | BS50: 03/07/2026 10:54 | BT50: 0 | BX50: Cobranzas_2025.csv | BY50: 2025 | BZ50: 01/01/2024 | CA50: 30/09/2031
A51: RESIDENCIAL PRADA | B51: Etapa 1 | C51: Edificio | D51: A | E51: Departamento | F51: 301 | G51: 630000 | H51: 630000 | AA51: Alejandro Jose Navarrete Maldonado | AB51: 46304395 | AC51: Calle Jose Mariano Arce 139 – Dpto. 202 | AE51: 956466496 | AF51: anavarrete@nmabogados.com.pe | AG51: LIMA | AH51: PUEBLO LIBRE | AI51: 45775 | AJ51: 45775 | AK51: CUOTA INICIAL | AL51: 1 | AM51: 45000 | AN51: 0 | AO51: 0 | AP51: 45000 | AQ51: 45000 | AR51: 0 | AS51: 0 | AT51: Crédito Hipotecario | AU51: Scotiabank Perú | AV51: 000-2768484 | AW51: TRANSFERENCIA BANCARIA | AY51: 8240169 | AZ51: No | BB51: 4 | BC51: CANCELADO | BN51: Si | BO51: 45775.391 | BP51: Carla Michue M | BR51: 8 | BS51: 03/07/2026 10:54 | BT51: 0 | BX51: Cobranzas_2025.csv | BY51: 2025 | BZ51: 01/01/2024 | CA51: 30/09/2031
A52: RESIDENCIAL PRADA | B52: Etapa 1 | C52: Edificio | D52: A | E52: Departamento | F52: 301 | G52: 630000 | H52: 630000 | AA52: Alejandro Jose Navarrete Maldonado | AB52: 46304395 | AC52: Calle Jose Mariano Arce 139 – Dpto. 202 | AE52: 956466496 | AF52: anavarrete@nmabogados.com.pe | AG52: LIMA | AH52: PUEBLO LIBRE | AI52: 45833 | AJ52: 45833 | AK52: CUOTA INICIAL | AL52: 2 | AM52: 44000 | AN52: 0 | AO52: 0 | AP52: 44000 | AQ52: 44000 | AR52: 0 | AS52: 0 | AT52: Crédito Hipotecario | AU52: Scotiabank Perú | AV52: 000-2768484 | AW52: TRANSFERENCIA BANCARIA | AY52: 006190692 | AZ52: No | BB52: 4 | BC52: CANCELADO | BN52: Si | BO52: 45775.391 | BP52: Carla Michue M | BR52: 8 | BS52: 03/07/2026 10:56 | BT52: 0 | BX52: Cobranzas_2025.csv | BY52: 2025 | BZ52: 01/01/2024 | CA52: 30/09/2031
A53: RESIDENCIAL PRADA | B53: Etapa 1 | C53: Edificio | D53: A | E53: Departamento | F53: 301 | G53: 630000 | H53: 630000 | AA53: Alejandro Jose Navarrete Maldonado | AB53: 46304395 | AC53: Calle Jose Mariano Arce 139 – Dpto. 202 | AE53: 956466496 | AF53: anavarrete@nmabogados.com.pe | AG53: LIMA | AH53: PUEBLO LIBRE | AI53: 45869 | AJ53: 45833 | AK53: SALDO FINANCIAR | AL53: 1 | AM53: 528000 | AN53: 0 | AO53: 0 | AP53: 528000 | AQ53: 68000 | AR53: 0 | AS53: 0 | AT53: Crédito Hipotecario | AU53: Scotiabank Perú | AV53: 000-2768484 | AW53: TRANSFERENCIA BANCARIA | AY53: 1141936 | AZ53: No | BB53: 4 | BC53: CANCELADO | BN53: Si | BO53: 45775.391 | BP53: Carla Michue M | BR53: 8 | BS53: 03/07/2026 11:00 | BT53: 0 | BX53: Cobranzas_2025.csv | BY53: 2025 | BZ53: 01/01/2024 | CA53: 30/09/2031
A54: RESIDENCIAL PRADA | B54: Etapa 1 | C54: Edificio | D54: A | E54: Departamento | F54: 301 | G54: 630000 | H54: 630000 | AA54: Alejandro Jose Navarrete Maldonado | AB54: 46304395 | AC54: Calle Jose Mariano Arce 139 – Dpto. 202 | AE54: 956466496 | AF54: anavarrete@nmabogados.com.pe | AG54: LIMA | AH54: PUEBLO LIBRE | AI54: 45869 | AJ54: 45868 | AK54: SALDO FINANCIAR | AL54: 1 | AM54: 0 | AN54: 0 | AO54: 0 | AP54: 0 | AQ54: 460000 | AR54: 0 | AS54: 0 | AT54: Crédito Hipotecario | AU54: Scotiabank Perú | AV54: 000-2768484 | AW54: TRANSFERENCIA BANCARIA | AY54: 02708000009 | AZ54: No | BB54: 4 | BC54: CANCELADO | BN54: Si | BO54: 45775.391 | BP54: Carla Michue M | BR54: 8 | BS54: 03/07/2026 11:02 | BT54: 0 | BX54: Cobranzas_2025.csv | BY54: 2025 | BZ54: 01/01/2024 | CA54: 30/09/2031
A55: RESIDENCIAL PRADA | B55: Etapa 1 | C55: Edificio | D55: A | E55: Estacionamiento | F55: E 23 - D 17 | G55: 52000 | H55: 52000 | AA55: Alejandro Jose Navarrete Maldonado | AB55: 46304395 | AC55: Calle Jose Mariano Arce 139 – Dpto. 202 | AD55: 0 | AE55: 956466496 | AF55: anavarrete@nmabogados.com.pe | AG55: LIMA | AH55: PUEBLO LIBRE | AI55: 45877 | AJ55: 45873 | AK55: SEPARACION | AL55: 1 | AM55: 3000 | AN55: 0 | AO55: 0 | AP55: 3000 | AQ55: 3000 | AR55: 0 | AS55: 0 | AT55: Crédito Directo | AU55: Scotiabank Perú | AV55: 000-2768484 | AW55: TRANSFERENCIA BANCARIA | AY55: 2636117 | AZ55: No | BB55: 4 | BC55: CANCELADO | BN55: Si | BO55: 45961.433 | BP55: Magaly Guevara Perez | BR55: 54 | BS55: 14/07/2026 10:02 | BT55: 0 | BX55: Cobranzas_2025.csv | BY55: 2025 | BZ55: 01/01/2024 | CA55: 30/09/2031
A56: RESIDENCIAL PRADA | B56: Etapa 1 | C56: Edificio | D56: A | E56: Estacionamiento | F56: E 23 - D 17 | G56: 52000 | H56: 52000 | AA56: Alejandro Jose Navarrete Maldonado | AB56: 46304395 | AC56: Calle Jose Mariano Arce 139 – Dpto. 202 | AD56: 0 | AE56: 956466496 | AF56: anavarrete@nmabogados.com.pe | AG56: LIMA | AH56: PUEBLO LIBRE | AI56: 45877 | AJ56: 45873 | AK56: CUOTA INICIAL | AL56: 1 | AM56: 7000 | AN56: 0 | AO56: 0 | AP56: 7000 | AQ56: 7000 | AR56: 0 | AS56: 0 | AT56: Crédito Directo | AU56: Scotiabank Perú | AV56: 000-2768484 | AW56: TRANSFERENCIA BANCARIA | AY56: 2636117 | AZ56: No | BB56: 4 | BC56: CANCELADO | BN56: Si | BO56: 45961.433 | BP56: Magaly Guevara Perez | BR56: 54 | BS56: 14/07/2026 10:02 | BT56: 0 | BX56: Cobranzas_2025.csv | BY56: 2025 | BZ56: 01/01/2024 | CA56: 30/09/2031
A57: RESIDENCIAL PRADA | B57: Etapa 1 | C57: Edificio | D57: A | E57: Estacionamiento | F57: E 23 - D 17 | G57: 52000 | H57: 52000 | AA57: Alejandro Jose Navarrete Maldonado | AB57: 46304395 | AC57: Calle Jose Mariano Arce 139 – Dpto. 202 | AD57: 0 | AE57: 956466496 | AF57: anavarrete@nmabogados.com.pe | AG57: LIMA | AH57: PUEBLO LIBRE | AI57: 45961 | AJ57: 45961 | AK57: SALDO FINANCIAR | AL57: 1 | AM57: 14000 | AN57: 0 | AO57: 0 | AP57: 14000 | AQ57: 14000 | AR57: 0 | AS57: 0 | AT57: Crédito Directo | AU57: Scotiabank Perú | AV57: 000-2768484 | AW57: TRANSFERENCIA BANCARIA | AY57: 009555099 | AZ57: No | BB57: 4 | BC57: CANCELADO | BN57: Si | BO57: 45961.433 | BP57: Magaly Guevara Perez | BR57: 54 | BS57: 03/07/2026 11:16 | BT57: 0 | BX57: Cobranzas_2025.csv | BY57: 2025 | BZ57: 01/01/2024 | CA57: 30/09/2031
A58: RESIDENCIAL PRADA | B58: Etapa 1 | C58: Edificio | D58: A | E58: Estacionamiento | F58: E 23 - D 17 | G58: 52000 | H58: 52000 | AA58: Alejandro Jose Navarrete Maldonado | AB58: 46304395 | AC58: Calle Jose Mariano Arce 139 – Dpto. 202 | AD58: 0 | AE58: 956466496 | AF58: anavarrete@nmabogados.com.pe | AG58: LIMA | AH58: PUEBLO LIBRE | AI58: 46022 | AJ58: 46022 | AK58: SALDO FINANCIAR | AL58: 2 | AM58: 14000 | AN58: 0 | AO58: 0 | AP58: 14000 | AQ58: 14000 | AR58: 0 | AS58: 0 | AT58: Crédito Directo | AU58: Scotiabank Perú | AV58: 000-2768484 | AW58: TRANSFERENCIA BANCARIA | AY58: 059881 | AZ58: No | BB58: 4 | BC58: CANCELADO | BN58: Si | BO58: 45961.433 | BP58: Magaly Guevara Perez | BR58: 54 | BS58: 03/07/2026 11:18 | BT58: 0 | BX58: Cobranzas_2025.csv | BY58: 2025 | BZ58: 01/01/2024 | CA58: 30/09/2031
A59: RESIDENCIAL PRADA | B59: Etapa 1 | C59: Edificio | D59: A | E59: Departamento | F59: 504 | G59: 417700 | H59: 417700 | AA59: Alvaro Geanfranco Mendoza Jump | AB59: 72112648 | AC59: Urb. San Francisco Mz. B Lt. 11 Departamento de Huanuco, Provincia de Huanuco, Dsitrito Amarilis | AD59: 938217737 | AE59: 938217737 | AF59: alvaromej17@gmail.com | AG59: HUANUCO | AH59: AMARILIS | AI59: 45912 | AJ59: 45912 | AK59: SEPARACION | AL59: 1 | AM59: 3000 | AN59: 0 | AO59: 0 | AP59: 3000 | AQ59: 3000 | AR59: 0 | AS59: 0 | AT59: Ahorro | AU59: Scotiabank Perú | AV59: 000-2768484 | AW59: TRANSFERENCIA BANCARIA | AY59: 00673199 | AZ59: No | BB59: 4 | BC59: CANCELADO | BN59: Si | BO59: 45919.616 | BP59: Kenny Salazar S | BR59: 36 | BS59: 02/06/2026 17:13 | BT59: 0 | BX59: Cobranzas_2025.csv | BY59: 2025 | BZ59: 01/01/2024 | CA59: 30/09/2031
A60: RESIDENCIAL PRADA | B60: Etapa 1 | C60: Edificio | D60: A | E60: Departamento | F60: 504 | G60: 417700 | H60: 417700 | AA60: Alvaro Geanfranco Mendoza Jump | AB60: 72112648 | AC60: Urb. San Francisco Mz. B Lt. 11 Departamento de Huanuco, Provincia de Huanuco, Dsitrito Amarilis | AD60: 938217737 | AE60: 938217737 | AF60: alvaromej17@gmail.com | AG60: HUANUCO | AH60: AMARILIS | AI60: 45919 | AJ60: 45919 | AK60: CUOTA INICIAL | AL60: 1 | AM60: 10000 | AN60: 0 | AO60: 0 | AP60: 10000 | AQ60: 10000 | AR60: 0 | AS60: 0 | AT60: Ahorro | AU60: Scotiabank Perú | AV60: 000-2768484 | AW60: TRANSFERENCIA BANCARIA | AY60: 02785402 | AZ60: No | BB60: 4 | BC60: CANCELADO | BN60: Si | BO60: 45919.616 | BP60: Kenny Salazar S | BR60: 36 | BS60: 23/06/2026 15:59 | BT60: 0 | BX60: Cobranzas_2025.csv | BY60: 2025 | BZ60: 01/01/2024 | CA60: 30/09/2031
A61: RESIDENCIAL PRADA | B61: Etapa 1 | C61: Edificio | D61: A | E61: Departamento | F61: 1104 | G61: 397000 | H61: 397000 | AA61: Ana Fabiola Alvarez Elias | AB61: 06789211 | AC61: Jr. Caraveli 968 Interior 103 | AD61: 991502978 | AE61: 986642025 | AF61: anafabiola1@hotmail.com | AG61: LIMA | AH61: BREÑA | AI61: 45703 | AJ61: 45703 | AK61: SEPARACION | AL61: 1 | AM61: 3000 | AN61: 0 | AO61: 0 | AP61: 3000 | AQ61: 3000 | AR61: 0 | AS61: 0 | AT61: Crédito Hipotecario | AU61: Scotiabank Perú | AV61: 000-2768484 | AW61: POS VISA | AX61: 06789211 | AY61: 31010 | AZ61: No | BA61: NO PRECISA | BB61: 1 | BC61: CANCELADO | BN61: Si | BO61: 45730.741 | BP61: Carla Michue M | BR61: 9 | BS61: 29/05/2026 12:21 | BT61: 0 | BX61: Cobranzas_2025.csv | BY61: 2025 | BZ61: 01/01/2024 | CA61: 30/09/2031
A62: RESIDENCIAL PRADA | B62: Etapa 1 | C62: Edificio | D62: A | E62: Departamento | F62: 1104 | G62: 397000 | H62: 397000 | AA62: Ana Fabiola Alvarez Elias | AB62: 06789211 | AC62: Jr. Caraveli 968 Interior 103 | AD62: 991502978 | AE62: 986642025 | AF62: anafabiola1@hotmail.com | AG62: LIMA | AH62: BREÑA | AI62: 45730 | AJ62: 45730 | AK62: CUOTA INICIAL | AL62: 2 | AM62: 23450 | AN62: 0 | AO62: 0 | AP62: 23450 | AQ62: 23450 | AR62: 0 | AS62: 0 | AT62: Crédito Hipotecario | AU62: Scotiabank Perú | AV62: 000-2768484 | AW62: TRANSFERENCIA BANCARIA | AX62: 06789211 | AY62: 281328 | AZ62: No | BA62: NO PRECISA | BB62: 1 | BC62: CANCELADO | BN62: Si | BO62: 45730.741 | BP62: Carla Michue M | BR62: 9 | BS62: 29/05/2026 12:21 | BT62: 0 | BX62: Cobranzas_2025.csv | BY62: 2025 | BZ62: 01/01/2024 | CA62: 30/09/2031
A63: RESIDENCIAL PRADA | B63: Etapa 1 | C63: Edificio | D63: A | E63: Departamento | F63: 1104 | G63: 397000 | H63: 397000 | AA63: Ana Fabiola Alvarez Elias | AB63: 06789211 | AC63: Jr. Caraveli 968 Interior 103 | AD63: 991502978 | AE63: 986642025 | AF63: anafabiola1@hotmail.com | AG63: LIMA | AH63: BREÑA | AI63: 45730 | AJ63: 45730 | AK63: CUOTA INICIAL | AL63: 3 | AM63: 78000 | AN63: 0 | AO63: 0 | AP63: 78000 | AQ63: 78000 | AR63: 0 | AS63: 0 | AT63: Crédito Hipotecario | AU63: Scotiabank Perú | AV63: 000-2768484 | AW63: TRANSFERENCIA BANCARIA | AX63: 06789211 | AY63: 7502425 | AZ63: No | BA63: NO PRECISA | BB63: 1 | BC63: CANCELADO | BN63: Si | BO63: 45730.741 | BP63: Carla Michue M | BR63: 9 | BS63: 29/05/2026 12:21 | BT63: 0 | BX63: Cobranzas_2025.csv | BY63: 2025 | BZ63: 01/01/2024 | CA63: 30/09/2031
A64: RESIDENCIAL PRADA | B64: Etapa 1 | C64: Edificio | D64: A | E64: Departamento | F64: 1104 | G64: 397000 | H64: 397000 | AA64: Ana Fabiola Alvarez Elias | AB64: 06789211 | AC64: Jr. Caraveli 968 Interior 103 | AD64: 991502978 | AE64: 986642025 | AF64: anafabiola1@hotmail.com | AG64: LIMA | AH64: BREÑA | AI64: 45746 | AJ64: 45747 | AK64: SALDO FINANCIAR | AL64: 1 | AM64: 292550 | AN64: 0 | AO64: 0 | AP64: 292550 | AQ64: 34500 | AR64: 0 | AS64: 0 | AT64: Crédito Hipotecario | AU64: Scotiabank Perú | AV64: 000-2768484 | AW64: DEPOSITO EN CUENTA | AY64: 23022025 | AZ64: No | BB64: 4 | BC64: CANCELADO | BN64: Si | BO64: 45730.741 | BP64: Carla Michue M | BR64: 9 | BS64: 07/07/2026 14:22 | BT64: 0 | BX64: Cobranzas_2025.csv | BY64: 2025 | BZ64: 01/01/2024 | CA64: 30/09/2031
A65: RESIDENCIAL PRADA | B65: Etapa 1 | C65: Edificio | D65: A | E65: Departamento | F65: 1104 | G65: 397000 | H65: 397000 | AA65: Ana Fabiola Alvarez Elias | AB65: 06789211 | AC65: Jr. Caraveli 968 Interior 103 | AD65: 991502978 | AE65: 986642025 | AF65: anafabiola1@hotmail.com | AG65: LIMA | AH65: BREÑA | AI65: 45746 | AJ65: 45747 | AK65: SALDO FINANCIAR | AL65: 1 | AM65: 0 | AN65: 0 | AO65: 0 | AP65: 0 | AQ65: 258050 | AR65: 0 | AS65: 0 | AT65: Crédito Hipotecario | AU65: Scotiabank Perú | AV65: 000-2768484 | AW65: TRANSFERENCIA BANCARIA | AY65: 30032025 | AZ65: No | BB65: 4 | BC65: CANCELADO | BN65: Si | BO65: 45730.741 | BP65: Carla Michue M | BR65: 9 | BS65: 07/07/2026 14:23 | BT65: 0 | BX65: Cobranzas_2025.csv | BY65: 2025 | BZ65: 01/01/2024 | CA65: 30/09/2031
A66: RESIDENCIAL PRADA | B66: Etapa 1 | C66: Edificio | D66: A | E66: Estacionamiento | F66: E 15 | G66: 50500 | H66: 50500 | AA66: Ana Fabiola Alvarez Elias | AB66: 06789211 | AC66: Jr. Caraveli 968 Interior 103 | AD66: 0 | AE66: 986642025 | AF66: anafabiola1@hotmail.com | AG66: LIMA | AH66: BREÑA | AI66: 45824 | AJ66: 45824 | AK66: SEPARACION | AL66: 1 | AM66: 3000 | AN66: 0 | AO66: 0 | AP66: 3000 | AQ66: 3000 | AR66: 0 | AS66: 0 | AT66: Crédito Directo | AU66: Scotiabank Perú | AV66: 000-2768484 | AW66: DEPOSITO EN CUENTA | AY66: 005993292 | AZ66: No | BB66: 4 | BC66: CANCELADO | BN66: Si | BO66: 45868.492 | BP66: Magaly Guevara Perez | BR66: 62 | BS66: 18/08/2026 11:26 | BT66: 0 | BX66: Cobranzas_2025.csv | BY66: 2025 | BZ66: 01/01/2024 | CA66: 30/09/2031
A67: RESIDENCIAL PRADA | B67: Etapa 1 | C67: Edificio | D67: A | E67: Estacionamiento | F67: E 15 | G67: 50500 | H67: 50500 | AA67: Ana Fabiola Alvarez Elias | AB67: 06789211 | AC67: Jr. Caraveli 968 Interior 103 | AD67: 0 | AE67: 986642025 | AF67: anafabiola1@hotmail.com | AG67: LIMA | AH67: BREÑA | AI67: 45824 | AJ67: 45824 | AK67: CUOTA INICIAL | AL67: 1 | AM67: 7000 | AN67: 0 | AO67: 0 | AP67: 7000 | AQ67: 7000 | AR67: 0 | AS67: 0 | AT67: Crédito Directo | AU67: Scotiabank Perú | AV67: 000-2768484 | AW67: TRANSFERENCIA BANCARIA | AY67: 0005993292 | AZ67: No | BB67: 4 | BC67: CANCELADO | BN67: Si | BO67: 45868.492 | BP67: Magaly Guevara Perez | BR67: 62 | BS67: 18/08/2026 11:27 | BT67: 0 | BX67: Cobranzas_2025.csv | BY67: 2025 | BZ67: 01/01/2024 | CA67: 30/09/2031
A68: RESIDENCIAL PRADA | B68: Etapa 1 | C68: Edificio | D68: A | E68: Estacionamiento | F68: E 15 | G68: 50500 | H68: 50500 | AA68: Ana Fabiola Alvarez Elias | AB68: 06789211 | AC68: Jr. Caraveli 968 Interior 103 | AD68: 0 | AE68: 986642025 | AF68: anafabiola1@hotmail.com | AG68: LIMA | AH68: BREÑA | AI68: 45868 | AJ68: 45868 | AK68: SALDO FINANCIAR | AL68: 1 | AM68: 3000 | AN68: 0 | AO68: 0 | AP68: 3000 | AQ68: 3000 | AR68: 0 | AS68: 0 | AT68: Crédito Directo | AU68: Scotiabank Perú | AV68: 000-2768484 | AW68: TRANSFERENCIA BANCARIA | AY68: 009170000000276848424 | AZ68: No | BB68: 4 | BC68: CANCELADO | BN68: Si | BO68: 45868.492 | BP68: Magaly Guevara Perez | BR68: 62 | BS68: 18/08/2026 11:28 | BT68: 0 | BX68: Cobranzas_2025.csv | BY68: 2025 | BZ68: 01/01/2024 | CA68: 30/09/2031
A69: RESIDENCIAL PRADA | B69: Etapa 1 | C69: Edificio | D69: A | E69: Estacionamiento | F69: E 15 | G69: 50500 | H69: 50500 | AA69: Ana Fabiola Alvarez Elias | AB69: 06789211 | AC69: Jr. Caraveli 968 Interior 103 | AD69: 0 | AE69: 986642025 | AF69: anafabiola1@hotmail.com | AG69: LIMA | AH69: BREÑA | AI69: 45901 | AJ69: 45901 | AK69: SALDO FINANCIAR | AL69: 2 | AM69: 3000 | AN69: 0 | AO69: 0 | AP69: 3000 | AQ69: 3000 | AR69: 0 | AS69: 0 | AT69: Crédito Directo | AU69: Scotiabank Perú | AV69: 00917000000276848424 | AW69: TRANSFERENCIA BANCARIA | AY69: 00000031360000003138 | AZ69: No | BB69: 4 | BC69: CANCELADO | BN69: Si | BO69: 45868.492 | BP69: Magaly Guevara Perez | BR69: 62 | BS69: 18/08/2026 11:29 | BT69: 0 | BX69: Cobranzas_2025.csv | BY69: 2025 | BZ69: 01/01/2024 | CA69: 30/09/2031
A70: RESIDENCIAL PRADA | B70: Etapa 1 | C70: Edificio | D70: A | E70: Estacionamiento | F70: E 15 | G70: 50500 | H70: 50500 | AA70: Ana Fabiola Alvarez Elias | AB70: 06789211 | AC70: Jr. Caraveli 968 Interior 103 | AD70: 0 | AE70: 986642025 | AF70: anafabiola1@hotmail.com | AG70: LIMA | AH70: BREÑA | AI70: 45931 | AJ70: 45931 | AK70: SALDO FINANCIAR | AL70: 3 | AM70: 3000 | AN70: 0 | AO70: 0 | AP70: 3000 | AQ70: 3000 | AR70: 0 | AS70: 0 | AT70: Crédito Directo | AU70: Scotiabank Perú | AV70: 00917000000276848424 | AW70: TRANSFERENCIA BANCARIA | AY70: 0000320400003206 | AZ70: No | BB70: 4 | BC70: CANCELADO | BN70: Si | BO70: 45868.492 | BP70: Magaly Guevara Perez | BR70: 62 | BS70: 18/08/2026 11:30 | BT70: 0 | BX70: Cobranzas_2025.csv | BY70: 2025 | BZ70: 01/01/2024 | CA70: 30/09/2031
A71: RESIDENCIAL PRADA | B71: Etapa 1 | C71: Edificio | D71: A | E71: Estacionamiento | F71: E 15 | G71: 50500 | H71: 50500 | AA71: Ana Fabiola Alvarez Elias | AB71: 06789211 | AC71: Jr. Caraveli 968 Interior 103 | AD71: 0 | AE71: 986642025 | AF71: anafabiola1@hotmail.com | AG71: LIMA | AH71: BREÑA | AI71: 45958 | AJ71: 45958 | AK71: SALDO FINANCIAR | AL71: 4 | AM71: 3000 | AN71: 0 | AO71: 0 | AP71: 3000 | AQ71: 3000 | AR71: 0 | AS71: 0 | AT71: Crédito Directo | AU71: Scotiabank Perú | AV71: 000-2768484 | AW71: TRANSFERENCIA BANCARIA | AY71: 0000326400003266 | AZ71: No | BB71: 4 | BC71: CANCELADO | BN71: Si | BO71: 45868.492 | BP71: Magaly Guevara Perez | BR71: 62 | BS71: 18/08/2026 11:30 | BT71: 0 | BX71: Cobranzas_2025.csv | BY71: 2025 | BZ71: 01/01/2024 | CA71: 30/09/2031
A72: RESIDENCIAL PRADA | B72: Etapa 1 | C72: Edificio | D72: A | E72: Estacionamiento | F72: E 15 | G72: 50500 | H72: 50500 | AA72: Ana Fabiola Alvarez Elias | AB72: 06789211 | AC72: Jr. Caraveli 968 Interior 103 | AD72: 0 | AE72: 986642025 | AF72: anafabiola1@hotmail.com | AG72: LIMA | AH72: BREÑA | AI72: 45992 | AJ72: 45992 | AK72: SALDO FINANCIAR | AL72: 5 | AM72: 3000 | AN72: 0 | AO72: 0 | AP72: 3000 | AQ72: 3000 | AR72: 0 | AS72: 0 | AT72: Crédito Directo | AU72: Scotiabank Perú | AV72: 00917000000276848424 | AW72: TRANSFERENCIA BANCARIA | AY72: 00003352000003354 | AZ72: No | BB72: 4 | BC72: CANCELADO | BN72: Si | BO72: 45868.492 | BP72: Magaly Guevara Perez | BR72: 62 | BS72: 18/08/2026 11:31 | BT72: 0 | BX72: Cobranzas_2025.csv | BY72: 2025 | BZ72: 01/01/2024 | CA72: 30/09/2031
A73: RESIDENCIAL PRADA | B73: Etapa 1 | C73: Edificio | D73: A | E73: Estacionamiento | F73: E 15 | G73: 50500 | H73: 50500 | AA73: Ana Fabiola Alvarez Elias | AB73: 06789211 | AC73: Jr. Caraveli 968 Interior 103 | AD73: 0 | AE73: 986642025 | AF73: anafabiola1@hotmail.com | AG73: LIMA | AH73: BREÑA | AI73: 46020 | AJ73: 46020 | AK73: SALDO FINANCIAR | AL73: 6 | AM73: 3000 | AN73: 0 | AO73: 0 | AP73: 3000 | AQ73: 3000 | AR73: 0 | AS73: 0 | AT73: Crédito Directo | AU73: Scotiabank Perú | AV73: 00917000000407141928 | AW73: TRANSFERENCIA BANCARIA | AY73: 7844655577681 | AZ73: No | BB73: 4 | BC73: CANCELADO | BN73: Si | BO73: 45868.492 | BP73: Magaly Guevara Perez | BR73: 62 | BS73: 18/08/2026 11:38 | BT73: 0 | BX73: Cobranzas_2025.csv | BY73: 2025 | BZ73: 01/01/2024 | CA73: 30/09/2031
A74: RESIDENCIAL VENECIA | B74: Etapa 1 | C74: Edificio | D74: A | E74: Departamento | F74: 704 | G74: 438000 | H74: 438000 | AA74: ANAMELVA JULIETA AQUISE TIZNADO | AB74: 40917666 | AC74: Urb. Aziruni Ciudad Jardin Mz. G2 Lt 04 | AD74: 0 | AE74: 987249596 | AF74: anamelvaaquise@gmail.com | AG74: PUNO | AH74: PUNO | AI74: 45972 | AJ74: 45972 | AK74: SEPARACION | AL74: 1 | AM74: 3000 | AN74: 0 | AO74: 0 | AP74: 3000 | AQ74: 3000 | AR74: 0 | AS74: 0 | AT74: Crédito Hipotecario | AU74: Scotiabank Perú | AV74: 0004071419 | AW74: TRANSFERENCIA BANCARIA | AY74: 5516474 | AZ74: No | BB74: 4 | BC74: CANCELADO | BN74: Si | BO74: 46178.351 | BP74: Magaly Guevara Perez | BR74: 14 | BS74: 24/05/2026 21:14 | BT74: 0 | BX74: Cobranzas_2025.csv | BY74: 2025 | BZ74: 01/01/2024 | CA74: 30/09/2031
A75: RESIDENCIAL VENECIA | B75: Etapa 1 | C75: Edificio | D75: A | E75: Departamento | F75: 704 | G75: 438000 | H75: 438000 | AA75: ANAMELVA JULIETA AQUISE TIZNADO | AB75: 40917666 | AC75: Urb. Aziruni Ciudad Jardin Mz. G2 Lt 04 | AD75: 0 | AE75: 987249596 | AF75: anamelvaaquise@gmail.com | AG75: PUNO | AH75: PUNO | AI75: 46004 | AJ75: 46004 | AK75: CUOTA INICIAL | AL75: 1 | AM75: 20000 | AN75: 0 | AO75: 0 | AP75: 20000 | AQ75: 20000 | AR75: 0 | AS75: 0 | AT75: Crédito Hipotecario | AU75: Scotiabank Perú | AV75: 0004071419 | AW75: TRANSFERENCIA BANCARIA | AY75: 5531532 | AZ75: No | BB75: 4 | BC75: CANCELADO | BN75: Si | BO75: 46178.351 | BP75: Magaly Guevara Perez | BR75: 14 | BS75: 24/05/2026 21:16 | BT75: 0 | BX75: Cobranzas_2025.csv | BY75: 2025 | BZ75: 01/01/2024 | CA75: 30/09/2031
A76: RESIDENCIAL PRADA | B76: Etapa 1 | C76: Edificio | D76: A | E76: Departamento | F76: 1003 | G76: 675000 | H76: 675000 | I76: Edificio | J76: A | K76: Estacionamiento | L76: E 11 - D 08 | M76: 60400 | N76: 60400 | AA76: ANDEAN AYNI TRAVEL AGENCIA DE VIAJES Y TRANSPORTE EIRL | AB76: 20610697403 | AC76: JR. DANTE NAVA NRO. 310 BAR. NUEVA UNVERSIDAD | AD76: 0 | AE76: 951923088 | AF76: operacionesjudith@gmail.com | AG76: PUNO | AH76: PUNO | AI76: 45835 | AJ76: 45835 | AK76: SEPARACION | AL76: 1 | AM76: 3000 | AN76: 0 | AO76: 0 | AP76: 3000 | AQ76: 3000 | AR76: 0 | AS76: 0 | AT76: Crédito Directo | AU76: Scotiabank Perú | AV76: 000-2768484 | AW76: TRANSFERENCIA BANCARIA | AY76: 06083805 | AZ76: Si | BB76: 4 | BC76: CANCELADO | BN76: Si | BO76: 45985.738 | BP76: Magaly Guevara Perez | BR76: 28 | BS76: 09/06/2026 09:42 | BT76: 0 | BX76: Cobranzas_2025.csv | BY76: 2025 | BZ76: 01/01/2024 | CA76: 30/09/2031
A77: RESIDENCIAL PRADA | B77: Etapa 1 | C77: Edificio | D77: A | E77: Departamento | F77: 1003 | G77: 675000 | H77: 675000 | I77: Edificio | J77: A | K77: Estacionamiento | L77: E 11 - D 08 | M77: 60400 | N77: 60400 | AA77: ANDEAN AYNI TRAVEL AGENCIA DE VIAJES Y TRANSPORTE EIRL | AB77: 20610697403 | AC77: JR. DANTE NAVA NRO. 310 BAR. NUEVA UNVERSIDAD | AD77: 0 | AE77: 951923088 | AF77: operacionesjudith@gmail.com | AG77: PUNO | AH77: PUNO | AI77: 45985 | AJ77: 45985 | AK77: CUOTA INICIAL | AL77: 1 | AM77: 270000 | AN77: 0 | AO77: 0 | AP77: 270000 | AQ77: 270000 | AR77: 0 | AS77: 0 | AT77: Crédito Directo | AU77: Scotiabank Perú | AV77: 000-2768484 | AW77: TRANSFERENCIA BANCARIA | AY77: 0349568 | AZ77: Si | BB77: 3.38 | BC77: CANCELADO | BN77: Si | BO77: 45985.738 | BP77: Magaly Guevara Perez | BR77: 28 | BS77: 09/06/2026 09:45 | BT77: 0 | BX77: Cobranzas_2025.csv | BY77: 2025 | BZ77: 01/01/2024 | CA77: 30/09/2031
A78: RESIDENCIAL PRADA | B78: Etapa 1 | C78: Edificio | D78: A | E78: Departamento | F78: 1003 | G78: 675000 | H78: 675000 | I78: Edificio | J78: A | K78: Estacionamiento | L78: E 11 - D 08 | M78: 60400 | N78: 60400 | AA78: ANDEAN AYNI TRAVEL AGENCIA DE VIAJES Y TRANSPORTE EIRL | AB78: 20610697403 | AC78: JR. DANTE NAVA NRO. 310 BAR. NUEVA UNVERSIDAD | AD78: 0 | AE78: 951923088 | AF78: operacionesjudith@gmail.com | AG78: PUNO | AH78: PUNO | AI78: 46008 | AJ78: 46010 | AK78: SALDO FINANCIAR | AL78: 1 | AM78: 66057.14 | AN78: 0 | AO78: 0 | AP78: 66057.14 | AQ78: 66057.14 | AR78: 0 | AS78: 0 | AT78: Crédito Directo | AU78: Scotiabank Perú | AV78: 000-2768484 | AW78: TRANSFERENCIA BANCARIA | AY78: 0780435 | AZ78: Si | BB78: 3.38 | BC78: CANCELADO | BN78: Si | BO78: 45985.738 | BP78: Magaly Guevara Perez | BR78: 28 | BS78: 09/06/2026 09:47 | BT78: 0 | BX78: Cobranzas_2025.csv | BY78: 2025 | BZ78: 01/01/2024 | CA78: 30/09/2031
A79: RESIDENCIAL PRADA | B79: Etapa 1 | C79: Edificio | D79: A | E79: Estacionamiento | F79: E 14 - D 11 | G79: 56300 | H79: 56300 | AA79: Ayleen Katia Messarina Rios | AB79: 70512701 | AC79: Departamento 101 Urbanización Santa Rosa de Surco etapa 2 Mz D Lt 23 | AD79: 978722675 | AE79: 978722675 | AF79: ayleen30mr@gmail.com | AG79: LIMA | AH79: SANTIAGO DE SURCO | AI79: 45748 | AJ79: 45748 | AK79: SALDO FINANCIAR | AL79: 1 | AM79: 3800 | AN79: 0 | AO79: 0 | AP79: 3800 | AQ79: 3800 | AR79: 0 | AS79: 0 | AT79: Crédito Directo | AU79: Scotiabank Perú | AV79: 000-2768484 | AW79: TRANSFERENCIA BANCARIA | AY79: 01459586 | AZ79: Si | BB79: 4 | BC79: CANCELADO | BN79: Si | BO79: 45748.63 | BP79: Magaly Guevara Perez | BR79: 56 | BS79: 28/06/2026 21:23 | BT79: 0 | BX79: Cobranzas_2025.csv | BY79: 2025 | BZ79: 01/01/2024 | CA79: 30/09/2031
A80: RESIDENCIAL PRADA | B80: Etapa 1 | C80: Edificio | D80: A | E80: Estacionamiento | F80: E 14 - D 11 | G80: 56300 | H80: 56300 | AA80: Ayleen Katia Messarina Rios | AB80: 70512701 | AC80: Departamento 101 Urbanización Santa Rosa de Surco etapa 2 Mz D Lt 23 | AD80: 978722675 | AE80: 978722675 | AF80: ayleen30mr@gmail.com | AG80: LIMA | AH80: SANTIAGO DE SURCO | AI80: 45778 | AJ80: 45796 | AK80: SALDO FINANCIAR | AL80: 2 | AM80: 3800 | AN80: 0 | AO80: 0 | AP80: 3800 | AQ80: 3800 | AR80: 0 | AS80: 0 | AT80: Crédito Directo | AU80: Scotiabank Perú | AV80: 000-2768484 | AW80: TRANSFERENCIA BANCARIA | AY80: 03388134 | AZ80: Si | BB80: 4 | BC80: CANCELADO | BN80: Si | BO80: 45748.63 | BP80: Magaly Guevara Perez | BR80: 56 | BS80: 28/06/2026 21:24 | BT80: 0 | BX80: Cobranzas_2025.csv | BY80: 2025 | BZ80: 01/01/2024 | CA80: 30/09/2031
A81: RESIDENCIAL PRADA | B81: Etapa 1 | C81: Edificio | D81: A | E81: Estacionamiento | F81: E 14 - D 11 | G81: 56300 | H81: 56300 | AA81: Ayleen Katia Messarina Rios | AB81: 70512701 | AC81: Departamento 101 Urbanización Santa Rosa de Surco etapa 2 Mz D Lt 23 | AD81: 978722675 | AE81: 978722675 | AF81: ayleen30mr@gmail.com | AG81: LIMA | AH81: SANTIAGO DE SURCO | AI81: 45809 | AJ81: 45810 | AK81: SALDO FINANCIAR | AL81: 3 | AM81: 3800 | AN81: 0 | AO81: 0 | AP81: 3800 | AQ81: 3800 | AR81: 0 | AS81: 0 | AT81: Crédito Directo | AU81: Scotiabank Perú | AV81: 000-2768484 | AW81: TRANSFERENCIA BANCARIA | AY81: 03577668 | AZ81: Si | BB81: 4 | BC81: CANCELADO | BN81: Si | BO81: 45748.63 | BP81: Magaly Guevara Perez | BR81: 56 | BS81: 28/06/2026 21:25 | BT81: 0 | BX81: Cobranzas_2025.csv | BY81: 2025 | BZ81: 01/01/2024 | CA81: 30/09/2031
A82: RESIDENCIAL PRADA | B82: Etapa 1 | C82: Edificio | D82: A | E82: Estacionamiento | F82: E 14 - D 11 | G82: 56300 | H82: 56300 | AA82: Ayleen Katia Messarina Rios | AB82: 70512701 | AC82: Departamento 101 Urbanización Santa Rosa de Surco etapa 2 Mz D Lt 23 | AD82: 978722675 | AE82: 978722675 | AF82: ayleen30mr@gmail.com | AG82: LIMA | AH82: SANTIAGO DE SURCO | AI82: 45839 | AJ82: 45838 | AK82: SALDO FINANCIAR | AL82: 4 | AM82: 3800 | AN82: 0 | AO82: 0 | AP82: 3800 | AQ82: 3800 | AR82: 0 | AS82: 0 | AT82: Crédito Directo | AU82: Scotiabank Perú | AV82: 000-2768484 | AW82: TRANSFERENCIA BANCARIA | AY82: 04294427 | AZ82: Si | BB82: 4 | BC82: CANCELADO | BN82: Si | BO82: 45748.63 | BP82: Magaly Guevara Perez | BR82: 56 | BS82: 28/06/2026 21:26 | BT82: 0 | BX82: Cobranzas_2025.csv | BY82: 2025 | BZ82: 01/01/2024 | CA82: 30/09/2031
A83: RESIDENCIAL PRADA | B83: Etapa 1 | C83: Edificio | D83: A | E83: Estacionamiento | F83: E 14 - D 11 | G83: 56300 | H83: 56300 | AA83: Ayleen Katia Messarina Rios | AB83: 70512701 | AC83: Departamento 101 Urbanización Santa Rosa de Surco etapa 2 Mz D Lt 23 | AD83: 978722675 | AE83: 978722675 | AF83: ayleen30mr@gmail.com | AG83: LIMA | AH83: SANTIAGO DE SURCO | AI83: 45870 | AJ83: 45868 | AK83: SALDO FINANCIAR | AL83: 5 | AM83: 3800 | AN83: 0 | AO83: 0 | AP83: 3800 | AQ83: 3800 | AR83: 0 | AS83: 0 | AT83: Crédito Directo | AU83: Scotiabank Perú | AV83: 000-2768484 | AW83: TRANSFERENCIA BANCARIA | AY83: 05185364 | AZ83: Si | BB83: 4 | BC83: CANCELADO | BN83: Si | BO83: 45748.63 | BP83: Magaly Guevara Perez | BR83: 56 | BS83: 28/06/2026 21:30 | BT83: 0 | BX83: Cobranzas_2025.csv | BY83: 2025 | BZ83: 01/01/2024 | CA83: 30/09/2031
A84: RESIDENCIAL PRADA | B84: Etapa 1 | C84: Edificio | D84: A | E84: Estacionamiento | F84: E 14 - D 11 | G84: 56300 | H84: 56300 | AA84: Ayleen Katia Messarina Rios | AB84: 70512701 | AC84: Departamento 101 Urbanización Santa Rosa de Surco etapa 2 Mz D Lt 23 | AD84: 978722675 | AE84: 978722675 | AF84: ayleen30mr@gmail.com | AG84: LIMA | AH84: SANTIAGO DE SURCO | AI84: 45901 | AJ84: 45902 | AK84: SALDO FINANCIAR | AL84: 6 | AM84: 3800 | AN84: 0 | AO84: 0 | AP84: 3800 | AQ84: 3800 | AR84: 0 | AS84: 0 | AT84: Crédito Directo | AU84: Scotiabank Perú | AV84: 000-2768484 | AW84: TRANSFERENCIA BANCARIA | AY84: 00510042 | AZ84: Si | BB84: 4 | BC84: CANCELADO | BN84: Si | BO84: 45748.63 | BP84: Magaly Guevara Perez | BR84: 56 | BS84: 28/06/2026 21:31 | BT84: 0 | BX84: Cobranzas_2025.csv | BY84: 2025 | BZ84: 01/01/2024 | CA84: 30/09/2031
A85: RESIDENCIAL PRADA | B85: Etapa 1 | C85: Edificio | D85: A | E85: Estacionamiento | F85: E 14 - D 11 | G85: 56300 | H85: 56300 | AA85: Ayleen Katia Messarina Rios | AB85: 70512701 | AC85: Departamento 101 Urbanización Santa Rosa de Surco etapa 2 Mz D Lt 23 | AD85: 978722675 | AE85: 978722675 | AF85: ayleen30mr@gmail.com | AG85: LIMA | AH85: SANTIAGO DE SURCO | AI85: 45931 | AJ85: 45942 | AK85: SALDO FINANCIAR | AL85: 7 | AM85: 3800 | AN85: 0 | AO85: 0 | AP85: 3800 | AQ85: 3800 | AR85: 0 | AS85: 0 | AT85: Crédito Directo | AU85: Scotiabank Perú | AV85: 000-2768484 | AW85: TRANSFERENCIA BANCARIA | AY85: 02106124 | AZ85: Si | BB85: 4 | BC85: CANCELADO | BN85: Si | BO85: 45748.63 | BP85: Magaly Guevara Perez | BR85: 56 | BS85: 28/06/2026 21:31 | BT85: 0 | BX85: Cobranzas_2025.csv | BY85: 2025 | BZ85: 01/01/2024 | CA85: 30/09/2031
A86: RESIDENCIAL PRADA | B86: Etapa 1 | C86: Edificio | D86: A | E86: Estacionamiento | F86: E 14 - D 11 | G86: 56300 | H86: 56300 | AA86: Ayleen Katia Messarina Rios | AB86: 70512701 | AC86: Departamento 101 Urbanización Santa Rosa de Surco etapa 2 Mz D Lt 23 | AD86: 978722675 | AE86: 978722675 | AF86: ayleen30mr@gmail.com | AG86: LIMA | AH86: SANTIAGO DE SURCO | AI86: 45962 | AJ86: 45980 | AK86: SALDO FINANCIAR | AL86: 8 | AM86: 3800 | AN86: 0 | AO86: 0 | AP86: 3800 | AQ86: 3800 | AR86: 0 | AS86: 0 | AT86: Crédito Directo | AU86: Scotiabank Perú | AV86: 000-2768484 | AW86: TRANSFERENCIA BANCARIA | AY86: 00374413 | AZ86: Si | BB86: 4 | BC86: CANCELADO | BN86: Si | BO86: 45748.63 | BP86: Magaly Guevara Perez | BR86: 56 | BS86: 28/06/2026 21:32 | BT86: 0 | BX86: Cobranzas_2025.csv | BY86: 2025 | BZ86: 01/01/2024 | CA86: 30/09/2031
A87: RESIDENCIAL PRADA | B87: Etapa 1 | C87: Edificio | D87: A | E87: Estacionamiento | F87: E 14 - D 11 | G87: 56300 | H87: 56300 | AA87: Ayleen Katia Messarina Rios | AB87: 70512701 | AC87: Departamento 101 Urbanización Santa Rosa de Surco etapa 2 Mz D Lt 23 | AD87: 978722675 | AE87: 978722675 | AF87: ayleen30mr@gmail.com | AG87: LIMA | AH87: SANTIAGO DE SURCO | AI87: 45992 | AJ87: 46033 | AK87: SALDO FINANCIAR | AL87: 9 | AM87: 3800 | AN87: 0 | AO87: 0 | AP87: 3800 | AQ87: 3800 | AR87: 0 | AS87: 0 | AT87: Crédito Directo | AU87: Scotiabank Perú | AV87: 000-2768484 | AW87: TRANSFERENCIA BANCARIA | AY87: 01802980 | AZ87: Si | BB87: 4 | BC87: CANCELADO | BN87: Si | BO87: 45748.63 | BP87: Magaly Guevara Perez | BR87: 56 | BS87: 28/06/2026 21:33 | BT87: 0 | BX87: Cobranzas_2025.csv | BY87: 2025 | BZ87: 01/01/2024 | CA87: 30/09/2031
A88: RESIDENCIAL VENECIA | B88: Etapa 1 | C88: Edificio | D88: A | E88: Departamento | F88: 204 | G88: 483000 | H88: 443000 | I88: Edificio | J88: A | K88: Estacionamiento | L88: E 14 - D 4 | M88: 42800 | N88: 42800 | AA88: Carlos La Cruz Crespo | AB88: 09022488 | AC88: comas | AD88: 0 | AE88: 997009340 | AF88: carlos.14lacruz@gmail.com | AG88: LIMA | AH88: COMAS | AI88: 45795 | AJ88: 45795 | AK88: SEPARACION | AL88: 1 | AM88: 3000 | AN88: 0 | AO88: 0 | AP88: 3000 | AQ88: 1000 | AR88: 0 | AS88: 0 | AT88: Crédito Directo | AU88: Scotiabank Perú | AV88: 0004071419 | AW88: TRANSFERENCIA BANCARIA | AY88: 473500004737 | AZ88: No | BB88: 4 | BC88: CANCELADO | BN88: Si | BO88: 45839.335 | BP88: Magaly Guevara Perez | BR88: 2 | BS88: 18/08/2026 13:41 | BT88: 0 | BX88: Cobranzas_2025.csv | BY88: 2025 | BZ88: 01/01/2024 | CA88: 30/09/2031
A89: RESIDENCIAL VENECIA | B89: Etapa 1 | C89: Edificio | D89: A | E89: Departamento | F89: 204 | G89: 483000 | H89: 443000 | I89: Edificio | J89: A | K89: Estacionamiento | L89: E 14 - D 4 | M89: 42800 | N89: 42800 | AA89: Carlos La Cruz Crespo | AB89: 09022488 | AC89: comas | AD89: 0 | AE89: 997009340 | AF89: carlos.14lacruz@gmail.com | AG89: LIMA | AH89: COMAS | AI89: 45795 | AJ89: 45797 | AK89: SEPARACION | AL89: 1 | AM89: 0 | AN89: 0 | AO89: 0 | AP89: 0 | AQ89: 2000 | AR89: 0 | AS89: 0 | AT89: Crédito Directo | AU89: Scotiabank Perú | AV89: 0004071419 | AW89: TRANSFERENCIA BANCARIA | AY89: 474400004746 | AZ89: No | BB89: 4 | BC89: CANCELADO | BN89: Si | BO89: 45839.335 | BP89: Magaly Guevara Perez | BR89: 2 | BS89: 18/08/2026 13:41 | BT89: 0 | BX89: Cobranzas_2025.csv | BY89: 2025 | BZ89: 01/01/2024 | CA89: 30/09/2031
A90: RESIDENCIAL PRADA | B90: Etapa 1 | C90: Edificio | D90: A | E90: Departamento | F90: 601 | G90: 630000 | H90: 630000 | I90: Edificio | J90: A | K90: Estacionamiento | L90: E 28 - D 22 | M90: 60000 | N90: 60000 | AA90: Chistopher Omar Peña Camargo | AB90: 44062837 | AC90: Av. San Felipe 351 | AE90: 964328569 | AF90: ciruvision@gmail.com | AG90: LIMA | AH90: JESUS MARIA | AI90: 45804 | AJ90: 45804 | AK90: SEPARACION | AL90: 1 | AM90: 3000 | AN90: 0 | AO90: 0 | AP90: 3000 | AQ90: 3000 | AR90: 0 | AS90: 0 | AT90: Crédito Hipotecario | AU90: Scotiabank Perú | AV90: 000-2768484 | AW90: TRANSFERENCIA BANCARIA | AY90: 00002220000000002222 | AZ90: No | BB90: 4 | BC90: CANCELADO | BN90: Si | BO90: 45831.692 | BP90: Carla Michue M | BR90: 12 | BS90: 03/07/2026 14:39 | BT90: 0 | BX90: Cobranzas_2025.csv | BY90: 2025 | BZ90: 01/01/2024 | CA90: 30/09/2031
A91: RESIDENCIAL PRADA | B91: Etapa 1 | C91: Edificio | D91: A | E91: Departamento | F91: 601 | G91: 630000 | H91: 630000 | I91: Edificio | J91: A | K91: Estacionamiento | L91: E 28 - D 22 | M91: 60000 | N91: 60000 | AA91: Chistopher Omar Peña Camargo | AB91: 44062837 | AC91: Av. San Felipe 351 | AE91: 964328569 | AF91: ciruvision@gmail.com | AG91: LIMA | AH91: JESUS MARIA | AI91: 45831 | AJ91: 45831 | AK91: CUOTA INICIAL | AL91: 2 | AM91: 107000 | AN91: 0 | AO91: 0 | AP91: 107000 | AQ91: 107000 | AR91: 0 | AS91: 0 | AT91: Crédito Hipotecario | AU91: Scotiabank Perú | AV91: 000-2768484 | AW91: TRANSFERENCIA BANCARIA | AX91: 44062837 | AY91: 006128332 | AZ91: No | BA91: NO PRECISA | BB91: 1 | BC91: CANCELADO | BN91: Si | BO91: 45831.692 | BP91: Carla Michue M | BR91: 12 | BS91: 29/05/2026 12:21 | BT91: 0 | BX91: Cobranzas_2025.csv | BY91: 2025 | BZ91: 01/01/2024 | CA91: 30/09/2031
A92: RESIDENCIAL PRADA | B92: Etapa 1 | C92: Edificio | D92: A | E92: Departamento | F92: 601 | G92: 630000 | H92: 630000 | I92: Edificio | J92: A | K92: Estacionamiento | L92: E 28 - D 22 | M92: 60000 | N92: 60000 | AA92: Chistopher Omar Peña Camargo | AB92: 44062837 | AC92: Av. San Felipe 351 | AE92: 964328569 | AF92: ciruvision@gmail.com | AG92: LIMA | AH92: JESUS MARIA | AI92: 45868 | AJ92: 45936 | AK92: SALDO FINANCIAR | AL92: 1 | AM92: 580000 | AN92: 0 | AO92: 0 | AP92: 580000 | AQ92: 580000 | AR92: 0 | AS92: 0 | AT92: Crédito Hipotecario | AU92: Scotiabank Perú | AV92: 000-2768484 | AW92: TRANSFERENCIA BANCARIA | AY92: EB01-137 | AZ92: No | BB92: 4 | BC92: CANCELADO | BN92: Si | BO92: 45831.692 | BP92: Carla Michue M | BR92: 12 | BS92: 14/08/2026 11:43 | BT92: 0 | BX92: Cobranzas_2025.csv | BY92: 2025 | BZ92: 01/01/2024 | CA92: 30/09/2031
A93: RESIDENCIAL PRADA | B93: Etapa 1 | C93: Edificio | D93: A | E93: Departamento | F93: 302 | G93: 435500 | H93: 435500 | AA93: Cristhiam Ortiz Angeles | AB93: 45110882 | AC93: Av. Olavegoya 1879 departamento 301 | AD93: 992532732 | AE93: 992532732 | AF93: Cristhian4520@gmail.com | AG93: LIMA | AH93: JESUS MARIA | AI93: 45688 | AJ93: 45838 | AK93: SALDO FINANCIAR | AL93: 1 | AM93: 370950 | AN93: 0 | AO93: 0 | AP93: 370950 | AQ93: 370950 | AR93: 0 | AS93: 0 | AT93: Crédito Hipotecario | AU93: Scotiabank Perú | AV93: 000-2768484 | AW93: TRANSFERENCIA BANCARIA | AY93: EB01-76 | AZ93: No | BB93: 4 | BC93: CANCELADO | BN93: Si | BO93: 45499.613 | BP93: Kenny Salazar S | BR93: 34 | BS93: 07/07/2026 08:58 | BT93: 0 | BX93: Cobranzas_2025.csv | BY93: 2025 | BZ93: 01/01/2024 | CA93: 30/09/2031
A94: RESIDENCIAL PRADA | B94: Etapa 1 | C94: Edificio | D94: A | E94: Departamento | F94: 902 | G94: 433500 | H94: 433500 | I94: Edificio | J94: A | K94: Estacionamiento | L94: E 43 | M94: 50500 | N94: 50500 | AA94: Daniel Alejandro Aguayo Vera | AB94: 76121899 | AC94: Calle los Rosales 743 Lima- Chaclacayo. | AD94: 943151339 | AE94: 943151339 | AF94: daniel_aguayo25@hotmail.com | AG94: LIMA | AH94: SAN ISIDRO | AI94: 45985 | AJ94: 45985 | AK94: SEPARACION | AL94: 1 | AM94: 3000 | AN94: 0 | AO94: 0 | AP94: 3000 | AQ94: 3000 | AR94: 0 | AS94: 0 | AT94: Crédito Hipotecario | AU94: Scotiabank Perú | AV94: 000-2768484 | AW94: TRANSFERENCIA BANCARIA | AY94: 05149943 | AZ94: No | BB94: 4 | BC94: CANCELADO | BN94: Si | BO94: 46008.744 | BP94: Kenny Salazar S | BR94: 41 | BS94: 03/06/2026 09:48 | BT94: 0 | BX94: Cobranzas_2025.csv | BY94: 2025 | BZ94: 01/01/2024 | CA94: 30/09/2031
A95: RESIDENCIAL PRADA | B95: Etapa 1 | C95: Edificio | D95: A | E95: Departamento | F95: 902 | G95: 433500 | H95: 433500 | I95: Edificio | J95: A | K95: Estacionamiento | L95: E 43 | M95: 50500 | N95: 50500 | AA95: Daniel Alejandro Aguayo Vera | AB95: 76121899 | AC95: Calle los Rosales 743 Lima- Chaclacayo. | AD95: 943151339 | AE95: 943151339 | AF95: daniel_aguayo25@hotmail.com | AG95: LIMA | AH95: SAN ISIDRO | AI95: 46008 | AJ95: 46008 | AK95: CUOTA INICIAL | AL95: 1 | AM95: 45400 | AN95: 0 | AO95: 0 | AP95: 45400 | AQ95: 45400 | AR95: 0 | AS95: 0 | AT95: Crédito Hipotecario | AU95: Scotiabank Perú | AV95: 00917000000276848424 | AW95: TRANSFERENCIA BANCARIA | AX95: 76121899 | AY95: 0797612 | AZ95: No | BB95: 4 | BC95: CANCELADO | BN95: Si | BO95: 46008.744 | BP95: Kenny Salazar S | BR95: 41 | BS95: 05/06/2026 13:42 | BT95: 0 | BX95: Cobranzas_2025.csv | BY95: 2025 | BZ95: 01/01/2024 | CA95: 30/09/2031
A96: RESIDENCIAL BEYOND | B96: Etapa 1 | C96: Edificio | D96: A | E96: Departamento | F96: 302 | G96: 430000 | H96: 381000 | AA96: Danixa Thalia Manosalva Ameri | AB96: 48569476 | AC96: Jr. Huáscar 1825 dpto.101 | AD96: 0 | AE96: 992382005 | AF96: danixamanosalva94@gmail.com | AG96: LIMA | AH96: JESUS MARIA | AI96: 45932 | AJ96: 45932 | AK96: SEPARACION | AL96: 1 | AM96: 3000 | AN96: 0 | AO96: 0 | AP96: 3000 | AQ96: 3000 | AR96: 0 | AS96: 0 | AT96: Ahorro | AU96: Banco de Credito del Perú | AV96: 194-7325779-0-65 | AW96: TRANSFERENCIA BANCARIA | AY96: 04998185 | AZ96: No | BB96: 4 | BC96: CANCELADO | BN96: Si | BO96: 45940.419 | BP96: Magaly Guevara Perez | BR96: 6 | BS96: 01/05/2026 11:35 | BT96: 0 | BX96: Cobranzas_2025.csv | BY96: 2025 | BZ96: 01/01/2024 | CA96: 30/09/2031
A97: RESIDENCIAL BEYOND | B97: Etapa 1 | C97: Edificio | D97: A | E97: Departamento | F97: 302 | G97: 430000 | H97: 381000 | AA97: Danixa Thalia Manosalva Ameri | AB97: 48569476 | AC97: Jr. Huáscar 1825 dpto.101 | AD97: 0 | AE97: 992382005 | AF97: danixamanosalva94@gmail.com | AG97: LIMA | AH97: JESUS MARIA | AI97: 45940 | AJ97: 45940 | AK97: CUOTA INICIAL | AL97: 1 | AM97: 17000 | AN97: 0 | AO97: 0 | AP97: 17000 | AQ97: 17000 | AR97: 0 | AS97: 0 | AT97: Ahorro | AU97: Banco de Credito del Perú | AV97: 194-7325779-0-65 | AW97: TRANSFERENCIA BANCARIA | AY97: 04077899 | AZ97: No | BB97: 4 | BC97: CANCELADO | BN97: Si | BO97: 45940.419 | BP97: Magaly Guevara Perez | BR97: 6 | BS97: 12/08/2026 17:43 | BT97: 0 | BX97: Cobranzas_2025.csv | BY97: 2025 | BZ97: 01/01/2024 | CA97: 30/09/2031
A98: RESIDENCIAL BEYOND | B98: Etapa 1 | C98: Edificio | D98: A | E98: Departamento | F98: 302 | G98: 430000 | H98: 381000 | AA98: Danixa Thalia Manosalva Ameri | AB98: 48569476 | AC98: Jr. Huáscar 1825 dpto.101 | AD98: 0 | AE98: 992382005 | AF98: danixamanosalva94@gmail.com | AG98: LIMA | AH98: JESUS MARIA | AI98: 45965 | AJ98: 45965 | AK98: CUOTA INICIAL | AL98: 2 | AM98: 44000 | AN98: 0 | AO98: 0 | AP98: 44000 | AQ98: 22000 | AR98: 0 | AS98: 0 | AT98: Ahorro | AU98: Banco de Credito del Perú | AV98: 194-7325779-0-65 | AW98: TRANSFERENCIA BANCARIA | AY98: 04571213 | AZ98: No | BB98: 4 | BC98: CANCELADO | BN98: Si | BO98: 45940.419 | BP98: Magaly Guevara Perez | BR98: 6 | BS98: 12/08/2026 17:46 | BT98: 0 | BX98: Cobranzas_2025.csv | BY98: 2025 | BZ98: 01/01/2024 | CA98: 30/09/2031
A99: RESIDENCIAL BEYOND | B99: Etapa 1 | C99: Edificio | D99: A | E99: Departamento | F99: 302 | G99: 430000 | H99: 381000 | AA99: Danixa Thalia Manosalva Ameri | AB99: 48569476 | AC99: Jr. Huáscar 1825 dpto.101 | AD99: 0 | AE99: 992382005 | AF99: danixamanosalva94@gmail.com | AG99: LIMA | AH99: JESUS MARIA | AI99: 45965 | AJ99: 45965 | AK99: CUOTA INICIAL | AL99: 2 | AM99: 0 | AN99: 0 | AO99: 0 | AP99: 0 | AQ99: 22000 | AR99: 0 | AS99: 0 | AT99: Ahorro | AU99: Banco de Credito del Perú | AV99: 194-7325779-0-65 | AW99: TRANSFERENCIA BANCARIA | AY99: 04576779 | AZ99: No | BB99: 4 | BC99: CANCELADO | BN99: Si | BO99: 45940.419 | BP99: Magaly Guevara Perez | BR99: 6 | BS99: 12/08/2026 17:46 | BT99: 0 | BX99: Cobranzas_2025.csv | BY99: 2025 | BZ99: 01/01/2024 | CA99: 30/09/2031
A100: RESIDENCIAL PRADA | B100: Etapa 1 | C100: Edificio | D100: A | E100: Departamento | F100: 1001 | G100: 615000 | H100: 615000 | AA100: Danny Romel Ore Guerreros | AB100: 47474967 | AC100: Psj. Ollantay 7 Barrio Vista Alegre | AD100: 966327809 | AE100: 966327809 | AF100: romelore67@gmail.com | AG100: HUAMANGA | AH100: CARMEN ALTO | AI100: 45867 | AJ100: 45867 | AK100: SEPARACION | AL100: 1 | AM100: 3000 | AN100: 0 | AO100: 0 | AP100: 3000 | AQ100: 3000 | AR100: 0 | AS100: 0 | AT100: Crédito Hipotecario | AU100: Scotiabank Perú | AV100: 000-2768484 | AW100: TRANSFERENCIA BANCARIA | AX100: 47474967 | AY100: 01135502 | AZ100: No | BA100: NO PRECISA | BB100: 4 | BC100: CANCELADO | BN100: Si | BO100: 45885.587 | BP100: Kenny Salazar S | BR100: 47 | BS100: 03/06/2026 15:03 | BT100: 0 | BX100: Cobranzas_2025.csv | BY100: 2025 | BZ100: 01/01/2024 | CA100: 30/09/2031
...

Sheet Prada
C5: REPORTE DE COBRANZAS
B6: Prada
C8: Vendido | F8: Cobranzas
C9: Monto | D9: Unidades | F9: Avance | G9: Cobrado | H9: Por Cobrar | I9: Vencido | J9: Tasa de Morosidad | K9: Clientes Morosos (unidades) | L9: Dias de Atraso (Promedio)
B11: Departamentos | C11: 25253600 | D11: 62 | F11: =IF(C11=0,0,G11/C11) | G11: =SUM(G12:G13) | H11: =SUM(H12:H13) | I11: =SUM(I12:I13) | J11: =IF(C11=0,0,I11/C11) | K11: 7 | L11: 90
B12: Departamento | C12: 16401100 | D12: 31 | F12: =IF(C12=0,0,G12/C12) | G12: =IFERROR(SUMPRODUCT(--ISNUMBER(SEARCH($B$6,'Base_Cobranzas'!$A$2:$A$1005)),--((--ISNUMBER(SEARCH("DEPART",UPPER('Base_Cobranzas'!$E$2:$E$1005)))+--ISNUMBER(SEARCH("DEPART",UPPER('Base_Cobranzas'!$K$2:$K$1005)))+--ISNUMBER(SEARCH("DEPART",UPPER('Base_Cobranzas'!$Q$2:$Q$1005)))+--ISNUMBER(SEARCH("DEPART",UPPER('Base_Cobranzas'!$W$2:$W$1005))))>0),--((--ISNUMBER(SEARCH("ESTACION",UPPER('Base_Cobranzas'!$E$2:$E$1005)))+--ISNUMBER(SEARCH("ESTACION",UPPER('Base_Cobranzas'!$K$2:$K$1005)))+--ISNUMBER(SEARCH("ESTACION",UPPER('Base_Cobranzas'!$Q$2:$Q$1005)))+--ISNUMBER(SEARCH("ESTACION",UPPER('Base_Cobranzas'!$W$2:$W$1005))))=0),--('Base_Cobranzas'!$AQ$2:$AQ$1005>0),'Base_Cobranzas'!$AQ$2:$AQ$1005),0) | H12: =IFERROR(SUMPRODUCT(--ISNUMBER(SEARCH($B$6,'Base_Cobranzas'!$A$2:$A$1005)),--((--ISNUMBER(SEARCH("DEPART",UPPER('Base_Cobranzas'!$E$2:$E$1005)))+--ISNUMBER(SEARCH("DEPART",UPPER('Base_Cobranzas'!$K$2:$K$1005)))+--ISNUMBER(SEARCH("DEPART",UPPER('Base_Cobranzas'!$Q$2:$Q$1005)))+--ISNUMBER(SEARCH("DEPART",UPPER('Base_Cobranzas'!$W$2:$W$1005))))>0),--((--ISNUMBER(SEARCH("ESTACION",UPPER('Base_Cobranzas'!$E$2:$E$1005)))+--ISNUMBER(SEARCH("ESTACION",UPPER('Base_Cobranzas'!$K$2:$K$1005)))+--ISNUMBER(SEARCH("ESTACION",UPPER('Base_Cobranzas'!$Q$2:$Q$1005)))+--ISNUMBER(SEARCH("ESTACION",UPPER('Base_Cobranzas'!$W$2:$W$1005))))=0),--ISNUMBER(SEARCH("PENDIENTE",UPPER(TRIM('Base_Cobranzas'!$BC$2:$BC$1005)))),'Base_Cobranzas'!$AR$2:$AR$1005),0) | I12: =IFERROR(SUMPRODUCT(--ISNUMBER(SEARCH($B$6,'Base_Cobranzas'!$A$2:$A$1005)),--((--ISNUMBER(SEARCH("DEPART",UPPER('Base_Cobranzas'!$E$2:$E$1005)))+--ISNUMBER(SEARCH("DEPART",UPPER('Base_Cobranzas'!$K$2:$K$1005)))+--ISNUMBER(SEARCH("DEPART",UPPER('Base_Cobranzas'!$Q$2:$Q$1005)))+--ISNUMBER(SEARCH("DEPART",UPPER('Base_Cobranzas'!$W$2:$W$1005))))>0),--((--ISNUMBER(SEARCH("ESTACION",UPPER('Base_Cobranzas'!$E$2:$E$1005)))+--ISNUMBER(SEARCH("ESTACION",UPPER('Base_Cobranzas'!$K$2:$K$1005)))+--ISNUMBER(SEARCH("ESTACION",UPPER('Base_Cobranzas'!$Q$2:$Q$1005)))+--ISNUMBER(SEARCH("ESTACION",UPPER('Base_Cobranzas'!$W$2:$W$1005))))=0),--ISNUMBER(SEARCH("VENCIDO",UPPER(TRIM('Base_Cobranzas'!$BC$2:$BC$1005)))),'Base_Cobranzas'!$AR$2:$AR$1005),0) | J12: =IF(C12=0,0,I12/C12) | K12: 4 | L12: 122
B13: Departamento + Estacionamiento | C13: 8852500 | D13: 31 | F13: =IF(C13=0,0,G13/C13) | G13: =IFERROR(SUMPRODUCT(--ISNUMBER(SEARCH($B$6,'Base_Cobranzas'!$A$2:$A$1005)),--((--ISNUMBER(SEARCH("DEPART",UPPER('Base_Cobranzas'!$E$2:$E$1005)))+--ISNUMBER(SEARCH("DEPART",UPPER('Base_Cobranzas'!$K$2:$K$1005)))+--ISNUMBER(SEARCH("DEPART",UPPER('Base_Cobranzas'!$Q$2:$Q$1005)))+--ISNUMBER(SEARCH("DEPART",UPPER('Base_Cobranzas'!$W$2:$W$1005))))>0),--((--ISNUMBER(SEARCH("ESTACION",UPPER('Base_Cobranzas'!$E$2:$E$1005)))+--ISNUMBER(SEARCH("ESTACION",UPPER('Base_Cobranzas'!$K$2:$K$1005)))+--ISNUMBER(SEARCH("ESTACION",UPPER('Base_Cobranzas'!$Q$2:$Q$1005)))+--ISNUMBER(SEARCH("ESTACION",UPPER('Base_Cobranzas'!$W$2:$W$1005))))>0),--('Base_Cobranzas'!$AQ$2:$AQ$1005>0),'Base_Cobranzas'!$AQ$2:$AQ$1005),0) | H13: =IFERROR(SUMPRODUCT(--ISNUMBER(SEARCH($B$6,'Base_Cobranzas'!$A$2:$A$1005)),--((--ISNUMBER(SEARCH("DEPART",UPPER('Base_Cobranzas'!$E$2:$E$1005)))+--ISNUMBER(SEARCH("DEPART",UPPER('Base_Cobranzas'!$K$2:$K$1005)))+--ISNUMBER(SEARCH("DEPART",UPPER('Base_Cobranzas'!$Q$2:$Q$1005)))+--ISNUMBER(SEARCH("DEPART",UPPER('Base_Cobranzas'!$W$2:$W$1005))))>0),--((--ISNUMBER(SEARCH("ESTACION",UPPER('Base_Cobranzas'!$E$2:$E$1005)))+--ISNUMBER(SEARCH("ESTACION",UPPER('Base_Cobranzas'!$K$2:$K$1005)))+--ISNUMBER(SEARCH("ESTACION",UPPER('Base_Cobranzas'!$Q$2:$Q$1005)))+--ISNUMBER(SEARCH("ESTACION",UPPER('Base_Cobranzas'!$W$2:$W$1005))))>0),--ISNUMBER(SEARCH("PENDIENTE",UPPER(TRIM('Base_Cobranzas'!$BC$2:$BC$1005)))),'Base_Cobranzas'!$AR$2:$AR$1005),0) | I13: =IFERROR(SUMPRODUCT(--ISNUMBER(SEARCH($B$6,'Base_Cobranzas'!$A$2:$A$1005)),--((--ISNUMBER(SEARCH("DEPART",UPPER('Base_Cobranzas'!$E$2:$E$1005)))+--ISNUMBER(SEARCH("DEPART",UPPER('Base_Cobranzas'!$K$2:$K$1005)))+--ISNUMBER(SEARCH("DEPART",UPPER('Base_Cobranzas'!$Q$2:$Q$1005)))+--ISNUMBER(SEARCH("DEPART",UPPER('Base_Cobranzas'!$W$2:$W$1005))))>0),--((--ISNUMBER(SEARCH("ESTACION",UPPER('Base_Cobranzas'!$E$2:$E$1005)))+--ISNUMBER(SEARCH("ESTACION",UPPER('Base_Cobranzas'!$K$2:$K$1005)))+--ISNUMBER(SEARCH("ESTACION",UPPER('Base_Cobranzas'!$Q$2:$Q$1005)))+--ISNUMBER(SEARCH("ESTACION",UPPER('Base_Cobranzas'!$W$2:$W$1005))))>0),--ISNUMBER(SEARCH("VENCIDO",UPPER(TRIM('Base_Cobranzas'!$BC$2:$BC$1005)))),'Base_Cobranzas'!$AR$2:$AR$1005),0) | J13: =IF(C13=0,0,I13/C13) | K13: 3 | L13: 58
B15: Estacionamientos | C15: 966400 | D15: 18 | F15: =IF(C15=0,0,G15/C15) | G15: =IFERROR(SUMPRODUCT(--ISNUMBER(SEARCH($B$6,'Base_Cobranzas'!$A$2:$A$1005)),--((--ISNUMBER(SEARCH("DEPART",UPPER('Base_Cobranzas'!$E$2:$E$1005)))+--ISNUMBER(SEARCH("DEPART",UPPER('Base_Cobranzas'!$K$2:$K$1005)))+--ISNUMBER(SEARCH("DEPART",UPPER('Base_Cobranzas'!$Q$2:$Q$1005)))+--ISNUMBER(SEARCH("DEPART",UPPER('Base_Cobranzas'!$W$2:$W$1005))))=0),--((--ISNUMBER(SEARCH("ESTACION",UPPER('Base_Cobranzas'!$E$2:$E$1005)))+--ISNUMBER(SEARCH("ESTACION",UPPER('Base_Cobranzas'!$K$2:$K$1005)))+--ISNUMBER(SEARCH("ESTACION",UPPER('Base_Cobranzas'!$Q$2:$Q$1005)))+--ISNUMBER(SEARCH("ESTACION",UPPER('Base_Cobranzas'!$W$2:$W$1005))))>0),--('Base_Cobranzas'!$AQ$2:$AQ$1005>0),'Base_Cobranzas'!$AQ$2:$AQ$1005),0) | H15: =IFERROR(SUMPRODUCT(--ISNUMBER(SEARCH($B$6,'Base_Cobranzas'!$A$2:$A$1005)),--((--ISNUMBER(SEARCH("DEPART",UPPER('Base_Cobranzas'!$E$2:$E$1005)))+--ISNUMBER(SEARCH("DEPART",UPPER('Base_Cobranzas'!$K$2:$K$1005)))+--ISNUMBER(SEARCH("DEPART",UPPER('Base_Cobranzas'!$Q$2:$Q$1005)))+--ISNUMBER(SEARCH("DEPART",UPPER('Base_Cobranzas'!$W$2:$W$1005))))=0),--((--ISNUMBER(SEARCH("ESTACION",UPPER('Base_Cobranzas'!$E$2:$E$1005)))+--ISNUMBER(SEARCH("ESTACION",UPPER('Base_Cobranzas'!$K$2:$K$1005)))+--ISNUMBER(SEARCH("ESTACION",UPPER('Base_Cobranzas'!$Q$2:$Q$1005)))+--ISNUMBER(SEARCH("ESTACION",UPPER('Base_Cobranzas'!$W$2:$W$1005))))>0),--ISNUMBER(SEARCH("PENDIENTE",UPPER(TRIM('Base_Cobranzas'!$BC$2:$BC$1005)))),'Base_Cobranzas'!$AR$2:$AR$1005),0) | I15: =IFERROR(SUMPRODUCT(--ISNUMBER(SEARCH($B$6,'Base_Cobranzas'!$A$2:$A$1005)),--((--ISNUMBER(SEARCH("DEPART",UPPER('Base_Cobranzas'!$E$2:$E$1005)))+--ISNUMBER(SEARCH("DEPART",UPPER('Base_Cobranzas'!$K$2:$K$1005)))+--ISNUMBER(SEARCH("DEPART",UPPER('Base_Cobranzas'!$Q$2:$Q$1005)))+--ISNUMBER(SEARCH("DEPART",UPPER('Base_Cobranzas'!$W$2:$W$1005))))=0),--((--ISNUMBER(SEARCH("ESTACION",UPPER('Base_Cobranzas'!$E$2:$E$1005)))+--ISNUMBER(SEARCH("ESTACION",UPPER('Base_Cobranzas'!$K$2:$K$1005)))+--ISNUMBER(SEARCH("ESTACION",UPPER('Base_Cobranzas'!$Q$2:$Q$1005)))+--ISNUMBER(SEARCH("ESTACION",UPPER('Base_Cobranzas'!$W$2:$W$1005))))>0),--ISNUMBER(SEARCH("VENCIDO",UPPER(TRIM('Base_Cobranzas'!$BC$2:$BC$1005)))),'Base_Cobranzas'!$AR$2:$AR$1005),0) | J15: =IF(C15=0,0,I15/C15) | K15: 6 | L15: 50
B17: Depositos | C17: 0 | D17: 0 | F17: =IF(C17=0,0,G17/C17) | G17: =IFERROR(SUMPRODUCT(--ISNUMBER(SEARCH($B$6,'Base_Cobranzas'!$A$2:$A$1005)),--((--ISNUMBER(SEARCH("DEPART",UPPER('Base_Cobranzas'!$E$2:$E$1005)))+--ISNUMBER(SEARCH("DEPART",UPPER('Base_Cobranzas'!$K$2:$K$1005)))+--ISNUMBER(SEARCH("DEPART",UPPER('Base_Cobranzas'!$Q$2:$Q$1005)))+--ISNUMBER(SEARCH("DEPART",UPPER('Base_Cobranzas'!$W$2:$W$1005))))=0),--((--ISNUMBER(SEARCH("ESTACION",UPPER('Base_Cobranzas'!$E$2:$E$1005)))+--ISNUMBER(SEARCH("ESTACION",UPPER('Base_Cobranzas'!$K$2:$K$1005)))+--ISNUMBER(SEARCH("ESTACION",UPPER('Base_Cobranzas'!$Q$2:$Q$1005)))+--ISNUMBER(SEARCH("ESTACION",UPPER('Base_Cobranzas'!$W$2:$W$1005))))=0),--((--ISNUMBER(SEARCH("DEPOS",UPPER('Base_Cobranzas'!$E$2:$E$1005)))+--ISNUMBER(SEARCH("DEPOS",UPPER('Base_Cobranzas'!$K$2:$K$1005)))+--ISNUMBER(SEARCH("DEPOS",UPPER('Base_Cobranzas'!$Q$2:$Q$1005)))+--ISNUMBER(SEARCH("DEPOS",UPPER('Base_Cobranzas'!$W$2:$W$1005))))>0),--('Base_Cobranzas'!$AQ$2:$AQ$1005>0),'Base_Cobranzas'!$AQ$2:$AQ$1005),0) | H17: =IFERROR(SUMPRODUCT(--ISNUMBER(SEARCH($B$6,'Base_Cobranzas'!$A$2:$A$1005)),--((--ISNUMBER(SEARCH("DEPART",UPPER('Base_Cobranzas'!$E$2:$E$1005)))+--ISNUMBER(SEARCH("DEPART",UPPER('Base_Cobranzas'!$K$2:$K$1005)))+--ISNUMBER(SEARCH("DEPART",UPPER('Base_Cobranzas'!$Q$2:$Q$1005)))+--ISNUMBER(SEARCH("DEPART",UPPER('Base_Cobranzas'!$W$2:$W$1005))))=0),--((--ISNUMBER(SEARCH("ESTACION",UPPER('Base_Cobranzas'!$E$2:$E$1005)))+--ISNUMBER(SEARCH("ESTACION",UPPER('Base_Cobranzas'!$K$2:$K$1005)))+--ISNUMBER(SEARCH("ESTACION",UPPER('Base_Cobranzas'!$Q$2:$Q$1005)))+--ISNUMBER(SEARCH("ESTACION",UPPER('Base_Cobranzas'!$W$2:$W$1005))))=0),--((--ISNUMBER(SEARCH("DEPOS",UPPER('Base_Cobranzas'!$E$2:$E$1005)))+--ISNUMBER(SEARCH("DEPOS",UPPER('Base_Cobranzas'!$K$2:$K$1005)))+--ISNUMBER(SEARCH("DEPOS",UPPER('Base_Cobranzas'!$Q$2:$Q$1005)))+--ISNUMBER(SEARCH("DEPOS",UPPER('Base_Cobranzas'!$W$2:$W$1005))))>0),--ISNUMBER(SEARCH("PENDIENTE",UPPER(TRIM('Base_Cobranzas'!$BC$2:$BC$1005)))),'Base_Cobranzas'!$AR$2:$AR$1005),0) | I17: =IFERROR(SUMPRODUCT(--ISNUMBER(SEARCH($B$6,'Base_Cobranzas'!$A$2:$A$1005)),--((--ISNUMBER(SEARCH("DEPART",UPPER('Base_Cobranzas'!$E$2:$E$1005)))+--ISNUMBER(SEARCH("DEPART",UPPER('Base_Cobranzas'!$K$2:$K$1005)))+--ISNUMBER(SEARCH("DEPART",UPPER('Base_Cobranzas'!$Q$2:$Q$1005)))+--ISNUMBER(SEARCH("DEPART",UPPER('Base_Cobranzas'!$W$2:$W$1005))))=0),--((--ISNUMBER(SEARCH("ESTACION",UPPER('Base_Cobranzas'!$E$2:$E$1005)))+--ISNUMBER(SEARCH("ESTACION",UPPER('Base_Cobranzas'!$K$2:$K$1005)))+--ISNUMBER(SEARCH("ESTACION",UPPER('Base_Cobranzas'!$Q$2:$Q$1005)))+--ISNUMBER(SEARCH("ESTACION",UPPER('Base_Cobranzas'!$W$2:$W$1005))))=0),--((--ISNUMBER(SEARCH("DEPOS",UPPER('Base_Cobranzas'!$E$2:$E$1005)))+--ISNUMBER(SEARCH("DEPOS",UPPER('Base_Cobranzas'!$K$2:$K$1005)))+--ISNUMBER(SEARCH("DEPOS",UPPER('Base_Cobranzas'!$Q$2:$Q$1005)))+--ISNUMBER(SEARCH("DEPOS",UPPER('Base_Cobranzas'!$W$2:$W$1005))))>0),--ISNUMBER(SEARCH("VENCIDO",UPPER(TRIM('Base_Cobranzas'!$BC$2:$BC$1005)))),'Base_Cobranzas'!$AR$2:$AR$1005),0) | J17: =IF(C17=0,0,I17/C17) | K17: 0 | L17: 0
B19: Local Comercial | C19: 0 | D19: 0 | F19: =IF(C19=0,0,G19/C19) | G19: =IFERROR(SUMPRODUCT(--ISNUMBER(SEARCH($B$6,'Base_Cobranzas'!$A$2:$A$1005)),--(((--ISNUMBER(SEARCH("LOCAL",UPPER('Base_Cobranzas'!$E$2:$E$1005)))+--ISNUMBER(SEARCH("LOCAL",UPPER('Base_Cobranzas'!$K$2:$K$1005)))+--ISNUMBER(SEARCH("LOCAL",UPPER('Base_Cobranzas'!$Q$2:$Q$1005)))+--ISNUMBER(SEARCH("LOCAL",UPPER('Base_Cobranzas'!$W$2:$W$1005))))+(--ISNUMBER(SEARCH("COMERCIAL",UPPER('Base_Cobranzas'!$E$2:$E$1005)))+--ISNUMBER(SEARCH("COMERCIAL",UPPER('Base_Cobranzas'!$K$2:$K$1005)))+--ISNUMBER(SEARCH("COMERCIAL",UPPER('Base_Cobranzas'!$Q$2:$Q$1005)))+--ISNUMBER(SEARCH("COMERCIAL",UPPER('Base_Cobranzas'!$W$2:$W$1005)))))>0),--('Base_Cobranzas'!$AQ$2:$AQ$1005>0),'Base_Cobranzas'!$AQ$2:$AQ$1005),0) | H19: =IFERROR(SUMPRODUCT(--ISNUMBER(SEARCH($B$6,'Base_Cobranzas'!$A$2:$A$1005)),--(((--ISNUMBER(SEARCH("LOCAL",UPPER('Base_Cobranzas'!$E$2:$E$1005)))+--ISNUMBER(SEARCH("LOCAL",UPPER('Base_Cobranzas'!$K$2:$K$1005)))+--ISNUMBER(SEARCH("LOCAL",UPPER('Base_Cobranzas'!$Q$2:$Q$1005)))+--ISNUMBER(SEARCH("LOCAL",UPPER('Base_Cobranzas'!$W$2:$W$1005))))+(--ISNUMBER(SEARCH("COMERCIAL",UPPER('Base_Cobranzas'!$E$2:$E$1005)))+--ISNUMBER(SEARCH("COMERCIAL",UPPER('Base_Cobranzas'!$K$2:$K$1005)))+--ISNUMBER(SEARCH("COMERCIAL",UPPER('Base_Cobranzas'!$Q$2:$Q$1005)))+--ISNUMBER(SEARCH("COMERCIAL",UPPER('Base_Cobranzas'!$W$2:$W$1005)))))>0),--ISNUMBER(SEARCH("PENDIENTE",UPPER(TRIM('Base_Cobranzas'!$BC$2:$BC$1005)))),'Base_Cobranzas'!$AR$2:$AR$1005),0) | I19: =IFERROR(SUMPRODUCT(--ISNUMBER(SEARCH($B$6,'Base_Cobranzas'!$A$2:$A$1005)),--(((--ISNUMBER(SEARCH("LOCAL",UPPER('Base_Cobranzas'!$E$2:$E$1005)))+--ISNUMBER(SEARCH("LOCAL",UPPER('Base_Cobranzas'!$K$2:$K$1005)))+--ISNUMBER(SEARCH("LOCAL",UPPER('Base_Cobranzas'!$Q$2:$Q$1005)))+--ISNUMBER(SEARCH("LOCAL",UPPER('Base_Cobranzas'!$W$2:$W$1005))))+(--ISNUMBER(SEARCH("COMERCIAL",UPPER('Base_Cobranzas'!$E$2:$E$1005)))+--ISNUMBER(SEARCH("COMERCIAL",UPPER('Base_Cobranzas'!$K$2:$K$1005)))+--ISNUMBER(SEARCH("COMERCIAL",UPPER('Base_Cobranzas'!$Q$2:$Q$1005)))+--ISNUMBER(SEARCH("COMERCIAL",UPPER('Base_Cobranzas'!$W$2:$W$1005)))))>0),--ISNUMBER(SEARCH("VENCIDO",UPPER(TRIM('Base_Cobranzas'!$BC$2:$BC$1005)))),'Base_Cobranzas'!$AR$2:$AR$1005),0) | J19: =IF(C19=0,0,I19/C19) | K19: 0 | L19: 0
A21: =+IF(ROUND(C21,0)=ROUND(G21+H21+I21,0),"OK","REVISAR") | B21: Total | C21: 26220000 | D21: 80 | F21: =IF(C21=0,0,G21/C21) | G21: =G11+G15+G17+G19 | H21: =H11+H15+H17+H19 | I21: =I11+I15+I17+I19 | J21: =IF(C21=0,0,I21/C21) | K21: 12 | L21: 74
B31: COBRANZA REAL
B33: Tipo de Credito | C33: 2024 | D33: 2025 | E33: 46023 | F33: 46054 | G33: 46082 | H33: 46113 | I33: 46143 | J33: 46174 | K33: 46204 | L33: 46235 | M33: 46266 | N33: Total
B34: Crédito Directo | C34: =IFERROR(SUMPRODUCT(--ISNUMBER(SEARCH($B$6,'Base_Cobranzas'!$A$2:$A$1005)),--('Base_Cobranzas'!$AJ$2:$AJ$1005>=IF(C$33<3000,DATE(C$33,1,1),C$33)),--('Base_Cobranzas'!$AJ$2:$AJ$1005<IF(C$33<3000,DATE(C$33+1,1,1),EDATE(C$33,1))),--ISNUMBER(SEARCH(IF(ISNUMBER(SEARCH("DIRECTO",UPPER($B34))),"DIRECTO",IF(ISNUMBER(SEARCH("HIPOT",UPPER($B34))),"HIPOT",IF(ISNUMBER(SEARCH("AHORRO",UPPER($B34))),"AHORRO",UPPER($B34)))),UPPER('Base_Cobranzas'!$AT$2:$AT$1005))),--('Base_Cobranzas'!$AQ$2:$AQ$1005>0),'Base_Cobranzas'!$AQ$2:$AQ$1005),0) | D34: =IFERROR(SUMPRODUCT(--ISNUMBER(SEARCH($B$6,'Base_Cobranzas'!$A$2:$A$1005)),--('Base_Cobranzas'!$AJ$2:$AJ$1005>=IF(D$33<3000,DATE(D$33,1,1),D$33)),--('Base_Cobranzas'!$AJ$2:$AJ$1005<IF(D$33<3000,DATE(D$33+1,1,1),EDATE(D$33,1))),--ISNUMBER(SEARCH(IF(ISNUMBER(SEARCH("DIRECTO",UPPER($B34))),"DIRECTO",IF(ISNUMBER(SEARCH("HIPOT",UPPER($B34))),"HIPOT",IF(ISNUMBER(SEARCH("AHORRO",UPPER($B34))),"AHORRO",UPPER($B34)))),UPPER('Base_Cobranzas'!$AT$2:$AT$1005))),--('Base_Cobranzas'!$AQ$2:$AQ$1005>0),'Base_Cobranzas'!$AQ$2:$AQ$1005),0) | E34: =IFERROR(SUMPRODUCT(--ISNUMBER(SEARCH($B$6,'Base_Cobranzas'!$A$2:$A$1005)),--('Base_Cobranzas'!$AJ$2:$AJ$1005>=IF(E$33<3000,DATE(E$33,1,1),E$33)),--('Base_Cobranzas'!$AJ$2:$AJ$1005<IF(E$33<3000,DATE(E$33+1,1,1),EDATE(E$33,1))),--ISNUMBER(SEARCH(IF(ISNUMBER(SEARCH("DIRECTO",UPPER($B34))),"DIRECTO",IF(ISNUMBER(SEARCH("HIPOT",UPPER($B34))),"HIPOT",IF(ISNUMBER(SEARCH("AHORRO",UPPER($B34))),"AHORRO",UPPER($B34)))),UPPER('Base_Cobranzas'!$AT$2:$AT$1005))),--('Base_Cobranzas'!$AQ$2:$AQ$1005>0),'Base_Cobranzas'!$AQ$2:$AQ$1005),0) | F34: =IFERROR(SUMPRODUCT(--ISNUMBER(SEARCH($B$6,'Base_Cobranzas'!$A$2:$A$1005)),--('Base_Cobranzas'!$AJ$2:$AJ$1005>=IF(F$33<3000,DATE(F$33,1,1),F$33)),--('Base_Cobranzas'!$AJ$2:$AJ$1005<IF(F$33<3000,DATE(F$33+1,1,1),EDATE(F$33,1))),--ISNUMBER(SEARCH(IF(ISNUMBER(SEARCH("DIRECTO",UPPER($B34))),"DIRECTO",IF(ISNUMBER(SEARCH("HIPOT",UPPER($B34))),"HIPOT",IF(ISNUMBER(SEARCH("AHORRO",UPPER($B34))),"AHORRO",UPPER($B34)))),UPPER('Base_Cobranzas'!$AT$2:$AT$1005))),--('Base_Cobranzas'!$AQ$2:$AQ$1005>0),'Base_Cobranzas'!$AQ$2:$AQ$1005),0) | G34: =IFERROR(SUMPRODUCT(--ISNUMBER(SEARCH($B$6,'Base_Cobranzas'!$A$2:$A$1005)),--('Base_Cobranzas'!$AJ$2:$AJ$1005>=IF(G$33<3000,DATE(G$33,1,1),G$33)),--('Base_Cobranzas'!$AJ$2:$AJ$1005<IF(G$33<3000,DATE(G$33+1,1,1),EDATE(G$33,1))),--ISNUMBER(SEARCH(IF(ISNUMBER(SEARCH("DIRECTO",UPPER($B34))),"DIRECTO",IF(ISNUMBER(SEARCH("HIPOT",UPPER($B34))),"HIPOT",IF(ISNUMBER(SEARCH("AHORRO",UPPER($B34))),"AHORRO",UPPER($B34)))),UPPER('Base_Cobranzas'!$AT$2:$AT$1005))),--('Base_Cobranzas'!$AQ$2:$AQ$1005>0),'Base_Cobranzas'!$AQ$2:$AQ$1005),0) | H34: =IFERROR(SUMPRODUCT(--ISNUMBER(SEARCH($B$6,'Base_Cobranzas'!$A$2:$A$1005)),--('Base_Cobranzas'!$AJ$2:$AJ$1005>=IF(H$33<3000,DATE(H$33,1,1),H$33)),--('Base_Cobranzas'!$AJ$2:$AJ$1005<IF(H$33<3000,DATE(H$33+1,1,1),EDATE(H$33,1))),--ISNUMBER(SEARCH(IF(ISNUMBER(SEARCH("DIRECTO",UPPER($B34))),"DIRECTO",IF(ISNUMBER(SEARCH("HIPOT",UPPER($B34))),"HIPOT",IF(ISNUMBER(SEARCH("AHORRO",UPPER($B34))),"AHORRO",UPPER($B34)))),UPPER('Base_Cobranzas'!$AT$2:$AT$1005))),--('Base_Cobranzas'!$AQ$2:$AQ$1005>0),'Base_Cobranzas'!$AQ$2:$AQ$1005),0) | I34: =IFERROR(SUMPRODUCT(--ISNUMBER(SEARCH($B$6,'Base_Cobranzas'!$A$2:$A$1005)),--('Base_Cobranzas'!$AJ$2:$AJ$1005>=IF(I$33<3000,DATE(I$33,1,1),I$33)),--('Base_Cobranzas'!$AJ$2:$AJ$1005<IF(I$33<3000,DATE(I$33+1,1,1),EDATE(I$33,1))),--ISNUMBER(SEARCH(IF(ISNUMBER(SEARCH("DIRECTO",UPPER($B34))),"DIRECTO",IF(ISNUMBER(SEARCH("HIPOT",UPPER($B34))),"HIPOT",IF(ISNUMBER(SEARCH("AHORRO",UPPER($B34))),"AHORRO",UPPER($B34)))),UPPER('Base_Cobranzas'!$AT$2:$AT$1005))),--('Base_Cobranzas'!$AQ$2:$AQ$1005>0),'Base_Cobranzas'!$AQ$2:$AQ$1005),0) | J34: =IFERROR(SUMPRODUCT(--ISNUMBER(SEARCH($B$6,'Base_Cobranzas'!$A$2:$A$1005)),--('Base_Cobranzas'!$AJ$2:$AJ$1005>=IF(J$33<3000,DATE(J$33,1,1),J$33)),--('Base_Cobranzas'!$AJ$2:$AJ$1005<IF(J$33<3000,DATE(J$33+1,1,1),EDATE(J$33,1))),--ISNUMBER(SEARCH(IF(ISNUMBER(SEARCH("DIRECTO",UPPER($B34))),"DIRECTO",IF(ISNUMBER(SEARCH("HIPOT",UPPER($B34))),"HIPOT",IF(ISNUMBER(SEARCH("AHORRO",UPPER($B34))),"AHORRO",UPPER($B34)))),UPPER('Base_Cobranzas'!$AT$2:$AT$1005))),--('Base_Cobranzas'!$AQ$2:$AQ$1005>0),'Base_Cobranzas'!$AQ$2:$AQ$1005),0) | ... M34: =IFERROR(SUMPRODUCT(--ISNUMBER(SEARCH($B$6,'Base_Cobranzas'!$A$2:$A$1005)),--('Base_Cobranzas'!$AJ$2:$AJ$1005>=IF(M$33<3000,DATE(M$33,1,1),M$33)),--('Base_Cobranzas'!$AJ$2:$AJ$1005<IF(M$33<3000,DATE(M$33+1,1,1),EDATE(M$33,1))),--ISNUMBER(SEARCH(IF(ISNUMBER(SEARCH("DIRECTO",UPPER($B34))),"DIRECTO",IF(ISNUMBER(SEARCH("HIPOT",UPPER($B34))),"HIPOT",IF(ISNUMBER(SEARCH("AHORRO",UPPER($B34))),"AHORRO",UPPER($B34)))),UPPER('Base_Cobranzas'!$AT$2:$AT$1005))),--('Base_Cobranzas'!$AQ$2:$AQ$1005>0),'Base_Cobranzas'!$AQ$2:$AQ$1005),0) | N34: =SUM(C34:M34)
B35: Crédito Hipotecario | C35: =IFERROR(SUMPRODUCT(--ISNUMBER(SEARCH($B$6,'Base_Cobranzas'!$A$2:$A$1005)),--('Base_Cobranzas'!$AJ$2:$AJ$1005>=IF(C$33<3000,DATE(C$33,1,1),C$33)),--('Base_Cobranzas'!$AJ$2:$AJ$1005<IF(C$33<3000,DATE(C$33+1,1,1),EDATE(C$33,1))),--ISNUMBER(SEARCH(IF(ISNUMBER(SEARCH("DIRECTO",UPPER($B35))),"DIRECTO",IF(ISNUMBER(SEARCH("HIPOT",UPPER($B35))),"HIPOT",IF(ISNUMBER(SEARCH("AHORRO",UPPER($B35))),"AHORRO",UPPER($B35)))),UPPER('Base_Cobranzas'!$AT$2:$AT$1005))),--('Base_Cobranzas'!$AQ$2:$AQ$1005>0),'Base_Cobranzas'!$AQ$2:$AQ$1005),0) | D35: =IFERROR(SUMPRODUCT(--ISNUMBER(SEARCH($B$6,'Base_Cobranzas'!$A$2:$A$1005)),--('Base_Cobranzas'!$AJ$2:$AJ$1005>=IF(D$33<3000,DATE(D$33,1,1),D$33)),--('Base_Cobranzas'!$AJ$2:$AJ$1005<IF(D$33<3000,DATE(D$33+1,1,1),EDATE(D$33,1))),--ISNUMBER(SEARCH(IF(ISNUMBER(SEARCH("DIRECTO",UPPER($B35))),"DIRECTO",IF(ISNUMBER(SEARCH("HIPOT",UPPER($B35))),"HIPOT",IF(ISNUMBER(SEARCH("AHORRO",UPPER($B35))),"AHORRO",UPPER($B35)))),UPPER('Base_Cobranzas'!$AT$2:$AT$1005))),--('Base_Cobranzas'!$AQ$2:$AQ$1005>0),'Base_Cobranzas'!$AQ$2:$AQ$1005),0) | E35: =IFERROR(SUMPRODUCT(--ISNUMBER(SEARCH($B$6,'Base_Cobranzas'!$A$2:$A$1005)),--('Base_Cobranzas'!$AJ$2:$AJ$1005>=IF(E$33<3000,DATE(E$33,1,1),E$33)),--('Base_Cobranzas'!$AJ$2:$AJ$1005<IF(E$33<3000,DATE(E$33+1,1,1),EDATE(E$33,1))),--ISNUMBER(SEARCH(IF(ISNUMBER(SEARCH("DIRECTO",UPPER($B35))),"DIRECTO",IF(ISNUMBER(SEARCH("HIPOT",UPPER($B35))),"HIPOT",IF(ISNUMBER(SEARCH("AHORRO",UPPER($B35))),"AHORRO",UPPER($B35)))),UPPER('Base_Cobranzas'!$AT$2:$AT$1005))),--('Base_Cobranzas'!$AQ$2:$AQ$1005>0),'Base_Cobranzas'!$AQ$2:$AQ$1005),0) | F35: =IFERROR(SUMPRODUCT(--ISNUMBER(SEARCH($B$6,'Base_Cobranzas'!$A$2:$A$1005)),--('Base_Cobranzas'!$AJ$2:$AJ$1005>=IF(F$33<3000,DATE(F$33,1,1),F$33)),--('Base_Cobranzas'!$AJ$2:$AJ$1005<IF(F$33<3000,DATE(F$33+1,1,1),EDATE(F$33,1))),--ISNUMBER(SEARCH(IF(ISNUMBER(SEARCH("DIRECTO",UPPER($B35))),"DIRECTO",IF(ISNUMBER(SEARCH("HIPOT",UPPER($B35))),"HIPOT",IF(ISNUMBER(SEARCH("AHORRO",UPPER($B35))),"AHORRO",UPPER($B35)))),UPPER('Base_Cobranzas'!$AT$2:$AT$1005))),--('Base_Cobranzas'!$AQ$2:$AQ$1005>0),'Base_Cobranzas'!$AQ$2:$AQ$1005),0) | G35: =IFERROR(SUMPRODUCT(--ISNUMBER(SEARCH($B$6,'Base_Cobranzas'!$A$2:$A$1005)),--('Base_Cobranzas'!$AJ$2:$AJ$1005>=IF(G$33<3000,DATE(G$33,1,1),G$33)),--('Base_Cobranzas'!$AJ$2:$AJ$1005<IF(G$33<3000,DATE(G$33+1,1,1),EDATE(G$33,1))),--ISNUMBER(SEARCH(IF(ISNUMBER(SEARCH("DIRECTO",UPPER($B35))),"DIRECTO",IF(ISNUMBER(SEARCH("HIPOT",UPPER($B35))),"HIPOT",IF(ISNUMBER(SEARCH("AHORRO",UPPER($B35))),"AHORRO",UPPER($B35)))),UPPER('Base_Cobranzas'!$AT$2:$AT$1005))),--('Base_Cobranzas'!$AQ$2:$AQ$1005>0),'Base_Cobranzas'!$AQ$2:$AQ$1005),0) | H35: =IFERROR(SUMPRODUCT(--ISNUMBER(SEARCH($B$6,'Base_Cobranzas'!$A$2:$A$1005)),--('Base_Cobranzas'!$AJ$2:$AJ$1005>=IF(H$33<3000,DATE(H$33,1,1),H$33)),--('Base_Cobranzas'!$AJ$2:$AJ$1005<IF(H$33<3000,DATE(H$33+1,1,1),EDATE(H$33,1))),--ISNUMBER(SEARCH(IF(ISNUMBER(SEARCH("DIRECTO",UPPER($B35))),"DIRECTO",IF(ISNUMBER(SEARCH("HIPOT",UPPER($B35))),"HIPOT",IF(ISNUMBER(SEARCH("AHORRO",UPPER($B35))),"AHORRO",UPPER($B35)))),UPPER('Base_Cobranzas'!$AT$2:$AT$1005))),--('Base_Cobranzas'!$AQ$2:$AQ$1005>0),'Base_Cobranzas'!$AQ$2:$AQ$1005),0) | I35: =IFERROR(SUMPRODUCT(--ISNUMBER(SEARCH($B$6,'Base_Cobranzas'!$A$2:$A$1005)),--('Base_Cobranzas'!$AJ$2:$AJ$1005>=IF(I$33<3000,DATE(I$33,1,1),I$33)),--('Base_Cobranzas'!$AJ$2:$AJ$1005<IF(I$33<3000,DATE(I$33+1,1,1),EDATE(I$33,1))),--ISNUMBER(SEARCH(IF(ISNUMBER(SEARCH("DIRECTO",UPPER($B35))),"DIRECTO",IF(ISNUMBER(SEARCH("HIPOT",UPPER($B35))),"HIPOT",IF(ISNUMBER(SEARCH("AHORRO",UPPER($B35))),"AHORRO",UPPER($B35)))),UPPER('Base_Cobranzas'!$AT$2:$AT$1005))),--('Base_Cobranzas'!$AQ$2:$AQ$1005>0),'Base_Cobranzas'!$AQ$2:$AQ$1005),0) | J35: =IFERROR(SUMPRODUCT(--ISNUMBER(SEARCH($B$6,'Base_Cobranzas'!$A$2:$A$1005)),--('Base_Cobranzas'!$AJ$2:$AJ$1005>=IF(J$33<3000,DATE(J$33,1,1),J$33)),--('Base_Cobranzas'!$AJ$2:$AJ$1005<IF(J$33<3000,DATE(J$33+1,1,1),EDATE(J$33,1))),--ISNUMBER(SEARCH(IF(ISNUMBER(SEARCH("DIRECTO",UPPER($B35))),"DIRECTO",IF(ISNUMBER(SEARCH("HIPOT",UPPER($B35))),"HIPOT",IF(ISNUMBER(SEARCH("AHORRO",UPPER($B35))),"AHORRO",UPPER($B35)))),UPPER('Base_Cobranzas'!$AT$2:$AT$1005))),--('Base_Cobranzas'!$AQ$2:$AQ$1005>0),'Base_Cobranzas'!$AQ$2:$AQ$1005),0) | ... M35: =IFERROR(SUMPRODUCT(--ISNUMBER(SEARCH($B$6,'Base_Cobranzas'!$A$2:$A$1005)),--('Base_Cobranzas'!$AJ$2:$AJ$1005>=IF(M$33<3000,DATE(M$33,1,1),M$33)),--('Base_Cobranzas'!$AJ$2:$AJ$1005<IF(M$33<3000,DATE(M$33+1,1,1),EDATE(M$33,1))),--ISNUMBER(SEARCH(IF(ISNUMBER(SEARCH("DIRECTO",UPPER($B35))),"DIRECTO",IF(ISNUMBER(SEARCH("HIPOT",UPPER($B35))),"HIPOT",IF(ISNUMBER(SEARCH("AHORRO",UPPER($B35))),"AHORRO",UPPER($B35)))),UPPER('Base_Cobranzas'!$AT$2:$AT$1005))),--('Base_Cobranzas'!$AQ$2:$AQ$1005>0),'Base_Cobranzas'!$AQ$2:$AQ$1005),0) | N35: =SUM(C35:M35)
B36: Ahorro | C36: =IFERROR(SUMPRODUCT(--ISNUMBER(SEARCH($B$6,'Base_Cobranzas'!$A$2:$A$1005)),--('Base_Cobranzas'!$AJ$2:$AJ$1005>=IF(C$33<3000,DATE(C$33,1,1),C$33)),--('Base_Cobranzas'!$AJ$2:$AJ$1005<IF(C$33<3000,DATE(C$33+1,1,1),EDATE(C$33,1))),--ISNUMBER(SEARCH(IF(ISNUMBER(SEARCH("DIRECTO",UPPER($B36))),"DIRECTO",IF(ISNUMBER(SEARCH("HIPOT",UPPER($B36))),"HIPOT",IF(ISNUMBER(SEARCH("AHORRO",UPPER($B36))),"AHORRO",UPPER($B36)))),UPPER('Base_Cobranzas'!$AT$2:$AT$1005))),--('Base_Cobranzas'!$AQ$2:$AQ$1005>0),'Base_Cobranzas'!$AQ$2:$AQ$1005),0) | D36: =IFERROR(SUMPRODUCT(--ISNUMBER(SEARCH($B$6,'Base_Cobranzas'!$A$2:$A$1005)),--('Base_Cobranzas'!$AJ$2:$AJ$1005>=IF(D$33<3000,DATE(D$33,1,1),D$33)),--('Base_Cobranzas'!$AJ$2:$AJ$1005<IF(D$33<3000,DATE(D$33+1,1,1),EDATE(D$33,1))),--ISNUMBER(SEARCH(IF(ISNUMBER(SEARCH("DIRECTO",UPPER($B36))),"DIRECTO",IF(ISNUMBER(SEARCH("HIPOT",UPPER($B36))),"HIPOT",IF(ISNUMBER(SEARCH("AHORRO",UPPER($B36))),"AHORRO",UPPER($B36)))),UPPER('Base_Cobranzas'!$AT$2:$AT$1005))),--('Base_Cobranzas'!$AQ$2:$AQ$1005>0),'Base_Cobranzas'!$AQ$2:$AQ$1005),0) | E36: =IFERROR(SUMPRODUCT(--ISNUMBER(SEARCH($B$6,'Base_Cobranzas'!$A$2:$A$1005)),--('Base_Cobranzas'!$AJ$2:$AJ$1005>=IF(E$33<3000,DATE(E$33,1,1),E$33)),--('Base_Cobranzas'!$AJ$2:$AJ$1005<IF(E$33<3000,DATE(E$33+1,1,1),EDATE(E$33,1))),--ISNUMBER(SEARCH(IF(ISNUMBER(SEARCH("DIRECTO",UPPER($B36))),"DIRECTO",IF(ISNUMBER(SEARCH("HIPOT",UPPER($B36))),"HIPOT",IF(ISNUMBER(SEARCH("AHORRO",UPPER($B36))),"AHORRO",UPPER($B36)))),UPPER('Base_Cobranzas'!$AT$2:$AT$1005))),--('Base_Cobranzas'!$AQ$2:$AQ$1005>0),'Base_Cobranzas'!$AQ$2:$AQ$1005),0) | F36: =IFERROR(SUMPRODUCT(--ISNUMBER(SEARCH($B$6,'Base_Cobranzas'!$A$2:$A$1005)),--('Base_Cobranzas'!$AJ$2:$AJ$1005>=IF(F$33<3000,DATE(F$33,1,1),F$33)),--('Base_Cobranzas'!$AJ$2:$AJ$1005<IF(F$33<3000,DATE(F$33+1,1,1),EDATE(F$33,1))),--ISNUMBER(SEARCH(IF(ISNUMBER(SEARCH("DIRECTO",UPPER($B36))),"DIRECTO",IF(ISNUMBER(SEARCH("HIPOT",UPPER($B36))),"HIPOT",IF(ISNUMBER(SEARCH("AHORRO",UPPER($B36))),"AHORRO",UPPER($B36)))),UPPER('Base_Cobranzas'!$AT$2:$AT$1005))),--('Base_Cobranzas'!$AQ$2:$AQ$1005>0),'Base_Cobranzas'!$AQ$2:$AQ$1005),0) | G36: =IFERROR(SUMPRODUCT(--ISNUMBER(SEARCH($B$6,'Base_Cobranzas'!$A$2:$A$1005)),--('Base_Cobranzas'!$AJ$2:$AJ$1005>=IF(G$33<3000,DATE(G$33,1,1),G$33)),--('Base_Cobranzas'!$AJ$2:$AJ$1005<IF(G$33<3000,DATE(G$33+1,1,1),EDATE(G$33,1))),--ISNUMBER(SEARCH(IF(ISNUMBER(SEARCH("DIRECTO",UPPER($B36))),"DIRECTO",IF(ISNUMBER(SEARCH("HIPOT",UPPER($B36))),"HIPOT",IF(ISNUMBER(SEARCH("AHORRO",UPPER($B36))),"AHORRO",UPPER($B36)))),UPPER('Base_Cobranzas'!$AT$2:$AT$1005))),--('Base_Cobranzas'!$AQ$2:$AQ$1005>0),'Base_Cobranzas'!$AQ$2:$AQ$1005),0) | H36: =IFERROR(SUMPRODUCT(--ISNUMBER(SEARCH($B$6,'Base_Cobranzas'!$A$2:$A$1005)),--('Base_Cobranzas'!$AJ$2:$AJ$1005>=IF(H$33<3000,DATE(H$33,1,1),H$33)),--('Base_Cobranzas'!$AJ$2:$AJ$1005<IF(H$33<3000,DATE(H$33+1,1,1),EDATE(H$33,1))),--ISNUMBER(SEARCH(IF(ISNUMBER(SEARCH("DIRECTO",UPPER($B36))),"DIRECTO",IF(ISNUMBER(SEARCH("HIPOT",UPPER($B36))),"HIPOT",IF(ISNUMBER(SEARCH("AHORRO",UPPER($B36))),"AHORRO",UPPER($B36)))),UPPER('Base_Cobranzas'!$AT$2:$AT$1005))),--('Base_Cobranzas'!$AQ$2:$AQ$1005>0),'Base_Cobranzas'!$AQ$2:$AQ$1005),0) | I36: =IFERROR(SUMPRODUCT(--ISNUMBER(SEARCH($B$6,'Base_Cobranzas'!$A$2:$A$1005)),--('Base_Cobranzas'!$AJ$2:$AJ$1005>=IF(I$33<3000,DATE(I$33,1,1),I$33)),--('Base_Cobranzas'!$AJ$2:$AJ$1005<IF(I$33<3000,DATE(I$33+1,1,1),EDATE(I$33,1))),--ISNUMBER(SEARCH(IF(ISNUMBER(SEARCH("DIRECTO",UPPER($B36))),"DIRECTO",IF(ISNUMBER(SEARCH("HIPOT",UPPER($B36))),"HIPOT",IF(ISNUMBER(SEARCH("AHORRO",UPPER($B36))),"AHORRO",UPPER($B36)))),UPPER('Base_Cobranzas'!$AT$2:$AT$1005))),--('Base_Cobranzas'!$AQ$2:$AQ$1005>0),'Base_Cobranzas'!$AQ$2:$AQ$1005),0) | J36: =IFERROR(SUMPRODUCT(--ISNUMBER(SEARCH($B$6,'Base_Cobranzas'!$A$2:$A$1005)),--('Base_Cobranzas'!$AJ$2:$AJ$1005>=IF(J$33<3000,DATE(J$33,1,1),J$33)),--('Base_Cobranzas'!$AJ$2:$AJ$1005<IF(J$33<3000,DATE(J$33+1,1,1),EDATE(J$33,1))),--ISNUMBER(SEARCH(IF(ISNUMBER(SEARCH("DIRECTO",UPPER($B36))),"DIRECTO",IF(ISNUMBER(SEARCH("HIPOT",UPPER($B36))),"HIPOT",IF(ISNUMBER(SEARCH("AHORRO",UPPER($B36))),"AHORRO",UPPER($B36)))),UPPER('Base_Cobranzas'!$AT$2:$AT$1005))),--('Base_Cobranzas'!$AQ$2:$AQ$1005>0),'Base_Cobranzas'!$AQ$2:$AQ$1005),0) | ... M36: =IFERROR(SUMPRODUCT(--ISNUMBER(SEARCH($B$6,'Base_Cobranzas'!$A$2:$A$1005)),--('Base_Cobranzas'!$AJ$2:$AJ$1005>=IF(M$33<3000,DATE(M$33,1,1),M$33)),--('Base_Cobranzas'!$AJ$2:$AJ$1005<IF(M$33<3000,DATE(M$33+1,1,1),EDATE(M$33,1))),--ISNUMBER(SEARCH(IF(ISNUMBER(SEARCH("DIRECTO",UPPER($B36))),"DIRECTO",IF(ISNUMBER(SEARCH("HIPOT",UPPER($B36))),"HIPOT",IF(ISNUMBER(SEARCH("AHORRO",UPPER($B36))),"AHORRO",UPPER($B36)))),UPPER('Base_Cobranzas'!$AT$2:$AT$1005))),--('Base_Cobranzas'!$AQ$2:$AQ$1005>0),'Base_Cobranzas'!$AQ$2:$AQ$1005),0) | N36: =SUM(C36:M36)
B37: Total | C37: =SUM(C34:C36) | D37: =SUM(D34:D36) | E37: =SUM(E34:E36) | F37: =SUM(F34:F36) | G37: =SUM(G34:G36) | H37: =SUM(H34:H36) | I37: =SUM(I34:I36) | J37: =SUM(J34:J36) | ... M37: =SUM(M34:M36) | N37: =SUM(C37:M37) | O37: =IF($G$21=N37,"OK","REVISAR")
B39: Acumulado | C39: =C37 | D39: =C39+D37 | E39: =D39+E37 | F39: =E39+F37 | G39: =F39+G37 | H39: =G39+H37 | I39: =H39+I37 | J39: =I39+J37 | K39: =J39+K37 | ... M39: =L39+M37
B43: COBRANZA PROYECTADA
B45: Tipo de Credito | C45: 46296 | D45: Total
B46: Crédito Directo | C46: =IFERROR(SUMPRODUCT(--ISNUMBER(SEARCH($B$6,'Base_Cobranzas'!$A$2:$A$1005)),--('Base_Cobranzas'!$AI$2:$AI$1005>=IF(C$45<3000,DATE(C$45,1,1),C$45)),--('Base_Cobranzas'!$AI$2:$AI$1005<IF(C$45<3000,DATE(C$45+1,1,1),EDATE(C$45,1))),--ISNUMBER(SEARCH(IF(ISNUMBER(SEARCH("DIRECTO",UPPER($B46))),"DIRECTO",IF(ISNUMBER(SEARCH("HIPOT",UPPER($B46))),"HIPOT",IF(ISNUMBER(SEARCH("AHORRO",UPPER($B46))),"AHORRO",UPPER($B46)))),UPPER('Base_Cobranzas'!$AT$2:$AT$1005))),--ISNUMBER(SEARCH("PENDIENTE",UPPER(TRIM('Base_Cobranzas'!$BC$2:$BC$1005)))),'Base_Cobranzas'!$AR$2:$AR$1005),0) | D46: =SUM(C46:C46)
B47: Crédito Hipotecario | C47: =IFERROR(SUMPRODUCT(--ISNUMBER(SEARCH($B$6,'Base_Cobranzas'!$A$2:$A$1005)),--('Base_Cobranzas'!$AI$2:$AI$1005>=IF(C$45<3000,DATE(C$45,1,1),C$45)),--('Base_Cobranzas'!$AI$2:$AI$1005<IF(C$45<3000,DATE(C$45+1,1,1),EDATE(C$45,1))),--ISNUMBER(SEARCH(IF(ISNUMBER(SEARCH("DIRECTO",UPPER($B47))),"DIRECTO",IF(ISNUMBER(SEARCH("HIPOT",UPPER($B47))),"HIPOT",IF(ISNUMBER(SEARCH("AHORRO",UPPER($B47))),"AHORRO",UPPER($B47)))),UPPER('Base_Cobranzas'!$AT$2:$AT$1005))),--ISNUMBER(SEARCH("PENDIENTE",UPPER(TRIM('Base_Cobranzas'!$BC$2:$BC$1005)))),'Base_Cobranzas'!$AR$2:$AR$1005),0) | D47: =SUM(C47:C47)
B48: Ahorro | C48: =IFERROR(SUMPRODUCT(--ISNUMBER(SEARCH($B$6,'Base_Cobranzas'!$A$2:$A$1005)),--('Base_Cobranzas'!$AI$2:$AI$1005>=IF(C$45<3000,DATE(C$45,1,1),C$45)),--('Base_Cobranzas'!$AI$2:$AI$1005<IF(C$45<3000,DATE(C$45+1,1,1),EDATE(C$45,1))),--ISNUMBER(SEARCH(IF(ISNUMBER(SEARCH("DIRECTO",UPPER($B48))),"DIRECTO",IF(ISNUMBER(SEARCH("HIPOT",UPPER($B48))),"HIPOT",IF(ISNUMBER(SEARCH("AHORRO",UPPER($B48))),"AHORRO",UPPER($B48)))),UPPER('Base_Cobranzas'!$AT$2:$AT$1005))),--ISNUMBER(SEARCH("PENDIENTE",UPPER(TRIM('Base_Cobranzas'!$BC$2:$BC$1005)))),'Base_Cobranzas'!$AR$2:$AR$1005),0) | D48: =SUM(C48:C48)
B49: Total | C49: =SUM(C46:C48) | D49: =SUM(C49:C49) | E49: =IF($H$21=D49,"OK","REVISAR")
B51: Acumulado | C51: =C49
B55: COBRANZA MOROSA
B57: Tipo de Credito | C57: 45901 | D57: 45931 | E57: 45962 | F57: 45992 | G57: 46023 | H57: 46054 | I57: 46082 | J57: 46113 | K57: 46143 | L57: 46174 | M57: 46204 | N57: 46235 | O57: 46266 | P57: Total
B58: Crédito Directo | C58: =IFERROR(SUMPRODUCT(--ISNUMBER(SEARCH($B$6,'Base_Cobranzas'!$A$2:$A$1005)),--('Base_Cobranzas'!$AI$2:$AI$1005>=IF(C$57<3000,DATE(C$57,1,1),C$57)),--('Base_Cobranzas'!$AI$2:$AI$1005<IF(C$57<3000,DATE(C$57+1,1,1),EDATE(C$57,1))),--ISNUMBER(SEARCH(IF(ISNUMBER(SEARCH("DIRECTO",UPPER($B58))),"DIRECTO",IF(ISNUMBER(SEARCH("HIPOT",UPPER($B58))),"HIPOT",IF(ISNUMBER(SEARCH("AHORRO",UPPER($B58))),"AHORRO",UPPER($B58)))),UPPER('Base_Cobranzas'!$AT$2:$AT$1005))),--ISNUMBER(SEARCH("VENCIDO",UPPER(TRIM('Base_Cobranzas'!$BC$2:$BC$1005)))),'Base_Cobranzas'!$AR$2:$AR$1005),0) | D58: =IFERROR(SUMPRODUCT(--ISNUMBER(SEARCH($B$6,'Base_Cobranzas'!$A$2:$A$1005)),--('Base_Cobranzas'!$AI$2:$AI$1005>=IF(D$57<3000,DATE(D$57,1,1),D$57)),--('Base_Cobranzas'!$AI$2:$AI$1005<IF(D$57<3000,DATE(D$57+1,1,1),EDATE(D$57,1))),--ISNUMBER(SEARCH(IF(ISNUMBER(SEARCH("DIRECTO",UPPER($B58))),"DIRECTO",IF(ISNUMBER(SEARCH("HIPOT",UPPER($B58))),"HIPOT",IF(ISNUMBER(SEARCH("AHORRO",UPPER($B58))),"AHORRO",UPPER($B58)))),UPPER('Base_Cobranzas'!$AT$2:$AT$1005))),--ISNUMBER(SEARCH("VENCIDO",UPPER(TRIM('Base_Cobranzas'!$BC$2:$BC$1005)))),'Base_Cobranzas'!$AR$2:$AR$1005),0) | E58: =IFERROR(SUMPRODUCT(--ISNUMBER(SEARCH($B$6,'Base_Cobranzas'!$A$2:$A$1005)),--('Base_Cobranzas'!$AI$2:$AI$1005>=IF(E$57<3000,DATE(E$57,1,1),E$57)),--('Base_Cobranzas'!$AI$2:$AI$1005<IF(E$57<3000,DATE(E$57+1,1,1),EDATE(E$57,1))),--ISNUMBER(SEARCH(IF(ISNUMBER(SEARCH("DIRECTO",UPPER($B58))),"DIRECTO",IF(ISNUMBER(SEARCH("HIPOT",UPPER($B58))),"HIPOT",IF(ISNUMBER(SEARCH("AHORRO",UPPER($B58))),"AHORRO",UPPER($B58)))),UPPER('Base_Cobranzas'!$AT$2:$AT$1005))),--ISNUMBER(SEARCH("VENCIDO",UPPER(TRIM('Base_Cobranzas'!$BC$2:$BC$1005)))),'Base_Cobranzas'!$AR$2:$AR$1005),0) | F58: =IFERROR(SUMPRODUCT(--ISNUMBER(SEARCH($B$6,'Base_Cobranzas'!$A$2:$A$1005)),--('Base_Cobranzas'!$AI$2:$AI$1005>=IF(F$57<3000,DATE(F$57,1,1),F$57)),--('Base_Cobranzas'!$AI$2:$AI$1005<IF(F$57<3000,DATE(F$57+1,1,1),EDATE(F$57,1))),--ISNUMBER(SEARCH(IF(ISNUMBER(SEARCH("DIRECTO",UPPER($B58))),"DIRECTO",IF(ISNUMBER(SEARCH("HIPOT",UPPER($B58))),"HIPOT",IF(ISNUMBER(SEARCH("AHORRO",UPPER($B58))),"AHORRO",UPPER($B58)))),UPPER('Base_Cobranzas'!$AT$2:$AT$1005))),--ISNUMBER(SEARCH("VENCIDO",UPPER(TRIM('Base_Cobranzas'!$BC$2:$BC$1005)))),'Base_Cobranzas'!$AR$2:$AR$1005),0) | G58: =IFERROR(SUMPRODUCT(--ISNUMBER(SEARCH($B$6,'Base_Cobranzas'!$A$2:$A$1005)),--('Base_Cobranzas'!$AI$2:$AI$1005>=IF(G$57<3000,DATE(G$57,1,1),G$57)),--('Base_Cobranzas'!$AI$2:$AI$1005<IF(G$57<3000,DATE(G$57+1,1,1),EDATE(G$57,1))),--ISNUMBER(SEARCH(IF(ISNUMBER(SEARCH("DIRECTO",UPPER($B58))),"DIRECTO",IF(ISNUMBER(SEARCH("HIPOT",UPPER($B58))),"HIPOT",IF(ISNUMBER(SEARCH("AHORRO",UPPER($B58))),"AHORRO",UPPER($B58)))),UPPER('Base_Cobranzas'!$AT$2:$AT$1005))),--ISNUMBER(SEARCH("VENCIDO",UPPER(TRIM('Base_Cobranzas'!$BC$2:$BC$1005)))),'Base_Cobranzas'!$AR$2:$AR$1005),0) | H58: =IFERROR(SUMPRODUCT(--ISNUMBER(SEARCH($B$6,'Base_Cobranzas'!$A$2:$A$1005)),--('Base_Cobranzas'!$AI$2:$AI$1005>=IF(H$57<3000,DATE(H$57,1,1),H$57)),--('Base_Cobranzas'!$AI$2:$AI$1005<IF(H$57<3000,DATE(H$57+1,1,1),EDATE(H$57,1))),--ISNUMBER(SEARCH(IF(ISNUMBER(SEARCH("DIRECTO",UPPER($B58))),"DIRECTO",IF(ISNUMBER(SEARCH("HIPOT",UPPER($B58))),"HIPOT",IF(ISNUMBER(SEARCH("AHORRO",UPPER($B58))),"AHORRO",UPPER($B58)))),UPPER('Base_Cobranzas'!$AT$2:$AT$1005))),--ISNUMBER(SEARCH("VENCIDO",UPPER(TRIM('Base_Cobranzas'!$BC$2:$BC$1005)))),'Base_Cobranzas'!$AR$2:$AR$1005),0) | I58: =IFERROR(SUMPRODUCT(--ISNUMBER(SEARCH($B$6,'Base_Cobranzas'!$A$2:$A$1005)),--('Base_Cobranzas'!$AI$2:$AI$1005>=IF(I$57<3000,DATE(I$57,1,1),I$57)),--('Base_Cobranzas'!$AI$2:$AI$1005<IF(I$57<3000,DATE(I$57+1,1,1),EDATE(I$57,1))),--ISNUMBER(SEARCH(IF(ISNUMBER(SEARCH("DIRECTO",UPPER($B58))),"DIRECTO",IF(ISNUMBER(SEARCH("HIPOT",UPPER($B58))),"HIPOT",IF(ISNUMBER(SEARCH("AHORRO",UPPER($B58))),"AHORRO",UPPER($B58)))),UPPER('Base_Cobranzas'!$AT$2:$AT$1005))),--ISNUMBER(SEARCH("VENCIDO",UPPER(TRIM('Base_Cobranzas'!$BC$2:$BC$1005)))),'Base_Cobranzas'!$AR$2:$AR$1005),0) | J58: =IFERROR(SUMPRODUCT(--ISNUMBER(SEARCH($B$6,'Base_Cobranzas'!$A$2:$A$1005)),--('Base_Cobranzas'!$AI$2:$AI$1005>=IF(J$57<3000,DATE(J$57,1,1),J$57)),--('Base_Cobranzas'!$AI$2:$AI$1005<IF(J$57<3000,DATE(J$57+1,1,1),EDATE(J$57,1))),--ISNUMBER(SEARCH(IF(ISNUMBER(SEARCH("DIRECTO",UPPER($B58))),"DIRECTO",IF(ISNUMBER(SEARCH("HIPOT",UPPER($B58))),"HIPOT",IF(ISNUMBER(SEARCH("AHORRO",UPPER($B58))),"AHORRO",UPPER($B58)))),UPPER('Base_Cobranzas'!$AT$2:$AT$1005))),--ISNUMBER(SEARCH("VENCIDO",UPPER(TRIM('Base_Cobranzas'!$BC$2:$BC$1005)))),'Base_Cobranzas'!$AR$2:$AR$1005),0) | ... O58: =IFERROR(SUMPRODUCT(--ISNUMBER(SEARCH($B$6,'Base_Cobranzas'!$A$2:$A$1005)),--('Base_Cobranzas'!$AI$2:$AI$1005>=IF(O$57<3000,DATE(O$57,1,1),O$57)),--('Base_Cobranzas'!$AI$2:$AI$1005<IF(O$57<3000,DATE(O$57+1,1,1),EDATE(O$57,1))),--ISNUMBER(SEARCH(IF(ISNUMBER(SEARCH("DIRECTO",UPPER($B58))),"DIRECTO",IF(ISNUMBER(SEARCH("HIPOT",UPPER($B58))),"HIPOT",IF(ISNUMBER(SEARCH("AHORRO",UPPER($B58))),"AHORRO",UPPER($B58)))),UPPER('Base_Cobranzas'!$AT$2:$AT$1005))),--ISNUMBER(SEARCH("VENCIDO",UPPER(TRIM('Base_Cobranzas'!$BC$2:$BC$1005)))),'Base_Cobranzas'!$AR$2:$AR$1005),0) | P58: =SUM(C58:O58)
B59: Crédito Hipotecario | C59: =IFERROR(SUMPRODUCT(--ISNUMBER(SEARCH($B$6,'Base_Cobranzas'!$A$2:$A$1005)),--('Base_Cobranzas'!$AI$2:$AI$1005>=IF(C$57<3000,DATE(C$57,1,1),C$57)),--('Base_Cobranzas'!$AI$2:$AI$1005<IF(C$57<3000,DATE(C$57+1,1,1),EDATE(C$57,1))),--ISNUMBER(SEARCH(IF(ISNUMBER(SEARCH("DIRECTO",UPPER($B59))),"DIRECTO",IF(ISNUMBER(SEARCH("HIPOT",UPPER($B59))),"HIPOT",IF(ISNUMBER(SEARCH("AHORRO",UPPER($B59))),"AHORRO",UPPER($B59)))),UPPER('Base_Cobranzas'!$AT$2:$AT$1005))),--ISNUMBER(SEARCH("VENCIDO",UPPER(TRIM('Base_Cobranzas'!$BC$2:$BC$1005)))),'Base_Cobranzas'!$AR$2:$AR$1005),0) | D59: =IFERROR(SUMPRODUCT(--ISNUMBER(SEARCH($B$6,'Base_Cobranzas'!$A$2:$A$1005)),--('Base_Cobranzas'!$AI$2:$AI$1005>=IF(D$57<3000,DATE(D$57,1,1),D$57)),--('Base_Cobranzas'!$AI$2:$AI$1005<IF(D$57<3000,DATE(D$57+1,1,1),EDATE(D$57,1))),--ISNUMBER(SEARCH(IF(ISNUMBER(SEARCH("DIRECTO",UPPER($B59))),"DIRECTO",IF(ISNUMBER(SEARCH("HIPOT",UPPER($B59))),"HIPOT",IF(ISNUMBER(SEARCH("AHORRO",UPPER($B59))),"AHORRO",UPPER($B59)))),UPPER('Base_Cobranzas'!$AT$2:$AT$1005))),--ISNUMBER(SEARCH("VENCIDO",UPPER(TRIM('Base_Cobranzas'!$BC$2:$BC$1005)))),'Base_Cobranzas'!$AR$2:$AR$1005),0) | E59: =IFERROR(SUMPRODUCT(--ISNUMBER(SEARCH($B$6,'Base_Cobranzas'!$A$2:$A$1005)),--('Base_Cobranzas'!$AI$2:$AI$1005>=IF(E$57<3000,DATE(E$57,1,1),E$57)),--('Base_Cobranzas'!$AI$2:$AI$1005<IF(E$57<3000,DATE(E$57+1,1,1),EDATE(E$57,1))),--ISNUMBER(SEARCH(IF(ISNUMBER(SEARCH("DIRECTO",UPPER($B59))),"DIRECTO",IF(ISNUMBER(SEARCH("HIPOT",UPPER($B59))),"HIPOT",IF(ISNUMBER(SEARCH("AHORRO",UPPER($B59))),"AHORRO",UPPER($B59)))),UPPER('Base_Cobranzas'!$AT$2:$AT$1005))),--ISNUMBER(SEARCH("VENCIDO",UPPER(TRIM('Base_Cobranzas'!$BC$2:$BC$1005)))),'Base_Cobranzas'!$AR$2:$AR$1005),0) | F59: =IFERROR(SUMPRODUCT(--ISNUMBER(SEARCH($B$6,'Base_Cobranzas'!$A$2:$A$1005)),--('Base_Cobranzas'!$AI$2:$AI$1005>=IF(F$57<3000,DATE(F$57,1,1),F$57)),--('Base_Cobranzas'!$AI$2:$AI$1005<IF(F$57<3000,DATE(F$57+1,1,1),EDATE(F$57,1))),--ISNUMBER(SEARCH(IF(ISNUMBER(SEARCH("DIRECTO",UPPER($B59))),"DIRECTO",IF(ISNUMBER(SEARCH("HIPOT",UPPER($B59))),"HIPOT",IF(ISNUMBER(SEARCH("AHORRO",UPPER($B59))),"AHORRO",UPPER($B59)))),UPPER('Base_Cobranzas'!$AT$2:$AT$1005))),--ISNUMBER(SEARCH("VENCIDO",UPPER(TRIM('Base_Cobranzas'!$BC$2:$BC$1005)))),'Base_Cobranzas'!$AR$2:$AR$1005),0) | G59: =IFERROR(SUMPRODUCT(--ISNUMBER(SEARCH($B$6,'Base_Cobranzas'!$A$2:$A$1005)),--('Base_Cobranzas'!$AI$2:$AI$1005>=IF(G$57<3000,DATE(G$57,1,1),G$57)),--('Base_Cobranzas'!$AI$2:$AI$1005<IF(G$57<3000,DATE(G$57+1,1,1),EDATE(G$57,1))),--ISNUMBER(SEARCH(IF(ISNUMBER(SEARCH("DIRECTO",UPPER($B59))),"DIRECTO",IF(ISNUMBER(SEARCH("HIPOT",UPPER($B59))),"HIPOT",IF(ISNUMBER(SEARCH("AHORRO",UPPER($B59))),"AHORRO",UPPER($B59)))),UPPER('Base_Cobranzas'!$AT$2:$AT$1005))),--ISNUMBER(SEARCH("VENCIDO",UPPER(TRIM('Base_Cobranzas'!$BC$2:$BC$1005)))),'Base_Cobranzas'!$AR$2:$AR$1005),0) | H59: =IFERROR(SUMPRODUCT(--ISNUMBER(SEARCH($B$6,'Base_Cobranzas'!$A$2:$A$1005)),--('Base_Cobranzas'!$AI$2:$AI$1005>=IF(H$57<3000,DATE(H$57,1,1),H$57)),--('Base_Cobranzas'!$AI$2:$AI$1005<IF(H$57<3000,DATE(H$57+1,1,1),EDATE(H$57,1))),--ISNUMBER(SEARCH(IF(ISNUMBER(SEARCH("DIRECTO",UPPER($B59))),"DIRECTO",IF(ISNUMBER(SEARCH("HIPOT",UPPER($B59))),"HIPOT",IF(ISNUMBER(SEARCH("AHORRO",UPPER($B59))),"AHORRO",UPPER($B59)))),UPPER('Base_Cobranzas'!$AT$2:$AT$1005))),--ISNUMBER(SEARCH("VENCIDO",UPPER(TRIM('Base_Cobranzas'!$BC$2:$BC$1005)))),'Base_Cobranzas'!$AR$2:$AR$1005),0) | I59: =IFERROR(SUMPRODUCT(--ISNUMBER(SEARCH($B$6,'Base_Cobranzas'!$A$2:$A$1005)),--('Base_Cobranzas'!$AI$2:$AI$1005>=IF(I$57<3000,DATE(I$57,1,1),I$57)),--('Base_Cobranzas'!$AI$2:$AI$1005<IF(I$57<3000,DATE(I$57+1,1,1),EDATE(I$57,1))),--ISNUMBER(SEARCH(IF(ISNUMBER(SEARCH("DIRECTO",UPPER($B59))),"DIRECTO",IF(ISNUMBER(SEARCH("HIPOT",UPPER($B59))),"HIPOT",IF(ISNUMBER(SEARCH("AHORRO",UPPER($B59))),"AHORRO",UPPER($B59)))),UPPER('Base_Cobranzas'!$AT$2:$AT$1005))),--ISNUMBER(SEARCH("VENCIDO",UPPER(TRIM('Base_Cobranzas'!$BC$2:$BC$1005)))),'Base_Cobranzas'!$AR$2:$AR$1005),0) | J59: =IFERROR(SUMPRODUCT(--ISNUMBER(SEARCH($B$6,'Base_Cobranzas'!$A$2:$A$1005)),--('Base_Cobranzas'!$AI$2:$AI$1005>=IF(J$57<3000,DATE(J$57,1,1),J$57)),--('Base_Cobranzas'!$AI$2:$AI$1005<IF(J$57<3000,DATE(J$57+1,1,1),EDATE(J$57,1))),--ISNUMBER(SEARCH(IF(ISNUMBER(SEARCH("DIRECTO",UPPER($B59))),"DIRECTO",IF(ISNUMBER(SEARCH("HIPOT",UPPER($B59))),"HIPOT",IF(ISNUMBER(SEARCH("AHORRO",UPPER($B59))),"AHORRO",UPPER($B59)))),UPPER('Base_Cobranzas'!$AT$2:$AT$1005))),--ISNUMBER(SEARCH("VENCIDO",UPPER(TRIM('Base_Cobranzas'!$BC$2:$BC$1005)))),'Base_Cobranzas'!$AR$2:$AR$1005),0) | ... O59: =IFERROR(SUMPRODUCT(--ISNUMBER(SEARCH($B$6,'Base_Cobranzas'!$A$2:$A$1005)),--('Base_Cobranzas'!$AI$2:$AI$1005>=IF(O$57<3000,DATE(O$57,1,1),O$57)),--('Base_Cobranzas'!$AI$2:$AI$1005<IF(O$57<3000,DATE(O$57+1,1,1),EDATE(O$57,1))),--ISNUMBER(SEARCH(IF(ISNUMBER(SEARCH("DIRECTO",UPPER($B59))),"DIRECTO",IF(ISNUMBER(SEARCH("HIPOT",UPPER($B59))),"HIPOT",IF(ISNUMBER(SEARCH("AHORRO",UPPER($B59))),"AHORRO",UPPER($B59)))),UPPER('Base_Cobranzas'!$AT$2:$AT$1005))),--ISNUMBER(SEARCH("VENCIDO",UPPER(TRIM('Base_Cobranzas'!$BC$2:$BC$1005)))),'Base_Cobranzas'!$AR$2:$AR$1005),0) | P59: =SUM(C59:O59)
B60: Ahorro | C60: =IFERROR(SUMPRODUCT(--ISNUMBER(SEARCH($B$6,'Base_Cobranzas'!$A$2:$A$1005)),--('Base_Cobranzas'!$AI$2:$AI$1005>=IF(C$57<3000,DATE(C$57,1,1),C$57)),--('Base_Cobranzas'!$AI$2:$AI$1005<IF(C$57<3000,DATE(C$57+1,1,1),EDATE(C$57,1))),--ISNUMBER(SEARCH(IF(ISNUMBER(SEARCH("DIRECTO",UPPER($B60))),"DIRECTO",IF(ISNUMBER(SEARCH("HIPOT",UPPER($B60))),"HIPOT",IF(ISNUMBER(SEARCH("AHORRO",UPPER($B60))),"AHORRO",UPPER($B60)))),UPPER('Base_Cobranzas'!$AT$2:$AT$1005))),--ISNUMBER(SEARCH("VENCIDO",UPPER(TRIM('Base_Cobranzas'!$BC$2:$BC$1005)))),'Base_Cobranzas'!$AR$2:$AR$1005),0) | D60: =IFERROR(SUMPRODUCT(--ISNUMBER(SEARCH($B$6,'Base_Cobranzas'!$A$2:$A$1005)),--('Base_Cobranzas'!$AI$2:$AI$1005>=IF(D$57<3000,DATE(D$57,1,1),D$57)),--('Base_Cobranzas'!$AI$2:$AI$1005<IF(D$57<3000,DATE(D$57+1,1,1),EDATE(D$57,1))),--ISNUMBER(SEARCH(IF(ISNUMBER(SEARCH("DIRECTO",UPPER($B60))),"DIRECTO",IF(ISNUMBER(SEARCH("HIPOT",UPPER($B60))),"HIPOT",IF(ISNUMBER(SEARCH("AHORRO",UPPER($B60))),"AHORRO",UPPER($B60)))),UPPER('Base_Cobranzas'!$AT$2:$AT$1005))),--ISNUMBER(SEARCH("VENCIDO",UPPER(TRIM('Base_Cobranzas'!$BC$2:$BC$1005)))),'Base_Cobranzas'!$AR$2:$AR$1005),0) | E60: =IFERROR(SUMPRODUCT(--ISNUMBER(SEARCH($B$6,'Base_Cobranzas'!$A$2:$A$1005)),--('Base_Cobranzas'!$AI$2:$AI$1005>=IF(E$57<3000,DATE(E$57,1,1),E$57)),--('Base_Cobranzas'!$AI$2:$AI$1005<IF(E$57<3000,DATE(E$57+1,1,1),EDATE(E$57,1))),--ISNUMBER(SEARCH(IF(ISNUMBER(SEARCH("DIRECTO",UPPER($B60))),"DIRECTO",IF(ISNUMBER(SEARCH("HIPOT",UPPER($B60))),"HIPOT",IF(ISNUMBER(SEARCH("AHORRO",UPPER($B60))),"AHORRO",UPPER($B60)))),UPPER('Base_Cobranzas'!$AT$2:$AT$1005))),--ISNUMBER(SEARCH("VENCIDO",UPPER(TRIM('Base_Cobranzas'!$BC$2:$BC$1005)))),'Base_Cobranzas'!$AR$2:$AR$1005),0) | F60: =IFERROR(SUMPRODUCT(--ISNUMBER(SEARCH($B$6,'Base_Cobranzas'!$A$2:$A$1005)),--('Base_Cobranzas'!$AI$2:$AI$1005>=IF(F$57<3000,DATE(F$57,1,1),F$57)),--('Base_Cobranzas'!$AI$2:$AI$1005<IF(F$57<3000,DATE(F$57+1,1,1),EDATE(F$57,1))),--ISNUMBER(SEARCH(IF(ISNUMBER(SEARCH("DIRECTO",UPPER($B60))),"DIRECTO",IF(ISNUMBER(SEARCH("HIPOT",UPPER($B60))),"HIPOT",IF(ISNUMBER(SEARCH("AHORRO",UPPER($B60))),"AHORRO",UPPER($B60)))),UPPER('Base_Cobranzas'!$AT$2:$AT$1005))),--ISNUMBER(SEARCH("VENCIDO",UPPER(TRIM('Base_Cobranzas'!$BC$2:$BC$1005)))),'Base_Cobranzas'!$AR$2:$AR$1005),0) | G60: =IFERROR(SUMPRODUCT(--ISNUMBER(SEARCH($B$6,'Base_Cobranzas'!$A$2:$A$1005)),--('Base_Cobranzas'!$AI$2:$AI$1005>=IF(G$57<3000,DATE(G$57,1,1),G$57)),--('Base_Cobranzas'!$AI$2:$AI$1005<IF(G$57<3000,DATE(G$57+1,1,1),EDATE(G$57,1))),--ISNUMBER(SEARCH(IF(ISNUMBER(SEARCH("DIRECTO",UPPER($B60))),"DIRECTO",IF(ISNUMBER(SEARCH("HIPOT",UPPER($B60))),"HIPOT",IF(ISNUMBER(SEARCH("AHORRO",UPPER($B60))),"AHORRO",UPPER($B60)))),UPPER('Base_Cobranzas'!$AT$2:$AT$1005))),--ISNUMBER(SEARCH("VENCIDO",UPPER(TRIM('Base_Cobranzas'!$BC$2:$BC$1005)))),'Base_Cobranzas'!$AR$2:$AR$1005),0) | H60: =IFERROR(SUMPRODUCT(--ISNUMBER(SEARCH($B$6,'Base_Cobranzas'!$A$2:$A$1005)),--('Base_Cobranzas'!$AI$2:$AI$1005>=IF(H$57<3000,DATE(H$57,1,1),H$57)),--('Base_Cobranzas'!$AI$2:$AI$1005<IF(H$57<3000,DATE(H$57+1,1,1),EDATE(H$57,1))),--ISNUMBER(SEARCH(IF(ISNUMBER(SEARCH("DIRECTO",UPPER($B60))),"DIRECTO",IF(ISNUMBER(SEARCH("HIPOT",UPPER($B60))),"HIPOT",IF(ISNUMBER(SEARCH("AHORRO",UPPER($B60))),"AHORRO",UPPER($B60)))),UPPER('Base_Cobranzas'!$AT$2:$AT$1005))),--ISNUMBER(SEARCH("VENCIDO",UPPER(TRIM('Base_Cobranzas'!$BC$2:$BC$1005)))),'Base_Cobranzas'!$AR$2:$AR$1005),0) | I60: =IFERROR(SUMPRODUCT(--ISNUMBER(SEARCH($B$6,'Base_Cobranzas'!$A$2:$A$1005)),--('Base_Cobranzas'!$AI$2:$AI$1005>=IF(I$57<3000,DATE(I$57,1,1),I$57)),--('Base_Cobranzas'!$AI$2:$AI$1005<IF(I$57<3000,DATE(I$57+1,1,1),EDATE(I$57,1))),--ISNUMBER(SEARCH(IF(ISNUMBER(SEARCH("DIRECTO",UPPER($B60))),"DIRECTO",IF(ISNUMBER(SEARCH("HIPOT",UPPER($B60))),"HIPOT",IF(ISNUMBER(SEARCH("AHORRO",UPPER($B60))),"AHORRO",UPPER($B60)))),UPPER('Base_Cobranzas'!$AT$2:$AT$1005))),--ISNUMBER(SEARCH("VENCIDO",UPPER(TRIM('Base_Cobranzas'!$BC$2:$BC$1005)))),'Base_Cobranzas'!$AR$2:$AR$1005),0) | J60: =IFERROR(SUMPRODUCT(--ISNUMBER(SEARCH($B$6,'Base_Cobranzas'!$A$2:$A$1005)),--('Base_Cobranzas'!$AI$2:$AI$1005>=IF(J$57<3000,DATE(J$57,1,1),J$57)),--('Base_Cobranzas'!$AI$2:$AI$1005<IF(J$57<3000,DATE(J$57+1,1,1),EDATE(J$57,1))),--ISNUMBER(SEARCH(IF(ISNUMBER(SEARCH("DIRECTO",UPPER($B60))),"DIRECTO",IF(ISNUMBER(SEARCH("HIPOT",UPPER($B60))),"HIPOT",IF(ISNUMBER(SEARCH("AHORRO",UPPER($B60))),"AHORRO",UPPER($B60)))),UPPER('Base_Cobranzas'!$AT$2:$AT$1005))),--ISNUMBER(SEARCH("VENCIDO",UPPER(TRIM('Base_Cobranzas'!$BC$2:$BC$1005)))),'Base_Cobranzas'!$AR$2:$AR$1005),0) | ... O60: =IFERROR(SUMPRODUCT(--ISNUMBER(SEARCH($B$6,'Base_Cobranzas'!$A$2:$A$1005)),--('Base_Cobranzas'!$AI$2:$AI$1005>=IF(O$57<3000,DATE(O$57,1,1),O$57)),--('Base_Cobranzas'!$AI$2:$AI$1005<IF(O$57<3000,DATE(O$57+1,1,1),EDATE(O$57,1))),--ISNUMBER(SEARCH(IF(ISNUMBER(SEARCH("DIRECTO",UPPER($B60))),"DIRECTO",IF(ISNUMBER(SEARCH("HIPOT",UPPER($B60))),"HIPOT",IF(ISNUMBER(SEARCH("AHORRO",UPPER($B60))),"AHORRO",UPPER($B60)))),UPPER('Base_Cobranzas'!$AT$2:$AT$1005))),--ISNUMBER(SEARCH("VENCIDO",UPPER(TRIM('Base_Cobranzas'!$BC$2:$BC$1005)))),'Base_Cobranzas'!$AR$2:$AR$1005),0) | P60: =SUM(C60:O60)
B61: Total | C61: =SUM(C58:C60) | D61: =SUM(D58:D60) | E61: =SUM(E58:E60) | F61: =SUM(F58:F60) | G61: =SUM(G58:G60) | H61: =SUM(H58:H60) | I61: =SUM(I58:I60) | J61: =SUM(J58:J60) | ... O61: =SUM(O58:O60) | P61: =SUM(C61:O61) | Q61: =IF($I$21=P61,"OK","REVISAR")
B63: Acumulado | C63: =C61 | D63: =C63+D61 | E63: =D63+E61 | F63: =E63+F61 | G63: =F63+G61 | H63: =G63+H61 | I63: =H63+I61 | J63: =I63+J61 | K63: =J63+K61 | ... O63: =N63+O61

Sheet Beyond
C5: REPORTE DE COBRANZAS
B6: Beyond
C8: Vendido | F8: Cobranzas
C9: Monto | D9: Unidades | F9: Avance | G9: Cobrado | H9: Por Cobrar | I9: Vencido | J9: Tasa de Morosidad | K9: Clientes Morosos (unidades) | L9: Dias de Atraso (Promedio)
B11: Departamentos | C11: 21112400 | D11: 65 | F11: =IF(C11=0,0,G11/C11) | G11: =SUM(G12:G13) | H11: =SUM(H12:H13) | I11: =SUM(I12:I13) | J11: =IF(C11=0,0,I11/C11) | K11: 30 | L11: 142
B12: Departamento | C12: 12502900 | D12: 28 | F12: =IF(C12=0,0,G12/C12) | G12: =IFERROR(SUMPRODUCT(--ISNUMBER(SEARCH($B$6,'Base_Cobranzas'!$A$2:$A$1005)),--((--ISNUMBER(SEARCH("DEPART",UPPER('Base_Cobranzas'!$E$2:$E$1005)))+--ISNUMBER(SEARCH("DEPART",UPPER('Base_Cobranzas'!$K$2:$K$1005)))+--ISNUMBER(SEARCH("DEPART",UPPER('Base_Cobranzas'!$Q$2:$Q$1005)))+--ISNUMBER(SEARCH("DEPART",UPPER('Base_Cobranzas'!$W$2:$W$1005))))>0),--((--ISNUMBER(SEARCH("ESTACION",UPPER('Base_Cobranzas'!$E$2:$E$1005)))+--ISNUMBER(SEARCH("ESTACION",UPPER('Base_Cobranzas'!$K$2:$K$1005)))+--ISNUMBER(SEARCH("ESTACION",UPPER('Base_Cobranzas'!$Q$2:$Q$1005)))+--ISNUMBER(SEARCH("ESTACION",UPPER('Base_Cobranzas'!$W$2:$W$1005))))=0),--('Base_Cobranzas'!$AQ$2:$AQ$1005>0),'Base_Cobranzas'!$AQ$2:$AQ$1005),0) | H12: =IFERROR(SUMPRODUCT(--ISNUMBER(SEARCH($B$6,'Base_Cobranzas'!$A$2:$A$1005)),--((--ISNUMBER(SEARCH("DEPART",UPPER('Base_Cobranzas'!$E$2:$E$1005)))+--ISNUMBER(SEARCH("DEPART",UPPER('Base_Cobranzas'!$K$2:$K$1005)))+--ISNUMBER(SEARCH("DEPART",UPPER('Base_Cobranzas'!$Q$2:$Q$1005)))+--ISNUMBER(SEARCH("DEPART",UPPER('Base_Cobranzas'!$W$2:$W$1005))))>0),--((--ISNUMBER(SEARCH("ESTACION",UPPER('Base_Cobranzas'!$E$2:$E$1005)))+--ISNUMBER(SEARCH("ESTACION",UPPER('Base_Cobranzas'!$K$2:$K$1005)))+--ISNUMBER(SEARCH("ESTACION",UPPER('Base_Cobranzas'!$Q$2:$Q$1005)))+--ISNUMBER(SEARCH("ESTACION",UPPER('Base_Cobranzas'!$W$2:$W$1005))))=0),--ISNUMBER(SEARCH("PENDIENTE",UPPER(TRIM('Base_Cobranzas'!$BC$2:$BC$1005)))),'Base_Cobranzas'!$AR$2:$AR$1005),0) | I12: =IFERROR(SUMPRODUCT(--ISNUMBER(SEARCH($B$6,'Base_Cobranzas'!$A$2:$A$1005)),--((--ISNUMBER(SEARCH("DEPART",UPPER('Base_Cobranzas'!$E$2:$E$1005)))+--ISNUMBER(SEARCH("DEPART",UPPER('Base_Cobranzas'!$K$2:$K$1005)))+--ISNUMBER(SEARCH("DEPART",UPPER('Base_Cobranzas'!$Q$2:$Q$1005)))+--ISNUMBER(SEARCH("DEPART",UPPER('Base_Cobranzas'!$W$2:$W$1005))))>0),--((--ISNUMBER(SEARCH("ESTACION",UPPER('Base_Cobranzas'!$E$2:$E$1005)))+--ISNUMBER(SEARCH("ESTACION",UPPER('Base_Cobranzas'!$K$2:$K$1005)))+--ISNUMBER(SEARCH("ESTACION",UPPER('Base_Cobranzas'!$Q$2:$Q$1005)))+--ISNUMBER(SEARCH("ESTACION",UPPER('Base_Cobranzas'!$W$2:$W$1005))))=0),--ISNUMBER(SEARCH("VENCIDO",UPPER(TRIM('Base_Cobranzas'!$BC$2:$BC$1005)))),'Base_Cobranzas'!$AR$2:$AR$1005),0) | J12: =IF(C12=0,0,I12/C12) | K12: 22 | L12: 75
B13: Departamento + Estacionamiento | C13: 8609500 | D13: 37 | F13: =IF(C13=0,0,G13/C13) | G13: =IFERROR(SUMPRODUCT(--ISNUMBER(SEARCH($B$6,'Base_Cobranzas'!$A$2:$A$1005)),--((--ISNUMBER(SEARCH("DEPART",UPPER('Base_Cobranzas'!$E$2:$E$1005)))+--ISNUMBER(SEARCH("DEPART",UPPER('Base_Cobranzas'!$K$2:$K$1005)))+--ISNUMBER(SEARCH("DEPART",UPPER('Base_Cobranzas'!$Q$2:$Q$1005)))+--ISNUMBER(SEARCH("DEPART",UPPER('Base_Cobranzas'!$W$2:$W$1005))))>0),--((--ISNUMBER(SEARCH("ESTACION",UPPER('Base_Cobranzas'!$E$2:$E$1005)))+--ISNUMBER(SEARCH("ESTACION",UPPER('Base_Cobranzas'!$K$2:$K$1005)))+--ISNUMBER(SEARCH("ESTACION",UPPER('Base_Cobranzas'!$Q$2:$Q$1005)))+--ISNUMBER(SEARCH("ESTACION",UPPER('Base_Cobranzas'!$W$2:$W$1005))))>0),--('Base_Cobranzas'!$AQ$2:$AQ$1005>0),'Base_Cobranzas'!$AQ$2:$AQ$1005),0) | H13: =IFERROR(SUMPRODUCT(--ISNUMBER(SEARCH($B$6,'Base_Cobranzas'!$A$2:$A$1005)),--((--ISNUMBER(SEARCH("DEPART",UPPER('Base_Cobranzas'!$E$2:$E$1005)))+--ISNUMBER(SEARCH("DEPART",UPPER('Base_Cobranzas'!$K$2:$K$1005)))+--ISNUMBER(SEARCH("DEPART",UPPER('Base_Cobranzas'!$Q$2:$Q$1005)))+--ISNUMBER(SEARCH("DEPART",UPPER('Base_Cobranzas'!$W$2:$W$1005))))>0),--((--ISNUMBER(SEARCH("ESTACION",UPPER('Base_Cobranzas'!$E$2:$E$1005)))+--ISNUMBER(SEARCH("ESTACION",UPPER('Base_Cobranzas'!$K$2:$K$1005)))+--ISNUMBER(SEARCH("ESTACION",UPPER('Base_Cobranzas'!$Q$2:$Q$1005)))+--ISNUMBER(SEARCH("ESTACION",UPPER('Base_Cobranzas'!$W$2:$W$1005))))>0),--ISNUMBER(SEARCH("PENDIENTE",UPPER(TRIM('Base_Cobranzas'!$BC$2:$BC$1005)))),'Base_Cobranzas'!$AR$2:$AR$1005),0) | I13: =IFERROR(SUMPRODUCT(--ISNUMBER(SEARCH($B$6,'Base_Cobranzas'!$A$2:$A$1005)),--((--ISNUMBER(SEARCH("DEPART",UPPER('Base_Cobranzas'!$E$2:$E$1005)))+--ISNUMBER(SEARCH("DEPART",UPPER('Base_Cobranzas'!$K$2:$K$1005)))+--ISNUMBER(SEARCH("DEPART",UPPER('Base_Cobranzas'!$Q$2:$Q$1005)))+--ISNUMBER(SEARCH("DEPART",UPPER('Base_Cobranzas'!$W$2:$W$1005))))>0),--((--ISNUMBER(SEARCH("ESTACION",UPPER('Base_Cobranzas'!$E$2:$E$1005)))+--ISNUMBER(SEARCH("ESTACION",UPPER('Base_Cobranzas'!$K$2:$K$1005)))+--ISNUMBER(SEARCH("ESTACION",UPPER('Base_Cobranzas'!$Q$2:$Q$1005)))+--ISNUMBER(SEARCH("ESTACION",UPPER('Base_Cobranzas'!$W$2:$W$1005))))>0),--ISNUMBER(SEARCH("VENCIDO",UPPER(TRIM('Base_Cobranzas'!$BC$2:$BC$1005)))),'Base_Cobranzas'!$AR$2:$AR$1005),0) | J13: =IF(C13=0,0,I13/C13) | K13: 8 | L13: 216
B15: Estacionamientos | C15: 604800 | D15: 12 | F15: =IF(C15=0,0,G15/C15) | G15: =IFERROR(SUMPRODUCT(--ISNUMBER(SEARCH($B$6,'Base_Cobranzas'!$A$2:$A$1005)),--((--ISNUMBER(SEARCH("DEPART",UPPER('Base_Cobranzas'!$E$2:$E$1005)))+--ISNUMBER(SEARCH("DEPART",UPPER('Base_Cobranzas'!$K$2:$K$1005)))+--ISNUMBER(SEARCH("DEPART",UPPER('Base_Cobranzas'!$Q$2:$Q$1005)))+--ISNUMBER(SEARCH("DEPART",UPPER('Base_Cobranzas'!$W$2:$W$1005))))=0),--((--ISNUMBER(SEARCH("ESTACION",UPPER('Base_Cobranzas'!$E$2:$E$1005)))+--ISNUMBER(SEARCH("ESTACION",UPPER('Base_Cobranzas'!$K$2:$K$1005)))+--ISNUMBER(SEARCH("ESTACION",UPPER('Base_Cobranzas'!$Q$2:$Q$1005)))+--ISNUMBER(SEARCH("ESTACION",UPPER('Base_Cobranzas'!$W$2:$W$1005))))>0),--('Base_Cobranzas'!$AQ$2:$AQ$1005>0),'Base_Cobranzas'!$AQ$2:$AQ$1005),0) | H15: =IFERROR(SUMPRODUCT(--ISNUMBER(SEARCH($B$6,'Base_Cobranzas'!$A$2:$A$1005)),--((--ISNUMBER(SEARCH("DEPART",UPPER('Base_Cobranzas'!$E$2:$E$1005)))+--ISNUMBER(SEARCH("DEPART",UPPER('Base_Cobranzas'!$K$2:$K$1005)))+--ISNUMBER(SEARCH("DEPART",UPPER('Base_Cobranzas'!$Q$2:$Q$1005)))+--ISNUMBER(SEARCH("DEPART",UPPER('Base_Cobranzas'!$W$2:$W$1005))))=0),--((--ISNUMBER(SEARCH("ESTACION",UPPER('Base_Cobranzas'!$E$2:$E$1005)))+--ISNUMBER(SEARCH("ESTACION",UPPER('Base_Cobranzas'!$K$2:$K$1005)))+--ISNUMBER(SEARCH("ESTACION",UPPER('Base_Cobranzas'!$Q$2:$Q$1005)))+--ISNUMBER(SEARCH("ESTACION",UPPER('Base_Cobranzas'!$W$2:$W$1005))))>0),--ISNUMBER(SEARCH("PENDIENTE",UPPER(TRIM('Base_Cobranzas'!$BC$2:$BC$1005)))),'Base_Cobranzas'!$AR$2:$AR$1005),0) | I15: =IFERROR(SUMPRODUCT(--ISNUMBER(SEARCH($B$6,'Base_Cobranzas'!$A$2:$A$1005)),--((--ISNUMBER(SEARCH("DEPART",UPPER('Base_Cobranzas'!$E$2:$E$1005)))+--ISNUMBER(SEARCH("DEPART",UPPER('Base_Cobranzas'!$K$2:$K$1005)))+--ISNUMBER(SEARCH("DEPART",UPPER('Base_Cobranzas'!$Q$2:$Q$1005)))+--ISNUMBER(SEARCH("DEPART",UPPER('Base_Cobranzas'!$W$2:$W$1005))))=0),--((--ISNUMBER(SEARCH("ESTACION",UPPER('Base_Cobranzas'!$E$2:$E$1005)))+--ISNUMBER(SEARCH("ESTACION",UPPER('Base_Cobranzas'!$K$2:$K$1005)))+--ISNUMBER(SEARCH("ESTACION",UPPER('Base_Cobranzas'!$Q$2:$Q$1005)))+--ISNUMBER(SEARCH("ESTACION",UPPER('Base_Cobranzas'!$W$2:$W$1005))))>0),--ISNUMBER(SEARCH("VENCIDO",UPPER(TRIM('Base_Cobranzas'!$BC$2:$BC$1005)))),'Base_Cobranzas'!$AR$2:$AR$1005),0) | J15: =IF(C15=0,0,I15/C15) | K15: 6 | L15: 108
B17: Depositos | C17: 19100 | D17: 2 | F17: =IF(C17=0,0,G17/C17) | G17: =IFERROR(SUMPRODUCT(--ISNUMBER(SEARCH($B$6,'Base_Cobranzas'!$A$2:$A$1005)),--((--ISNUMBER(SEARCH("DEPART",UPPER('Base_Cobranzas'!$E$2:$E$1005)))+--ISNUMBER(SEARCH("DEPART",UPPER('Base_Cobranzas'!$K$2:$K$1005)))+--ISNUMBER(SEARCH("DEPART",UPPER('Base_Cobranzas'!$Q$2:$Q$1005)))+--ISNUMBER(SEARCH("DEPART",UPPER('Base_Cobranzas'!$W$2:$W$1005))))=0),--((--ISNUMBER(SEARCH("ESTACION",UPPER('Base_Cobranzas'!$E$2:$E$1005)))+--ISNUMBER(SEARCH("ESTACION",UPPER('Base_Cobranzas'!$K$2:$K$1005)))+--ISNUMBER(SEARCH("ESTACION",UPPER('Base_Cobranzas'!$Q$2:$Q$1005)))+--ISNUMBER(SEARCH("ESTACION",UPPER('Base_Cobranzas'!$W$2:$W$1005))))=0),--((--ISNUMBER(SEARCH("DEPOS",UPPER('Base_Cobranzas'!$E$2:$E$1005)))+--ISNUMBER(SEARCH("DEPOS",UPPER('Base_Cobranzas'!$K$2:$K$1005)))+--ISNUMBER(SEARCH("DEPOS",UPPER('Base_Cobranzas'!$Q$2:$Q$1005)))+--ISNUMBER(SEARCH("DEPOS",UPPER('Base_Cobranzas'!$W$2:$W$1005))))>0),--('Base_Cobranzas'!$AQ$2:$AQ$1005>0),'Base_Cobranzas'!$AQ$2:$AQ$1005),0) | H17: =IFERROR(SUMPRODUCT(--ISNUMBER(SEARCH($B$6,'Base_Cobranzas'!$A$2:$A$1005)),--((--ISNUMBER(SEARCH("DEPART",UPPER('Base_Cobranzas'!$E$2:$E$1005)))+--ISNUMBER(SEARCH("DEPART",UPPER('Base_Cobranzas'!$K$2:$K$1005)))+--ISNUMBER(SEARCH("DEPART",UPPER('Base_Cobranzas'!$Q$2:$Q$1005)))+--ISNUMBER(SEARCH("DEPART",UPPER('Base_Cobranzas'!$W$2:$W$1005))))=0),--((--ISNUMBER(SEARCH("ESTACION",UPPER('Base_Cobranzas'!$E$2:$E$1005)))+--ISNUMBER(SEARCH("ESTACION",UPPER('Base_Cobranzas'!$K$2:$K$1005)))+--ISNUMBER(SEARCH("ESTACION",UPPER('Base_Cobranzas'!$Q$2:$Q$1005)))+--ISNUMBER(SEARCH("ESTACION",UPPER('Base_Cobranzas'!$W$2:$W$1005))))=0),--((--ISNUMBER(SEARCH("DEPOS",UPPER('Base_Cobranzas'!$E$2:$E$1005)))+--ISNUMBER(SEARCH("DEPOS",UPPER('Base_Cobranzas'!$K$2:$K$1005)))+--ISNUMBER(SEARCH("DEPOS",UPPER('Base_Cobranzas'!$Q$2:$Q$1005)))+--ISNUMBER(SEARCH("DEPOS",UPPER('Base_Cobranzas'!$W$2:$W$1005))))>0),--ISNUMBER(SEARCH("PENDIENTE",UPPER(TRIM('Base_Cobranzas'!$BC$2:$BC$1005)))),'Base_Cobranzas'!$AR$2:$AR$1005),0) | I17: =IFERROR(SUMPRODUCT(--ISNUMBER(SEARCH($B$6,'Base_Cobranzas'!$A$2:$A$1005)),--((--ISNUMBER(SEARCH("DEPART",UPPER('Base_Cobranzas'!$E$2:$E$1005)))+--ISNUMBER(SEARCH("DEPART",UPPER('Base_Cobranzas'!$K$2:$K$1005)))+--ISNUMBER(SEARCH("DEPART",UPPER('Base_Cobranzas'!$Q$2:$Q$1005)))+--ISNUMBER(SEARCH("DEPART",UPPER('Base_Cobranzas'!$W$2:$W$1005))))=0),--((--ISNUMBER(SEARCH("ESTACION",UPPER('Base_Cobranzas'!$E$2:$E$1005)))+--ISNUMBER(SEARCH("ESTACION",UPPER('Base_Cobranzas'!$K$2:$K$1005)))+--ISNUMBER(SEARCH("ESTACION",UPPER('Base_Cobranzas'!$Q$2:$Q$1005)))+--ISNUMBER(SEARCH("ESTACION",UPPER('Base_Cobranzas'!$W$2:$W$1005))))=0),--((--ISNUMBER(SEARCH("DEPOS",UPPER('Base_Cobranzas'!$E$2:$E$1005)))+--ISNUMBER(SEARCH("DEPOS",UPPER('Base_Cobranzas'!$K$2:$K$1005)))+--ISNUMBER(SEARCH("DEPOS",UPPER('Base_Cobranzas'!$Q$2:$Q$1005)))+--ISNUMBER(SEARCH("DEPOS",UPPER('Base_Cobranzas'!$W$2:$W$1005))))>0),--ISNUMBER(SEARCH("VENCIDO",UPPER(TRIM('Base_Cobranzas'!$BC$2:$BC$1005)))),'Base_Cobranzas'!$AR$2:$AR$1005),0) | J17: =IF(C17=0,0,I17/C17) | K17: 0 | L17: 0
B19: Local Comercial | C19: 0 | D19: 0 | F19: =IF(C19=0,0,G19/C19) | G19: =IFERROR(SUMPRODUCT(--ISNUMBER(SEARCH($B$6,'Base_Cobranzas'!$A$2:$A$1005)),--(((--ISNUMBER(SEARCH("LOCAL",UPPER('Base_Cobranzas'!$E$2:$E$1005)))+--ISNUMBER(SEARCH("LOCAL",UPPER('Base_Cobranzas'!$K$2:$K$1005)))+--ISNUMBER(SEARCH("LOCAL",UPPER('Base_Cobranzas'!$Q$2:$Q$1005)))+--ISNUMBER(SEARCH("LOCAL",UPPER('Base_Cobranzas'!$W$2:$W$1005))))+(--ISNUMBER(SEARCH("COMERCIAL",UPPER('Base_Cobranzas'!$E$2:$E$1005)))+--ISNUMBER(SEARCH("COMERCIAL",UPPER('Base_Cobranzas'!$K$2:$K$1005)))+--ISNUMBER(SEARCH("COMERCIAL",UPPER('Base_Cobranzas'!$Q$2:$Q$1005)))+--ISNUMBER(SEARCH("COMERCIAL",UPPER('Base_Cobranzas'!$W$2:$W$1005)))))>0),--('Base_Cobranzas'!$AQ$2:$AQ$1005>0),'Base_Cobranzas'!$AQ$2:$AQ$1005),0) | H19: =IFERROR(SUMPRODUCT(--ISNUMBER(SEARCH($B$6,'Base_Cobranzas'!$A$2:$A$1005)),--(((--ISNUMBER(SEARCH("LOCAL",UPPER('Base_Cobranzas'!$E$2:$E$1005)))+--ISNUMBER(SEARCH("LOCAL",UPPER('Base_Cobranzas'!$K$2:$K$1005)))+--ISNUMBER(SEARCH("LOCAL",UPPER('Base_Cobranzas'!$Q$2:$Q$1005)))+--ISNUMBER(SEARCH("LOCAL",UPPER('Base_Cobranzas'!$W$2:$W$1005))))+(--ISNUMBER(SEARCH("COMERCIAL",UPPER('Base_Cobranzas'!$E$2:$E$1005)))+--ISNUMBER(SEARCH("COMERCIAL",UPPER('Base_Cobranzas'!$K$2:$K$1005)))+--ISNUMBER(SEARCH("COMERCIAL",UPPER('Base_Cobranzas'!$Q$2:$Q$1005)))+--ISNUMBER(SEARCH("COMERCIAL",UPPER('Base_Cobranzas'!$W$2:$W$1005)))))>0),--ISNUMBER(SEARCH("PENDIENTE",UPPER(TRIM('Base_Cobranzas'!$BC$2:$BC$1005)))),'Base_Cobranzas'!$AR$2:$AR$1005),0) | I19: =IFERROR(SUMPRODUCT(--ISNUMBER(SEARCH($B$6,'Base_Cobranzas'!$A$2:$A$1005)),--(((--ISNUMBER(SEARCH("LOCAL",UPPER('Base_Cobranzas'!$E$2:$E$1005)))+--ISNUMBER(SEARCH("LOCAL",UPPER('Base_Cobranzas'!$K$2:$K$1005)))+--ISNUMBER(SEARCH("LOCAL",UPPER('Base_Cobranzas'!$Q$2:$Q$1005)))+--ISNUMBER(SEARCH("LOCAL",UPPER('Base_Cobranzas'!$W$2:$W$1005))))+(--ISNUMBER(SEARCH("COMERCIAL",UPPER('Base_Cobranzas'!$E$2:$E$1005)))+--ISNUMBER(SEARCH("COMERCIAL",UPPER('Base_Cobranzas'!$K$2:$K$1005)))+--ISNUMBER(SEARCH("COMERCIAL",UPPER('Base_Cobranzas'!$Q$2:$Q$1005)))+--ISNUMBER(SEARCH("COMERCIAL",UPPER('Base_Cobranzas'!$W$2:$W$1005)))))>0),--ISNUMBER(SEARCH("VENCIDO",UPPER(TRIM('Base_Cobranzas'!$BC$2:$BC$1005)))),'Base_Cobranzas'!$AR$2:$AR$1005),0) | J19: =IF(C19=0,0,I19/C19) | K19: 0 | L19: 0
A21: =+IF(ROUND(C21,0)=ROUND(G21+H21+I21,0),"OK","REVISAR") | B21: Total | C21: 21736300 | D21: 79 | F21: =IF(C21=0,0,G21/C21) | G21: =G11+G15+G17+G19 | H21: =H11+H15+H17+H19 | I21: =I11+I15+I17+I19 | J21: =IF(C21=0,0,I21/C21) | K21: 31 | L21: 134
B31: COBRANZA REAL
B33: Tipo de Credito | C33: 2024 | D33: 2025 | E33: 46023 | F33: 46054 | G33: 46082 | H33: 46113 | I33: 46143 | J33: 46174 | K33: 46204 | L33: 46235 | M33: 46266 | N33: 46296 | O33: 46327 | P33: Total
B34: Crédito Directo | C34: =IFERROR(SUMPRODUCT(--ISNUMBER(SEARCH($B$6,'Base_Cobranzas'!$A$2:$A$1005)),--('Base_Cobranzas'!$AJ$2:$AJ$1005>=IF(C$33<3000,DATE(C$33,1,1),C$33)),--('Base_Cobranzas'!$AJ$2:$AJ$1005<IF(C$33<3000,DATE(C$33+1,1,1),EDATE(C$33,1))),--ISNUMBER(SEARCH(IF(ISNUMBER(SEARCH("DIRECTO",UPPER($B34))),"DIRECTO",IF(ISNUMBER(SEARCH("HIPOT",UPPER($B34))),"HIPOT",IF(ISNUMBER(SEARCH("AHORRO",UPPER($B34))),"AHORRO",UPPER($B34)))),UPPER('Base_Cobranzas'!$AT$2:$AT$1005))),--('Base_Cobranzas'!$AQ$2:$AQ$1005>0),'Base_Cobranzas'!$AQ$2:$AQ$1005),0) | D34: =IFERROR(SUMPRODUCT(--ISNUMBER(SEARCH($B$6,'Base_Cobranzas'!$A$2:$A$1005)),--('Base_Cobranzas'!$AJ$2:$AJ$1005>=IF(D$33<3000,DATE(D$33,1,1),D$33)),--('Base_Cobranzas'!$AJ$2:$AJ$1005<IF(D$33<3000,DATE(D$33+1,1,1),EDATE(D$33,1))),--ISNUMBER(SEARCH(IF(ISNUMBER(SEARCH("DIRECTO",UPPER($B34))),"DIRECTO",IF(ISNUMBER(SEARCH("HIPOT",UPPER($B34))),"HIPOT",IF(ISNUMBER(SEARCH("AHORRO",UPPER($B34))),"AHORRO",UPPER($B34)))),UPPER('Base_Cobranzas'!$AT$2:$AT$1005))),--('Base_Cobranzas'!$AQ$2:$AQ$1005>0),'Base_Cobranzas'!$AQ$2:$AQ$1005),0) | E34: =IFERROR(SUMPRODUCT(--ISNUMBER(SEARCH($B$6,'Base_Cobranzas'!$A$2:$A$1005)),--('Base_Cobranzas'!$AJ$2:$AJ$1005>=IF(E$33<3000,DATE(E$33,1,1),E$33)),--('Base_Cobranzas'!$AJ$2:$AJ$1005<IF(E$33<3000,DATE(E$33+1,1,1),EDATE(E$33,1))),--ISNUMBER(SEARCH(IF(ISNUMBER(SEARCH("DIRECTO",UPPER($B34))),"DIRECTO",IF(ISNUMBER(SEARCH("HIPOT",UPPER($B34))),"HIPOT",IF(ISNUMBER(SEARCH("AHORRO",UPPER($B34))),"AHORRO",UPPER($B34)))),UPPER('Base_Cobranzas'!$AT$2:$AT$1005))),--('Base_Cobranzas'!$AQ$2:$AQ$1005>0),'Base_Cobranzas'!$AQ$2:$AQ$1005),0) | F34: =IFERROR(SUMPRODUCT(--ISNUMBER(SEARCH($B$6,'Base_Cobranzas'!$A$2:$A$1005)),--('Base_Cobranzas'!$AJ$2:$AJ$1005>=IF(F$33<3000,DATE(F$33,1,1),F$33)),--('Base_Cobranzas'!$AJ$2:$AJ$1005<IF(F$33<3000,DATE(F$33+1,1,1),EDATE(F$33,1))),--ISNUMBER(SEARCH(IF(ISNUMBER(SEARCH("DIRECTO",UPPER($B34))),"DIRECTO",IF(ISNUMBER(SEARCH("HIPOT",UPPER($B34))),"HIPOT",IF(ISNUMBER(SEARCH("AHORRO",UPPER($B34))),"AHORRO",UPPER($B34)))),UPPER('Base_Cobranzas'!$AT$2:$AT$1005))),--('Base_Cobranzas'!$AQ$2:$AQ$1005>0),'Base_Cobranzas'!$AQ$2:$AQ$1005),0) | G34: =IFERROR(SUMPRODUCT(--ISNUMBER(SEARCH($B$6,'Base_Cobranzas'!$A$2:$A$1005)),--('Base_Cobranzas'!$AJ$2:$AJ$1005>=IF(G$33<3000,DATE(G$33,1,1),G$33)),--('Base_Cobranzas'!$AJ$2:$AJ$1005<IF(G$33<3000,DATE(G$33+1,1,1),EDATE(G$33,1))),--ISNUMBER(SEARCH(IF(ISNUMBER(SEARCH("DIRECTO",UPPER($B34))),"DIRECTO",IF(ISNUMBER(SEARCH("HIPOT",UPPER($B34))),"HIPOT",IF(ISNUMBER(SEARCH("AHORRO",UPPER($B34))),"AHORRO",UPPER($B34)))),UPPER('Base_Cobranzas'!$AT$2:$AT$1005))),--('Base_Cobranzas'!$AQ$2:$AQ$1005>0),'Base_Cobranzas'!$AQ$2:$AQ$1005),0) | H34: =IFERROR(SUMPRODUCT(--ISNUMBER(SEARCH($B$6,'Base_Cobranzas'!$A$2:$A$1005)),--('Base_Cobranzas'!$AJ$2:$AJ$1005>=IF(H$33<3000,DATE(H$33,1,1),H$33)),--('Base_Cobranzas'!$AJ$2:$AJ$1005<IF(H$33<3000,DATE(H$33+1,1,1),EDATE(H$33,1))),--ISNUMBER(SEARCH(IF(ISNUMBER(SEARCH("DIRECTO",UPPER($B34))),"DIRECTO",IF(ISNUMBER(SEARCH("HIPOT",UPPER($B34))),"HIPOT",IF(ISNUMBER(SEARCH("AHORRO",UPPER($B34))),"AHORRO",UPPER($B34)))),UPPER('Base_Cobranzas'!$AT$2:$AT$1005))),--('Base_Cobranzas'!$AQ$2:$AQ$1005>0),'Base_Cobranzas'!$AQ$2:$AQ$1005),0) | I34: =IFERROR(SUMPRODUCT(--ISNUMBER(SEARCH($B$6,'Base_Cobranzas'!$A$2:$A$1005)),--('Base_Cobranzas'!$AJ$2:$AJ$1005>=IF(I$33<3000,DATE(I$33,1,1),I$33)),--('Base_Cobranzas'!$AJ$2:$AJ$1005<IF(I$33<3000,DATE(I$33+1,1,1),EDATE(I$33,1))),--ISNUMBER(SEARCH(IF(ISNUMBER(SEARCH("DIRECTO",UPPER($B34))),"DIRECTO",IF(ISNUMBER(SEARCH("HIPOT",UPPER($B34))),"HIPOT",IF(ISNUMBER(SEARCH("AHORRO",UPPER($B34))),"AHORRO",UPPER($B34)))),UPPER('Base_Cobranzas'!$AT$2:$AT$1005))),--('Base_Cobranzas'!$AQ$2:$AQ$1005>0),'Base_Cobranzas'!$AQ$2:$AQ$1005),0) | J34: =IFERROR(SUMPRODUCT(--ISNUMBER(SEARCH($B$6,'Base_Cobranzas'!$A$2:$A$1005)),--('Base_Cobranzas'!$AJ$2:$AJ$1005>=IF(J$33<3000,DATE(J$33,1,1),J$33)),--('Base_Cobranzas'!$AJ$2:$AJ$1005<IF(J$33<3000,DATE(J$33+1,1,1),EDATE(J$33,1))),--ISNUMBER(SEARCH(IF(ISNUMBER(SEARCH("DIRECTO",UPPER($B34))),"DIRECTO",IF(ISNUMBER(SEARCH("HIPOT",UPPER($B34))),"HIPOT",IF(ISNUMBER(SEARCH("AHORRO",UPPER($B34))),"AHORRO",UPPER($B34)))),UPPER('Base_Cobranzas'!$AT$2:$AT$1005))),--('Base_Cobranzas'!$AQ$2:$AQ$1005>0),'Base_Cobranzas'!$AQ$2:$AQ$1005),0) | ... O34: =IFERROR(SUMPRODUCT(--ISNUMBER(SEARCH($B$6,'Base_Cobranzas'!$A$2:$A$1005)),--('Base_Cobranzas'!$AJ$2:$AJ$1005>=IF(O$33<3000,DATE(O$33,1,1),O$33)),--('Base_Cobranzas'!$AJ$2:$AJ$1005<IF(O$33<3000,DATE(O$33+1,1,1),EDATE(O$33,1))),--ISNUMBER(SEARCH(IF(ISNUMBER(SEARCH("DIRECTO",UPPER($B34))),"DIRECTO",IF(ISNUMBER(SEARCH("HIPOT",UPPER($B34))),"HIPOT",IF(ISNUMBER(SEARCH("AHORRO",UPPER($B34))),"AHORRO",UPPER($B34)))),UPPER('Base_Cobranzas'!$AT$2:$AT$1005))),--('Base_Cobranzas'!$AQ$2:$AQ$1005>0),'Base_Cobranzas'!$AQ$2:$AQ$1005),0) | P34: =SUM(C34:O34)
B35: Crédito Hipotecario | C35: =IFERROR(SUMPRODUCT(--ISNUMBER(SEARCH($B$6,'Base_Cobranzas'!$A$2:$A$1005)),--('Base_Cobranzas'!$AJ$2:$AJ$1005>=IF(C$33<3000,DATE(C$33,1,1),C$33)),--('Base_Cobranzas'!$AJ$2:$AJ$1005<IF(C$33<3000,DATE(C$33+1,1,1),EDATE(C$33,1))),--ISNUMBER(SEARCH(IF(ISNUMBER(SEARCH("DIRECTO",UPPER($B35))),"DIRECTO",IF(ISNUMBER(SEARCH("HIPOT",UPPER($B35))),"HIPOT",IF(ISNUMBER(SEARCH("AHORRO",UPPER($B35))),"AHORRO",UPPER($B35)))),UPPER('Base_Cobranzas'!$AT$2:$AT$1005))),--('Base_Cobranzas'!$AQ$2:$AQ$1005>0),'Base_Cobranzas'!$AQ$2:$AQ$1005),0) | D35: =IFERROR(SUMPRODUCT(--ISNUMBER(SEARCH($B$6,'Base_Cobranzas'!$A$2:$A$1005)),--('Base_Cobranzas'!$AJ$2:$AJ$1005>=IF(D$33<3000,DATE(D$33,1,1),D$33)),--('Base_Cobranzas'!$AJ$2:$AJ$1005<IF(D$33<3000,DATE(D$33+1,1,1),EDATE(D$33,1))),--ISNUMBER(SEARCH(IF(ISNUMBER(SEARCH("DIRECTO",UPPER($B35))),"DIRECTO",IF(ISNUMBER(SEARCH("HIPOT",UPPER($B35))),"HIPOT",IF(ISNUMBER(SEARCH("AHORRO",UPPER($B35))),"AHORRO",UPPER($B35)))),UPPER('Base_Cobranzas'!$AT$2:$AT$1005))),--('Base_Cobranzas'!$AQ$2:$AQ$1005>0),'Base_Cobranzas'!$AQ$2:$AQ$1005),0) | E35: =IFERROR(SUMPRODUCT(--ISNUMBER(SEARCH($B$6,'Base_Cobranzas'!$A$2:$A$1005)),--('Base_Cobranzas'!$AJ$2:$AJ$1005>=IF(E$33<3000,DATE(E$33,1,1),E$33)),--('Base_Cobranzas'!$AJ$2:$AJ$1005<IF(E$33<3000,DATE(E$33+1,1,1),EDATE(E$33,1))),--ISNUMBER(SEARCH(IF(ISNUMBER(SEARCH("DIRECTO",UPPER($B35))),"DIRECTO",IF(ISNUMBER(SEARCH("HIPOT",UPPER($B35))),"HIPOT",IF(ISNUMBER(SEARCH("AHORRO",UPPER($B35))),"AHORRO",UPPER($B35)))),UPPER('Base_Cobranzas'!$AT$2:$AT$1005))),--('Base_Cobranzas'!$AQ$2:$AQ$1005>0),'Base_Cobranzas'!$AQ$2:$AQ$1005),0) | F35: =IFERROR(SUMPRODUCT(--ISNUMBER(SEARCH($B$6,'Base_Cobranzas'!$A$2:$A$1005)),--('Base_Cobranzas'!$AJ$2:$AJ$1005>=IF(F$33<3000,DATE(F$33,1,1),F$33)),--('Base_Cobranzas'!$AJ$2:$AJ$1005<IF(F$33<3000,DATE(F$33+1,1,1),EDATE(F$33,1))),--ISNUMBER(SEARCH(IF(ISNUMBER(SEARCH("DIRECTO",UPPER($B35))),"DIRECTO",IF(ISNUMBER(SEARCH("HIPOT",UPPER($B35))),"HIPOT",IF(ISNUMBER(SEARCH("AHORRO",UPPER($B35))),"AHORRO",UPPER($B35)))),UPPER('Base_Cobranzas'!$AT$2:$AT$1005))),--('Base_Cobranzas'!$AQ$2:$AQ$1005>0),'Base_Cobranzas'!$AQ$2:$AQ$1005),0) | G35: =IFERROR(SUMPRODUCT(--ISNUMBER(SEARCH($B$6,'Base_Cobranzas'!$A$2:$A$1005)),--('Base_Cobranzas'!$AJ$2:$AJ$1005>=IF(G$33<3000,DATE(G$33,1,1),G$33)),--('Base_Cobranzas'!$AJ$2:$AJ$1005<IF(G$33<3000,DATE(G$33+1,1,1),EDATE(G$33,1))),--ISNUMBER(SEARCH(IF(ISNUMBER(SEARCH("DIRECTO",UPPER($B35))),"DIRECTO",IF(ISNUMBER(SEARCH("HIPOT",UPPER($B35))),"HIPOT",IF(ISNUMBER(SEARCH("AHORRO",UPPER($B35))),"AHORRO",UPPER($B35)))),UPPER('Base_Cobranzas'!$AT$2:$AT$1005))),--('Base_Cobranzas'!$AQ$2:$AQ$1005>0),'Base_Cobranzas'!$AQ$2:$AQ$1005),0) | H35: =IFERROR(SUMPRODUCT(--ISNUMBER(SEARCH($B$6,'Base_Cobranzas'!$A$2:$A$1005)),--('Base_Cobranzas'!$AJ$2:$AJ$1005>=IF(H$33<3000,DATE(H$33,1,1),H$33)),--('Base_Cobranzas'!$AJ$2:$AJ$1005<IF(H$33<3000,DATE(H$33+1,1,1),EDATE(H$33,1))),--ISNUMBER(SEARCH(IF(ISNUMBER(SEARCH("DIRECTO",UPPER($B35))),"DIRECTO",IF(ISNUMBER(SEARCH("HIPOT",UPPER($B35))),"HIPOT",IF(ISNUMBER(SEARCH("AHORRO",UPPER($B35))),"AHORRO",UPPER($B35)))),UPPER('Base_Cobranzas'!$AT$2:$AT$1005))),--('Base_Cobranzas'!$AQ$2:$AQ$1005>0),'Base_Cobranzas'!$AQ$2:$AQ$1005),0) | I35: =IFERROR(SUMPRODUCT(--ISNUMBER(SEARCH($B$6,'Base_Cobranzas'!$A$2:$A$1005)),--('Base_Cobranzas'!$AJ$2:$AJ$1005>=IF(I$33<3000,DATE(I$33,1,1),I$33)),--('Base_Cobranzas'!$AJ$2:$AJ$1005<IF(I$33<3000,DATE(I$33+1,1,1),EDATE(I$33,1))),--ISNUMBER(SEARCH(IF(ISNUMBER(SEARCH("DIRECTO",UPPER($B35))),"DIRECTO",IF(ISNUMBER(SEARCH("HIPOT",UPPER($B35))),"HIPOT",IF(ISNUMBER(SEARCH("AHORRO",UPPER($B35))),"AHORRO",UPPER($B35)))),UPPER('Base_Cobranzas'!$AT$2:$AT$1005))),--('Base_Cobranzas'!$AQ$2:$AQ$1005>0),'Base_Cobranzas'!$AQ$2:$AQ$1005),0) | J35: =IFERROR(SUMPRODUCT(--ISNUMBER(SEARCH($B$6,'Base_Cobranzas'!$A$2:$A$1005)),--('Base_Cobranzas'!$AJ$2:$AJ$1005>=IF(J$33<3000,DATE(J$33,1,1),J$33)),--('Base_Cobranzas'!$AJ$2:$AJ$1005<IF(J$33<3000,DATE(J$33+1,1,1),EDATE(J$33,1))),--ISNUMBER(SEARCH(IF(ISNUMBER(SEARCH("DIRECTO",UPPER($B35))),"DIRECTO",IF(ISNUMBER(SEARCH("HIPOT",UPPER($B35))),"HIPOT",IF(ISNUMBER(SEARCH("AHORRO",UPPER($B35))),"AHORRO",UPPER($B35)))),UPPER('Base_Cobranzas'!$AT$2:$AT$1005))),--('Base_Cobranzas'!$AQ$2:$AQ$1005>0),'Base_Cobranzas'!$AQ$2:$AQ$1005),0) | ... O35: =IFERROR(SUMPRODUCT(--ISNUMBER(SEARCH($B$6,'Base_Cobranzas'!$A$2:$A$1005)),--('Base_Cobranzas'!$AJ$2:$AJ$1005>=IF(O$33<3000,DATE(O$33,1,1),O$33)),--('Base_Cobranzas'!$AJ$2:$AJ$1005<IF(O$33<3000,DATE(O$33+1,1,1),EDATE(O$33,1))),--ISNUMBER(SEARCH(IF(ISNUMBER(SEARCH("DIRECTO",UPPER($B35))),"DIRECTO",IF(ISNUMBER(SEARCH("HIPOT",UPPER($B35))),"HIPOT",IF(ISNUMBER(SEARCH("AHORRO",UPPER($B35))),"AHORRO",UPPER($B35)))),UPPER('Base_Cobranzas'!$AT$2:$AT$1005))),--('Base_Cobranzas'!$AQ$2:$AQ$1005>0),'Base_Cobranzas'!$AQ$2:$AQ$1005),0) | P35: =SUM(C35:O35)
B36: Ahorro | C36: =IFERROR(SUMPRODUCT(--ISNUMBER(SEARCH($B$6,'Base_Cobranzas'!$A$2:$A$1005)),--('Base_Cobranzas'!$AJ$2:$AJ$1005>=IF(C$33<3000,DATE(C$33,1,1),C$33)),--('Base_Cobranzas'!$AJ$2:$AJ$1005<IF(C$33<3000,DATE(C$33+1,1,1),EDATE(C$33,1))),--ISNUMBER(SEARCH(IF(ISNUMBER(SEARCH("DIRECTO",UPPER($B36))),"DIRECTO",IF(ISNUMBER(SEARCH("HIPOT",UPPER($B36))),"HIPOT",IF(ISNUMBER(SEARCH("AHORRO",UPPER($B36))),"AHORRO",UPPER($B36)))),UPPER('Base_Cobranzas'!$AT$2:$AT$1005))),--('Base_Cobranzas'!$AQ$2:$AQ$1005>0),'Base_Cobranzas'!$AQ$2:$AQ$1005),0) | D36: =IFERROR(SUMPRODUCT(--ISNUMBER(SEARCH($B$6,'Base_Cobranzas'!$A$2:$A$1005)),--('Base_Cobranzas'!$AJ$2:$AJ$1005>=IF(D$33<3000,DATE(D$33,1,1),D$33)),--('Base_Cobranzas'!$AJ$2:$AJ$1005<IF(D$33<3000,DATE(D$33+1,1,1),EDATE(D$33,1))),--ISNUMBER(SEARCH(IF(ISNUMBER(SEARCH("DIRECTO",UPPER($B36))),"DIRECTO",IF(ISNUMBER(SEARCH("HIPOT",UPPER($B36))),"HIPOT",IF(ISNUMBER(SEARCH("AHORRO",UPPER($B36))),"AHORRO",UPPER($B36)))),UPPER('Base_Cobranzas'!$AT$2:$AT$1005))),--('Base_Cobranzas'!$AQ$2:$AQ$1005>0),'Base_Cobranzas'!$AQ$2:$AQ$1005),0) | E36: =IFERROR(SUMPRODUCT(--ISNUMBER(SEARCH($B$6,'Base_Cobranzas'!$A$2:$A$1005)),--('Base_Cobranzas'!$AJ$2:$AJ$1005>=IF(E$33<3000,DATE(E$33,1,1),E$33)),--('Base_Cobranzas'!$AJ$2:$AJ$1005<IF(E$33<3000,DATE(E$33+1,1,1),EDATE(E$33,1))),--ISNUMBER(SEARCH(IF(ISNUMBER(SEARCH("DIRECTO",UPPER($B36))),"DIRECTO",IF(ISNUMBER(SEARCH("HIPOT",UPPER($B36))),"HIPOT",IF(ISNUMBER(SEARCH("AHORRO",UPPER($B36))),"AHORRO",UPPER($B36)))),UPPER('Base_Cobranzas'!$AT$2:$AT$1005))),--('Base_Cobranzas'!$AQ$2:$AQ$1005>0),'Base_Cobranzas'!$AQ$2:$AQ$1005),0) | F36: =IFERROR(SUMPRODUCT(--ISNUMBER(SEARCH($B$6,'Base_Cobranzas'!$A$2:$A$1005)),--('Base_Cobranzas'!$AJ$2:$AJ$1005>=IF(F$33<3000,DATE(F$33,1,1),F$33)),--('Base_Cobranzas'!$AJ$2:$AJ$1005<IF(F$33<3000,DATE(F$33+1,1,1),EDATE(F$33,1))),--ISNUMBER(SEARCH(IF(ISNUMBER(SEARCH("DIRECTO",UPPER($B36))),"DIRECTO",IF(ISNUMBER(SEARCH("HIPOT",UPPER($B36))),"HIPOT",IF(ISNUMBER(SEARCH("AHORRO",UPPER($B36))),"AHORRO",UPPER($B36)))),UPPER('Base_Cobranzas'!$AT$2:$AT$1005))),--('Base_Cobranzas'!$AQ$2:$AQ$1005>0),'Base_Cobranzas'!$AQ$2:$AQ$1005),0) | G36: =IFERROR(SUMPRODUCT(--ISNUMBER(SEARCH($B$6,'Base_Cobranzas'!$A$2:$A$1005)),--('Base_Cobranzas'!$AJ$2:$AJ$1005>=IF(G$33<3000,DATE(G$33,1,1),G$33)),--('Base_Cobranzas'!$AJ$2:$AJ$1005<IF(G$33<3000,DATE(G$33+1,1,1),EDATE(G$33,1))),--ISNUMBER(SEARCH(IF(ISNUMBER(SEARCH("DIRECTO",UPPER($B36))),"DIRECTO",IF(ISNUMBER(SEARCH("HIPOT",UPPER($B36))),"HIPOT",IF(ISNUMBER(SEARCH("AHORRO",UPPER($B36))),"AHORRO",UPPER($B36)))),UPPER('Base_Cobranzas'!$AT$2:$AT$1005))),--('Base_Cobranzas'!$AQ$2:$AQ$1005>0),'Base_Cobranzas'!$AQ$2:$AQ$1005),0) | H36: =IFERROR(SUMPRODUCT(--ISNUMBER(SEARCH($B$6,'Base_Cobranzas'!$A$2:$A$1005)),--('Base_Cobranzas'!$AJ$2:$AJ$1005>=IF(H$33<3000,DATE(H$33,1,1),H$33)),--('Base_Cobranzas'!$AJ$2:$AJ$1005<IF(H$33<3000,DATE(H$33+1,1,1),EDATE(H$33,1))),--ISNUMBER(SEARCH(IF(ISNUMBER(SEARCH("DIRECTO",UPPER($B36))),"DIRECTO",IF(ISNUMBER(SEARCH("HIPOT",UPPER($B36))),"HIPOT",IF(ISNUMBER(SEARCH("AHORRO",UPPER($B36))),"AHORRO",UPPER($B36)))),UPPER('Base_Cobranzas'!$AT$2:$AT$1005))),--('Base_Cobranzas'!$AQ$2:$AQ$1005>0),'Base_Cobranzas'!$AQ$2:$AQ$1005),0) | I36: =IFERROR(SUMPRODUCT(--ISNUMBER(SEARCH($B$6,'Base_Cobranzas'!$A$2:$A$1005)),--('Base_Cobranzas'!$AJ$2:$AJ$1005>=IF(I$33<3000,DATE(I$33,1,1),I$33)),--('Base_Cobranzas'!$AJ$2:$AJ$1005<IF(I$33<3000,DATE(I$33+1,1,1),EDATE(I$33,1))),--ISNUMBER(SEARCH(IF(ISNUMBER(SEARCH("DIRECTO",UPPER($B36))),"DIRECTO",IF(ISNUMBER(SEARCH("HIPOT",UPPER($B36))),"HIPOT",IF(ISNUMBER(SEARCH("AHORRO",UPPER($B36))),"AHORRO",UPPER($B36)))),UPPER('Base_Cobranzas'!$AT$2:$AT$1005))),--('Base_Cobranzas'!$AQ$2:$AQ$1005>0),'Base_Cobranzas'!$AQ$2:$AQ$1005),0) | J36: =IFERROR(SUMPRODUCT(--ISNUMBER(SEARCH($B$6,'Base_Cobranzas'!$A$2:$A$1005)),--('Base_Cobranzas'!$AJ$2:$AJ$1005>=IF(J$33<3000,DATE(J$33,1,1),J$33)),--('Base_Cobranzas'!$AJ$2:$AJ$1005<IF(J$33<3000,DATE(J$33+1,1,1),EDATE(J$33,1))),--ISNUMBER(SEARCH(IF(ISNUMBER(SEARCH("DIRECTO",UPPER($B36))),"DIRECTO",IF(ISNUMBER(SEARCH("HIPOT",UPPER($B36))),"HIPOT",IF(ISNUMBER(SEARCH("AHORRO",UPPER($B36))),"AHORRO",UPPER($B36)))),UPPER('Base_Cobranzas'!$AT$2:$AT$1005))),--('Base_Cobranzas'!$AQ$2:$AQ$1005>0),'Base_Cobranzas'!$AQ$2:$AQ$1005),0) | ... O36: =IFERROR(SUMPRODUCT(--ISNUMBER(SEARCH($B$6,'Base_Cobranzas'!$A$2:$A$1005)),--('Base_Cobranzas'!$AJ$2:$AJ$1005>=IF(O$33<3000,DATE(O$33,1,1),O$33)),--('Base_Cobranzas'!$AJ$2:$AJ$1005<IF(O$33<3000,DATE(O$33+1,1,1),EDATE(O$33,1))),--ISNUMBER(SEARCH(IF(ISNUMBER(SEARCH("DIRECTO",UPPER($B36))),"DIRECTO",IF(ISNUMBER(SEARCH("HIPOT",UPPER($B36))),"HIPOT",IF(ISNUMBER(SEARCH("AHORRO",UPPER($B36))),"AHORRO",UPPER($B36)))),UPPER('Base_Cobranzas'!$AT$2:$AT$1005))),--('Base_Cobranzas'!$AQ$2:$AQ$1005>0),'Base_Cobranzas'!$AQ$2:$AQ$1005),0) | P36: =SUM(C36:O36)
B37: Total | C37: =SUM(C34:C36) | D37: =SUM(D34:D36) | E37: =SUM(E34:E36) | F37: =SUM(F34:F36) | G37: =SUM(G34:G36) | H37: =SUM(H34:H36) | I37: =SUM(I34:I36) | J37: =SUM(J34:J36) | ... O37: =SUM(O34:O36) | P37: =SUM(C37:O37) | Q37: =IF($G$21=P37,"OK","REVISAR")
B39: Acumulado | C39: =C37 | D39: =C39+D37 | E39: =D39+E37 | F39: =E39+F37 | G39: =F39+G37 | H39: =G39+H37 | I39: =H39+I37 | J39: =I39+J37 | K39: =J39+K37 | ... O39: =N39+O37
B43: COBRANZA PROYECTADA
B45: Tipo de Credito | C45: 46296 | D45: 46327 | E45: 46357 | F45: 46388 | G45: 46419 | H45: 46447 | I45: 46478 | J45: 46508 | K45: 46539 | L45: 46569 | M45: 46600 | N45: 46631 | O45: 46661 | P45: 46692 | Q45: 46722 | R45: 46753 | S45: Total
B46: Crédito Directo | C46: =IFERROR(SUMPRODUCT(--ISNUMBER(SEARCH($B$6,'Base_Cobranzas'!$A$2:$A$1005)),--('Base_Cobranzas'!$AI$2:$AI$1005>=IF(C$45<3000,DATE(C$45,1,1),C$45)),--('Base_Cobranzas'!$AI$2:$AI$1005<IF(C$45<3000,DATE(C$45+1,1,1),EDATE(C$45,1))),--ISNUMBER(SEARCH(IF(ISNUMBER(SEARCH("DIRECTO",UPPER($B46))),"DIRECTO",IF(ISNUMBER(SEARCH("HIPOT",UPPER($B46))),"HIPOT",IF(ISNUMBER(SEARCH("AHORRO",UPPER($B46))),"AHORRO",UPPER($B46)))),UPPER('Base_Cobranzas'!$AT$2:$AT$1005))),--ISNUMBER(SEARCH("PENDIENTE",UPPER(TRIM('Base_Cobranzas'!$BC$2:$BC$1005)))),'Base_Cobranzas'!$AR$2:$AR$1005),0) | D46: =IFERROR(SUMPRODUCT(--ISNUMBER(SEARCH($B$6,'Base_Cobranzas'!$A$2:$A$1005)),--('Base_Cobranzas'!$AI$2:$AI$1005>=IF(D$45<3000,DATE(D$45,1,1),D$45)),--('Base_Cobranzas'!$AI$2:$AI$1005<IF(D$45<3000,DATE(D$45+1,1,1),EDATE(D$45,1))),--ISNUMBER(SEARCH(IF(ISNUMBER(SEARCH("DIRECTO",UPPER($B46))),"DIRECTO",IF(ISNUMBER(SEARCH("HIPOT",UPPER($B46))),"HIPOT",IF(ISNUMBER(SEARCH("AHORRO",UPPER($B46))),"AHORRO",UPPER($B46)))),UPPER('Base_Cobranzas'!$AT$2:$AT$1005))),--ISNUMBER(SEARCH("PENDIENTE",UPPER(TRIM('Base_Cobranzas'!$BC$2:$BC$1005)))),'Base_Cobranzas'!$AR$2:$AR$1005),0) | E46: =IFERROR(SUMPRODUCT(--ISNUMBER(SEARCH($B$6,'Base_Cobranzas'!$A$2:$A$1005)),--('Base_Cobranzas'!$AI$2:$AI$1005>=IF(E$45<3000,DATE(E$45,1,1),E$45)),--('Base_Cobranzas'!$AI$2:$AI$1005<IF(E$45<3000,DATE(E$45+1,1,1),EDATE(E$45,1))),--ISNUMBER(SEARCH(IF(ISNUMBER(SEARCH("DIRECTO",UPPER($B46))),"DIRECTO",IF(ISNUMBER(SEARCH("HIPOT",UPPER($B46))),"HIPOT",IF(ISNUMBER(SEARCH("AHORRO",UPPER($B46))),"AHORRO",UPPER($B46)))),UPPER('Base_Cobranzas'!$AT$2:$AT$1005))),--ISNUMBER(SEARCH("PENDIENTE",UPPER(TRIM('Base_Cobranzas'!$BC$2:$BC$1005)))),'Base_Cobranzas'!$AR$2:$AR$1005),0) | F46: =IFERROR(SUMPRODUCT(--ISNUMBER(SEARCH($B$6,'Base_Cobranzas'!$A$2:$A$1005)),--('Base_Cobranzas'!$AI$2:$AI$1005>=IF(F$45<3000,DATE(F$45,1,1),F$45)),--('Base_Cobranzas'!$AI$2:$AI$1005<IF(F$45<3000,DATE(F$45+1,1,1),EDATE(F$45,1))),--ISNUMBER(SEARCH(IF(ISNUMBER(SEARCH("DIRECTO",UPPER($B46))),"DIRECTO",IF(ISNUMBER(SEARCH("HIPOT",UPPER($B46))),"HIPOT",IF(ISNUMBER(SEARCH("AHORRO",UPPER($B46))),"AHORRO",UPPER($B46)))),UPPER('Base_Cobranzas'!$AT$2:$AT$1005))),--ISNUMBER(SEARCH("PENDIENTE",UPPER(TRIM('Base_Cobranzas'!$BC$2:$BC$1005)))),'Base_Cobranzas'!$AR$2:$AR$1005),0) | G46: =IFERROR(SUMPRODUCT(--ISNUMBER(SEARCH($B$6,'Base_Cobranzas'!$A$2:$A$1005)),--('Base_Cobranzas'!$AI$2:$AI$1005>=IF(G$45<3000,DATE(G$45,1,1),G$45)),--('Base_Cobranzas'!$AI$2:$AI$1005<IF(G$45<3000,DATE(G$45+1,1,1),EDATE(G$45,1))),--ISNUMBER(SEARCH(IF(ISNUMBER(SEARCH("DIRECTO",UPPER($B46))),"DIRECTO",IF(ISNUMBER(SEARCH("HIPOT",UPPER($B46))),"HIPOT",IF(ISNUMBER(SEARCH("AHORRO",UPPER($B46))),"AHORRO",UPPER($B46)))),UPPER('Base_Cobranzas'!$AT$2:$AT$1005))),--ISNUMBER(SEARCH("PENDIENTE",UPPER(TRIM('Base_Cobranzas'!$BC$2:$BC$1005)))),'Base_Cobranzas'!$AR$2:$AR$1005),0) | H46: =IFERROR(SUMPRODUCT(--ISNUMBER(SEARCH($B$6,'Base_Cobranzas'!$A$2:$A$1005)),--('Base_Cobranzas'!$AI$2:$AI$1005>=IF(H$45<3000,DATE(H$45,1,1),H$45)),--('Base_Cobranzas'!$AI$2:$AI$1005<IF(H$45<3000,DATE(H$45+1,1,1),EDATE(H$45,1))),--ISNUMBER(SEARCH(IF(ISNUMBER(SEARCH("DIRECTO",UPPER($B46))),"DIRECTO",IF(ISNUMBER(SEARCH("HIPOT",UPPER($B46))),"HIPOT",IF(ISNUMBER(SEARCH("AHORRO",UPPER($B46))),"AHORRO",UPPER($B46)))),UPPER('Base_Cobranzas'!$AT$2:$AT$1005))),--ISNUMBER(SEARCH("PENDIENTE",UPPER(TRIM('Base_Cobranzas'!$BC$2:$BC$1005)))),'Base_Cobranzas'!$AR$2:$AR$1005),0) | I46: =IFERROR(SUMPRODUCT(--ISNUMBER(SEARCH($B$6,'Base_Cobranzas'!$A$2:$A$1005)),--('Base_Cobranzas'!$AI$2:$AI$1005>=IF(I$45<3000,DATE(I$45,1,1),I$45)),--('Base_Cobranzas'!$AI$2:$AI$1005<IF(I$45<3000,DATE(I$45+1,1,1),EDATE(I$45,1))),--ISNUMBER(SEARCH(IF(ISNUMBER(SEARCH("DIRECTO",UPPER($B46))),"DIRECTO",IF(ISNUMBER(SEARCH("HIPOT",UPPER($B46))),"HIPOT",IF(ISNUMBER(SEARCH("AHORRO",UPPER($B46))),"AHORRO",UPPER($B46)))),UPPER('Base_Cobranzas'!$AT$2:$AT$1005))),--ISNUMBER(SEARCH("PENDIENTE",UPPER(TRIM('Base_Cobranzas'!$BC$2:$BC$1005)))),'Base_Cobranzas'!$AR$2:$AR$1005),0) | J46: =IFERROR(SUMPRODUCT(--ISNUMBER(SEARCH($B$6,'Base_Cobranzas'!$A$2:$A$1005)),--('Base_Cobranzas'!$AI$2:$AI$1005>=IF(J$45<3000,DATE(J$45,1,1),J$45)),--('Base_Cobranzas'!$AI$2:$AI$1005<IF(J$45<3000,DATE(J$45+1,1,1),EDATE(J$45,1))),--ISNUMBER(SEARCH(IF(ISNUMBER(SEARCH("DIRECTO",UPPER($B46))),"DIRECTO",IF(ISNUMBER(SEARCH("HIPOT",UPPER($B46))),"HIPOT",IF(ISNUMBER(SEARCH("AHORRO",UPPER($B46))),"AHORRO",UPPER($B46)))),UPPER('Base_Cobranzas'!$AT$2:$AT$1005))),--ISNUMBER(SEARCH("PENDIENTE",UPPER(TRIM('Base_Cobranzas'!$BC$2:$BC$1005)))),'Base_Cobranzas'!$AR$2:$AR$1005),0) | ... R46: =IFERROR(SUMPRODUCT(--ISNUMBER(SEARCH($B$6,'Base_Cobranzas'!$A$2:$A$1005)),--('Base_Cobranzas'!$AI$2:$AI$1005>=IF(R$45<3000,DATE(R$45,1,1),R$45)),--('Base_Cobranzas'!$AI$2:$AI$1005<IF(R$45<3000,DATE(R$45+1,1,1),EDATE(R$45,1))),--ISNUMBER(SEARCH(IF(ISNUMBER(SEARCH("DIRECTO",UPPER($B46))),"DIRECTO",IF(ISNUMBER(SEARCH("HIPOT",UPPER($B46))),"HIPOT",IF(ISNUMBER(SEARCH("AHORRO",UPPER($B46))),"AHORRO",UPPER($B46)))),UPPER('Base_Cobranzas'!$AT$2:$AT$1005))),--ISNUMBER(SEARCH("PENDIENTE",UPPER(TRIM('Base_Cobranzas'!$BC$2:$BC$1005)))),'Base_Cobranzas'!$AR$2:$AR$1005),0) | S46: =SUM(C46:R46)
B47: Crédito Hipotecario | C47: =IFERROR(SUMPRODUCT(--ISNUMBER(SEARCH($B$6,'Base_Cobranzas'!$A$2:$A$1005)),--('Base_Cobranzas'!$AI$2:$AI$1005>=IF(C$45<3000,DATE(C$45,1,1),C$45)),--('Base_Cobranzas'!$AI$2:$AI$1005<IF(C$45<3000,DATE(C$45+1,1,1),EDATE(C$45,1))),--ISNUMBER(SEARCH(IF(ISNUMBER(SEARCH("DIRECTO",UPPER($B47))),"DIRECTO",IF(ISNUMBER(SEARCH("HIPOT",UPPER($B47))),"HIPOT",IF(ISNUMBER(SEARCH("AHORRO",UPPER($B47))),"AHORRO",UPPER($B47)))),UPPER('Base_Cobranzas'!$AT$2:$AT$1005))),--ISNUMBER(SEARCH("PENDIENTE",UPPER(TRIM('Base_Cobranzas'!$BC$2:$BC$1005)))),'Base_Cobranzas'!$AR$2:$AR$1005),0) | D47: =IFERROR(SUMPRODUCT(--ISNUMBER(SEARCH($B$6,'Base_Cobranzas'!$A$2:$A$1005)),--('Base_Cobranzas'!$AI$2:$AI$1005>=IF(D$45<3000,DATE(D$45,1,1),D$45)),--('Base_Cobranzas'!$AI$2:$AI$1005<IF(D$45<3000,DATE(D$45+1,1,1),EDATE(D$45,1))),--ISNUMBER(SEARCH(IF(ISNUMBER(SEARCH("DIRECTO",UPPER($B47))),"DIRECTO",IF(ISNUMBER(SEARCH("HIPOT",UPPER($B47))),"HIPOT",IF(ISNUMBER(SEARCH("AHORRO",UPPER($B47))),"AHORRO",UPPER($B47)))),UPPER('Base_Cobranzas'!$AT$2:$AT$1005))),--ISNUMBER(SEARCH("PENDIENTE",UPPER(TRIM('Base_Cobranzas'!$BC$2:$BC$1005)))),'Base_Cobranzas'!$AR$2:$AR$1005),0) | E47: =IFERROR(SUMPRODUCT(--ISNUMBER(SEARCH($B$6,'Base_Cobranzas'!$A$2:$A$1005)),--('Base_Cobranzas'!$AI$2:$AI$1005>=IF(E$45<3000,DATE(E$45,1,1),E$45)),--('Base_Cobranzas'!$AI$2:$AI$1005<IF(E$45<3000,DATE(E$45+1,1,1),EDATE(E$45,1))),--ISNUMBER(SEARCH(IF(ISNUMBER(SEARCH("DIRECTO",UPPER($B47))),"DIRECTO",IF(ISNUMBER(SEARCH("HIPOT",UPPER($B47))),"HIPOT",IF(ISNUMBER(SEARCH("AHORRO",UPPER($B47))),"AHORRO",UPPER($B47)))),UPPER('Base_Cobranzas'!$AT$2:$AT$1005))),--ISNUMBER(SEARCH("PENDIENTE",UPPER(TRIM('Base_Cobranzas'!$BC$2:$BC$1005)))),'Base_Cobranzas'!$AR$2:$AR$1005),0) | F47: =IFERROR(SUMPRODUCT(--ISNUMBER(SEARCH($B$6,'Base_Cobranzas'!$A$2:$A$1005)),--('Base_Cobranzas'!$AI$2:$AI$1005>=IF(F$45<3000,DATE(F$45,1,1),F$45)),--('Base_Cobranzas'!$AI$2:$AI$1005<IF(F$45<3000,DATE(F$45+1,1,1),EDATE(F$45,1))),--ISNUMBER(SEARCH(IF(ISNUMBER(SEARCH("DIRECTO",UPPER($B47))),"DIRECTO",IF(ISNUMBER(SEARCH("HIPOT",UPPER($B47))),"HIPOT",IF(ISNUMBER(SEARCH("AHORRO",UPPER($B47))),"AHORRO",UPPER($B47)))),UPPER('Base_Cobranzas'!$AT$2:$AT$1005))),--ISNUMBER(SEARCH("PENDIENTE",UPPER(TRIM('Base_Cobranzas'!$BC$2:$BC$1005)))),'Base_Cobranzas'!$AR$2:$AR$1005),0) | G47: =IFERROR(SUMPRODUCT(--ISNUMBER(SEARCH($B$6,'Base_Cobranzas'!$A$2:$A$1005)),--('Base_Cobranzas'!$AI$2:$AI$1005>=IF(G$45<3000,DATE(G$45,1,1),G$45)),--('Base_Cobranzas'!$AI$2:$AI$1005<IF(G$45<3000,DATE(G$45+1,1,1),EDATE(G$45,1))),--ISNUMBER(SEARCH(IF(ISNUMBER(SEARCH("DIRECTO",UPPER($B47))),"DIRECTO",IF(ISNUMBER(SEARCH("HIPOT",UPPER($B47))),"HIPOT",IF(ISNUMBER(SEARCH("AHORRO",UPPER($B47))),"AHORRO",UPPER($B47)))),UPPER('Base_Cobranzas'!$AT$2:$AT$1005))),--ISNUMBER(SEARCH("PENDIENTE",UPPER(TRIM('Base_Cobranzas'!$BC$2:$BC$1005)))),'Base_Cobranzas'!$AR$2:$AR$1005),0) | H47: =IFERROR(SUMPRODUCT(--ISNUMBER(SEARCH($B$6,'Base_Cobranzas'!$A$2:$A$1005)),--('Base_Cobranzas'!$AI$2:$AI$1005>=IF(H$45<3000,DATE(H$45,1,1),H$45)),--('Base_Cobranzas'!$AI$2:$AI$1005<IF(H$45<3000,DATE(H$45+1,1,1),EDATE(H$45,1))),--ISNUMBER(SEARCH(IF(ISNUMBER(SEARCH("DIRECTO",UPPER($B47))),"DIRECTO",IF(ISNUMBER(SEARCH("HIPOT",UPPER($B47))),"HIPOT",IF(ISNUMBER(SEARCH("AHORRO",UPPER($B47))),"AHORRO",UPPER($B47)))),UPPER('Base_Cobranzas'!$AT$2:$AT$1005))),--ISNUMBER(SEARCH("PENDIENTE",UPPER(TRIM('Base_Cobranzas'!$BC$2:$BC$1005)))),'Base_Cobranzas'!$AR$2:$AR$1005),0) | I47: =IFERROR(SUMPRODUCT(--ISNUMBER(SEARCH($B$6,'Base_Cobranzas'!$A$2:$A$1005)),--('Base_Cobranzas'!$AI$2:$AI$1005>=IF(I$45<3000,DATE(I$45,1,1),I$45)),--('Base_Cobranzas'!$AI$2:$AI$1005<IF(I$45<3000,DATE(I$45+1,1,1),EDATE(I$45,1))),--ISNUMBER(SEARCH(IF(ISNUMBER(SEARCH("DIRECTO",UPPER($B47))),"DIRECTO",IF(ISNUMBER(SEARCH("HIPOT",UPPER($B47))),"HIPOT",IF(ISNUMBER(SEARCH("AHORRO",UPPER($B47))),"AHORRO",UPPER($B47)))),UPPER('Base_Cobranzas'!$AT$2:$AT$1005))),--ISNUMBER(SEARCH("PENDIENTE",UPPER(TRIM('Base_Cobranzas'!$BC$2:$BC$1005)))),'Base_Cobranzas'!$AR$2:$AR$1005),0) | J47: =IFERROR(SUMPRODUCT(--ISNUMBER(SEARCH($B$6,'Base_Cobranzas'!$A$2:$A$1005)),--('Base_Cobranzas'!$AI$2:$AI$1005>=IF(J$45<3000,DATE(J$45,1,1),J$45)),--('Base_Cobranzas'!$AI$2:$AI$1005<IF(J$45<3000,DATE(J$45+1,1,1),EDATE(J$45,1))),--ISNUMBER(SEARCH(IF(ISNUMBER(SEARCH("DIRECTO",UPPER($B47))),"DIRECTO",IF(ISNUMBER(SEARCH("HIPOT",UPPER($B47))),"HIPOT",IF(ISNUMBER(SEARCH("AHORRO",UPPER($B47))),"AHORRO",UPPER($B47)))),UPPER('Base_Cobranzas'!$AT$2:$AT$1005))),--ISNUMBER(SEARCH("PENDIENTE",UPPER(TRIM('Base_Cobranzas'!$BC$2:$BC$1005)))),'Base_Cobranzas'!$AR$2:$AR$1005),0) | ... R47: =IFERROR(SUMPRODUCT(--ISNUMBER(SEARCH($B$6,'Base_Cobranzas'!$A$2:$A$1005)),--('Base_Cobranzas'!$AI$2:$AI$1005>=IF(R$45<3000,DATE(R$45,1,1),R$45)),--('Base_Cobranzas'!$AI$2:$AI$1005<IF(R$45<3000,DATE(R$45+1,1,1),EDATE(R$45,1))),--ISNUMBER(SEARCH(IF(ISNUMBER(SEARCH("DIRECTO",UPPER($B47))),"DIRECTO",IF(ISNUMBER(SEARCH("HIPOT",UPPER($B47))),"HIPOT",IF(ISNUMBER(SEARCH("AHORRO",UPPER($B47))),"AHORRO",UPPER($B47)))),UPPER('Base_Cobranzas'!$AT$2:$AT$1005))),--ISNUMBER(SEARCH("PENDIENTE",UPPER(TRIM('Base_Cobranzas'!$BC$2:$BC$1005)))),'Base_Cobranzas'!$AR$2:$AR$1005),0) | S47: =SUM(C47:R47)
B48: Ahorro | C48: =IFERROR(SUMPRODUCT(--ISNUMBER(SEARCH($B$6,'Base_Cobranzas'!$A$2:$A$1005)),--('Base_Cobranzas'!$AI$2:$AI$1005>=IF(C$45<3000,DATE(C$45,1,1),C$45)),--('Base_Cobranzas'!$AI$2:$AI$1005<IF(C$45<3000,DATE(C$45+1,1,1),EDATE(C$45,1))),--ISNUMBER(SEARCH(IF(ISNUMBER(SEARCH("DIRECTO",UPPER($B48))),"DIRECTO",IF(ISNUMBER(SEARCH("HIPOT",UPPER($B48))),"HIPOT",IF(ISNUMBER(SEARCH("AHORRO",UPPER($B48))),"AHORRO",UPPER($B48)))),UPPER('Base_Cobranzas'!$AT$2:$AT$1005))),--ISNUMBER(SEARCH("PENDIENTE",UPPER(TRIM('Base_Cobranzas'!$BC$2:$BC$1005)))),'Base_Cobranzas'!$AR$2:$AR$1005),0) | D48: =IFERROR(SUMPRODUCT(--ISNUMBER(SEARCH($B$6,'Base_Cobranzas'!$A$2:$A$1005)),--('Base_Cobranzas'!$AI$2:$AI$1005>=IF(D$45<3000,DATE(D$45,1,1),D$45)),--('Base_Cobranzas'!$AI$2:$AI$1005<IF(D$45<3000,DATE(D$45+1,1,1),EDATE(D$45,1))),--ISNUMBER(SEARCH(IF(ISNUMBER(SEARCH("DIRECTO",UPPER($B48))),"DIRECTO",IF(ISNUMBER(SEARCH("HIPOT",UPPER($B48))),"HIPOT",IF(ISNUMBER(SEARCH("AHORRO",UPPER($B48))),"AHORRO",UPPER($B48)))),UPPER('Base_Cobranzas'!$AT$2:$AT$1005))),--ISNUMBER(SEARCH("PENDIENTE",UPPER(TRIM('Base_Cobranzas'!$BC$2:$BC$1005)))),'Base_Cobranzas'!$AR$2:$AR$1005),0) | E48: =IFERROR(SUMPRODUCT(--ISNUMBER(SEARCH($B$6,'Base_Cobranzas'!$A$2:$A$1005)),--('Base_Cobranzas'!$AI$2:$AI$1005>=IF(E$45<3000,DATE(E$45,1,1),E$45)),--('Base_Cobranzas'!$AI$2:$AI$1005<IF(E$45<3000,DATE(E$45+1,1,1),EDATE(E$45,1))),--ISNUMBER(SEARCH(IF(ISNUMBER(SEARCH("DIRECTO",UPPER($B48))),"DIRECTO",IF(ISNUMBER(SEARCH("HIPOT",UPPER($B48))),"HIPOT",IF(ISNUMBER(SEARCH("AHORRO",UPPER($B48))),"AHORRO",UPPER($B48)))),UPPER('Base_Cobranzas'!$AT$2:$AT$1005))),--ISNUMBER(SEARCH("PENDIENTE",UPPER(TRIM('Base_Cobranzas'!$BC$2:$BC$1005)))),'Base_Cobranzas'!$AR$2:$AR$1005),0) | F48: =IFERROR(SUMPRODUCT(--ISNUMBER(SEARCH($B$6,'Base_Cobranzas'!$A$2:$A$1005)),--('Base_Cobranzas'!$AI$2:$AI$1005>=IF(F$45<3000,DATE(F$45,1,1),F$45)),--('Base_Cobranzas'!$AI$2:$AI$1005<IF(F$45<3000,DATE(F$45+1,1,1),EDATE(F$45,1))),--ISNUMBER(SEARCH(IF(ISNUMBER(SEARCH("DIRECTO",UPPER($B48))),"DIRECTO",IF(ISNUMBER(SEARCH("HIPOT",UPPER($B48))),"HIPOT",IF(ISNUMBER(SEARCH("AHORRO",UPPER($B48))),"AHORRO",UPPER($B48)))),UPPER('Base_Cobranzas'!$AT$2:$AT$1005))),--ISNUMBER(SEARCH("PENDIENTE",UPPER(TRIM('Base_Cobranzas'!$BC$2:$BC$1005)))),'Base_Cobranzas'!$AR$2:$AR$1005),0) | G48: =IFERROR(SUMPRODUCT(--ISNUMBER(SEARCH($B$6,'Base_Cobranzas'!$A$2:$A$1005)),--('Base_Cobranzas'!$AI$2:$AI$1005>=IF(G$45<3000,DATE(G$45,1,1),G$45)),--('Base_Cobranzas'!$AI$2:$AI$1005<IF(G$45<3000,DATE(G$45+1,1,1),EDATE(G$45,1))),--ISNUMBER(SEARCH(IF(ISNUMBER(SEARCH("DIRECTO",UPPER($B48))),"DIRECTO",IF(ISNUMBER(SEARCH("HIPOT",UPPER($B48))),"HIPOT",IF(ISNUMBER(SEARCH("AHORRO",UPPER($B48))),"AHORRO",UPPER($B48)))),UPPER('Base_Cobranzas'!$AT$2:$AT$1005))),--ISNUMBER(SEARCH("PENDIENTE",UPPER(TRIM('Base_Cobranzas'!$BC$2:$BC$1005)))),'Base_Cobranzas'!$AR$2:$AR$1005),0) | H48: =IFERROR(SUMPRODUCT(--ISNUMBER(SEARCH($B$6,'Base_Cobranzas'!$A$2:$A$1005)),--('Base_Cobranzas'!$AI$2:$AI$1005>=IF(H$45<3000,DATE(H$45,1,1),H$45)),--('Base_Cobranzas'!$AI$2:$AI$1005<IF(H$45<3000,DATE(H$45+1,1,1),EDATE(H$45,1))),--ISNUMBER(SEARCH(IF(ISNUMBER(SEARCH("DIRECTO",UPPER($B48))),"DIRECTO",IF(ISNUMBER(SEARCH("HIPOT",UPPER($B48))),"HIPOT",IF(ISNUMBER(SEARCH("AHORRO",UPPER($B48))),"AHORRO",UPPER($B48)))),UPPER('Base_Cobranzas'!$AT$2:$AT$1005))),--ISNUMBER(SEARCH("PENDIENTE",UPPER(TRIM('Base_Cobranzas'!$BC$2:$BC$1005)))),'Base_Cobranzas'!$AR$2:$AR$1005),0) | I48: =IFERROR(SUMPRODUCT(--ISNUMBER(SEARCH($B$6,'Base_Cobranzas'!$A$2:$A$1005)),--('Base_Cobranzas'!$AI$2:$AI$1005>=IF(I$45<3000,DATE(I$45,1,1),I$45)),--('Base_Cobranzas'!$AI$2:$AI$1005<IF(I$45<3000,DATE(I$45+1,1,1),EDATE(I$45,1))),--ISNUMBER(SEARCH(IF(ISNUMBER(SEARCH("DIRECTO",UPPER($B48))),"DIRECTO",IF(ISNUMBER(SEARCH("HIPOT",UPPER($B48))),"HIPOT",IF(ISNUMBER(SEARCH("AHORRO",UPPER($B48))),"AHORRO",UPPER($B48)))),UPPER('Base_Cobranzas'!$AT$2:$AT$1005))),--ISNUMBER(SEARCH("PENDIENTE",UPPER(TRIM('Base_Cobranzas'!$BC$2:$BC$1005)))),'Base_Cobranzas'!$AR$2:$AR$1005),0) | J48: =IFERROR(SUMPRODUCT(--ISNUMBER(SEARCH($B$6,'Base_Cobranzas'!$A$2:$A$1005)),--('Base_Cobranzas'!$AI$2:$AI$1005>=IF(J$45<3000,DATE(J$45,1,1),J$45)),--('Base_Cobranzas'!$AI$2:$AI$1005<IF(J$45<3000,DATE(J$45+1,1,1),EDATE(J$45,1))),--ISNUMBER(SEARCH(IF(ISNUMBER(SEARCH("DIRECTO",UPPER($B48))),"DIRECTO",IF(ISNUMBER(SEARCH("HIPOT",UPPER($B48))),"HIPOT",IF(ISNUMBER(SEARCH("AHORRO",UPPER($B48))),"AHORRO",UPPER($B48)))),UPPER('Base_Cobranzas'!$AT$2:$AT$1005))),--ISNUMBER(SEARCH("PENDIENTE",UPPER(TRIM('Base_Cobranzas'!$BC$2:$BC$1005)))),'Base_Cobranzas'!$AR$2:$AR$1005),0) | ... R48: =IFERROR(SUMPRODUCT(--ISNUMBER(SEARCH($B$6,'Base_Cobranzas'!$A$2:$A$1005)),--('Base_Cobranzas'!$AI$2:$AI$1005>=IF(R$45<3000,DATE(R$45,1,1),R$45)),--('Base_Cobranzas'!$AI$2:$AI$1005<IF(R$45<3000,DATE(R$45+1,1,1),EDATE(R$45,1))),--ISNUMBER(SEARCH(IF(ISNUMBER(SEARCH("DIRECTO",UPPER($B48))),"DIRECTO",IF(ISNUMBER(SEARCH("HIPOT",UPPER($B48))),"HIPOT",IF(ISNUMBER(SEARCH("AHORRO",UPPER($B48))),"AHORRO",UPPER($B48)))),UPPER('Base_Cobranzas'!$AT$2:$AT$1005))),--ISNUMBER(SEARCH("PENDIENTE",UPPER(TRIM('Base_Cobranzas'!$BC$2:$BC$1005)))),'Base_Cobranzas'!$AR$2:$AR$1005),0) | S48: =SUM(C48:R48)
B49: Total | C49: =SUM(C46:C48) | D49: =SUM(D46:D48) | E49: =SUM(E46:E48) | F49: =SUM(F46:F48) | G49: =SUM(G46:G48) | H49: =SUM(H46:H48) | I49: =SUM(I46:I48) | J49: =SUM(J46:J48) | ... R49: =SUM(R46:R48) | S49: =SUM(C49:R49) | T49: =IF($H$21=S49,"OK","REVISAR")
B51: Acumulado | C51: =C49 | D51: =C51+D49 | E51: =D51+E49 | F51: =E51+F49 | G51: =F51+G49 | H51: =G51+H49 | I51: =H51+I49 | J51: =I51+J49 | K51: =J51+K49 | ... R51: =Q51+R49
B55: COBRANZA MOROSA
B57: Tipo de Credito | C57: 45717 | D57: 45748 | E57: 45778 | F57: 45809 | G57: 45839 | H57: 45870 | I57: 45901 | J57: 45931 | K57: 45962 | L57: 45992 | M57: 46023 | N57: 46054 | O57: 46082 | P57: 46113 | Q57: 46143 | R57: 46174 | S57: 46204 | T57: 46235 | U57: 46266 | V57: Total
B58: Crédito Directo | C58: =IFERROR(SUMPRODUCT(--ISNUMBER(SEARCH($B$6,'Base_Cobranzas'!$A$2:$A$1005)),--('Base_Cobranzas'!$AI$2:$AI$1005>=IF(C$57<3000,DATE(C$57,1,1),C$57)),--('Base_Cobranzas'!$AI$2:$AI$1005<IF(C$57<3000,DATE(C$57+1,1,1),EDATE(C$57,1))),--ISNUMBER(SEARCH(IF(ISNUMBER(SEARCH("DIRECTO",UPPER($B58))),"DIRECTO",IF(ISNUMBER(SEARCH("HIPOT",UPPER($B58))),"HIPOT",IF(ISNUMBER(SEARCH("AHORRO",UPPER($B58))),"AHORRO",UPPER($B58)))),UPPER('Base_Cobranzas'!$AT$2:$AT$1005))),--ISNUMBER(SEARCH("VENCIDO",UPPER(TRIM('Base_Cobranzas'!$BC$2:$BC$1005)))),'Base_Cobranzas'!$AR$2:$AR$1005),0) | D58: =IFERROR(SUMPRODUCT(--ISNUMBER(SEARCH($B$6,'Base_Cobranzas'!$A$2:$A$1005)),--('Base_Cobranzas'!$AI$2:$AI$1005>=IF(D$57<3000,DATE(D$57,1,1),D$57)),--('Base_Cobranzas'!$AI$2:$AI$1005<IF(D$57<3000,DATE(D$57+1,1,1),EDATE(D$57,1))),--ISNUMBER(SEARCH(IF(ISNUMBER(SEARCH("DIRECTO",UPPER($B58))),"DIRECTO",IF(ISNUMBER(SEARCH("HIPOT",UPPER($B58))),"HIPOT",IF(ISNUMBER(SEARCH("AHORRO",UPPER($B58))),"AHORRO",UPPER($B58)))),UPPER('Base_Cobranzas'!$AT$2:$AT$1005))),--ISNUMBER(SEARCH("VENCIDO",UPPER(TRIM('Base_Cobranzas'!$BC$2:$BC$1005)))),'Base_Cobranzas'!$AR$2:$AR$1005),0) | E58: =IFERROR(SUMPRODUCT(--ISNUMBER(SEARCH($B$6,'Base_Cobranzas'!$A$2:$A$1005)),--('Base_Cobranzas'!$AI$2:$AI$1005>=IF(E$57<3000,DATE(E$57,1,1),E$57)),--('Base_Cobranzas'!$AI$2:$AI$1005<IF(E$57<3000,DATE(E$57+1,1,1),EDATE(E$57,1))),--ISNUMBER(SEARCH(IF(ISNUMBER(SEARCH("DIRECTO",UPPER($B58))),"DIRECTO",IF(ISNUMBER(SEARCH("HIPOT",UPPER($B58))),"HIPOT",IF(ISNUMBER(SEARCH("AHORRO",UPPER($B58))),"AHORRO",UPPER($B58)))),UPPER('Base_Cobranzas'!$AT$2:$AT$1005))),--ISNUMBER(SEARCH("VENCIDO",UPPER(TRIM('Base_Cobranzas'!$BC$2:$BC$1005)))),'Base_Cobranzas'!$AR$2:$AR$1005),0) | F58: =IFERROR(SUMPRODUCT(--ISNUMBER(SEARCH($B$6,'Base_Cobranzas'!$A$2:$A$1005)),--('Base_Cobranzas'!$AI$2:$AI$1005>=IF(F$57<3000,DATE(F$57,1,1),F$57)),--('Base_Cobranzas'!$AI$2:$AI$1005<IF(F$57<3000,DATE(F$57+1,1,1),EDATE(F$57,1))),--ISNUMBER(SEARCH(IF(ISNUMBER(SEARCH("DIRECTO",UPPER($B58))),"DIRECTO",IF(ISNUMBER(SEARCH("HIPOT",UPPER($B58))),"HIPOT",IF(ISNUMBER(SEARCH("AHORRO",UPPER($B58))),"AHORRO",UPPER($B58)))),UPPER('Base_Cobranzas'!$AT$2:$AT$1005))),--ISNUMBER(SEARCH("VENCIDO",UPPER(TRIM('Base_Cobranzas'!$BC$2:$BC$1005)))),'Base_Cobranzas'!$AR$2:$AR$1005),0) | G58: =IFERROR(SUMPRODUCT(--ISNUMBER(SEARCH($B$6,'Base_Cobranzas'!$A$2:$A$1005)),--('Base_Cobranzas'!$AI$2:$AI$1005>=IF(G$57<3000,DATE(G$57,1,1),G$57)),--('Base_Cobranzas'!$AI$2:$AI$1005<IF(G$57<3000,DATE(G$57+1,1,1),EDATE(G$57,1))),--ISNUMBER(SEARCH(IF(ISNUMBER(SEARCH("DIRECTO",UPPER($B58))),"DIRECTO",IF(ISNUMBER(SEARCH("HIPOT",UPPER($B58))),"HIPOT",IF(ISNUMBER(SEARCH("AHORRO",UPPER($B58))),"AHORRO",UPPER($B58)))),UPPER('Base_Cobranzas'!$AT$2:$AT$1005))),--ISNUMBER(SEARCH("VENCIDO",UPPER(TRIM('Base_Cobranzas'!$BC$2:$BC$1005)))),'Base_Cobranzas'!$AR$2:$AR$1005),0) | H58: =IFERROR(SUMPRODUCT(--ISNUMBER(SEARCH($B$6,'Base_Cobranzas'!$A$2:$A$1005)),--('Base_Cobranzas'!$AI$2:$AI$1005>=IF(H$57<3000,DATE(H$57,1,1),H$57)),--('Base_Cobranzas'!$AI$2:$AI$1005<IF(H$57<3000,DATE(H$57+1,1,1),EDATE(H$57,1))),--ISNUMBER(SEARCH(IF(ISNUMBER(SEARCH("DIRECTO",UPPER($B58))),"DIRECTO",IF(ISNUMBER(SEARCH("HIPOT",UPPER($B58))),"HIPOT",IF(ISNUMBER(SEARCH("AHORRO",UPPER($B58))),"AHORRO",UPPER($B58)))),UPPER('Base_Cobranzas'!$AT$2:$AT$1005))),--ISNUMBER(SEARCH("VENCIDO",UPPER(TRIM('Base_Cobranzas'!$BC$2:$BC$1005)))),'Base_Cobranzas'!$AR$2:$AR$1005),0) | I58: =IFERROR(SUMPRODUCT(--ISNUMBER(SEARCH($B$6,'Base_Cobranzas'!$A$2:$A$1005)),--('Base_Cobranzas'!$AI$2:$AI$1005>=IF(I$57<3000,DATE(I$57,1,1),I$57)),--('Base_Cobranzas'!$AI$2:$AI$1005<IF(I$57<3000,DATE(I$57+1,1,1),EDATE(I$57,1))),--ISNUMBER(SEARCH(IF(ISNUMBER(SEARCH("DIRECTO",UPPER($B58))),"DIRECTO",IF(ISNUMBER(SEARCH("HIPOT",UPPER($B58))),"HIPOT",IF(ISNUMBER(SEARCH("AHORRO",UPPER($B58))),"AHORRO",UPPER($B58)))),UPPER('Base_Cobranzas'!$AT$2:$AT$1005))),--ISNUMBER(SEARCH("VENCIDO",UPPER(TRIM('Base_Cobranzas'!$BC$2:$BC$1005)))),'Base_Cobranzas'!$AR$2:$AR$1005),0) | J58: =IFERROR(SUMPRODUCT(--ISNUMBER(SEARCH($B$6,'Base_Cobranzas'!$A$2:$A$1005)),--('Base_Cobranzas'!$AI$2:$AI$1005>=IF(J$57<3000,DATE(J$57,1,1),J$57)),--('Base_Cobranzas'!$AI$2:$AI$1005<IF(J$57<3000,DATE(J$57+1,1,1),EDATE(J$57,1))),--ISNUMBER(SEARCH(IF(ISNUMBER(SEARCH("DIRECTO",UPPER($B58))),"DIRECTO",IF(ISNUMBER(SEARCH("HIPOT",UPPER($B58))),"HIPOT",IF(ISNUMBER(SEARCH("AHORRO",UPPER($B58))),"AHORRO",UPPER($B58)))),UPPER('Base_Cobranzas'!$AT$2:$AT$1005))),--ISNUMBER(SEARCH("VENCIDO",UPPER(TRIM('Base_Cobranzas'!$BC$2:$BC$1005)))),'Base_Cobranzas'!$AR$2:$AR$1005),0) | ... U58: =IFERROR(SUMPRODUCT(--ISNUMBER(SEARCH($B$6,'Base_Cobranzas'!$A$2:$A$1005)),--('Base_Cobranzas'!$AI$2:$AI$1005>=IF(U$57<3000,DATE(U$57,1,1),U$57)),--('Base_Cobranzas'!$AI$2:$AI$1005<IF(U$57<3000,DATE(U$57+1,1,1),EDATE(U$57,1))),--ISNUMBER(SEARCH(IF(ISNUMBER(SEARCH("DIRECTO",UPPER($B58))),"DIRECTO",IF(ISNUMBER(SEARCH("HIPOT",UPPER($B58))),"HIPOT",IF(ISNUMBER(SEARCH("AHORRO",UPPER($B58))),"AHORRO",UPPER($B58)))),UPPER('Base_Cobranzas'!$AT$2:$AT$1005))),--ISNUMBER(SEARCH("VENCIDO",UPPER(TRIM('Base_Cobranzas'!$BC$2:$BC$1005)))),'Base_Cobranzas'!$AR$2:$AR$1005),0) | V58: =SUM(C58:U58)
B59: Crédito Hipotecario | C59: =IFERROR(SUMPRODUCT(--ISNUMBER(SEARCH($B$6,'Base_Cobranzas'!$A$2:$A$1005)),--('Base_Cobranzas'!$AI$2:$AI$1005>=IF(C$57<3000,DATE(C$57,1,1),C$57)),--('Base_Cobranzas'!$AI$2:$AI$1005<IF(C$57<3000,DATE(C$57+1,1,1),EDATE(C$57,1))),--ISNUMBER(SEARCH(IF(ISNUMBER(SEARCH("DIRECTO",UPPER($B59))),"DIRECTO",IF(ISNUMBER(SEARCH("HIPOT",UPPER($B59))),"HIPOT",IF(ISNUMBER(SEARCH("AHORRO",UPPER($B59))),"AHORRO",UPPER($B59)))),UPPER('Base_Cobranzas'!$AT$2:$AT$1005))),--ISNUMBER(SEARCH("VENCIDO",UPPER(TRIM('Base_Cobranzas'!$BC$2:$BC$1005)))),'Base_Cobranzas'!$AR$2:$AR$1005),0) | D59: =IFERROR(SUMPRODUCT(--ISNUMBER(SEARCH($B$6,'Base_Cobranzas'!$A$2:$A$1005)),--('Base_Cobranzas'!$AI$2:$AI$1005>=IF(D$57<3000,DATE(D$57,1,1),D$57)),--('Base_Cobranzas'!$AI$2:$AI$1005<IF(D$57<3000,DATE(D$57+1,1,1),EDATE(D$57,1))),--ISNUMBER(SEARCH(IF(ISNUMBER(SEARCH("DIRECTO",UPPER($B59))),"DIRECTO",IF(ISNUMBER(SEARCH("HIPOT",UPPER($B59))),"HIPOT",IF(ISNUMBER(SEARCH("AHORRO",UPPER($B59))),"AHORRO",UPPER($B59)))),UPPER('Base_Cobranzas'!$AT$2:$AT$1005))),--ISNUMBER(SEARCH("VENCIDO",UPPER(TRIM('Base_Cobranzas'!$BC$2:$BC$1005)))),'Base_Cobranzas'!$AR$2:$AR$1005),0) | E59: =IFERROR(SUMPRODUCT(--ISNUMBER(SEARCH($B$6,'Base_Cobranzas'!$A$2:$A$1005)),--('Base_Cobranzas'!$AI$2:$AI$1005>=IF(E$57<3000,DATE(E$57,1,1),E$57)),--('Base_Cobranzas'!$AI$2:$AI$1005<IF(E$57<3000,DATE(E$57+1,1,1),EDATE(E$57,1))),--ISNUMBER(SEARCH(IF(ISNUMBER(SEARCH("DIRECTO",UPPER($B59))),"DIRECTO",IF(ISNUMBER(SEARCH("HIPOT",UPPER($B59))),"HIPOT",IF(ISNUMBER(SEARCH("AHORRO",UPPER($B59))),"AHORRO",UPPER($B59)))),UPPER('Base_Cobranzas'!$AT$2:$AT$1005))),--ISNUMBER(SEARCH("VENCIDO",UPPER(TRIM('Base_Cobranzas'!$BC$2:$BC$1005)))),'Base_Cobranzas'!$AR$2:$AR$1005),0) | F59: =IFERROR(SUMPRODUCT(--ISNUMBER(SEARCH($B$6,'Base_Cobranzas'!$A$2:$A$1005)),--('Base_Cobranzas'!$AI$2:$AI$1005>=IF(F$57<3000,DATE(F$57,1,1),F$57)),--('Base_Cobranzas'!$AI$2:$AI$1005<IF(F$57<3000,DATE(F$57+1,1,1),EDATE(F$57,1))),--ISNUMBER(SEARCH(IF(ISNUMBER(SEARCH("DIRECTO",UPPER($B59))),"DIRECTO",IF(ISNUMBER(SEARCH("HIPOT",UPPER($B59))),"HIPOT",IF(ISNUMBER(SEARCH("AHORRO",UPPER($B59))),"AHORRO",UPPER($B59)))),UPPER('Base_Cobranzas'!$AT$2:$AT$1005))),--ISNUMBER(SEARCH("VENCIDO",UPPER(TRIM('Base_Cobranzas'!$BC$2:$BC$1005)))),'Base_Cobranzas'!$AR$2:$AR$1005),0) | G59: =IFERROR(SUMPRODUCT(--ISNUMBER(SEARCH($B$6,'Base_Cobranzas'!$A$2:$A$1005)),--('Base_Cobranzas'!$AI$2:$AI$1005>=IF(G$57<3000,DATE(G$57,1,1),G$57)),--('Base_Cobranzas'!$AI$2:$AI$1005<IF(G$57<3000,DATE(G$57+1,1,1),EDATE(G$57,1))),--ISNUMBER(SEARCH(IF(ISNUMBER(SEARCH("DIRECTO",UPPER($B59))),"DIRECTO",IF(ISNUMBER(SEARCH("HIPOT",UPPER($B59))),"HIPOT",IF(ISNUMBER(SEARCH("AHORRO",UPPER($B59))),"AHORRO",UPPER($B59)))),UPPER('Base_Cobranzas'!$AT$2:$AT$1005))),--ISNUMBER(SEARCH("VENCIDO",UPPER(TRIM('Base_Cobranzas'!$BC$2:$BC$1005)))),'Base_Cobranzas'!$AR$2:$AR$1005),0) | H59: =IFERROR(SUMPRODUCT(--ISNUMBER(SEARCH($B$6,'Base_Cobranzas'!$A$2:$A$1005)),--('Base_Cobranzas'!$AI$2:$AI$1005>=IF(H$57<3000,DATE(H$57,1,1),H$57)),--('Base_Cobranzas'!$AI$2:$AI$1005<IF(H$57<3000,DATE(H$57+1,1,1),EDATE(H$57,1))),--ISNUMBER(SEARCH(IF(ISNUMBER(SEARCH("DIRECTO",UPPER($B59))),"DIRECTO",IF(ISNUMBER(SEARCH("HIPOT",UPPER($B59))),"HIPOT",IF(ISNUMBER(SEARCH("AHORRO",UPPER($B59))),"AHORRO",UPPER($B59)))),UPPER('Base_Cobranzas'!$AT$2:$AT$1005))),--ISNUMBER(SEARCH("VENCIDO",UPPER(TRIM('Base_Cobranzas'!$BC$2:$BC$1005)))),'Base_Cobranzas'!$AR$2:$AR$1005),0) | I59: =IFERROR(SUMPRODUCT(--ISNUMBER(SEARCH($B$6,'Base_Cobranzas'!$A$2:$A$1005)),--('Base_Cobranzas'!$AI$2:$AI$1005>=IF(I$57<3000,DATE(I$57,1,1),I$57)),--('Base_Cobranzas'!$AI$2:$AI$1005<IF(I$57<3000,DATE(I$57+1,1,1),EDATE(I$57,1))),--ISNUMBER(SEARCH(IF(ISNUMBER(SEARCH("DIRECTO",UPPER($B59))),"DIRECTO",IF(ISNUMBER(SEARCH("HIPOT",UPPER($B59))),"HIPOT",IF(ISNUMBER(SEARCH("AHORRO",UPPER($B59))),"AHORRO",UPPER($B59)))),UPPER('Base_Cobranzas'!$AT$2:$AT$1005))),--ISNUMBER(SEARCH("VENCIDO",UPPER(TRIM('Base_Cobranzas'!$BC$2:$BC$1005)))),'Base_Cobranzas'!$AR$2:$AR$1005),0) | J59: =IFERROR(SUMPRODUCT(--ISNUMBER(SEARCH($B$6,'Base_Cobranzas'!$A$2:$A$1005)),--('Base_Cobranzas'!$AI$2:$AI$1005>=IF(J$57<3000,DATE(J$57,1,1),J$57)),--('Base_Cobranzas'!$AI$2:$AI$1005<IF(J$57<3000,DATE(J$57+1,1,1),EDATE(J$57,1))),--ISNUMBER(SEARCH(IF(ISNUMBER(SEARCH("DIRECTO",UPPER($B59))),"DIRECTO",IF(ISNUMBER(SEARCH("HIPOT",UPPER($B59))),"HIPOT",IF(ISNUMBER(SEARCH("AHORRO",UPPER($B59))),"AHORRO",UPPER($B59)))),UPPER('Base_Cobranzas'!$AT$2:$AT$1005))),--ISNUMBER(SEARCH("VENCIDO",UPPER(TRIM('Base_Cobranzas'!$BC$2:$BC$1005)))),'Base_Cobranzas'!$AR$2:$AR$1005),0) | ... U59: =IFERROR(SUMPRODUCT(--ISNUMBER(SEARCH($B$6,'Base_Cobranzas'!$A$2:$A$1005)),--('Base_Cobranzas'!$AI$2:$AI$1005>=IF(U$57<3000,DATE(U$57,1,1),U$57)),--('Base_Cobranzas'!$AI$2:$AI$1005<IF(U$57<3000,DATE(U$57+1,1,1),EDATE(U$57,1))),--ISNUMBER(SEARCH(IF(ISNUMBER(SEARCH("DIRECTO",UPPER($B59))),"DIRECTO",IF(ISNUMBER(SEARCH("HIPOT",UPPER($B59))),"HIPOT",IF(ISNUMBER(SEARCH("AHORRO",UPPER($B59))),"AHORRO",UPPER($B59)))),UPPER('Base_Cobranzas'!$AT$2:$AT$1005))),--ISNUMBER(SEARCH("VENCIDO",UPPER(TRIM('Base_Cobranzas'!$BC$2:$BC$1005)))),'Base_Cobranzas'!$AR$2:$AR$1005),0) | V59: =SUM(C59:U59)
B60: Ahorro | C60: =IFERROR(SUMPRODUCT(--ISNUMBER(SEARCH($B$6,'Base_Cobranzas'!$A$2:$A$1005)),--('Base_Cobranzas'!$AI$2:$AI$1005>=IF(C$57<3000,DATE(C$57,1,1),C$57)),--('Base_Cobranzas'!$AI$2:$AI$1005<IF(C$57<3000,DATE(C$57+1,1,1),EDATE(C$57,1))),--ISNUMBER(SEARCH(IF(ISNUMBER(SEARCH("DIRECTO",UPPER($B60))),"DIRECTO",IF(ISNUMBER(SEARCH("HIPOT",UPPER($B60))),"HIPOT",IF(ISNUMBER(SEARCH("AHORRO",UPPER($B60))),"AHORRO",UPPER($B60)))),UPPER('Base_Cobranzas'!$AT$2:$AT$1005))),--ISNUMBER(SEARCH("VENCIDO",UPPER(TRIM('Base_Cobranzas'!$BC$2:$BC$1005)))),'Base_Cobranzas'!$AR$2:$AR$1005),0) | D60: =IFERROR(SUMPRODUCT(--ISNUMBER(SEARCH($B$6,'Base_Cobranzas'!$A$2:$A$1005)),--('Base_Cobranzas'!$AI$2:$AI$1005>=IF(D$57<3000,DATE(D$57,1,1),D$57)),--('Base_Cobranzas'!$AI$2:$AI$1005<IF(D$57<3000,DATE(D$57+1,1,1),EDATE(D$57,1))),--ISNUMBER(SEARCH(IF(ISNUMBER(SEARCH("DIRECTO",UPPER($B60))),"DIRECTO",IF(ISNUMBER(SEARCH("HIPOT",UPPER($B60))),"HIPOT",IF(ISNUMBER(SEARCH("AHORRO",UPPER($B60))),"AHORRO",UPPER($B60)))),UPPER('Base_Cobranzas'!$AT$2:$AT$1005))),--ISNUMBER(SEARCH("VENCIDO",UPPER(TRIM('Base_Cobranzas'!$BC$2:$BC$1005)))),'Base_Cobranzas'!$AR$2:$AR$1005),0) | E60: =IFERROR(SUMPRODUCT(--ISNUMBER(SEARCH($B$6,'Base_Cobranzas'!$A$2:$A$1005)),--('Base_Cobranzas'!$AI$2:$AI$1005>=IF(E$57<3000,DATE(E$57,1,1),E$57)),--('Base_Cobranzas'!$AI$2:$AI$1005<IF(E$57<3000,DATE(E$57+1,1,1),EDATE(E$57,1))),--ISNUMBER(SEARCH(IF(ISNUMBER(SEARCH("DIRECTO",UPPER($B60))),"DIRECTO",IF(ISNUMBER(SEARCH("HIPOT",UPPER($B60))),"HIPOT",IF(ISNUMBER(SEARCH("AHORRO",UPPER($B60))),"AHORRO",UPPER($B60)))),UPPER('Base_Cobranzas'!$AT$2:$AT$1005))),--ISNUMBER(SEARCH("VENCIDO",UPPER(TRIM('Base_Cobranzas'!$BC$2:$BC$1005)))),'Base_Cobranzas'!$AR$2:$AR$1005),0) | F60: =IFERROR(SUMPRODUCT(--ISNUMBER(SEARCH($B$6,'Base_Cobranzas'!$A$2:$A$1005)),--('Base_Cobranzas'!$AI$2:$AI$1005>=IF(F$57<3000,DATE(F$57,1,1),F$57)),--('Base_Cobranzas'!$AI$2:$AI$1005<IF(F$57<3000,DATE(F$57+1,1,1),EDATE(F$57,1))),--ISNUMBER(SEARCH(IF(ISNUMBER(SEARCH("DIRECTO",UPPER($B60))),"DIRECTO",IF(ISNUMBER(SEARCH("HIPOT",UPPER($B60))),"HIPOT",IF(ISNUMBER(SEARCH("AHORRO",UPPER($B60))),"AHORRO",UPPER($B60)))),UPPER('Base_Cobranzas'!$AT$2:$AT$1005))),--ISNUMBER(SEARCH("VENCIDO",UPPER(TRIM('Base_Cobranzas'!$BC$2:$BC$1005)))),'Base_Cobranzas'!$AR$2:$AR$1005),0) | G60: =IFERROR(SUMPRODUCT(--ISNUMBER(SEARCH($B$6,'Base_Cobranzas'!$A$2:$A$1005)),--('Base_Cobranzas'!$AI$2:$AI$1005>=IF(G$57<3000,DATE(G$57,1,1),G$57)),--('Base_Cobranzas'!$AI$2:$AI$1005<IF(G$57<3000,DATE(G$57+1,1,1),EDATE(G$57,1))),--ISNUMBER(SEARCH(IF(ISNUMBER(SEARCH("DIRECTO",UPPER($B60))),"DIRECTO",IF(ISNUMBER(SEARCH("HIPOT",UPPER($B60))),"HIPOT",IF(ISNUMBER(SEARCH("AHORRO",UPPER($B60))),"AHORRO",UPPER($B60)))),UPPER('Base_Cobranzas'!$AT$2:$AT$1005))),--ISNUMBER(SEARCH("VENCIDO",UPPER(TRIM('Base_Cobranzas'!$BC$2:$BC$1005)))),'Base_Cobranzas'!$AR$2:$AR$1005),0) | H60: =IFERROR(SUMPRODUCT(--ISNUMBER(SEARCH($B$6,'Base_Cobranzas'!$A$2:$A$1005)),--('Base_Cobranzas'!$AI$2:$AI$1005>=IF(H$57<3000,DATE(H$57,1,1),H$57)),--('Base_Cobranzas'!$AI$2:$AI$1005<IF(H$57<3000,DATE(H$57+1,1,1),EDATE(H$57,1))),--ISNUMBER(SEARCH(IF(ISNUMBER(SEARCH("DIRECTO",UPPER($B60))),"DIRECTO",IF(ISNUMBER(SEARCH("HIPOT",UPPER($B60))),"HIPOT",IF(ISNUMBER(SEARCH("AHORRO",UPPER($B60))),"AHORRO",UPPER($B60)))),UPPER('Base_Cobranzas'!$AT$2:$AT$1005))),--ISNUMBER(SEARCH("VENCIDO",UPPER(TRIM('Base_Cobranzas'!$BC$2:$BC$1005)))),'Base_Cobranzas'!$AR$2:$AR$1005),0) | I60: =IFERROR(SUMPRODUCT(--ISNUMBER(SEARCH($B$6,'Base_Cobranzas'!$A$2:$A$1005)),--('Base_Cobranzas'!$AI$2:$AI$1005>=IF(I$57<3000,DATE(I$57,1,1),I$57)),--('Base_Cobranzas'!$AI$2:$AI$1005<IF(I$57<3000,DATE(I$57+1,1,1),EDATE(I$57,1))),--ISNUMBER(SEARCH(IF(ISNUMBER(SEARCH("DIRECTO",UPPER($B60))),"DIRECTO",IF(ISNUMBER(SEARCH("HIPOT",UPPER($B60))),"HIPOT",IF(ISNUMBER(SEARCH("AHORRO",UPPER($B60))),"AHORRO",UPPER($B60)))),UPPER('Base_Cobranzas'!$AT$2:$AT$1005))),--ISNUMBER(SEARCH("VENCIDO",UPPER(TRIM('Base_Cobranzas'!$BC$2:$BC$1005)))),'Base_Cobranzas'!$AR$2:$AR$1005),0) | J60: =IFERROR(SUMPRODUCT(--ISNUMBER(SEARCH($B$6,'Base_Cobranzas'!$A$2:$A$1005)),--('Base_Cobranzas'!$AI$2:$AI$1005>=IF(J$57<3000,DATE(J$57,1,1),J$57)),--('Base_Cobranzas'!$AI$2:$AI$1005<IF(J$57<3000,DATE(J$57+1,1,1),EDATE(J$57,1))),--ISNUMBER(SEARCH(IF(ISNUMBER(SEARCH("DIRECTO",UPPER($B60))),"DIRECTO",IF(ISNUMBER(SEARCH("HIPOT",UPPER($B60))),"HIPOT",IF(ISNUMBER(SEARCH("AHORRO",UPPER($B60))),"AHORRO",UPPER($B60)))),UPPER('Base_Cobranzas'!$AT$2:$AT$1005))),--ISNUMBER(SEARCH("VENCIDO",UPPER(TRIM('Base_Cobranzas'!$BC$2:$BC$1005)))),'Base_Cobranzas'!$AR$2:$AR$1005),0) | ... U60: =IFERROR(SUMPRODUCT(--ISNUMBER(SEARCH($B$6,'Base_Cobranzas'!$A$2:$A$1005)),--('Base_Cobranzas'!$AI$2:$AI$1005>=IF(U$57<3000,DATE(U$57,1,1),U$57)),--('Base_Cobranzas'!$AI$2:$AI$1005<IF(U$57<3000,DATE(U$57+1,1,1),EDATE(U$57,1))),--ISNUMBER(SEARCH(IF(ISNUMBER(SEARCH("DIRECTO",UPPER($B60))),"DIRECTO",IF(ISNUMBER(SEARCH("HIPOT",UPPER($B60))),"HIPOT",IF(ISNUMBER(SEARCH("AHORRO",UPPER($B60))),"AHORRO",UPPER($B60)))),UPPER('Base_Cobranzas'!$AT$2:$AT$1005))),--ISNUMBER(SEARCH("VENCIDO",UPPER(TRIM('Base_Cobranzas'!$BC$2:$BC$1005)))),'Base_Cobranzas'!$AR$2:$AR$1005),0) | V60: =SUM(C60:U60)
B61: Total | C61: =SUM(C58:C60) | D61: =SUM(D58:D60) | E61: =SUM(E58:E60) | F61: =SUM(F58:F60) | G61: =SUM(G58:G60) | H61: =SUM(H58:H60) | I61: =SUM(I58:I60) | J61: =SUM(J58:J60) | ... U61: =SUM(U58:U60) | V61: =SUM(C61:U61) | W61: =IF($I$21=V61,"OK","REVISAR")
B63: Acumulado | C63: =C61 | D63: =C63+D61 | E63: =D63+E61 | F63: =E63+F61 | G63: =F63+G61 | H63: =G63+H61 | I63: =H63+I61 | J63: =I63+J61 | K63: =J63+K61 | ... U63: =T63+U61

Sheet Venecia
C5: REPORTE DE COBRANZAS
B6: Venecia
C8: Vendido | F8: Cobranzas
C9: Monto | D9: Unidades | F9: Avance | G9: Cobrado | H9: Por Cobrar | I9: Vencido | J9: Tasa de Morosidad | K9: Clientes Morosos (unidades) | L9: Dias de Atraso (Promedio)
B11: Departamentos | C11: 8831400 | D11: 25 | F11: =IF(C11=0,0,G11/C11) | G11: =SUM(G12:G13) | H11: =SUM(H12:H13) | I11: =SUM(I12:I13) | J11: =IF(C11=0,0,I11/C11) | K11: 9 | L11: 46
