Workbook

Sheet Base_Cobranzas
A1: Proyecto | B1: Etapa | C1: Tipo_Construccion_1 | D1: Nombre_Tipo_Construccion_1 | E1: TipoInmueble_1 | F1: NroInmueble_1 | G1: AreaTechada_1 | H1: AreaLibre_1 | I1: PrecioLista_1 | J1: PrecioVenta_1 | K1: Tipo_Construccion_2 | L1: Nombre_Tipo_Construccion_2 | M1: TipoInmueble_2 | N1: NroInmueble_2 | O1: AreaTechada_2 | P1: AreaLibre_2 | Q1: PrecioLista_2 | R1: PrecioVenta_2 | S1: Tipo_Construccion_3 | T1: Nombre_Tipo_Construccion_3 | U1: TipoInmueble_3 | V1: NroInmueble_3 | W1: AreaTechada_3 | X1: AreaLibre_3 | Y1: PrecioLista_3 | Z1: PrecioVenta_3 | AA1: Tipo_Construccion_4 | AB1: Nombre_Tipo_Construccion_4 | AC1: TipoInmueble_4 | AD1: NroInmueble_4 | AE1: AreaTechada_4 | AF1: AreaLibre_4 | AG1: PrecioLista_4 | AH1: PrecioVenta_4 | AI1: Nombres_Titular | AJ1: NroDocumento | AK1: Direccion | AL1: TelefonoCasa | AM1: TelefonoCelular | AN1: CorreoElectronico | AO1: Provincia | AP1: Distrito | AQ1: Fecha_Programada | AR1: FechaPago | AS1: Tipo_Cuota | AT1: Nro_Cuota | AU1: Capital | AV1: Intereses | AW1: GastosAdministrativos | AX1: Monto_Cuota | AY1: Monto_Cuota_Pagado | AZ1: SaldoPorPagarCuota | BA1: MontoMora | BB1: TipoFinanciamiento | BC1: Entidad_Financiera | BD1: Nro_Cuenta | BE1: Medio_Pago | BF1: Nro_Documento | BG1: Nro_Operacion | BH1: Verificado | BI1: OrigenFondo | BJ1: TipoCambio | BK1: Estado | BL1: Estado_Letra | BM1: Ubicación_Letra | BN1: Casuistica_Cuota | BO1: Accio_Cuota | BP1: FechaPromesa | BQ1: ValorCompromiso | BR1: Porcentaje | BS1: Comentario_Cuota | BT1: Fecha_Modificiacion_Seguimiento | BU1: Usuario_Modificiacion_Seguimiento | BV1: Doc_Adjunto | BW1: FechaOperacionComercial | BX1: Asesor_Comercial | BY1: Asesor_Banco | BZ1: Correlativo | CA1: Fecha_Registro_Pago_Cargado | CB1: ComisionPago | CC1: IdCotizacion | CD1: Doc_Contable | CE1: Monto_EstadoCuenta | CF1: Archivo_Origen | CG1: Anio_Descarga | CH1: Fecha_Inicio_Reporte | CI1: Fecha_Fin_Reporte
A2: RESIDENCIAL PRADA | B2: Etapa 1 | C2: Edificio | D2: A | E2: Departamento | F2: 103 | G2: 60.94 | H2: 30.59 | I2: 520400 | J2: 520400 | AI2: Ayleen Katia Messarina Rios | AJ2: 70512701 | AK2: Departamento 101 Urbanización Santa Rosa de Surco etapa 2 Mz D Lt 23 | AL2: 978722675 | AM2: 978722675 | AN2: ayleen30mr@gmail.com | AO2: LIMA | AP2: SANTIAGO DE SURCO | AQ2: 45578 | AR2: 45578 | AS2: SEPARACION | AT2: 1 | AU2: 3000 | AV2: 0 | AW2: 0 | AX2: 3000 | AY2: 3000 | AZ2: 0 | BA2: 0 | BB2: Crédito Hipotecario | BC2: Scotiabank Perú | BD2: 000-2768484 | BE2: TRANSFERENCIA BANCARIA | BG2: 01871075 | BH2: No | BJ2: 4 | BK2: CANCELADO | BV2: Si | BW2: 45663.588 | BX2: Kenny Salazar S | BZ2: 31 | CA2: 26/06/2026 17:22 | CB2: 0 | CF2: Cobranzas_2024.csv | CG2: 2024 | CH2: 01/01/2024 | CI2: 31/08/2031
A3: RESIDENCIAL PRADA | B3: Etapa 1 | C3: Edificio | D3: A | E3: Estacionamiento | F3: E 14 - D 11 | G3: 14.63 | H3: 2.37 | I3: 56300 | J3: 56300 | AI3: Ayleen Katia Messarina Rios | AJ3: 70512701 | AK3: Departamento 101 Urbanización Santa Rosa de Surco etapa 2 Mz D Lt 23 | AL3: 978722675 | AM3: 978722675 | AN3: ayleen30mr@gmail.com | AO3: LIMA | AP3: SANTIAGO DE SURCO | AQ3: 45628 | AR3: 45628 | AS3: SEPARACION | AT3: 1 | AU3: 3000 | AV3: 0 | AW3: 0 | AX3: 3000 | AY3: 3000 | AZ3: 0 | BA3: 0 | BB3: Crédito Directo | BC3: Scotiabank Perú | BD3: 000-2768484 | BE3: TRANSFERENCIA BANCARIA | BG3: 000001100000012 | BH3: No | BJ3: 4 | BK3: CANCELADO | BV3: Si | BW3: 45748.63 | BX3: Magaly Guevara Perez | BZ3: 56 | CA3: 28/06/2026 21:22 | CB3: 0 | CF3: Cobranzas_2024.csv | CG3: 2024 | CH3: 01/01/2024 | CI3: 31/08/2031
A4: RESIDENCIAL PRADA | B4: Etapa 1 | C4: Edificio | D4: A | E4: Estacionamiento | F4: E 14 - D 11 | G4: 14.63 | H4: 2.37 | I4: 56300 | J4: 56300 | AI4: Ayleen Katia Messarina Rios | AJ4: 70512701 | AK4: Departamento 101 Urbanización Santa Rosa de Surco etapa 2 Mz D Lt 23 | AL4: 978722675 | AM4: 978722675 | AN4: ayleen30mr@gmail.com | AO4: LIMA | AP4: SANTIAGO DE SURCO | AQ4: 45628 | AR4: 45628 | AS4: CUOTA INICIAL | AT4: 1 | AU4: 7000 | AV4: 0 | AW4: 0 | AX4: 7000 | AY4: 7000 | AZ4: 0 | BA4: 0 | BB4: Crédito Directo | BC4: Scotiabank Perú | BD4: 000-2768484 | BE4: TRANSFERENCIA BANCARIA | BG4: 000001100000012 | BH4: No | BJ4: 4 | BK4: CANCELADO | BV4: Si | BW4: 45748.63 | BX4: Magaly Guevara Perez | BZ4: 56 | CA4: 28/06/2026 21:22 | CB4: 0 | CF4: Cobranzas_2024.csv | CG4: 2024 | CH4: 01/01/2024 | CI4: 31/08/2031
A5: RESIDENCIAL PRADA | B5: Etapa 1 | C5: Edificio | D5: A | E5: Departamento | F5: 302 | G5: 55 | H5: 0 | I5: 435500 | J5: 435500 | AI5: Cristhiam Ortiz Angeles | AJ5: 45110882 | AK5: Av. Olavegoya 1879 departamento 301 | AL5: 992532732 | AM5: 992532732 | AN5: Cristhian4520@gmail.com | AO5: LIMA | AP5: JESUS MARIA | AQ5: 45473 | AR5: 45473 | AS5: SEPARACION | AT5: 1 | AU5: 3000 | AV5: 0 | AW5: 0 | AX5: 3000 | AY5: 3000 | AZ5: 0 | BA5: 0 | BB5: Crédito Hipotecario | BC5: Scotiabank Perú | BD5: 000-2768484 | BE5: TRANSFERENCIA BANCARIA | BF5: 45110882 | BG5: 01226077 | BH5: No | BI5: NO PRECISA | BJ5: 4 | BK5: CANCELADO | BV5: Si | BW5: 45499.613 | BX5: Kenny Salazar S | BZ5: 34 | CA5: 02/06/2026 15:34 | CB5: 0 | CF5: Cobranzas_2024.csv | CG5: 2024 | CH5: 01/01/2024 | CI5: 31/08/2031
A6: RESIDENCIAL PRADA | B6: Etapa 1 | C6: Edificio | D6: A | E6: Departamento | F6: 302 | G6: 55 | H6: 0 | I6: 435500 | J6: 435500 | AI6: Cristhiam Ortiz Angeles | AJ6: 45110882 | AK6: Av. Olavegoya 1879 departamento 301 | AL6: 992532732 | AM6: 992532732 | AN6: Cristhian4520@gmail.com | AO6: LIMA | AP6: JESUS MARIA | AQ6: 45499 | AR6: 45499 | AS6: CUOTA INICIAL | AT6: 1 | AU6: 20000 | AV6: 0 | AW6: 0 | AX6: 20000 | AY6: 20000 | AZ6: 0 | BA6: 0 | BB6: Crédito Hipotecario | BC6: Scotiabank Perú | BD6: 000-2768484 | BE6: CHEQUE DE GERENCIA | BF6: 45110882 | BG6: 162515191002194000000022290 | BH6: Si | BI6: NO PRECISA | BJ6: 4 | BK6: CANCELADO | BV6: Si | BW6: 45499.613 | BX6: Kenny Salazar S | BZ6: 34 | CA6: 04/06/2026 14:01 | CB6: 0 | CF6: Cobranzas_2024.csv | CG6: 2024 | CH6: 01/01/2024 | CI6: 31/08/2031
A7: RESIDENCIAL PRADA | B7: Etapa 1 | C7: Edificio | D7: A | E7: Departamento | F7: 302 | G7: 55 | H7: 0 | I7: 435500 | J7: 435500 | AI7: Cristhiam Ortiz Angeles | AJ7: 45110882 | AK7: Av. Olavegoya 1879 departamento 301 | AL7: 992532732 | AM7: 992532732 | AN7: Cristhian4520@gmail.com | AO7: LIMA | AP7: JESUS MARIA | AQ7: 45534 | AR7: 45538 | AS7: CUOTA INICIAL | AT7: 2 | AU7: 8775 | AV7: 0 | AW7: 0 | AX7: 8775 | AY7: 8775 | AZ7: 0 | BA7: 0 | BB7: Crédito Hipotecario | BC7: Scotiabank Perú | BD7: 000-2768484 | BE7: TRANSFERENCIA BANCARIA | BG7: U26966 | BH7: No | BJ7: 4 | BK7: CANCELADO | BV7: Si | BW7: 45499.613 | BX7: Kenny Salazar S | BZ7: 34 | CA7: 07/07/2026 08:47 | CB7: 0 | CF7: Cobranzas_2024.csv | CG7: 2024 | CH7: 01/01/2024 | CI7: 31/08/2031
A8: RESIDENCIAL PRADA | B8: Etapa 1 | C8: Edificio | D8: A | E8: Departamento | F8: 302 | G8: 55 | H8: 0 | I8: 435500 | J8: 435500 | AI8: Cristhiam Ortiz Angeles | AJ8: 45110882 | AK8: Av. Olavegoya 1879 departamento 301 | AL8: 992532732 | AM8: 992532732 | AN8: Cristhian4520@gmail.com | AO8: LIMA | AP8: JESUS MARIA | AQ8: 45565 | AR8: 45538 | AS8: CUOTA INICIAL | AT8: 3 | AU8: 0 | AV8: 0 | AW8: 0 | AX8: 11775 | AY8: 1225 | AZ8: 0 | BA8: 0 | BB8: Crédito Hipotecario | BC8: Scotiabank Perú | BD8: 000-2768484 | BE8: TRANSFERENCIA BANCARIA | BG8: U26966 | BH8: No | BJ8: 4 | BK8: CANCELADO | BV8: Si | BW8: 45499.613 | BX8: Kenny Salazar S | BZ8: 34 | CA8: 07/07/2026 08:47 | CB8: 0 | CF8: Cobranzas_2024.csv | CG8: 2024 | CH8: 01/01/2024 | CI8: 31/08/2031
A9: RESIDENCIAL PRADA | B9: Etapa 1 | C9: Edificio | D9: A | E9: Departamento | F9: 302 | G9: 55 | H9: 0 | I9: 435500 | J9: 435500 | AI9: Cristhiam Ortiz Angeles | AJ9: 45110882 | AK9: Av. Olavegoya 1879 departamento 301 | AL9: 992532732 | AM9: 992532732 | AN9: Cristhian4520@gmail.com | AO9: LIMA | AP9: JESUS MARIA | AQ9: 45565 | AR9: 45569 | AS9: CUOTA INICIAL | AT9: 3 | AU9: 0 | AV9: 0 | AW9: 0 | AX9: 0 | AY9: 10000 | AZ9: 0 | BA9: 0 | BB9: Crédito Hipotecario | BC9: Scotiabank Perú | BD9: 000-2768484 | BE9: TRANSFERENCIA BANCARIA | BG9: U27618 | BH9: No | BJ9: 4 | BK9: CANCELADO | BV9: Si | BW9: 45499.613 | BX9: Kenny Salazar S | BZ9: 34 | CA9: 07/07/2026 08:52 | CB9: 0 | CF9: Cobranzas_2024.csv | CG9: 2024 | CH9: 01/01/2024 | CI9: 31/08/2031
A10: RESIDENCIAL PRADA | B10: Etapa 1 | C10: Edificio | D10: A | E10: Departamento | F10: 302 | G10: 55 | H10: 0 | I10: 435500 | J10: 435500 | AI10: Cristhiam Ortiz Angeles | AJ10: 45110882 | AK10: Av. Olavegoya 1879 departamento 301 | AL10: 992532732 | AM10: 992532732 | AN10: Cristhian4520@gmail.com | AO10: LIMA | AP10: JESUS MARIA | AQ10: 45565 | AR10: 45693 | AS10: CUOTA INICIAL | AT10: 3 | AU10: 11775 | AV10: 0 | AW10: 0 | AX10: 0 | AY10: 550 | AZ10: 0 | BA10: 0 | BB10: Crédito Hipotecario | BC10: Scotiabank Perú | BD10: 000-2768484 | BE10: TRANSFERENCIA BANCARIA | BG10: U28731 | BH10: No | BJ10: 4 | BK10: CANCELADO | BV10: Si | BW10: 45499.613 | BX10: Kenny Salazar S | BZ10: 34 | CA10: 07/07/2026 08:56 | CB10: 0 | CF10: Cobranzas_2024.csv | CG10: 2024 | CH10: 01/01/2024 | CI10: 31/08/2031
A11: RESIDENCIAL PRADA | B11: Etapa 1 | C11: Edificio | D11: A | E11: Departamento | F11: 302 | G11: 55 | H11: 0 | I11: 435500 | J11: 435500 | AI11: Cristhiam Ortiz Angeles | AJ11: 45110882 | AK11: Av. Olavegoya 1879 departamento 301 | AL11: 992532732 | AM11: 992532732 | AN11: Cristhian4520@gmail.com | AO11: LIMA | AP11: JESUS MARIA | AQ11: 45656 | AR11: 45693 | AS11: CUOTA INICIAL | AT11: 4 | AU11: 21000 | AV11: 0 | AW11: 0 | AX11: 21000 | AY11: 21000 | AZ11: 0 | BA11: 0 | BB11: Crédito Hipotecario | BC11: Scotiabank Perú | BD11: 000-2768484 | BE11: TRANSFERENCIA BANCARIA | BG11: U28731 | BH11: No | BJ11: 4 | BK11: CANCELADO | BV11: Si | BW11: 45499.613 | BX11: Kenny Salazar S | BZ11: 34 | CA11: 07/07/2026 08:56 | CB11: 0 | CF11: Cobranzas_2024.csv | CG11: 2024 | CH11: 01/01/2024 | CI11: 31/08/2031
A12: RESIDENCIAL BEYOND | B12: Etapa 1 | C12: Edificio | D12: A | E12: Departamento | F12: 505 | G12: 72 | H12: 0 | I12: 532100 | J12: 500000 | K12: Edificio | L12: A | M12: Estacionamiento | N12: E 05 | O12: 12 | P12: 0 | Q12: 45600 | R12: 45600 | S12: Edificio | T12: A | U12: Depósito | V12: D 05 | W12: 4.4 | X12: 0 | Y12: 15900 | Z12: 15900 | AI12: Dante Enrique Segura Florian | AJ12: 45587286 | AK12: 1845 San Andres Dr Pitsburg CA 94565 - San Francisco | AL12: 0 | AM12: +15103330517 | AN12: d.segura@uaa.edu | AQ12: 45368 | AR12: 45368 | AS12: SEPARACION | AT12: 1 | AU12: 3000 | AV12: 0 | AW12: 0 | AX12: 3000 | AY12: 3000 | AZ12: 0 | BA12: 0 | BB12: Crédito Directo | BC12: Banco de Credito del Perú | BD12: 194-7325779-0-65 | BE12: TRANSFERENCIA BANCARIA | BG12: 7844655595634 | BH12: No | BJ12: 4 | BK12: CANCELADO | BV12: Si | BW12: 45386.403 | BX12: Carla Michue M | BZ12: 35 | CA12: 25/05/2026 17:28 | CB12: 0 | CF12: Cobranzas_2024.csv | CG12: 2024 | CH12: 01/01/2024 | CI12: 31/08/2031
A13: RESIDENCIAL PRADA | B13: Etapa 1 | C13: Edificio | D13: A | E13: Departamento | F13: 703 | G13: 88.27 | H13: 0 | I13: 654000 | J13: 654000 | K13: Edificio | L13: A | M13: Estacionamiento | N13: E 06 - D 04 | O13: 15.9 | P13: 2.26 | Q13: 57500 | R13: 57500 | AI13: David Edgar Valencia Cordova | AJ13: 41844906 | AK13: P. Joven Año Nuevo Jr. Montero Rosas 860 | AL13: 991846561 | AM13: 991846561 | AN13: davico29@gmail.com | AO13: LIMA | AP13: COMAS | AQ13: 45655 | AR13: 45655 | AS13: SEPARACION | AT13: 1 | AU13: 3000 | AV13: 0 | AW13: 0 | AX13: 3000 | AY13: 3000 | AZ13: 0 | BA13: 0 | BB13: Crédito Hipotecario | BC13: Scotiabank Perú | BD13: 000-2768484 | BE13: TRANSFERENCIA BANCARIA | BF13: 41844906 | BG13: 00000082000000000 | BH13: No | BI13: NO PRECISA | BJ13: 4 | BK13: CANCELADO | BV13: Si | BW13: 45687.617 | BX13: Carla Michue M | BZ13: 38 | CA13: 02/06/2026 18:05 | CB13: 0 | CF13: Cobranzas_2024.csv | CG13: 2024 | CH13: 01/01/2024 | CI13: 31/08/2031
A14: RESIDENCIAL PRADA | B14: Etapa 1 | C14: Edificio | D14: A | E14: Departamento | F14: 205 | G14: 68.72 | H14: 0 | I14: 490000 | J14: 490000 | AI14: Elizabeth Rocio Urbina Ñañez | AJ14: 71404863 | AK14: Av. Arequipa 2651 | AM14: 943921218 | AN14: elizabethurbina9624@gmail.com | AO14: LIMA | AP14: LINCE | AQ14: 45620 | AR14: 45620 | AS14: SEPARACION | AT14: 1 | AU14: 2000 | AV14: 0 | AW14: 0 | AX14: 2000 | AY14: 2000 | AZ14: 0 | BA14: 0 | BB14: Crédito Hipotecario | BC14: Scotiabank Perú | BD14: 000-2768484 | BE14: TRANSFERENCIA BANCARIA | BG14: FD893378 | BH14: No | BJ14: 4 | BK14: CANCELADO | BV14: Si | BW14: 45750.733 | BX14: Carla Michue M | BZ14: 5 | CA14: 29/06/2026 21:44 | CB14: 0 | CF14: Cobranzas_2024.csv | CG14: 2024 | CH14: 01/01/2024 | CI14: 31/08/2031
A15: RESIDENCIAL PRADA | B15: Etapa 1 | C15: Edificio | D15: A | E15: Departamento | F15: 101 | G15: 80.58 | H15: 18.9 | I15: 637000 | J15: 637000 | AI15: Elmo Calatayud Chumbes | AJ15: 15580131 | AK15: Avenida Tomas Valles 1530 Block 14 departamento 204 | AL15: 955600933 | AM15: 955600933 | AN15: ec.calatayud@gmail.com | AO15: LIMA | AP15: LOS OLIVOS | AQ15: 45595 | AR15: 45595 | AS15: SEPARACION | AT15: 1 | AU15: 3000 | AV15: 0 | AW15: 0 | AX15: 3000 | AY15: 3000 | AZ15: 0 | BA15: 0 | BB15: Crédito Hipotecario | BC15: Scotiabank Perú | BD15: 000-2768484 | BE15: TRANSFERENCIA BANCARIA | BG15: 04797111 | BH15: No | BJ15: 4 | BK15: CANCELADO | BV15: Si | BW15: 45626.65 | BX15: Carla Michue M | BZ15: 25 | CA15: 26/06/2026 14:52 | CB15: 0 | CF15: Cobranzas_2024.csv | CG15: 2024 | CH15: 01/01/2024 | CI15: 31/08/2031
A16: RESIDENCIAL PRADA | B16: Etapa 1 | C16: Edificio | D16: A | E16: Departamento | F16: 101 | G16: 80.58 | H16: 18.9 | I16: 637000 | J16: 637000 | AI16: Elmo Calatayud Chumbes | AJ16: 15580131 | AK16: Avenida Tomas Valles 1530 Block 14 departamento 204 | AL16: 955600933 | AM16: 955600933 | AN16: ec.calatayud@gmail.com | AO16: LIMA | AP16: LOS OLIVOS | AQ16: 45626 | AR16: 45626 | AS16: CUOTA INICIAL | AT16: 1 | AU16: 27000 | AV16: 0 | AW16: 0 | AX16: 27000 | AY16: 27000 | AZ16: 0 | BA16: 0 | BB16: Crédito Hipotecario | BC16: Scotiabank Perú | BD16: 000-2768484 | BE16: TRANSFERENCIA BANCARIA | BG16: 78446555266223 | BH16: No | BJ16: 4 | BK16: CANCELADO | BV16: Si | BW16: 45626.65 | BX16: Carla Michue M | BZ16: 25 | CA16: 26/06/2026 14:53 | CB16: 0 | CF16: Cobranzas_2024.csv | CG16: 2024 | CH16: 01/01/2024 | CI16: 31/08/2031
A17: RESIDENCIAL PRADA | B17: Etapa 1 | C17: Edificio | D17: A | E17: Departamento | F17: 101 | G17: 80.58 | H17: 18.9 | I17: 637000 | J17: 637000 | AI17: Elmo Calatayud Chumbes | AJ17: 15580131 | AK17: Avenida Tomas Valles 1530 Block 14 departamento 204 | AL17: 955600933 | AM17: 955600933 | AN17: ec.calatayud@gmail.com | AO17: LIMA | AP17: LOS OLIVOS | AQ17: 45626 | AR17: 45626 | AS17: CUOTA INICIAL | AT17: 2 | AU17: 3000 | AV17: 0 | AW17: 0 | AX17: 3000 | AY17: 3000 | AZ17: 0 | BA17: 0 | BB17: Crédito Hipotecario | BC17: Scotiabank Perú | BD17: 000-2768484 | BE17: TRANSFERENCIA BANCARIA | BG17: 7844655544194 | BH17: No | BJ17: 4 | BK17: CANCELADO | BV17: Si | BW17: 45626.65 | BX17: Carla Michue M | BZ17: 25 | CA17: 26/06/2026 14:53 | CB17: 0 | CF17: Cobranzas_2024.csv | CG17: 2024 | CH17: 01/01/2024 | CI17: 31/08/2031
A18: RESIDENCIAL PRADA | B18: Etapa 1 | C18: Edificio | D18: A | E18: Departamento | F18: 101 | G18: 80.58 | H18: 18.9 | I18: 637000 | J18: 637000 | AI18: Elmo Calatayud Chumbes | AJ18: 15580131 | AK18: Avenida Tomas Valles 1530 Block 14 departamento 204 | AL18: 955600933 | AM18: 955600933 | AN18: ec.calatayud@gmail.com | AO18: LIMA | AP18: LOS OLIVOS | AQ18: 45656 | AR18: 45656 | AS18: CUOTA INICIAL | AT18: 3 | AU18: 0 | AV18: 0 | AW18: 0 | AX18: 30700 | AY18: 30000 | AZ18: 0 | BA18: 0 | BB18: Crédito Hipotecario | BC18: Scotiabank Perú | BD18: 000-2768484 | BE18: TRANSFERENCIA BANCARIA | BG18: 7844655610530 | BH18: No | BJ18: 4 | BK18: CANCELADO | BV18: Si | BW18: 45626.65 | BX18: Carla Michue M | BZ18: 25 | CA18: 26/06/2026 14:55 | CB18: 0 | CF18: Cobranzas_2024.csv | CG18: 2024 | CH18: 01/01/2024 | CI18: 31/08/2031
A19: RESIDENCIAL PRADA | B19: Etapa 1 | C19: Edificio | D19: A | E19: Departamento | F19: 101 | G19: 80.58 | H19: 18.9 | I19: 637000 | J19: 637000 | AI19: Elmo Calatayud Chumbes | AJ19: 15580131 | AK19: Avenida Tomas Valles 1530 Block 14 departamento 204 | AL19: 955600933 | AM19: 955600933 | AN19: ec.calatayud@gmail.com | AO19: LIMA | AP19: LOS OLIVOS | AQ19: 45656 | AR19: 45656 | AS19: CUOTA INICIAL | AT19: 3 | AU19: 30700 | AV19: 0 | AW19: 0 | AX19: 0 | AY19: 700 | AZ19: 0 | BA19: 0 | BB19: Crédito Hipotecario | BC19: Scotiabank Perú | BD19: 000-2768484 | BE19: TRANSFERENCIA BANCARIA | BG19: 7844655610860 | BH19: No | BJ19: 4 | BK19: CANCELADO | BV19: Si | BW19: 45626.65 | BX19: Carla Michue M | BZ19: 25 | CA19: 26/06/2026 14:56 | CB19: 0 | CF19: Cobranzas_2024.csv | CG19: 2024 | CH19: 01/01/2024 | CI19: 31/08/2031
A20: RESIDENCIAL PRADA | B20: Etapa 1 | C20: Edificio | D20: A | E20: Departamento | F20: 203 | G20: 88.27 | H20: 0 | I20: 654000 | J20: 654000 | K20: Edificio | L20: A | M20: Estacionamiento | N20: E 12 - D 09 | O20: 13 | P20: 3.89 | Q20: 56300 | R20: 56300 | AI20: Gilberto Videla Flores | AJ20: 06571347 | AK20: Mz D Lt 7 Urb. La Estrella | AM20: 969742622 | AN20: gvidelaf@gmail.com | AO20: LIMA | AP20: LOS OLIVOS | AQ20: 45535 | AR20: 45535 | AS20: SEPARACION | AT20: 1 | AU20: 3000 | AV20: 0 | AW20: 0 | AX20: 3000 | AY20: 3000 | AZ20: 0 | BA20: 0 | BB20: Crédito Directo | BC20: Scotiabank Perú | BD20: 000-2768484 | BE20: POS VISA | BF20: 06571347 | BG20: 0059 | BH20: No | BI20: NO PRECISA | BJ20: 1 | BK20: CANCELADO | BV20: Si | BW20: 45539.381 | BX20: Carla Michue M | BZ20: 24 | CA20: 29/05/2026 12:21 | CB20: 0 | CF20: Cobranzas_2024.csv | CG20: 2024 | CH20: 01/01/2024 | CI20: 31/08/2031
A21: RESIDENCIAL PRADA | B21: Etapa 1 | C21: Edificio | D21: A | E21: Departamento | F21: 203 | G21: 88.27 | H21: 0 | I21: 654000 | J21: 654000 | K21: Edificio | L21: A | M21: Estacionamiento | N21: E 12 - D 09 | O21: 13 | P21: 3.89 | Q21: 56300 | R21: 56300 | AI21: Gilberto Videla Flores | AJ21: 06571347 | AK21: Mz D Lt 7 Urb. La Estrella | AM21: 969742622 | AN21: gvidelaf@gmail.com | AO21: LIMA | AP21: LOS OLIVOS | AQ21: 45539 | AR21: 45539 | AS21: CUOTA INICIAL | AT21: 2 | AU21: 281120 | AV21: 0 | AW21: 0 | AX21: 281120 | AY21: 281120 | AZ21: 0 | BA21: 0 | BB21: Crédito Directo | BC21: Scotiabank Perú | BD21: 000-2768484 | BE21: TRANSFERENCIA BANCARIA | BG21: 0953413 | BH21: No | BJ21: 4 | BK21: CANCELADO | BV21: Si | BW21: 45539.381 | BX21: Carla Michue M | BZ21: 24 | CA21: 30/06/2026 16:33 | CB21: 0 | CF21: Cobranzas_2024.csv | CG21: 2024 | CH21: 01/01/2024 | CI21: 31/08/2031
A22: RESIDENCIAL PRADA | B22: Etapa 1 | C22: Edificio | D22: A | E22: Departamento | F22: 203 | G22: 88.27 | H22: 0 | I22: 654000 | J22: 654000 | K22: Edificio | L22: A | M22: Estacionamiento | N22: E 12 - D 09 | O22: 13 | P22: 3.89 | Q22: 56300 | R22: 56300 | AI22: Gilberto Videla Flores | AJ22: 06571347 | AK22: Mz D Lt 7 Urb. La Estrella | AM22: 969742622 | AN22: gvidelaf@gmail.com | AO22: LIMA | AP22: LOS OLIVOS | AQ22: 45559 | AR22: 45559 | AS22: SALDO FINANCIAR | AT22: 3 | AU22: 248605 | AV22: 0 | AW22: 0 | AX22: 248605 | AY22: 248605 | AZ22: 0 | BA22: 0 | BB22: Crédito Directo | BC22: Scotiabank Perú | BD22: 000-2768484 | BE22: TRANSFERENCIA BANCARIA | BG22: 0036913 | BH22: No | BJ22: 4 | BK22: CANCELADO | BV22: Si | BW22: 45539.381 | BX22: Carla Michue M | BZ22: 24 | CA22: 30/06/2026 16:48 | CB22: 0 | CF22: Cobranzas_2024.csv | CG22: 2024 | CH22: 01/01/2024 | CI22: 31/08/2031
A23: RESIDENCIAL PRADA | B23: Etapa 1 | C23: Edificio | D23: A | E23: Departamento | F23: 104 | G23: 68.52 | H23: 31.7 | I23: 609100 | J23: 609100 | K23: Edificio | L23: A | M23: Estacionamiento | N23: E 26 - D 20 | O23: 14.6 | P23: 3.89 | Q23: 64600 | R23: 64600 | AI23: Gilda Victoria Sampi González | AJ23: 43636501 | AK23: Av. Brasil 863 departamento 702-A | AL23: 966422784 | AM23: 966422784 | AN23: victoria.sampi@gmail.com | AO23: LIMA | AP23: JESUS MARIA | AQ23: 45494 | AR23: 45494 | AS23: SEPARACION | AT23: 1 | AU23: 3000 | AV23: 0 | AW23: 0 | AX23: 3000 | AY23: 3000 | AZ23: 0 | BA23: 0 | BB23: Crédito Hipotecario | BC23: Scotiabank Perú | BD23: 000-2768484 | BE23: TRANSFERENCIA BANCARIA | BF23: 43636501 | BG23: 00998929 | BH23: No | BI23: NO PRECISA | BJ23: 4 | BK23: CANCELADO | BV23: Si | BW23: 45537.593 | BX23: Kenny Salazar S | BZ23: 32 | CA23: 02/06/2026 14:50 | CB23: 0 | CF23: Cobranzas_2024.csv | CG23: 2024 | CH23: 01/01/2024 | CI23: 31/08/2031
A24: RESIDENCIAL PRADA | B24: Etapa 1 | C24: Edificio | D24: A | E24: Departamento | F24: 104 | G24: 68.52 | H24: 31.7 | I24: 609100 | J24: 609100 | K24: Edificio | L24: A | M24: Estacionamiento | N24: E 26 - D 20 | O24: 14.6 | P24: 3.89 | Q24: 64600 | R24: 64600 | AI24: Gilda Victoria Sampi González | AJ24: 43636501 | AK24: Av. Brasil 863 departamento 702-A | AL24: 966422784 | AM24: 966422784 | AN24: victoria.sampi@gmail.com | AO24: LIMA | AP24: JESUS MARIA | AQ24: 45537 | AR24: 45537 | AS24: CUOTA INICIAL | AT24: 1 | AU24: 134740 | AV24: 0 | AW24: 0 | AX24: 134740 | AY24: 134740 | AZ24: 0 | BA24: 0 | BB24: Crédito Hipotecario | BC24: Scotiabank Perú | BD24: 000-2768484 | BE24: TRANSFERENCIA BANCARIA | BF24: 43636501 | BG24: 009107870 | BH24: No | BI24: NO PRECISA | BJ24: 4 | BK24: CANCELADO | BV24: Si | BW24: 45537.593 | BX24: Kenny Salazar S | BZ24: 32 | CA24: 04/06/2026 09:52 | CB24: 0 | CF24: Cobranzas_2024.csv | CG24: 2024 | CH24: 01/01/2024 | CI24: 31/08/2031
A25: RESIDENCIAL PRADA | B25: Etapa 1 | C25: Edificio | D25: A | E25: Departamento | F25: 605 | G25: 68.72 | H25: 0 | I25: 501000 | J25: 501000 | K25: Edificio | L25: A | M25: Estacionamiento | N25: E 07 - D 05 | O25: 15.4 | P25: 2.26 | Q25: 57300 | R25: 57300 | AI25: Jose Humberto Pehovaz Diez | AJ25: 49073756 | AK25: - | AM25: 952256518 | AN25: josehp99@gmail.com | AO25: LIMA | AP25: MAGDALENA DEL MAR | AQ25: 45338 | AR25: 45698 | AS25: SEPARACION | AT25: 1 | AU25: 3000 | AV25: 0 | AW25: 0 | AX25: 3000 | AY25: 3000 | AZ25: 0 | BA25: 0 | BB25: Crédito Hipotecario | BC25: Scotiabank Perú | BD25: 000-2768484 | BE25: TRANSFERENCIA BANCARIA | BF25: 49073756 | BG25: 7844655534521 | BH25: No | BI25: NO PRECISA | BJ25: 1 | BK25: CANCELADO | BV25: Si | BW25: 45709.697 | BX25: Carla Michue M | BZ25: 10 | CA25: 29/05/2026 12:21 | CB25: 0 | CF25: Cobranzas_2024.csv | CG25: 2024 | CH25: 01/01/2024 | CI25: 31/08/2031
A26: RESIDENCIAL PRADA | B26: Etapa 1 | C26: Edificio | D26: A | E26: Departamento | F26: 201 | G26: 84 | H26: 0 | I26: 622500 | J26: 622500 | AI26: Joseluis Gaspar Zapata Flores | AJ26: 46730672 | AK26: Jr. Los Clavles 141 P. J El Progreso 1er Sector | AM26: 948041027 | AN26: jlzapata91@gmail.com | AO26: LIMA | AP26: CARABAYLLO | AQ26: 45479 | AR26: 45479 | AS26: CUOTA INICIAL | AT26: 1 | AU26: 3000 | AV26: 0 | AW26: 0 | AX26: 3000 | AY26: 3000 | AZ26: 0 | BA26: 0 | BB26: Ahorro | BC26: Scotiabank Perú | BD26: 000-2768484 | BE26: TRANSFERENCIA BANCARIA | BG26: 03343387 | BH26: Si | BJ26: 4 | BK26: CANCELADO | BV26: Si | BW26: 45488.655 | BX26: Carla Michue M | BZ26: 6 | CA26: 29/06/2026 01:05 | CB26: 0 | CF26: Cobranzas_2024.csv | CG26: 2024 | CH26: 01/01/2024 | CI26: 31/08/2031
A27: RESIDENCIAL PRADA | B27: Etapa 1 | C27: Edificio | D27: A | E27: Departamento | F27: 201 | G27: 84 | H27: 0 | I27: 622500 | J27: 622500 | AI27: Joseluis Gaspar Zapata Flores | AJ27: 46730672 | AK27: Jr. Los Clavles 141 P. J El Progreso 1er Sector | AM27: 948041027 | AN27: jlzapata91@gmail.com | AO27: LIMA | AP27: CARABAYLLO | AQ27: 45488 | AR27: 45488 | AS27: CUOTA INICIAL | AT27: 2 | AU27: 20000 | AV27: 0 | AW27: 0 | AX27: 20000 | AY27: 20000 | AZ27: 0 | BA27: 0 | BB27: Ahorro | BC27: Scotiabank Perú | BD27: 000-2768484 | BE27: TRANSFERENCIA BANCARIA | BG27: 7844655656315 | BH27: No | BJ27: 4 | BK27: CANCELADO | BV27: Si | BW27: 45488.655 | BX27: Carla Michue M | BZ27: 6 | CA27: 29/06/2026 01:06 | CB27: 0 | CF27: Cobranzas_2024.csv | CG27: 2024 | CH27: 01/01/2024 | CI27: 31/08/2031
A28: RESIDENCIAL PRADA | B28: Etapa 1 | C28: Edificio | D28: A | E28: Departamento | F28: 201 | G28: 84 | H28: 0 | I28: 622500 | J28: 622500 | AI28: Joseluis Gaspar Zapata Flores | AJ28: 46730672 | AK28: Jr. Los Clavles 141 P. J El Progreso 1er Sector | AM28: 948041027 | AN28: jlzapata91@gmail.com | AO28: LIMA | AP28: CARABAYLLO | AQ28: 45656 | AR28: 45722 | AS28: CUOTA INICIAL | AT28: 3 | AU28: 0 | AV28: 0 | AW28: 0 | AX28: 67000 | AY28: 65000 | AZ28: 0 | BA28: 0 | BB28: Ahorro | BC28: Scotiabank Perú | BD28: 000-2768484 | BE28: TRANSFERENCIA BANCARIA | BG28: u26563 | BH28: No | BJ28: 4 | BK28: CANCELADO | BV28: Si | BW28: 45488.655 | BX28: Carla Michue M | BZ28: 6 | CA28: 29/06/2026 01:07 | CB28: 0 | CF28: Cobranzas_2024.csv | CG28: 2024 | CH28: 01/01/2024 | CI28: 31/08/2031
A29: RESIDENCIAL PRADA | B29: Etapa 1 | C29: Edificio | D29: A | E29: Departamento | F29: 201 | G29: 84 | H29: 0 | I29: 622500 | J29: 622500 | AI29: Joseluis Gaspar Zapata Flores | AJ29: 46730672 | AK29: Jr. Los Clavles 141 P. J El Progreso 1er Sector | AM29: 948041027 | AN29: jlzapata91@gmail.com | AO29: LIMA | AP29: CARABAYLLO | AQ29: 45656 | AR29: 45722 | AS29: CUOTA INICIAL | AT29: 3 | AU29: 67000 | AV29: 0 | AW29: 0 | AX29: 0 | AY29: 2000 | AZ29: 0 | BA29: 0 | BB29: Ahorro | BC29: Scotiabank Perú | BD29: 000-2768484 | BE29: TRANSFERENCIA BANCARIA | BG29: 7844655541508 | BH29: No | BJ29: 4 | BK29: CANCELADO | BV29: Si | BW29: 45488.655 | BX29: Carla Michue M | BZ29: 6 | CA29: 29/06/2026 01:08 | CB29: 0 | CF29: Cobranzas_2024.csv | CG29: 2024 | CH29: 01/01/2024 | CI29: 31/08/2031
A30: RESIDENCIAL PRADA | B30: Etapa 1 | C30: Edificio | D30: A | E30: Departamento | F30: 501 | G30: 83 | H30: 0 | I30: 612000 | J30: 612000 | AI30: Juan Carlos Ángeles Milla | AJ30: 32403305 | AK30: Av. Miraflores 218 | AM30: 942097700 | AN30: Vidang72@hotmail.com | AO30: HUAYLAS | AP30: HUAYLAS | AQ30: 45520 | AR30: 45520 | AS30: SEPARACION | AT30: 1 | AU30: 3000 | AV30: 0 | AW30: 0 | AX30: 3000 | AY30: 3000 | AZ30: 0 | BA30: 0 | BB30: Ahorro | BC30: Scotiabank Perú | BD30: 000-2768484 | BE30: TRANSFERENCIA BANCARIA | BF30: 32403305 | BG30: 02431073 | BH30: No | BI30: NO PRECISA | BJ30: 1 | BK30: CANCELADO | BV30: Si | BW30: 45541.594 | BX30: Carla Michue M | BZ30: 21 | CA30: 29/05/2026 12:21 | CB30: 0 | CF30: Cobranzas_2024.csv | CG30: 2024 | CH30: 01/01/2024 | CI30: 31/08/2031
A31: RESIDENCIAL PRADA | B31: Etapa 1 | C31: Edificio | D31: A | E31: Departamento | F31: 501 | G31: 83 | H31: 0 | I31: 612000 | J31: 612000 | AI31: Juan Carlos Ángeles Milla | AJ31: 32403305 | AK31: Av. Miraflores 218 | AM31: 942097700 | AN31: Vidang72@hotmail.com | AO31: HUAYLAS | AP31: HUAYLAS | AQ31: 45541 | AR31: 45541 | AS31: CUOTA INICIAL | AT31: 2 | AU31: 29500 | AV31: 0 | AW31: 0 | AX31: 29500 | AY31: 29500 | AZ31: 0 | BA31: 0 | BB31: Ahorro | BC31: Scotiabank Perú | BD31: 000-2768484 | BE31: TRANSFERENCIA BANCARIA | BF31: 32403305 | BG31: 0500010059 | BH31: No | BI31: NO PRECISA | BJ31: 1 | BK31: CANCELADO | BV31: Si | BW31: 45541.594 | BX31: Carla Michue M | BZ31: 21 | CA31: 29/05/2026 12:21 | CB31: 0 | CF31: Cobranzas_2024.csv | CG31: 2024 | CH31: 01/01/2024 | CI31: 31/08/2031
A32: RESIDENCIAL PRADA | B32: Etapa 1 | C32: Edificio | D32: A | E32: Departamento | F32: 403 | G32: 88.27 | H32: 0 | I32: 654000 | J32: 654000 | AI32: Liliana Lucila Luciano Claros | AJ32: 15764694 | AK32: MZ M5 – Lt. 7 urb. Paseo del Mar | AM32: 982406857 | AN32: liliana31_micaela@hotmail.com | AO32: SANTA | AP32: NUEVO CHIMBOTE | AQ32: 45586 | AR32: 45586 | AS32: SEPARACION | AT32: 1 | AU32: 3000 | AV32: 0 | AW32: 0 | AX32: 3000 | AY32: 3000 | AZ32: 0 | BA32: 0 | BB32: Crédito Hipotecario | BC32: Scotiabank Perú | BD32: 000-2768484 | BE32: EFECTIVO | BF32: 15764694 | BG32: 0500010056 | BH32: No | BI32: NO PRECISA | BJ32: 1 | BK32: CANCELADO | BV32: Si | BW32: 45619.386 | BX32: Carla Michue M | BZ32: 1 | CA32: 29/05/2026 12:20 | CB32: 0 | CF32: Cobranzas_2024.csv | CG32: 2024 | CH32: 01/01/2024 | CI32: 31/08/2031
A33: RESIDENCIAL PRADA | B33: Etapa 1 | C33: Edificio | D33: A | E33: Departamento | F33: 403 | G33: 88.27 | H33: 0 | I33: 654000 | J33: 654000 | AI33: Liliana Lucila Luciano Claros | AJ33: 15764694 | AK33: MZ M5 – Lt. 7 urb. Paseo del Mar | AM33: 982406857 | AN33: liliana31_micaela@hotmail.com | AO33: SANTA | AP33: NUEVO CHIMBOTE | AQ33: 45619 | AR33: 45619 | AS33: CUOTA INICIAL | AT33: 2 | AU33: 97800 | AV33: 0 | AW33: 0 | AX33: 97800 | AY33: 97800 | AZ33: 0 | BA33: 0 | BB33: Crédito Hipotecario | BC33: Scotiabank Perú | BD33: 000-2768484 | BE33: TRANSFERENCIA BANCARIA | BG33: 12007725 | BH33: No | BJ33: 4 | BK33: CANCELADO | BV33: Si | BW33: 45619.386 | BX33: Carla Michue M | BZ33: 1 | CA33: 07/07/2026 09:30 | CB33: 0 | CF33: Cobranzas_2024.csv | CG33: 2024 | CH33: 01/01/2024 | CI33: 31/08/2031
A34: RESIDENCIAL PRADA | B34: Etapa 1 | C34: Edificio | D34: A | E34: Departamento | F34: 403 | G34: 88.27 | H34: 0 | I34: 654000 | J34: 654000 | AI34: Liliana Lucila Luciano Claros | AJ34: 15764694 | AK34: MZ M5 – Lt. 7 urb. Paseo del Mar | AM34: 982406857 | AN34: liliana31_micaela@hotmail.com | AO34: SANTA | AP34: NUEVO CHIMBOTE | AQ34: 45631 | AR34: 45631 | AS34: CUOTA INICIAL | AT34: 3 | AU34: 30000 | AV34: 0 | AW34: 0 | AX34: 30000 | AY34: 30000 | AZ34: 0 | BA34: 0 | BB34: Crédito Hipotecario | BC34: Scotiabank Perú | BD34: 000-2768484 | BE34: DEPOSITO EN CUENTA | BF34: 15764694 | BG34: 05000010069 | BH34: No | BI34: NO PRECISA | BJ34: 1 | BK34: CANCELADO | BV34: Si | BW34: 45619.386 | BX34: Carla Michue M | BZ34: 1 | CA34: 29/05/2026 12:20 | CB34: 0 | CF34: Cobranzas_2024.csv | CG34: 2024 | CH34: 01/01/2024 | CI34: 31/08/2031
A35: RESIDENCIAL PRADA | B35: Etapa 1 | C35: Edificio | D35: A | E35: Departamento | F35: 403 | G35: 88.27 | H35: 0 | I35: 654000 | J35: 654000 | AI35: Liliana Lucila Luciano Claros | AJ35: 15764694 | AK35: MZ M5 – Lt. 7 urb. Paseo del Mar | AM35: 982406857 | AN35: liliana31_micaela@hotmail.com | AO35: SANTA | AP35: NUEVO CHIMBOTE | AQ35: 45657 | AR35: 45723 | AS35: SALDO FINANCIAR | AT35: 4 | AU35: 523200 | AV35: 0 | AW35: 0 | AX35: 523200 | AY35: 523200 | AZ35: 0 | BA35: 0 | BB35: Crédito Hipotecario | BC35: Scotiabank Perú | BD35: 000-2768484 | BE35: TRANSFERENCIA BANCARIA | BG35: 07032025 | BH35: Si | BJ35: 4 | BK35: CANCELADO | BV35: Si | BW35: 45619.386 | BX35: Carla Michue M | BZ35: 1 | CA35: 07/07/2026 09:31 | CB35: 0 | CF35: Cobranzas_2024.csv | CG35: 2024 | CH35: 01/01/2024 | CI35: 31/08/2031
A36: RESIDENCIAL PRADA | B36: Etapa 1 | C36: Edificio | D36: A | E36: Departamento | F36: 603 | G36: 88.27 | H36: 0 | I36: 654000 | J36: 654000 | AI36: Luis Alberto Ovalle Huamanguilla | AJ36: 43953371 | AK36: JR. NAPO NRO. 821 | AM36: 992764943 | AN36: aovalle2212@gmail.com | AO36: LIMA | AP36: BREÑA | AQ36: 45477 | AR36: 45477 | AS36: SEPARACION | AT36: 1 | AU36: 3000 | AV36: 0 | AW36: 0 | AX36: 3000 | AY36: 3000 | AZ36: 0 | BA36: 0 | BB36: Ahorro | BC36: Scotiabank Perú | BD36: 000-2768484 | BE36: TRANSFERENCIA BANCARIA | BG36: 901866 | BH36: No | BJ36: 4 | BK36: CANCELADO | BV36: Si | BW36: 45567.694 | BX36: Carla Michue M | BZ36: 11 | CA36: 07/07/2026 10:58 | CB36: 0 | CF36: Cobranzas_2024.csv | CG36: 2024 | CH36: 01/01/2024 | CI36: 31/08/2031
A37: RESIDENCIAL PRADA | B37: Etapa 1 | C37: Edificio | D37: A | E37: Departamento | F37: 603 | G37: 88.27 | H37: 0 | I37: 654000 | J37: 654000 | AI37: Luis Alberto Ovalle Huamanguilla | AJ37: 43953371 | AK37: JR. NAPO NRO. 821 | AM37: 992764943 | AN37: aovalle2212@gmail.com | AO37: LIMA | AP37: BREÑA | AQ37: 45656 | AR37: 45567 | AS37: SEPARACION | AT37: 5 | AU37: 5000 | AV37: 0 | AW37: 0 | AX37: 5000 | AY37: 5000 | AZ37: 0 | BA37: 0 | BB37: Ahorro | BC37: Scotiabank Perú | BD37: 000-2768484 | BE37: TRANSFERENCIA BANCARIA | BG37: 06056215 | BH37: No | BJ37: 4 | BK37: CANCELADO | BV37: Si | BW37: 45567.694 | BX37: Carla Michue M | BZ37: 11 | CA37: 07/07/2026 11:03 | CB37: 0 | CF37: Cobranzas_2024.csv | CG37: 2024 | CH37: 01/01/2024 | CI37: 31/08/2031
A38: RESIDENCIAL PRADA | B38: Etapa 1 | C38: Edificio | D38: A | E38: Departamento | F38: 603 | G38: 88.27 | H38: 0 | I38: 654000 | J38: 654000 | AI38: Luis Alberto Ovalle Huamanguilla | AJ38: 43953371 | AK38: JR. NAPO NRO. 821 | AM38: 992764943 | AN38: aovalle2212@gmail.com | AO38: LIMA | AP38: BREÑA | AQ38: 45656 | AR38: 45567 | AS38: CUOTA INICIAL | AT38: 1 | AU38: 57400 | AV38: 0 | AW38: 0 | AX38: 57400 | AY38: 20000 | AZ38: 0 | BA38: 0 | BB38: Ahorro | BC38: Scotiabank Perú | BD38: 000-2768484 | BE38: TRANSFERENCIA BANCARIA | BG38: 06056215 | BH38: No | BJ38: 4 | BK38: CANCELADO | BV38: Si | BW38: 45567.694 | BX38: Carla Michue M | BZ38: 11 | CA38: 07/07/2026 11:03 | CB38: 0 | CF38: Cobranzas_2024.csv | CG38: 2024 | CH38: 01/01/2024 | CI38: 31/08/2031
A39: RESIDENCIAL PRADA | B39: Etapa 1 | C39: Edificio | D39: A | E39: Departamento | F39: 603 | G39: 88.27 | H39: 0 | I39: 654000 | J39: 654000 | AI39: Luis Alberto Ovalle Huamanguilla | AJ39: 43953371 | AK39: JR. NAPO NRO. 821 | AM39: 992764943 | AN39: aovalle2212@gmail.com | AO39: LIMA | AP39: BREÑA | AQ39: 45656 | AR39: 45723 | AS39: CUOTA INICIAL | AT39: 1 | AU39: 0 | AV39: 0 | AW39: 0 | AX39: 0 | AY39: 37400 | AZ39: 0 | BA39: 0 | BB39: Ahorro | BC39: Scotiabank Perú | BD39: 000-2768484 | BE39: TRANSFERENCIA BANCARIA | BG39: U26926 | BH39: No | BJ39: 4 | BK39: CANCELADO | BV39: Si | BW39: 45567.694 | BX39: Carla Michue M | BZ39: 11 | CA39: 07/07/2026 11:04 | CB39: 0 | CF39: Cobranzas_2024.csv | CG39: 2024 | CH39: 01/01/2024 | CI39: 31/08/2031
A40: RESIDENCIAL PRADA | B40: Etapa 1 | C40: Edificio | D40: A | E40: Departamento | F40: 202 | G40: 56 | H40: 0 | I40: 446900 | J40: 446900 | AI40: María Cristina Collazos Romero | AJ40: 31676885 | AK40: Jr. Huandoy 242 | AL40: 969870030 | AM40: 969870030 | AN40: gerenciasnacks1@gmail.com | AO40: HUARAZ | AP40: HUARAZ | AQ40: 45526 | AR40: 45526 | AS40: SEPARACION | AT40: 1 | AU40: 3000 | AV40: 0 | AW40: 0 | AX40: 3000 | AY40: 3000 | AZ40: 0 | BA40: 0 | BB40: Crédito Hipotecario | BC40: Scotiabank Perú | BD40: 000-2768484 | BE40: TRANSFERENCIA BANCARIA | BF40: 31676885 | BG40: 0500010101 | BH40: No | BI40: NO PRECISA | BJ40: 4 | BK40: CANCELADO | BV40: Si | BW40: 45911.607 | BX40: Kenny Salazar S | BZ40: 33 | CA40: 02/06/2026 15:10 | CB40: 0 | CF40: Cobranzas_2024.csv | CG40: 2024 | CH40: 01/01/2024 | CI40: 31/08/2031
A41: RESIDENCIAL PRADA | B41: Etapa 1 | C41: Edificio | D41: A | E41: Departamento | F41: 505 | G41: 68.72 | H41: 0 | I41: 490000 | J41: 490000 | AI41: Marina Francisca Vasquez Samaniego | AJ41: 19907001 | AK41: Huandoy 887 | AL41: 964247615 | AM41: 964247615 | AN41: francisca4547@hotmail.com | AO41: LIMA | AP41: SAN MIGUEL | AQ41: 45617 | AR41: 45617 | AS41: SEPARACION | AT41: 1 | AU41: 3000 | AV41: 0 | AW41: 0 | AX41: 3000 | AY41: 3000 | AZ41: 0 | BA41: 0 | BB41: Crédito Hipotecario | BC41: Scotiabank Perú | BD41: 000-2768484 | BE41: TRANSFERENCIA BANCARIA | BF41: 19907001 | BG41: 00951165 | BH41: No | BI41: NO PRECISA | BJ41: 4 | BK41: CANCELADO | BV41: Si | BW41: 45652.617 | BX41: Carla Michue M | BZ41: 37 | CA41: 02/06/2026 17:25 | CB41: 0 | CF41: Cobranzas_2024.csv | CG41: 2024 | CH41: 01/01/2024 | CI41: 31/08/2031
A42: RESIDENCIAL PRADA | B42: Etapa 1 | C42: Edificio | D42: A | E42: Departamento | F42: 505 | G42: 68.72 | H42: 0 | I42: 490000 | J42: 490000 | AI42: Marina Francisca Vasquez Samaniego | AJ42: 19907001 | AK42: Huandoy 887 | AL42: 964247615 | AM42: 964247615 | AN42: francisca4547@hotmail.com | AO42: LIMA | AP42: SAN MIGUEL | AQ42: 45652 | AR42: 45652 | AS42: CUOTA INICIAL | AT42: 1 | AU42: 20000 | AV42: 0 | AW42: 0 | AX42: 20000 | AY42: 20000 | AZ42: 0 | BA42: 0 | BB42: Crédito Hipotecario | BC42: Scotiabank Perú | BD42: 000-2768484 | BE42: TRANSFERENCIA BANCARIA | BG42: 6204304 | BH42: No | BJ42: 4 | BK42: CANCELADO | BV42: Si | BW42: 45652.617 | BX42: Carla Michue M | BZ42: 37 | CA42: 07/07/2026 10:35 | CB42: 0 | CF42: Cobranzas_2024.csv | CG42: 2024 | CH42: 01/01/2024 | CI42: 31/08/2031
A43: RESIDENCIAL PRADA | B43: Etapa 1 | C43: Edificio | D43: A | E43: Departamento | F43: 701 | G43: 84 | H43: 0 | I43: 592500 | J43: 592500 | AI43: Richard Humberto Lima Garcia | AJ43: 10606793 | AK43: Mz E2 lote 10 Urb Coovitiomar - Ancón | AM43: 940170759 | AN43: richard_13_312@hotmail.com | AO43: LIMA | AP43: SANTA ROSA | AQ43: 45593 | AR43: 45593 | AS43: SEPARACION | AT43: 1 | AU43: 3000 | AV43: 0 | AW43: 0 | AX43: 3000 | AY43: 3000 | AZ43: 0 | BA43: 0 | BB43: Crédito Hipotecario | BC43: Scotiabank Perú | BD43: 000-2768484 | BE43: TRANSFERENCIA BANCARIA | BF43: 10606793 | BG43: 01525977 | BH43: No | BI43: NO PRECISA | BJ43: 1 | BK43: CANCELADO | BV43: Si | BW43: 45638.388 | BX43: Carla Michue M | BZ43: 3 | CA43: 29/05/2026 12:21 | CB43: 0 | CF43: Cobranzas_2024.csv | CG43: 2024 | CH43: 01/01/2024 | CI43: 31/08/2031
A44: RESIDENCIAL PRADA | B44: Etapa 1 | C44: Edificio | D44: A | E44: Departamento | F44: 701 | G44: 84 | H44: 0 | I44: 592500 | J44: 592500 | AI44: Richard Humberto Lima Garcia | AJ44: 10606793 | AK44: Mz E2 lote 10 Urb Coovitiomar - Ancón | AM44: 940170759 | AN44: richard_13_312@hotmail.com | AO44: LIMA | AP44: SANTA ROSA | AQ44: 45618 | AR44: 45618 | AS44: CUOTA INICIAL | AT44: 2 | AU44: 48000 | AV44: 0 | AW44: 0 | AX44: 48000 | AY44: 48000 | AZ44: 0 | BA44: 0 | BB44: Crédito Hipotecario | BC44: Scotiabank Perú | BD44: 000-2768484 | BE44: TRANSFERENCIA BANCARIA | BG44: 0144739 | BH44: No | BJ44: 4 | BK44: CANCELADO | BV44: Si | BW44: 45638.388 | BX44: Carla Michue M | BZ44: 3 | CA44: 14/07/2026 09:05 | CB44: 0 | CF44: Cobranzas_2024.csv | CG44: 2024 | CH44: 01/01/2024 | CI44: 31/08/2031
A45: RESIDENCIAL PRADA | B45: Etapa 1 | C45: Edificio | D45: A | E45: Departamento | F45: 701 | G45: 84 | H45: 0 | I45: 592500 | J45: 592500 | AI45: Richard Humberto Lima Garcia | AJ45: 10606793 | AK45: Mz E2 lote 10 Urb Coovitiomar - Ancón | AM45: 940170759 | AN45: richard_13_312@hotmail.com | AO45: LIMA | AP45: SANTA ROSA | AQ45: 45638 | AR45: 45638 | AS45: CUOTA INICIAL | AT45: 3 | AU45: 8250 | AV45: 0 | AW45: 0 | AX45: 8250 | AY45: 8250 | AZ45: 0 | BA45: 0 | BB45: Crédito Hipotecario | BC45: Scotiabank Perú | BD45: 000-2768484 | BE45: TRANSFERENCIA BANCARIA | BF45: 10606793 | BG45: 02209753 | BH45: No | BI45: NO PRECISA | BJ45: 1 | BK45: CANCELADO | BV45: Si | BW45: 45638.388 | BX45: Carla Michue M | BZ45: 3 | CA45: 29/05/2026 12:21 | CB45: 0 | CF45: Cobranzas_2024.csv | CG45: 2024 | CH45: 01/01/2024 | CI45: 31/08/2031
A46: RESIDENCIAL PRADA | B46: Etapa 1 | C46: Edificio | D46: A | E46: Departamento | F46: 705 | G46: 68.72 | H46: 0 | I46: 496000 | J46: 496000 | AI46: Sthefany Carolina Rodriguez Huamán | AJ46: 70270427 | AK46: - | AM46: 989492681 | AN46: sthefany.rodriguez2207@gmail.com | AO46: LIMA | AP46: CERCADO DE LIMA | AQ46: 45586 | AR46: 45586 | AS46: SEPARACION | AT46: 1 | AU46: 200 | AV46: 0 | AW46: 0 | AX46: 200 | AY46: 200 | AZ46: 0 | BA46: 0 | BB46: Ahorro | BC46: Scotiabank Perú | BD46: 000-2768484 | BE46: TRANSFERENCIA BANCARIA | BF46: 70270427 | BG46: 7844655610334 | BH46: No | BI46: NO PRECISA | BJ46: 1 | BK46: CANCELADO | BV46: Si | BW46: 45829.39 | BX46: Carla Michue M | BZ46: 2 | CA46: 29/05/2026 12:20 | CB46: 0 | CF46: Cobranzas_2024.csv | CG46: 2024 | CH46: 01/01/2024 | CI46: 31/08/2031
A47: RESIDENCIAL PRADA | B47: Etapa 1 | C47: Edificio | D47: A | E47: Departamento | F47: 705 | G47: 68.72 | H47: 0 | I47: 496000 | J47: 496000 | AI47: Sthefany Carolina Rodriguez Huamán | AJ47: 70270427 | AK47: - | AM47: 989492681 | AN47: sthefany.rodriguez2207@gmail.com | AO47: LIMA | AP47: CERCADO DE LIMA | AQ47: 45587 | AR47: 45587 | AS47: SEPARACION | AT47: 2 | AU47: 2800 | AV47: 0 | AW47: 0 | AX47: 2800 | AY47: 2800 | AZ47: 0 | BA47: 0 | BB47: Ahorro | BC47: Scotiabank Perú | BD47: 000-2768484 | BE47: EFECTIVO | BF47: 70270427 | BG47: 0500010021 | BH47: No | BI47: NO PRECISA | BJ47: 1 | BK47: CANCELADO | BV47: Si | BW47: 45829.39 | BX47: Carla Michue M | BZ47: 2 | CA47: 29/05/2026 12:20 | CB47: 0 | CF47: Cobranzas_2024.csv | CG47: 2024 | CH47: 01/01/2024 | CI47: 31/08/2031
A48: RESIDENCIAL BEYOND | B48: Etapa 1 | C48: Edificio | D48: A | E48: Departamento | F48: 205 | G48: 72 | H48: 16 | I48: 587000 | J48: 577000 | AI48: Tania Milagros Cotrina Vara | AJ48: 10140034 | AK48: Av. Arnaldo Marquez 1526 Dpto. 26 | AL48: 0 | AM48: 941461159 | AN48: tamicov@hotmail.com | AO48: LIMA | AP48: JESUS MARIA | AQ48: 45641 | AR48: 45641 | AS48: SEPARACION | AT48: 1 | AU48: 3000 | AV48: 0 | AW48: 0 | AX48: 3000 | AY48: 3000 | AZ48: 0 | BA48: 0 | BB48: Ahorro | BC48: Banco de Credito del Perú | BD48: 194-7325779-0-65 | BE48: POS VISA | BF48: 10140034 | BG48: 594693007 | BH48: No | BI48: NO PRECISA | BJ48: 4 | BK48: CANCELADO | BV48: Si | BW48: 45918.416 | BX48: Magaly Guevara Perez | BZ48: 4 | CA48: 01/05/2026 11:00 | CB48: 0 | CF48: Cobranzas_2024.csv | CG48: 2024 | CH48: 01/01/2024 | CI48: 31/08/2031
A49: RESIDENCIAL BEYOND | B49: Etapa 1 | C49: Edificio | D49: A | E49: Departamento | F49: 1306 | G49: 40 | H49: 0 | I49: 312500 | J49: 265000 | AI49: Alejandra Leslye Solorio Peña | AJ49: 75021688 | AK49: Jr. Santiago Wagner 2264 | AL49: 0 | AM49: 984934286 | AN49: aleslye3@gamil.com | AO49: LIMA | AP49: CERCADO DE LIMA | AQ49: 45919 | AR49: 45919 | AS49: SEPARACION | AT49: 1 | AU49: 3000 | AV49: 0 | AW49: 0 | AX49: 3000 | AY49: 3000 | AZ49: 0 | BA49: 0 | BB49: Ahorro | BC49: Banco de Credito del Perú | BD49: 194-7325779-0-65 | BE49: TRANSFERENCIA BANCARIA | BG49: 017776200 | BH49: No | BJ49: 4 | BK49: CANCELADO | BV49: Si | BW49: 45904.806 | BX49: Carla Michue M | BZ49: 11 | CA49: 23/05/2026 19:16 | CB49: 0 | CF49: Cobranzas_2025.csv | CG49: 2025 | CH49: 01/01/2024 | CI49: 31/08/2031
A50: RESIDENCIAL BEYOND | B50: Etapa 1 | C50: Edificio | D50: A | E50: Departamento | F50: 1306 | G50: 40 | H50: 0 | I50: 312500 | J50: 265000 | AI50: Alejandra Leslye Solorio Peña | AJ50: 75021688 | AK50: Jr. Santiago Wagner 2264 | AL50: 0 | AM50: 984934286 | AN50: aleslye3@gamil.com | AO50: LIMA | AP50: CERCADO DE LIMA | AQ50: 45904 | AR50: 45904 | AS50: CUOTA INICIAL | AT50: 1 | AU50: 65600 | AV50: 0 | AW50: 0 | AX50: 65600 | AY50: 65600 | AZ50: 0 | BA50: 0 | BB50: Ahorro | BC50: Banco de Credito del Perú | BD50: 194-7325779-0-65 | BE50: TRANSFERENCIA BANCARIA | BG50: 0833282 | BH50: No | BJ50: 4 | BK50: CANCELADO | BV50: Si | BW50: 45904.806 | BX50: Carla Michue M | BZ50: 11 | CA50: 23/05/2026 19:22 | CB50: 0 | CF50: Cobranzas_2025.csv | CG50: 2025 | CH50: 01/01/2024 | CI50: 31/08/2031
A51: RESIDENCIAL PRADA | B51: Etapa 1 | C51: Edificio | D51: A | E51: Departamento | F51: 301 | G51: 84 | H51: 0 | I51: 630000 | J51: 630000 | AI51: Alejandro Jose Navarrete Maldonado | AJ51: 46304395 | AK51: Calle Jose Mariano Arce 139 – Dpto. 202 | AM51: 956466496 | AN51: anavarrete@nmabogados.com.pe | AO51: LIMA | AP51: PUEBLO LIBRE | AQ51: 45754 | AR51: 45754 | AS51: SEPARACION | AT51: 1 | AU51: 3000 | AV51: 0 | AW51: 0 | AX51: 3000 | AY51: 3000 | AZ51: 0 | BA51: 0 | BB51: Crédito Hipotecario | BC51: Scotiabank Perú | BD51: 000-2768484 | BE51: TRANSFERENCIA BANCARIA | BF51: 46304395 | BG51: 2715 | BH51: No | BI51: NO PRECISA | BJ51: 1 | BK51: CANCELADO | BV51: Si | BW51: 45775.391 | BX51: Carla Michue M | BZ51: 8 | CA51: 29/05/2026 12:21 | CB51: 0 | CF51: Cobranzas_2025.csv | CG51: 2025 | CH51: 01/01/2024 | CI51: 31/08/2031
A52: RESIDENCIAL PRADA | B52: Etapa 1 | C52: Edificio | D52: A | E52: Departamento | F52: 301 | G52: 84 | H52: 0 | I52: 630000 | J52: 630000 | AI52: Alejandro Jose Navarrete Maldonado | AJ52: 46304395 | AK52: Calle Jose Mariano Arce 139 – Dpto. 202 | AM52: 956466496 | AN52: anavarrete@nmabogados.com.pe | AO52: LIMA | AP52: PUEBLO LIBRE | AQ52: 45775 | AR52: 45775 | AS52: SEPARACION | AT52: 6 | AU52: 10000 | AV52: 0 | AW52: 0 | AX52: 10000 | AY52: 10000 | AZ52: 0 | BA52: 0 | BB52: Crédito Hipotecario | BC52: Scotiabank Perú | BD52: 000-2768484 | BE52: TRANSFERENCIA BANCARIA | BG52: 8240169 | BH52: No | BJ52: 4 | BK52: CANCELADO | BV52: Si | BW52: 45775.391 | BX52: Carla Michue M | BZ52: 8 | CA52: 03/07/2026 10:54 | CB52: 0 | CF52: Cobranzas_2025.csv | CG52: 2025 | CH52: 01/01/2024 | CI52: 31/08/2031
A53: RESIDENCIAL PRADA | B53: Etapa 1 | C53: Edificio | D53: A | E53: Departamento | F53: 301 | G53: 84 | H53: 0 | I53: 630000 | J53: 630000 | AI53: Alejandro Jose Navarrete Maldonado | AJ53: 46304395 | AK53: Calle Jose Mariano Arce 139 – Dpto. 202 | AM53: 956466496 | AN53: anavarrete@nmabogados.com.pe | AO53: LIMA | AP53: PUEBLO LIBRE | AQ53: 45775 | AR53: 45775 | AS53: CUOTA INICIAL | AT53: 1 | AU53: 45000 | AV53: 0 | AW53: 0 | AX53: 45000 | AY53: 45000 | AZ53: 0 | BA53: 0 | BB53: Crédito Hipotecario | BC53: Scotiabank Perú | BD53: 000-2768484 | BE53: TRANSFERENCIA BANCARIA | BG53: 8240169 | BH53: No | BJ53: 4 | BK53: CANCELADO | BV53: Si | BW53: 45775.391 | BX53: Carla Michue M | BZ53: 8 | CA53: 03/07/2026 10:54 | CB53: 0 | CF53: Cobranzas_2025.csv | CG53: 2025 | CH53: 01/01/2024 | CI53: 31/08/2031
A54: RESIDENCIAL PRADA | B54: Etapa 1 | C54: Edificio | D54: A | E54: Departamento | F54: 301 | G54: 84 | H54: 0 | I54: 630000 | J54: 630000 | AI54: Alejandro Jose Navarrete Maldonado | AJ54: 46304395 | AK54: Calle Jose Mariano Arce 139 – Dpto. 202 | AM54: 956466496 | AN54: anavarrete@nmabogados.com.pe | AO54: LIMA | AP54: PUEBLO LIBRE | AQ54: 45833 | AR54: 45833 | AS54: CUOTA INICIAL | AT54: 2 | AU54: 44000 | AV54: 0 | AW54: 0 | AX54: 44000 | AY54: 44000 | AZ54: 0 | BA54: 0 | BB54: Crédito Hipotecario | BC54: Scotiabank Perú | BD54: 000-2768484 | BE54: TRANSFERENCIA BANCARIA | BG54: 006190692 | BH54: No | BJ54: 4 | BK54: CANCELADO | BV54: Si | BW54: 45775.391 | BX54: Carla Michue M | BZ54: 8 | CA54: 03/07/2026 10:56 | CB54: 0 | CF54: Cobranzas_2025.csv | CG54: 2025 | CH54: 01/01/2024 | CI54: 31/08/2031
A55: RESIDENCIAL PRADA | B55: Etapa 1 | C55: Edificio | D55: A | E55: Departamento | F55: 301 | G55: 84 | H55: 0 | I55: 630000 | J55: 630000 | AI55: Alejandro Jose Navarrete Maldonado | AJ55: 46304395 | AK55: Calle Jose Mariano Arce 139 – Dpto. 202 | AM55: 956466496 | AN55: anavarrete@nmabogados.com.pe | AO55: LIMA | AP55: PUEBLO LIBRE | AQ55: 45869 | AR55: 45833 | AS55: SALDO FINANCIAR | AT55: 1 | AU55: 528000 | AV55: 0 | AW55: 0 | AX55: 528000 | AY55: 68000 | AZ55: 0 | BA55: 0 | BB55: Crédito Hipotecario | BC55: Scotiabank Perú | BD55: 000-2768484 | BE55: TRANSFERENCIA BANCARIA | BG55: 1141936 | BH55: No | BJ55: 4 | BK55: CANCELADO | BV55: Si | BW55: 45775.391 | BX55: Carla Michue M | BZ55: 8 | CA55: 03/07/2026 11:00 | CB55: 0 | CF55: Cobranzas_2025.csv | CG55: 2025 | CH55: 01/01/2024 | CI55: 31/08/2031
A56: RESIDENCIAL PRADA | B56: Etapa 1 | C56: Edificio | D56: A | E56: Departamento | F56: 301 | G56: 84 | H56: 0 | I56: 630000 | J56: 630000 | AI56: Alejandro Jose Navarrete Maldonado | AJ56: 46304395 | AK56: Calle Jose Mariano Arce 139 – Dpto. 202 | AM56: 956466496 | AN56: anavarrete@nmabogados.com.pe | AO56: LIMA | AP56: PUEBLO LIBRE | AQ56: 45869 | AR56: 45868 | AS56: SALDO FINANCIAR | AT56: 1 | AU56: 0 | AV56: 0 | AW56: 0 | AX56: 0 | AY56: 460000 | AZ56: 0 | BA56: 0 | BB56: Crédito Hipotecario | BC56: Scotiabank Perú | BD56: 000-2768484 | BE56: TRANSFERENCIA BANCARIA | BG56: 02708000009 | BH56: No | BJ56: 4 | BK56: CANCELADO | BV56: Si | BW56: 45775.391 | BX56: Carla Michue M | BZ56: 8 | CA56: 03/07/2026 11:02 | CB56: 0 | CF56: Cobranzas_2025.csv | CG56: 2025 | CH56: 01/01/2024 | CI56: 31/08/2031
A57: RESIDENCIAL PRADA | B57: Etapa 1 | C57: Edificio | D57: A | E57: Estacionamiento | F57: E 23 - D 17 | G57: 12.49 | H57: 1.83 | I57: 52000 | J57: 52000 | AI57: Alejandro Jose Navarrete Maldonado | AJ57: 46304395 | AK57: Calle Jose Mariano Arce 139 – Dpto. 202 | AL57: 0 | AM57: 956466496 | AN57: anavarrete@nmabogados.com.pe | AO57: LIMA | AP57: PUEBLO LIBRE | AQ57: 45877 | AR57: 45873 | AS57: SEPARACION | AT57: 1 | AU57: 3000 | AV57: 0 | AW57: 0 | AX57: 3000 | AY57: 3000 | AZ57: 0 | BA57: 0 | BB57: Crédito Directo | BC57: Scotiabank Perú | BD57: 000-2768484 | BE57: TRANSFERENCIA BANCARIA | BG57: 2636117 | BH57: No | BJ57: 4 | BK57: CANCELADO | BV57: Si | BW57: 45961.433 | BX57: Magaly Guevara Perez | BZ57: 54 | CA57: 14/07/2026 10:02 | CB57: 0 | CF57: Cobranzas_2025.csv | CG57: 2025 | CH57: 01/01/2024 | CI57: 31/08/2031
A58: RESIDENCIAL PRADA | B58: Etapa 1 | C58: Edificio | D58: A | E58: Estacionamiento | F58: E 23 - D 17 | G58: 12.49 | H58: 1.83 | I58: 52000 | J58: 52000 | AI58: Alejandro Jose Navarrete Maldonado | AJ58: 46304395 | AK58: Calle Jose Mariano Arce 139 – Dpto. 202 | AL58: 0 | AM58: 956466496 | AN58: anavarrete@nmabogados.com.pe | AO58: LIMA | AP58: PUEBLO LIBRE | AQ58: 45877 | AR58: 45873 | AS58: CUOTA INICIAL | AT58: 1 | AU58: 7000 | AV58: 0 | AW58: 0 | AX58: 7000 | AY58: 7000 | AZ58: 0 | BA58: 0 | BB58: Crédito Directo | BC58: Scotiabank Perú | BD58: 000-2768484 | BE58: TRANSFERENCIA BANCARIA | BG58: 2636117 | BH58: No | BJ58: 4 | BK58: CANCELADO | BV58: Si | BW58: 45961.433 | BX58: Magaly Guevara Perez | BZ58: 54 | CA58: 14/07/2026 10:02 | CB58: 0 | CF58: Cobranzas_2025.csv | CG58: 2025 | CH58: 01/01/2024 | CI58: 31/08/2031
A59: RESIDENCIAL PRADA | B59: Etapa 1 | C59: Edificio | D59: A | E59: Estacionamiento | F59: E 23 - D 17 | G59: 12.49 | H59: 1.83 | I59: 52000 | J59: 52000 | AI59: Alejandro Jose Navarrete Maldonado | AJ59: 46304395 | AK59: Calle Jose Mariano Arce 139 – Dpto. 202 | AL59: 0 | AM59: 956466496 | AN59: anavarrete@nmabogados.com.pe | AO59: LIMA | AP59: PUEBLO LIBRE | AQ59: 45961 | AR59: 45961 | AS59: SALDO FINANCIAR | AT59: 1 | AU59: 14000 | AV59: 0 | AW59: 0 | AX59: 14000 | AY59: 14000 | AZ59: 0 | BA59: 0 | BB59: Crédito Directo | BC59: Scotiabank Perú | BD59: 000-2768484 | BE59: TRANSFERENCIA BANCARIA | BG59: 009555099 | BH59: No | BJ59: 4 | BK59: CANCELADO | BV59: Si | BW59: 45961.433 | BX59: Magaly Guevara Perez | BZ59: 54 | CA59: 03/07/2026 11:16 | CB59: 0 | CF59: Cobranzas_2025.csv | CG59: 2025 | CH59: 01/01/2024 | CI59: 31/08/2031
A60: RESIDENCIAL PRADA | B60: Etapa 1 | C60: Edificio | D60: A | E60: Estacionamiento | F60: E 23 - D 17 | G60: 12.49 | H60: 1.83 | I60: 52000 | J60: 52000 | AI60: Alejandro Jose Navarrete Maldonado | AJ60: 46304395 | AK60: Calle Jose Mariano Arce 139 – Dpto. 202 | AL60: 0 | AM60: 956466496 | AN60: anavarrete@nmabogados.com.pe | AO60: LIMA | AP60: PUEBLO LIBRE | AQ60: 46022 | AR60: 46022 | AS60: SALDO FINANCIAR | AT60: 2 | AU60: 14000 | AV60: 0 | AW60: 0 | AX60: 14000 | AY60: 14000 | AZ60: 0 | BA60: 0 | BB60: Crédito Directo | BC60: Scotiabank Perú | BD60: 000-2768484 | BE60: TRANSFERENCIA BANCARIA | BG60: 059881 | BH60: No | BJ60: 4 | BK60: CANCELADO | BV60: Si | BW60: 45961.433 | BX60: Magaly Guevara Perez | BZ60: 54 | CA60: 03/07/2026 11:18 | CB60: 0 | CF60: Cobranzas_2025.csv | CG60: 2025 | CH60: 01/01/2024 | CI60: 31/08/2031
A61: RESIDENCIAL PRADA | B61: Etapa 1 | C61: Edificio | D61: A | E61: Departamento | F61: 504 | G61: 60.93 | H61: 0 | I61: 417700 | J61: 417700 | AI61: Alvaro Geanfranco Mendoza Jump | AJ61: 72112648 | AK61: Urb. San Francisco Mz. B Lt. 11 Departamento de Huanuco, Provincia de Huanuco, Dsitrito Amarilis | AL61: 938217737 | AM61: 938217737 | AN61: alvaromej17@gmail.com | AO61: HUANUCO | AP61: AMARILIS | AQ61: 45912 | AR61: 45912 | AS61: SEPARACION | AT61: 1 | AU61: 3000 | AV61: 0 | AW61: 0 | AX61: 3000 | AY61: 3000 | AZ61: 0 | BA61: 0 | BB61: Ahorro | BC61: Scotiabank Perú | BD61: 000-2768484 | BE61: TRANSFERENCIA BANCARIA | BG61: 00673199 | BH61: No | BJ61: 4 | BK61: CANCELADO | BV61: Si | BW61: 45919.616 | BX61: Kenny Salazar S | BZ61: 36 | CA61: 02/06/2026 17:13 | CB61: 0 | CF61: Cobranzas_2025.csv | CG61: 2025 | CH61: 01/01/2024 | CI61: 31/08/2031
A62: RESIDENCIAL PRADA | B62: Etapa 1 | C62: Edificio | D62: A | E62: Departamento | F62: 504 | G62: 60.93 | H62: 0 | I62: 417700 | J62: 417700 | AI62: Alvaro Geanfranco Mendoza Jump | AJ62: 72112648 | AK62: Urb. San Francisco Mz. B Lt. 11 Departamento de Huanuco, Provincia de Huanuco, Dsitrito Amarilis | AL62: 938217737 | AM62: 938217737 | AN62: alvaromej17@gmail.com | AO62: HUANUCO | AP62: AMARILIS | AQ62: 45919 | AR62: 45919 | AS62: CUOTA INICIAL | AT62: 1 | AU62: 10000 | AV62: 0 | AW62: 0 | AX62: 10000 | AY62: 10000 | AZ62: 0 | BA62: 0 | BB62: Ahorro | BC62: Scotiabank Perú | BD62: 000-2768484 | BE62: TRANSFERENCIA BANCARIA | BG62: 02785402 | BH62: No | BJ62: 4 | BK62: CANCELADO | BV62: Si | BW62: 45919.616 | BX62: Kenny Salazar S | BZ62: 36 | CA62: 23/06/2026 15:59 | CB62: 0 | CF62: Cobranzas_2025.csv | CG62: 2025 | CH62: 01/01/2024 | CI62: 31/08/2031
A63: RESIDENCIAL PRADA | B63: Etapa 1 | C63: Edificio | D63: A | E63: Departamento | F63: 1104 | G63: 54.26 | H63: 0 | I63: 397000 | J63: 397000 | AI63: Ana Fabiola Alvarez Elias | AJ63: 06789211 | AK63: Jr. Caraveli 968 Interior 103 | AL63: 991502978 | AM63: 986642025 | AN63: anafabiola1@hotmail.com | AO63: LIMA | AP63: BREÑA | AQ63: 45703 | AR63: 45703 | AS63: SEPARACION | AT63: 1 | AU63: 3000 | AV63: 0 | AW63: 0 | AX63: 3000 | AY63: 3000 | AZ63: 0 | BA63: 0 | BB63: Crédito Hipotecario | BC63: Scotiabank Perú | BD63: 000-2768484 | BE63: POS VISA | BF63: 06789211 | BG63: 31010 | BH63: No | BI63: NO PRECISA | BJ63: 1 | BK63: CANCELADO | BV63: Si | BW63: 45730.741 | BX63: Carla Michue M | BZ63: 9 | CA63: 29/05/2026 12:21 | CB63: 0 | CF63: Cobranzas_2025.csv | CG63: 2025 | CH63: 01/01/2024 | CI63: 31/08/2031
A64: RESIDENCIAL PRADA | B64: Etapa 1 | C64: Edificio | D64: A | E64: Departamento | F64: 1104 | G64: 54.26 | H64: 0 | I64: 397000 | J64: 397000 | AI64: Ana Fabiola Alvarez Elias | AJ64: 06789211 | AK64: Jr. Caraveli 968 Interior 103 | AL64: 991502978 | AM64: 986642025 | AN64: anafabiola1@hotmail.com | AO64: LIMA | AP64: BREÑA | AQ64: 45730 | AR64: 45730 | AS64: CUOTA INICIAL | AT64: 2 | AU64: 23450 | AV64: 0 | AW64: 0 | AX64: 23450 | AY64: 23450 | AZ64: 0 | BA64: 0 | BB64: Crédito Hipotecario | BC64: Scotiabank Perú | BD64: 000-2768484 | BE64: TRANSFERENCIA BANCARIA | BF64: 06789211 | BG64: 281328 | BH64: No | BI64: NO PRECISA | BJ64: 1 | BK64: CANCELADO | BV64: Si | BW64: 45730.741 | BX64: Carla Michue M | BZ64: 9 | CA64: 29/05/2026 12:21 | CB64: 0 | CF64: Cobranzas_2025.csv | CG64: 2025 | CH64: 01/01/2024 | CI64: 31/08/2031
A65: RESIDENCIAL PRADA | B65: Etapa 1 | C65: Edificio | D65: A | E65: Departamento | F65: 1104 | G65: 54.26 | H65: 0 | I65: 397000 | J65: 397000 | AI65: Ana Fabiola Alvarez Elias | AJ65: 06789211 | AK65: Jr. Caraveli 968 Interior 103 | AL65: 991502978 | AM65: 986642025 | AN65: anafabiola1@hotmail.com | AO65: LIMA | AP65: BREÑA | AQ65: 45730 | AR65: 45730 | AS65: CUOTA INICIAL | AT65: 3 | AU65: 78000 | AV65: 0 | AW65: 0 | AX65: 78000 | AY65: 78000 | AZ65: 0 | BA65: 0 | BB65: Crédito Hipotecario | BC65: Scotiabank Perú | BD65: 000-2768484 | BE65: TRANSFERENCIA BANCARIA | BF65: 06789211 | BG65: 7502425 | BH65: No | BI65: NO PRECISA | BJ65: 1 | BK65: CANCELADO | BV65: Si | BW65: 45730.741 | BX65: Carla Michue M | BZ65: 9 | CA65: 29/05/2026 12:21 | CB65: 0 | CF65: Cobranzas_2025.csv | CG65: 2025 | CH65: 01/01/2024 | CI65: 31/08/2031
A66: RESIDENCIAL PRADA | B66: Etapa 1 | C66: Edificio | D66: A | E66: Departamento | F66: 1104 | G66: 54.26 | H66: 0 | I66: 397000 | J66: 397000 | AI66: Ana Fabiola Alvarez Elias | AJ66: 06789211 | AK66: Jr. Caraveli 968 Interior 103 | AL66: 991502978 | AM66: 986642025 | AN66: anafabiola1@hotmail.com | AO66: LIMA | AP66: BREÑA | AQ66: 45746 | AR66: 45747 | AS66: SALDO FINANCIAR | AT66: 1 | AU66: 292550 | AV66: 0 | AW66: 0 | AX66: 292550 | AY66: 34500 | AZ66: 0 | BA66: 0 | BB66: Crédito Hipotecario | BC66: Scotiabank Perú | BD66: 000-2768484 | BE66: DEPOSITO EN CUENTA | BG66: 23022025 | BH66: No | BJ66: 4 | BK66: CANCELADO | BV66: Si | BW66: 45730.741 | BX66: Carla Michue M | BZ66: 9 | CA66: 07/07/2026 14:22 | CB66: 0 | CF66: Cobranzas_2025.csv | CG66: 2025 | CH66: 01/01/2024 | CI66: 31/08/2031
A67: RESIDENCIAL PRADA | B67: Etapa 1 | C67: Edificio | D67: A | E67: Departamento | F67: 1104 | G67: 54.26 | H67: 0 | I67: 397000 | J67: 397000 | AI67: Ana Fabiola Alvarez Elias | AJ67: 06789211 | AK67: Jr. Caraveli 968 Interior 103 | AL67: 991502978 | AM67: 986642025 | AN67: anafabiola1@hotmail.com | AO67: LIMA | AP67: BREÑA | AQ67: 45746 | AR67: 45747 | AS67: SALDO FINANCIAR | AT67: 1 | AU67: 0 | AV67: 0 | AW67: 0 | AX67: 0 | AY67: 258050 | AZ67: 0 | BA67: 0 | BB67: Crédito Hipotecario | BC67: Scotiabank Perú | BD67: 000-2768484 | BE67: TRANSFERENCIA BANCARIA | BG67: 30032025 | BH67: No | BJ67: 4 | BK67: CANCELADO | BV67: Si | BW67: 45730.741 | BX67: Carla Michue M | BZ67: 9 | CA67: 07/07/2026 14:23 | CB67: 0 | CF67: Cobranzas_2025.csv | CG67: 2025 | CH67: 01/01/2024 | CI67: 31/08/2031
A68: RESIDENCIAL PRADA | B68: Etapa 1 | C68: Edificio | D68: A | E68: Estacionamiento | F68: E 15 | G68: 13.27 | H68: 0 | I68: 50500 | J68: 50500 | AI68: Ana Fabiola Alvarez Elias | AJ68: 06789211 | AK68: Jr. Caraveli 968 Interior 103 | AL68: 0 | AM68: 986642025 | AN68: anafabiola1@hotmail.com | AO68: LIMA | AP68: BREÑA | AQ68: 45824 | AR68: 45824 | AS68: SEPARACION | AT68: 1 | AU68: 3000 | AV68: 0 | AW68: 0 | AX68: 3000 | AY68: 3000 | AZ68: 0 | BA68: 0 | BB68: Crédito Directo | BC68: Scotiabank Perú | BD68: 000-2768484 | BE68: DEPOSITO EN CUENTA | BG68: 005993292 | BH68: No | BJ68: 4 | BK68: CANCELADO | BV68: Si | BW68: 45868.492 | BX68: Magaly Guevara Perez | BZ68: 62 | CA68: 18/08/2026 11:26 | CB68: 0 | CF68: Cobranzas_2025.csv | CG68: 2025 | CH68: 01/01/2024 | CI68: 31/08/2031
A69: RESIDENCIAL PRADA | B69: Etapa 1 | C69: Edificio | D69: A | E69: Estacionamiento | F69: E 15 | G69: 13.27 | H69: 0 | I69: 50500 | J69: 50500 | AI69: Ana Fabiola Alvarez Elias | AJ69: 06789211 | AK69: Jr. Caraveli 968 Interior 103 | AL69: 0 | AM69: 986642025 | AN69: anafabiola1@hotmail.com | AO69: LIMA | AP69: BREÑA | AQ69: 45824 | AR69: 45824 | AS69: CUOTA INICIAL | AT69: 1 | AU69: 7000 | AV69: 0 | AW69: 0 | AX69: 7000 | AY69: 7000 | AZ69: 0 | BA69: 0 | BB69: Crédito Directo | BC69: Scotiabank Perú | BD69: 000-2768484 | BE69: TRANSFERENCIA BANCARIA | BG69: 0005993292 | BH69: No | BJ69: 4 | BK69: CANCELADO | BV69: Si | BW69: 45868.492 | BX69: Magaly Guevara Perez | BZ69: 62 | CA69: 18/08/2026 11:27 | CB69: 0 | CF69: Cobranzas_2025.csv | CG69: 2025 | CH69: 01/01/2024 | CI69: 31/08/2031
A70: RESIDENCIAL PRADA | B70: Etapa 1 | C70: Edificio | D70: A | E70: Estacionamiento | F70: E 15 | G70: 13.27 | H70: 0 | I70: 50500 | J70: 50500 | AI70: Ana Fabiola Alvarez Elias | AJ70: 06789211 | AK70: Jr. Caraveli 968 Interior 103 | AL70: 0 | AM70: 986642025 | AN70: anafabiola1@hotmail.com | AO70: LIMA | AP70: BREÑA | AQ70: 45868 | AR70: 45868 | AS70: SALDO FINANCIAR | AT70: 1 | AU70: 3000 | AV70: 0 | AW70: 0 | AX70: 3000 | AY70: 3000 | AZ70: 0 | BA70: 0 | BB70: Crédito Directo | BC70: Scotiabank Perú | BD70: 000-2768484 | BE70: TRANSFERENCIA BANCARIA | BG70: 009170000000276848424 | BH70: No | BJ70: 4 | BK70: CANCELADO | BV70: Si | BW70: 45868.492 | BX70: Magaly Guevara Perez | BZ70: 62 | CA70: 18/08/2026 11:28 | CB70: 0 | CF70: Cobranzas_2025.csv | CG70: 2025 | CH70: 01/01/2024 | CI70: 31/08/2031
A71: RESIDENCIAL PRADA | B71: Etapa 1 | C71: Edificio | D71: A | E71: Estacionamiento | F71: E 15 | G71: 13.27 | H71: 0 | I71: 50500 | J71: 50500 | AI71: Ana Fabiola Alvarez Elias | AJ71: 06789211 | AK71: Jr. Caraveli 968 Interior 103 | AL71: 0 | AM71: 986642025 | AN71: anafabiola1@hotmail.com | AO71: LIMA | AP71: BREÑA | AQ71: 45901 | AR71: 45901 | AS71: SALDO FINANCIAR | AT71: 2 | AU71: 3000 | AV71: 0 | AW71: 0 | AX71: 3000 | AY71: 3000 | AZ71: 0 | BA71: 0 | BB71: Crédito Directo | BC71: Scotiabank Perú | BD71: 00917000000276848424 | BE71: TRANSFERENCIA BANCARIA | BG71: 00000031360000003138 | BH71: No | BJ71: 4 | BK71: CANCELADO | BV71: Si | BW71: 45868.492 | BX71: Magaly Guevara Perez | BZ71: 62 | CA71: 18/08/2026 11:29 | CB71: 0 | CF71: Cobranzas_2025.csv | CG71: 2025 | CH71: 01/01/2024 | CI71: 31/08/2031
A72: RESIDENCIAL PRADA | B72: Etapa 1 | C72: Edificio | D72: A | E72: Estacionamiento | F72: E 15 | G72: 13.27 | H72: 0 | I72: 50500 | J72: 50500 | AI72: Ana Fabiola Alvarez Elias | AJ72: 06789211 | AK72: Jr. Caraveli 968 Interior 103 | AL72: 0 | AM72: 986642025 | AN72: anafabiola1@hotmail.com | AO72: LIMA | AP72: BREÑA | AQ72: 45931 | AR72: 45931 | AS72: SALDO FINANCIAR | AT72: 3 | AU72: 3000 | AV72: 0 | AW72: 0 | AX72: 3000 | AY72: 3000 | AZ72: 0 | BA72: 0 | BB72: Crédito Directo | BC72: Scotiabank Perú | BD72: 00917000000276848424 | BE72: TRANSFERENCIA BANCARIA | BG72: 0000320400003206 | BH72: No | BJ72: 4 | BK72: CANCELADO | BV72: Si | BW72: 45868.492 | BX72: Magaly Guevara Perez | BZ72: 62 | CA72: 18/08/2026 11:30 | CB72: 0 | CF72: Cobranzas_2025.csv | CG72: 2025 | CH72: 01/01/2024 | CI72: 31/08/2031
A73: RESIDENCIAL PRADA | B73: Etapa 1 | C73: Edificio | D73: A | E73: Estacionamiento | F73: E 15 | G73: 13.27 | H73: 0 | I73: 50500 | J73: 50500 | AI73: Ana Fabiola Alvarez Elias | AJ73: 06789211 | AK73: Jr. Caraveli 968 Interior 103 | AL73: 0 | AM73: 986642025 | AN73: anafabiola1@hotmail.com | AO73: LIMA | AP73: BREÑA | AQ73: 45958 | AR73: 45958 | AS73: SALDO FINANCIAR | AT73: 4 | AU73: 3000 | AV73: 0 | AW73: 0 | AX73: 3000 | AY73: 3000 | AZ73: 0 | BA73: 0 | BB73: Crédito Directo | BC73: Scotiabank Perú | BD73: 000-2768484 | BE73: TRANSFERENCIA BANCARIA | BG73: 0000326400003266 | BH73: No | BJ73: 4 | BK73: CANCELADO | BV73: Si | BW73: 45868.492 | BX73: Magaly Guevara Perez | BZ73: 62 | CA73: 18/08/2026 11:30 | CB73: 0 | CF73: Cobranzas_2025.csv | CG73: 2025 | CH73: 01/01/2024 | CI73: 31/08/2031
A74: RESIDENCIAL PRADA | B74: Etapa 1 | C74: Edificio | D74: A | E74: Estacionamiento | F74: E 15 | G74: 13.27 | H74: 0 | I74: 50500 | J74: 50500 | AI74: Ana Fabiola Alvarez Elias | AJ74: 06789211 | AK74: Jr. Caraveli 968 Interior 103 | AL74: 0 | AM74: 986642025 | AN74: anafabiola1@hotmail.com | AO74: LIMA | AP74: BREÑA | AQ74: 45992 | AR74: 45992 | AS74: SALDO FINANCIAR | AT74: 5 | AU74: 3000 | AV74: 0 | AW74: 0 | AX74: 3000 | AY74: 3000 | AZ74: 0 | BA74: 0 | BB74: Crédito Directo | BC74: Scotiabank Perú | BD74: 00917000000276848424 | BE74: TRANSFERENCIA BANCARIA | BG74: 00003352000003354 | BH74: No | BJ74: 4 | BK74: CANCELADO | BV74: Si | BW74: 45868.492 | BX74: Magaly Guevara Perez | BZ74: 62 | CA74: 18/08/2026 11:31 | CB74: 0 | CF74: Cobranzas_2025.csv | CG74: 2025 | CH74: 01/01/2024 | CI74: 31/08/2031
A75: RESIDENCIAL PRADA | B75: Etapa 1 | C75: Edificio | D75: A | E75: Estacionamiento | F75: E 15 | G75: 13.27 | H75: 0 | I75: 50500 | J75: 50500 | AI75: Ana Fabiola Alvarez Elias | AJ75: 06789211 | AK75: Jr. Caraveli 968 Interior 103 | AL75: 0 | AM75: 986642025 | AN75: anafabiola1@hotmail.com | AO75: LIMA | AP75: BREÑA | AQ75: 46020 | AR75: 46020 | AS75: SALDO FINANCIAR | AT75: 6 | AU75: 3000 | AV75: 0 | AW75: 0 | AX75: 3000 | AY75: 3000 | AZ75: 0 | BA75: 0 | BB75: Crédito Directo | BC75: Scotiabank Perú | BD75: 00917000000407141928 | BE75: TRANSFERENCIA BANCARIA | BG75: 7844655577681 | BH75: No | BJ75: 4 | BK75: CANCELADO | BV75: Si | BW75: 45868.492 | BX75: Magaly Guevara Perez | BZ75: 62 | CA75: 18/08/2026 11:38 | CB75: 0 | CF75: Cobranzas_2025.csv | CG75: 2025 | CH75: 01/01/2024 | CI75: 31/08/2031
A76: RESIDENCIAL VENECIA | B76: Etapa 1 | C76: Edificio | D76: A | E76: Departamento | F76: 704 | G76: 67 | H76: 0 | I76: 438000 | J76: 438000 | AI76: ANAMELVA JULIETA AQUISE TIZNADO | AJ76: 40917666 | AK76: Urb. Aziruni Ciudad Jardin Mz. G2 Lt 04 | AL76: 0 | AM76: 987249596 | AN76: anamelvaaquise@gmail.com | AO76: PUNO | AP76: PUNO | AQ76: 45972 | AR76: 45972 | AS76: SEPARACION | AT76: 1 | AU76: 3000 | AV76: 0 | AW76: 0 | AX76: 3000 | AY76: 3000 | AZ76: 0 | BA76: 0 | BB76: Crédito Hipotecario | BC76: Scotiabank Perú | BD76: 0004071419 | BE76: TRANSFERENCIA BANCARIA | BG76: 5516474 | BH76: No | BJ76: 4 | BK76: CANCELADO | BV76: Si | BW76: 46178.351 | BX76: Magaly Guevara Perez | BZ76: 14 | CA76: 24/05/2026 21:14 | CB76: 0 | CF76: Cobranzas_2025.csv | CG76: 2025 | CH76: 01/01/2024 | CI76: 31/08/2031
A77: RESIDENCIAL VENECIA | B77: Etapa 1 | C77: Edificio | D77: A | E77: Departamento | F77: 704 | G77: 67 | H77: 0 | I77: 438000 | J77: 438000 | AI77: ANAMELVA JULIETA AQUISE TIZNADO | AJ77: 40917666 | AK77: Urb. Aziruni Ciudad Jardin Mz. G2 Lt 04 | AL77: 0 | AM77: 987249596 | AN77: anamelvaaquise@gmail.com | AO77: PUNO | AP77: PUNO | AQ77: 46004 | AR77: 46004 | AS77: CUOTA INICIAL | AT77: 1 | AU77: 20000 | AV77: 0 | AW77: 0 | AX77: 20000 | AY77: 20000 | AZ77: 0 | BA77: 0 | BB77: Crédito Hipotecario | BC77: Scotiabank Perú | BD77: 0004071419 | BE77: TRANSFERENCIA BANCARIA | BG77: 5531532 | BH77: No | BJ77: 4 | BK77: CANCELADO | BV77: Si | BW77: 46178.351 | BX77: Magaly Guevara Perez | BZ77: 14 | CA77: 24/05/2026 21:16 | CB77: 0 | CF77: Cobranzas_2025.csv | CG77: 2025 | CH77: 01/01/2024 | CI77: 31/08/2031
A78: RESIDENCIAL PRADA | B78: Etapa 1 | C78: Edificio | D78: A | E78: Departamento | F78: 1003 | G78: 88.27 | H78: 0 | I78: 675000 | J78: 675000 | K78: Edificio | L78: A | M78: Estacionamiento | N78: E 11 - D 08 | O78: 12.5 | P78: 3.8 | Q78: 60400 | R78: 60400 | AI78: ANDEAN AYNI TRAVEL AGENCIA DE VIAJES Y TRANSPORTE EIRL | AJ78: 20610697403 | AK78: JR. DANTE NAVA NRO. 310 BAR. NUEVA UNVERSIDAD | AL78: 0 | AM78: 951923088 | AN78: operacionesjudith@gmail.com | AO78: PUNO | AP78: PUNO | AQ78: 45835 | AR78: 45835 | AS78: SEPARACION | AT78: 1 | AU78: 3000 | AV78: 0 | AW78: 0 | AX78: 3000 | AY78: 3000 | AZ78: 0 | BA78: 0 | BB78: Crédito Directo | BC78: Scotiabank Perú | BD78: 000-2768484 | BE78: TRANSFERENCIA BANCARIA | BG78: 06083805 | BH78: Si | BJ78: 4 | BK78: CANCELADO | BV78: Si | BW78: 45985.738 | BX78: Magaly Guevara Perez | BZ78: 28 | CA78: 09/06/2026 09:42 | CB78: 0 | CF78: Cobranzas_2025.csv | CG78: 2025 | CH78: 01/01/2024 | CI78: 31/08/2031
A79: RESIDENCIAL PRADA | B79: Etapa 1 | C79: Edificio | D79: A | E79: Departamento | F79: 1003 | G79: 88.27 | H79: 0 | I79: 675000 | J79: 675000 | K79: Edificio | L79: A | M79: Estacionamiento | N79: E 11 - D 08 | O79: 12.5 | P79: 3.8 | Q79: 60400 | R79: 60400 | AI79: ANDEAN AYNI TRAVEL AGENCIA DE VIAJES Y TRANSPORTE EIRL | AJ79: 20610697403 | AK79: JR. DANTE NAVA NRO. 310 BAR. NUEVA UNVERSIDAD | AL79: 0 | AM79: 951923088 | AN79: operacionesjudith@gmail.com | AO79: PUNO | AP79: PUNO | AQ79: 45985 | AR79: 45985 | AS79: CUOTA INICIAL | AT79: 1 | AU79: 270000 | AV79: 0 | AW79: 0 | AX79: 270000 | AY79: 270000 | AZ79: 0 | BA79: 0 | BB79: Crédito Directo | BC79: Scotiabank Perú | BD79: 000-2768484 | BE79: TRANSFERENCIA BANCARIA | BG79: 0349568 | BH79: Si | BJ79: 3.38 | BK79: CANCELADO | BV79: Si | BW79: 45985.738 | BX79: Magaly Guevara Perez | BZ79: 28 | CA79: 09/06/2026 09:45 | CB79: 0 | CF79: Cobranzas_2025.csv | CG79: 2025 | CH79: 01/01/2024 | CI79: 31/08/2031
A80: RESIDENCIAL PRADA | B80: Etapa 1 | C80: Edificio | D80: A | E80: Departamento | F80: 1003 | G80: 88.27 | H80: 0 | I80: 675000 | J80: 675000 | K80: Edificio | L80: A | M80: Estacionamiento | N80: E 11 - D 08 | O80: 12.5 | P80: 3.8 | Q80: 60400 | R80: 60400 | AI80: ANDEAN AYNI TRAVEL AGENCIA DE VIAJES Y TRANSPORTE EIRL | AJ80: 20610697403 | AK80: JR. DANTE NAVA NRO. 310 BAR. NUEVA UNVERSIDAD | AL80: 0 | AM80: 951923088 | AN80: operacionesjudith@gmail.com | AO80: PUNO | AP80: PUNO | AQ80: 46008 | AR80: 46010 | AS80: SALDO FINANCIAR | AT80: 1 | AU80: 66057.14 | AV80: 0 | AW80: 0 | AX80: 66057.14 | AY80: 66057.14 | AZ80: 0 | BA80: 0 | BB80: Crédito Directo | BC80: Scotiabank Perú | BD80: 000-2768484 | BE80: TRANSFERENCIA BANCARIA | BG80: 0780435 | BH80: Si | BJ80: 3.38 | BK80: CANCELADO | BV80: Si | BW80: 45985.738 | BX80: Magaly Guevara Perez | BZ80: 28 | CA80: 09/06/2026 09:47 | CB80: 0 | CF80: Cobranzas_2025.csv | CG80: 2025 | CH80: 01/01/2024 | CI80: 31/08/2031
A81: RESIDENCIAL PRADA | B81: Etapa 1 | C81: Edificio | D81: A | E81: Departamento | F81: 103 | G81: 60.94 | H81: 30.59 | I81: 520400 | J81: 520400 | AI81: Ayleen Katia Messarina Rios | AJ81: 70512701 | AK81: Departamento 101 Urbanización Santa Rosa de Surco etapa 2 Mz D Lt 23 | AL81: 978722675 | AM81: 978722675 | AN81: ayleen30mr@gmail.com | AO81: LIMA | AP81: SANTIAGO DE SURCO | AQ81: 45663 | AR81: 45663 | AS81: CUOTA INICIAL | AT81: 1 | AU81: 117000 | AV81: 0 | AW81: 0 | AX81: 117000 | AY81: 117000 | AZ81: 0 | BA81: 0 | BB81: Crédito Hipotecario | BC81: Scotiabank Perú | BD81: 000-2768484 | BE81: TRANSFERENCIA BANCARIA | BG81: 00157 | BH81: No | BJ81: 4 | BK81: CANCELADO | BV81: Si | BW81: 45663.588 | BX81: Kenny Salazar S | BZ81: 31 | CA81: 26/06/2026 17:23 | CB81: 0 | CF81: Cobranzas_2025.csv | CG81: 2025 | CH81: 01/01/2024 | CI81: 31/08/2031
A82: RESIDENCIAL PRADA | B82: Etapa 1 | C82: Edificio | D82: A | E82: Departamento | F82: 103 | G82: 60.94 | H82: 30.59 | I82: 520400 | J82: 520400 | AI82: Ayleen Katia Messarina Rios | AJ82: 70512701 | AK82: Departamento 101 Urbanización Santa Rosa de Surco etapa 2 Mz D Lt 23 | AL82: 978722675 | AM82: 978722675 | AN82: ayleen30mr@gmail.com | AO82: LIMA | AP82: SANTIAGO DE SURCO | AQ82: 45688 | AR82: 45716 | AS82: SALDO FINANCIAR | AT82: 1 | AU82: 400400 | AV82: 0 | AW82: 0 | AX82: 400400 | AY82: 400400 | AZ82: 0 | BA82: 0 | BB82: Crédito Hipotecario | BC82: Scotiabank Perú | BD82: 000-2768484 | BE82: TRANSFERENCIA BANCARIA | BG82: 2612024 | BH82: No | BJ82: 4 | BK82: CANCELADO | BV82: Si | BW82: 45663.588 | BX82: Kenny Salazar S | BZ82: 31 | CA82: 26/06/2026 17:25 | CB82: 0 | CF82: Cobranzas_2025.csv | CG82: 2025 | CH82: 01/01/2024 | CI82: 31/08/2031
A83: RESIDENCIAL PRADA | B83: Etapa 1 | C83: Edificio | D83: A | E83: Estacionamiento | F83: E 14 - D 11 | G83: 14.63 | H83: 2.37 | I83: 56300 | J83: 56300 | AI83: Ayleen Katia Messarina Rios | AJ83: 70512701 | AK83: Departamento 101 Urbanización Santa Rosa de Surco etapa 2 Mz D Lt 23 | AL83: 978722675 | AM83: 978722675 | AN83: ayleen30mr@gmail.com | AO83: LIMA | AP83: SANTIAGO DE SURCO | AQ83: 45748 | AR83: 45748 | AS83: SALDO FINANCIAR | AT83: 1 | AU83: 3800 | AV83: 0 | AW83: 0 | AX83: 3800 | AY83: 3800 | AZ83: 0 | BA83: 0 | BB83: Crédito Directo | BC83: Scotiabank Perú | BD83: 000-2768484 | BE83: TRANSFERENCIA BANCARIA | BG83: 01459586 | BH83: No | BJ83: 4 | BK83: CANCELADO | BV83: Si | BW83: 45748.63 | BX83: Magaly Guevara Perez | BZ83: 56 | CA83: 28/06/2026 21:23 | CB83: 0 | CF83: Cobranzas_2025.csv | CG83: 2025 | CH83: 01/01/2024 | CI83: 31/08/2031
A84: RESIDENCIAL PRADA | B84: Etapa 1 | C84: Edificio | D84: A | E84: Estacionamiento | F84: E 14 - D 11 | G84: 14.63 | H84: 2.37 | I84: 56300 | J84: 56300 | AI84: Ayleen Katia Messarina Rios | AJ84: 70512701 | AK84: Departamento 101 Urbanización Santa Rosa de Surco etapa 2 Mz D Lt 23 | AL84: 978722675 | AM84: 978722675 | AN84: ayleen30mr@gmail.com | AO84: LIMA | AP84: SANTIAGO DE SURCO | AQ84: 45778 | AR84: 45796 | AS84: SALDO FINANCIAR | AT84: 2 | AU84: 3800 | AV84: 0 | AW84: 0 | AX84: 3800 | AY84: 3800 | AZ84: 0 | BA84: 0 | BB84: Crédito Directo | BC84: Scotiabank Perú | BD84: 000-2768484 | BE84: TRANSFERENCIA BANCARIA | BG84: 03388134 | BH84: No | BJ84: 4 | BK84: CANCELADO | BV84: Si | BW84: 45748.63 | BX84: Magaly Guevara Perez | BZ84: 56 | CA84: 28/06/2026 21:24 | CB84: 0 | CF84: Cobranzas_2025.csv | CG84: 2025 | CH84: 01/01/2024 | CI84: 31/08/2031
A85: RESIDENCIAL PRADA | B85: Etapa 1 | C85: Edificio | D85: A | E85: Estacionamiento | F85: E 14 - D 11 | G85: 14.63 | H85: 2.37 | I85: 56300 | J85: 56300 | AI85: Ayleen Katia Messarina Rios | AJ85: 70512701 | AK85: Departamento 101 Urbanización Santa Rosa de Surco etapa 2 Mz D Lt 23 | AL85: 978722675 | AM85: 978722675 | AN85: ayleen30mr@gmail.com | AO85: LIMA | AP85: SANTIAGO DE SURCO | AQ85: 45809 | AR85: 45810 | AS85: SALDO FINANCIAR | AT85: 3 | AU85: 3800 | AV85: 0 | AW85: 0 | AX85: 3800 | AY85: 3800 | AZ85: 0 | BA85: 0 | BB85: Crédito Directo | BC85: Scotiabank Perú | BD85: 000-2768484 | BE85: TRANSFERENCIA BANCARIA | BG85: 03577668 | BH85: No | BJ85: 4 | BK85: CANCELADO | BV85: Si | BW85: 45748.63 | BX85: Magaly Guevara Perez | BZ85: 56 | CA85: 28/06/2026 21:25 | CB85: 0 | CF85: Cobranzas_2025.csv | CG85: 2025 | CH85: 01/01/2024 | CI85: 31/08/2031
A86: RESIDENCIAL PRADA | B86: Etapa 1 | C86: Edificio | D86: A | E86: Estacionamiento | F86: E 14 - D 11 | G86: 14.63 | H86: 2.37 | I86: 56300 | J86: 56300 | AI86: Ayleen Katia Messarina Rios | AJ86: 70512701 | AK86: Departamento 101 Urbanización Santa Rosa de Surco etapa 2 Mz D Lt 23 | AL86: 978722675 | AM86: 978722675 | AN86: ayleen30mr@gmail.com | AO86: LIMA | AP86: SANTIAGO DE SURCO | AQ86: 45839 | AR86: 45838 | AS86: SALDO FINANCIAR | AT86: 4 | AU86: 3800 | AV86: 0 | AW86: 0 | AX86: 3800 | AY86: 3800 | AZ86: 0 | BA86: 0 | BB86: Crédito Directo | BC86: Scotiabank Perú | BD86: 000-2768484 | BE86: TRANSFERENCIA BANCARIA | BG86: 04294427 | BH86: No | BJ86: 4 | BK86: CANCELADO | BV86: Si | BW86: 45748.63 | BX86: Magaly Guevara Perez | BZ86: 56 | CA86: 28/06/2026 21:26 | CB86: 0 | CF86: Cobranzas_2025.csv | CG86: 2025 | CH86: 01/01/2024 | CI86: 31/08/2031
A87: RESIDENCIAL PRADA | B87: Etapa 1 | C87: Edificio | D87: A | E87: Estacionamiento | F87: E 14 - D 11 | G87: 14.63 | H87: 2.37 | I87: 56300 | J87: 56300 | AI87: Ayleen Katia Messarina Rios | AJ87: 70512701 | AK87: Departamento 101 Urbanización Santa Rosa de Surco etapa 2 Mz D Lt 23 | AL87: 978722675 | AM87: 978722675 | AN87: ayleen30mr@gmail.com | AO87: LIMA | AP87: SANTIAGO DE SURCO | AQ87: 45870 | AR87: 45868 | AS87: SALDO FINANCIAR | AT87: 5 | AU87: 3800 | AV87: 0 | AW87: 0 | AX87: 3800 | AY87: 3800 | AZ87: 0 | BA87: 0 | BB87: Crédito Directo | BC87: Scotiabank Perú | BD87: 000-2768484 | BE87: TRANSFERENCIA BANCARIA | BG87: 05185364 | BH87: No | BJ87: 4 | BK87: CANCELADO | BV87: Si | BW87: 45748.63 | BX87: Magaly Guevara Perez | BZ87: 56 | CA87: 28/06/2026 21:30 | CB87: 0 | CF87: Cobranzas_2025.csv | CG87: 2025 | CH87: 01/01/2024 | CI87: 31/08/2031
A88: RESIDENCIAL PRADA | B88: Etapa 1 | C88: Edificio | D88: A | E88: Estacionamiento | F88: E 14 - D 11 | G88: 14.63 | H88: 2.37 | I88: 56300 | J88: 56300 | AI88: Ayleen Katia Messarina Rios | AJ88: 70512701 | AK88: Departamento 101 Urbanización Santa Rosa de Surco etapa 2 Mz D Lt 23 | AL88: 978722675 | AM88: 978722675 | AN88: ayleen30mr@gmail.com | AO88: LIMA | AP88: SANTIAGO DE SURCO | AQ88: 45901 | AR88: 45902 | AS88: SALDO FINANCIAR | AT88: 6 | AU88: 3800 | AV88: 0 | AW88: 0 | AX88: 3800 | AY88: 3800 | AZ88: 0 | BA88: 0 | BB88: Crédito Directo | BC88: Scotiabank Perú | BD88: 000-2768484 | BE88: TRANSFERENCIA BANCARIA | BG88: 00510042 | BH88: No | BJ88: 4 | BK88: CANCELADO | BV88: Si | BW88: 45748.63 | BX88: Magaly Guevara Perez | BZ88: 56 | CA88: 28/06/2026 21:31 | CB88: 0 | CF88: Cobranzas_2025.csv | CG88: 2025 | CH88: 01/01/2024 | CI88: 31/08/2031
A89: RESIDENCIAL PRADA | B89: Etapa 1 | C89: Edificio | D89: A | E89: Estacionamiento | F89: E 14 - D 11 | G89: 14.63 | H89: 2.37 | I89: 56300 | J89: 56300 | AI89: Ayleen Katia Messarina Rios | AJ89: 70512701 | AK89: Departamento 101 Urbanización Santa Rosa de Surco etapa 2 Mz D Lt 23 | AL89: 978722675 | AM89: 978722675 | AN89: ayleen30mr@gmail.com | AO89: LIMA | AP89: SANTIAGO DE SURCO | AQ89: 45931 | AR89: 45942 | AS89: SALDO FINANCIAR | AT89: 7 | AU89: 3800 | AV89: 0 | AW89: 0 | AX89: 3800 | AY89: 3800 | AZ89: 0 | BA89: 0 | BB89: Crédito Directo | BC89: Scotiabank Perú | BD89: 000-2768484 | BE89: TRANSFERENCIA BANCARIA | BG89: 02106124 | BH89: No | BJ89: 4 | BK89: CANCELADO | BV89: Si | BW89: 45748.63 | BX89: Magaly Guevara Perez | BZ89: 56 | CA89: 28/06/2026 21:31 | CB89: 0 | CF89: Cobranzas_2025.csv | CG89: 2025 | CH89: 01/01/2024 | CI89: 31/08/2031
A90: RESIDENCIAL PRADA | B90: Etapa 1 | C90: Edificio | D90: A | E90: Estacionamiento | F90: E 14 - D 11 | G90: 14.63 | H90: 2.37 | I90: 56300 | J90: 56300 | AI90: Ayleen Katia Messarina Rios | AJ90: 70512701 | AK90: Departamento 101 Urbanización Santa Rosa de Surco etapa 2 Mz D Lt 23 | AL90: 978722675 | AM90: 978722675 | AN90: ayleen30mr@gmail.com | AO90: LIMA | AP90: SANTIAGO DE SURCO | AQ90: 45962 | AR90: 45980 | AS90: SALDO FINANCIAR | AT90: 8 | AU90: 3800 | AV90: 0 | AW90: 0 | AX90: 3800 | AY90: 3800 | AZ90: 0 | BA90: 0 | BB90: Crédito Directo | BC90: Scotiabank Perú | BD90: 000-2768484 | BE90: TRANSFERENCIA BANCARIA | BG90: 00374413 | BH90: No | BJ90: 4 | BK90: CANCELADO | BV90: Si | BW90: 45748.63 | BX90: Magaly Guevara Perez | BZ90: 56 | CA90: 28/06/2026 21:32 | CB90: 0 | CF90: Cobranzas_2025.csv | CG90: 2025 | CH90: 01/01/2024 | CI90: 31/08/2031
A91: RESIDENCIAL PRADA | B91: Etapa 1 | C91: Edificio | D91: A | E91: Estacionamiento | F91: E 14 - D 11 | G91: 14.63 | H91: 2.37 | I91: 56300 | J91: 56300 | AI91: Ayleen Katia Messarina Rios | AJ91: 70512701 | AK91: Departamento 101 Urbanización Santa Rosa de Surco etapa 2 Mz D Lt 23 | AL91: 978722675 | AM91: 978722675 | AN91: ayleen30mr@gmail.com | AO91: LIMA | AP91: SANTIAGO DE SURCO | AQ91: 45992 | AR91: 46033 | AS91: SALDO FINANCIAR | AT91: 9 | AU91: 3800 | AV91: 0 | AW91: 0 | AX91: 3800 | AY91: 3800 | AZ91: 0 | BA91: 0 | BB91: Crédito Directo | BC91: Scotiabank Perú | BD91: 000-2768484 | BE91: TRANSFERENCIA BANCARIA | BG91: 01802980 | BH91: No | BJ91: 4 | BK91: CANCELADO | BV91: Si | BW91: 45748.63 | BX91: Magaly Guevara Perez | BZ91: 56 | CA91: 28/06/2026 21:33 | CB91: 0 | CF91: Cobranzas_2025.csv | CG91: 2025 | CH91: 01/01/2024 | CI91: 31/08/2031
A92: RESIDENCIAL VENECIA | B92: Etapa 1 | C92: Edificio | D92: A | E92: Departamento | F92: 204 | G92: 67 | H92: 0 | I92: 483000 | J92: 443000 | K92: Edificio | L92: A | M92: Estacionamiento | N92: E 14 - D 4 | O92: 14.5 | P92: 0 | Q92: 42800 | R92: 42800 | AI92: Carlos La Cruz Crespo | AJ92: 09022488 | AK92: comas | AL92: 0 | AM92: 997009340 | AN92: carlos.14lacruz@gmail.com | AO92: LIMA | AP92: COMAS | AQ92: 45795 | AR92: 45795 | AS92: SEPARACION | AT92: 1 | AU92: 3000 | AV92: 0 | AW92: 0 | AX92: 3000 | AY92: 1000 | AZ92: 0 | BA92: 0 | BB92: Crédito Directo | BC92: Scotiabank Perú | BD92: 0004071419 | BE92: TRANSFERENCIA BANCARIA | BG92: 473500004737 | BH92: No | BJ92: 4 | BK92: CANCELADO | BV92: Si | BW92: 45839.335 | BX92: Magaly Guevara Perez | BZ92: 2 | CA92: 18/08/2026 13:41 | CB92: 0 | CF92: Cobranzas_2025.csv | CG92: 2025 | CH92: 01/01/2024 | CI92: 31/08/2031
A93: RESIDENCIAL VENECIA | B93: Etapa 1 | C93: Edificio | D93: A | E93: Departamento | F93: 204 | G93: 67 | H93: 0 | I93: 483000 | J93: 443000 | K93: Edificio | L93: A | M93: Estacionamiento | N93: E 14 - D 4 | O93: 14.5 | P93: 0 | Q93: 42800 | R93: 42800 | AI93: Carlos La Cruz Crespo | AJ93: 09022488 | AK93: comas | AL93: 0 | AM93: 997009340 | AN93: carlos.14lacruz@gmail.com | AO93: LIMA | AP93: COMAS | AQ93: 45795 | AR93: 45797 | AS93: SEPARACION | AT93: 1 | AU93: 0 | AV93: 0 | AW93: 0 | AX93: 0 | AY93: 2000 | AZ93: 0 | BA93: 0 | BB93: Crédito Directo | BC93: Scotiabank Perú | BD93: 0004071419 | BE93: TRANSFERENCIA BANCARIA | BG93: 474400004746 | BH93: No | BJ93: 4 | BK93: CANCELADO | BV93: Si | BW93: 45839.335 | BX93: Magaly Guevara Perez | BZ93: 2 | CA93: 18/08/2026 13:41 | CB93: 0 | CF93: Cobranzas_2025.csv | CG93: 2025 | CH93: 01/01/2024 | CI93: 31/08/2031
A94: RESIDENCIAL PRADA | B94: Etapa 1 | C94: Edificio | D94: A | E94: Departamento | F94: 601 | G94: 84 | H94: 0 | I94: 630000 | J94: 630000 | K94: Edificio | L94: A | M94: Estacionamiento | N94: E 28 - D 22 | O94: 13 | P94: 3.89 | Q94: 60000 | R94: 60000 | AI94: Chistopher Omar Peña Camargo | AJ94: 44062837 | AK94: Av. San Felipe 351 | AM94: 964328569 | AN94: ciruvision@gmail.com | AO94: LIMA | AP94: JESUS MARIA | AQ94: 45804 | AR94: 45804 | AS94: SEPARACION | AT94: 1 | AU94: 3000 | AV94: 0 | AW94: 0 | AX94: 3000 | AY94: 3000 | AZ94: 0 | BA94: 0 | BB94: Crédito Hipotecario | BC94: Scotiabank Perú | BD94: 000-2768484 | BE94: TRANSFERENCIA BANCARIA | BG94: 00002220000000002222 | BH94: No | BJ94: 4 | BK94: CANCELADO | BV94: Si | BW94: 45831.692 | BX94: Carla Michue M | BZ94: 12 | CA94: 03/07/2026 14:39 | CB94: 0 | CF94: Cobranzas_2025.csv | CG94: 2025 | CH94: 01/01/2024 | CI94: 31/08/2031
A95: RESIDENCIAL PRADA | B95: Etapa 1 | C95: Edificio | D95: A | E95: Departamento | F95: 601 | G95: 84 | H95: 0 | I95: 630000 | J95: 630000 | K95: Edificio | L95: A | M95: Estacionamiento | N95: E 28 - D 22 | O95: 13 | P95: 3.89 | Q95: 60000 | R95: 60000 | AI95: Chistopher Omar Peña Camargo | AJ95: 44062837 | AK95: Av. San Felipe 351 | AM95: 964328569 | AN95: ciruvision@gmail.com | AO95: LIMA | AP95: JESUS MARIA | AQ95: 45831 | AR95: 45831 | AS95: CUOTA INICIAL | AT95: 2 | AU95: 107000 | AV95: 0 | AW95: 0 | AX95: 107000 | AY95: 107000 | AZ95: 0 | BA95: 0 | BB95: Crédito Hipotecario | BC95: Scotiabank Perú | BD95: 000-2768484 | BE95: TRANSFERENCIA BANCARIA | BF95: 44062837 | BG95: 006128332 | BH95: No | BI95: NO PRECISA | BJ95: 1 | BK95: CANCELADO | BV95: Si | BW95: 45831.692 | BX95: Carla Michue M | BZ95: 12 | CA95: 29/05/2026 12:21 | CB95: 0 | CF95: Cobranzas_2025.csv | CG95: 2025 | CH95: 01/01/2024 | CI95: 31/08/2031
A96: RESIDENCIAL PRADA | B96: Etapa 1 | C96: Edificio | D96: A | E96: Departamento | F96: 601 | G96: 84 | H96: 0 | I96: 630000 | J96: 630000 | K96: Edificio | L96: A | M96: Estacionamiento | N96: E 28 - D 22 | O96: 13 | P96: 3.89 | Q96: 60000 | R96: 60000 | AI96: Chistopher Omar Peña Camargo | AJ96: 44062837 | AK96: Av. San Felipe 351 | AM96: 964328569 | AN96: ciruvision@gmail.com | AO96: LIMA | AP96: JESUS MARIA | AQ96: 45868 | AR96: 45936 | AS96: SALDO FINANCIAR | AT96: 1 | AU96: 580000 | AV96: 0 | AW96: 0 | AX96: 580000 | AY96: 580000 | AZ96: 0 | BA96: 0 | BB96: Crédito Hipotecario | BC96: Scotiabank Perú | BD96: 000-2768484 | BE96: TRANSFERENCIA BANCARIA | BG96: EB01-137 | BH96: No | BJ96: 4 | BK96: CANCELADO | BV96: Si | BW96: 45831.692 | BX96: Carla Michue M | BZ96: 12 | CA96: 14/08/2026 11:43 | CB96: 0 | CF96: Cobranzas_2025.csv | CG96: 2025 | CH96: 01/01/2024 | CI96: 31/08/2031
A97: RESIDENCIAL PRADA | B97: Etapa 1 | C97: Edificio | D97: A | E97: Departamento | F97: 302 | G97: 55 | H97: 0 | I97: 435500 | J97: 435500 | AI97: Cristhiam Ortiz Angeles | AJ97: 45110882 | AK97: Av. Olavegoya 1879 departamento 301 | AL97: 992532732 | AM97: 992532732 | AN97: Cristhian4520@gmail.com | AO97: LIMA | AP97: JESUS MARIA | AQ97: 45688 | AR97: 45838 | AS97: SALDO FINANCIAR | AT97: 1 | AU97: 370950 | AV97: 0 | AW97: 0 | AX97: 370950 | AY97: 370950 | AZ97: 0 | BA97: 0 | BB97: Crédito Hipotecario | BC97: Scotiabank Perú | BD97: 000-2768484 | BE97: TRANSFERENCIA BANCARIA | BG97: EB01-76 | BH97: No | BJ97: 4 | BK97: CANCELADO | BV97: Si | BW97: 45499.613 | BX97: Kenny Salazar S | BZ97: 34 | CA97: 07/07/2026 08:58 | CB97: 0 | CF97: Cobranzas_2025.csv | CG97: 2025 | CH97: 01/01/2024 | CI97: 31/08/2031
A98: RESIDENCIAL PRADA | B98: Etapa 1 | C98: Edificio | D98: A | E98: Departamento | F98: 902 | G98: 56 | H98: 0 | I98: 433500 | J98: 433500 | K98: Edificio | L98: A | M98: Estacionamiento | N98: E 43 | O98: 13.27 | P98: 0 | Q98: 50500 | R98: 50500 | AI98: Daniel Alejandro Aguayo Vera | AJ98: 76121899 | AK98: Calle los Rosales 743 Lima- Chaclacayo. | AL98: 943151339 | AM98: 943151339 | AN98: daniel_aguayo25@hotmail.com | AO98: LIMA | AP98: SAN ISIDRO | AQ98: 45985 | AR98: 45985 | AS98: SEPARACION | AT98: 1 | AU98: 3000 | AV98: 0 | AW98: 0 | AX98: 3000 | AY98: 3000 | AZ98: 0 | BA98: 0 | BB98: Crédito Hipotecario | BC98: Scotiabank Perú | BD98: 000-2768484 | BE98: TRANSFERENCIA BANCARIA | BG98: 05149943 | BH98: No | BJ98: 4 | BK98: CANCELADO | BV98: Si | BW98: 46008.744 | BX98: Kenny Salazar S | BZ98: 41 | CA98: 03/06/2026 09:48 | CB98: 0 | CF98: Cobranzas_2025.csv | CG98: 2025 | CH98: 01/01/2024 | CI98: 31/08/2031
A99: RESIDENCIAL PRADA | B99: Etapa 1 | C99: Edificio | D99: A | E99: Departamento | F99: 902 | G99: 56 | H99: 0 | I99: 433500 | J99: 433500 | K99: Edificio | L99: A | M99: Estacionamiento | N99: E 43 | O99: 13.27 | P99: 0 | Q99: 50500 | R99: 50500 | AI99: Daniel Alejandro Aguayo Vera | AJ99: 76121899 | AK99: Calle los Rosales 743 Lima- Chaclacayo. | AL99: 943151339 | AM99: 943151339 | AN99: daniel_aguayo25@hotmail.com | AO99: LIMA | AP99: SAN ISIDRO | AQ99: 46008 | AR99: 46008 | AS99: CUOTA INICIAL | AT99: 1 | AU99: 45400 | AV99: 0 | AW99: 0 | AX99: 45400 | AY99: 45400 | AZ99: 0 | BA99: 0 | BB99: Crédito Hipotecario | BC99: Scotiabank Perú | BD99: 00917000000276848424 | BE99: TRANSFERENCIA BANCARIA | BF99: 76121899 | BG99: 0797612 | BH99: No | BJ99: 4 | BK99: CANCELADO | BV99: Si | BW99: 46008.744 | BX99: Kenny Salazar S | BZ99: 41 | CA99: 05/06/2026 13:42 | CB99: 0 | CF99: Cobranzas_2025.csv | CG99: 2025 | CH99: 01/01/2024 | CI99: 31/08/2031
A100: RESIDENCIAL BEYOND | B100: Etapa 1 | C100: Edificio | D100: A | E100: Departamento | F100: 302 | G100: 57 | H100: 0 | I100: 430000 | J100: 381000 | AI100: Danixa Thalia Manosalva Ameri | AJ100: 48569476 | AK100: Jr. Huáscar 1825 dpto.101 | AL100: 0 | AM100: 992382005 | AN100: danixamanosalva94@gmail.com | AO100: LIMA | AP100: JESUS MARIA | AQ100: 45932 | AR100: 45932 | AS100: SEPARACION | AT100: 1 | AU100: 3000 | AV100: 0 | AW100: 0 | AX100: 3000 | AY100: 3000 | AZ100: 0 | BA100: 0 | BB100: Ahorro | BC100: Banco de Credito del Perú | BD100: 194-7325779-0-65 | BE100: TRANSFERENCIA BANCARIA | BG100: 04998185 | BH100: No | BJ100: 4 | BK100: CANCELADO | BV100: No | BW100: 45940.419 | BX100: Magaly Guevara Perez | BZ100: 6 | CA100: 01/05/2026 11:35 | CB100: 0 | CF100: Cobranzas_2025.csv | CG100: 2025 | CH100: 01/01/2024 | CI100: 31/08/2031
...

Sheet Prada
C5: REPORTE DE COBRANZAS
B6: Prada
C8: Vendido | F8: Cobranzas
C9: Monto | D9: Unidades | F9: Avance | G9: Cobrado | H9: Por Cobrar | I9: Vencido | J9: Tasa de Morosidad | K9: Clientes Morosos (unidades) | L9: Dias de Atraso (Promedio)
B11: Departamentos | C11: 24218600 | D11: 58 | F11: =IF(C11=0,0,G11/C11) -> 0.90244358 | G11: =SUM(G12:G13) -> 21855920 | H11: =SUM(H12:H13) -> 460800 | I11: =SUM(I12:I13) -> 1901880 | J11: =IF(C11=0,0,I11/C11) -> 0.078529725 | K11: 6 | L11: 71
B12: Departamento | C12: 16401100 | D12: 31 | F12: =IF(C12=0,0,G12/C12) -> 0.91229674 | G12: =IFERROR(SUMPRODUCT(--ISNUMBER(SEARCH($B$6,Base_Cobranzas!$A$2:$A$814)),--((--ISNUMBER(SEARCH("DEPART",UPPER(Base_Cobranzas!$E$2:$E$814)))+--ISNUMBER(SEARCH("DEPART",UPPER(Base_Cobranzas!$M$2:$M$814)))+--ISNUMBER(SEARCH("DEPART",UPPER(Base_Cobranzas!$U$2:$U$814)))+--ISNUMBER(SEARCH("DEPART",UPPER(Base_Cobranzas!$AC$2:$AC$814))))>0),--((--ISNUMBER(SEARCH("ESTACION",UPPER(Base_Cobranzas!$E$2:$E$814)))+--ISNUMBER(SEARCH("ESTACION",UPPER(Base_Cobranzas!$M$2:$M$814)))+--ISNUMBER(SEARCH("ESTACION",UPPER(Base_Cobranzas!$U$2:$U$814)))+--ISNUMBER(SEARCH("ESTACION",UPPER(Base_Cobranzas!$AC$2:$AC$814))))=0),--(Base_Cobranzas!$AY$2:$AY$814>0),Base_Cobranzas!$AY$2:$AY$814),0) -> 14962670 | H12: =IFERROR(SUMPRODUCT(--ISNUMBER(SEARCH($B$6,Base_Cobranzas!$A$2:$A$814)),--((--ISNUMBER(SEARCH("DEPART",UPPER(Base_Cobranzas!$E$2:$E$814)))+--ISNUMBER(SEARCH("DEPART",UPPER(Base_Cobranzas!$M$2:$M$814)))+--ISNUMBER(SEARCH("DEPART",UPPER(Base_Cobranzas!$U$2:$U$814)))+--ISNUMBER(SEARCH("DEPART",UPPER(Base_Cobranzas!$AC$2:$AC$814))))>0),--((--ISNUMBER(SEARCH("ESTACION",UPPER(Base_Cobranzas!$E$2:$E$814)))+--ISNUMBER(SEARCH("ESTACION",UPPER(Base_Cobranzas!$M$2:$M$814)))+--ISNUMBER(SEARCH("ESTACION",UPPER(Base_Cobranzas!$U$2:$U$814)))+--ISNUMBER(SEARCH("ESTACION",UPPER(Base_Cobranzas!$AC$2:$AC$814))))=0),--ISNUMBER(SEARCH("PENDIENTE",UPPER(TRIM(Base_Cobranzas!$BK$2:$BK$814)))),Base_Cobranzas!$AZ$2:$AZ$814),0) -> 0 | I12: =IFERROR(SUMPRODUCT(--ISNUMBER(SEARCH($B$6,Base_Cobranzas!$A$2:$A$814)),--((--ISNUMBER(SEARCH("DEPART",UPPER(Base_Cobranzas!$E$2:$E$814)))+--ISNUMBER(SEARCH("DEPART",UPPER(Base_Cobranzas!$M$2:$M$814)))+--ISNUMBER(SEARCH("DEPART",UPPER(Base_Cobranzas!$U$2:$U$814)))+--ISNUMBER(SEARCH("DEPART",UPPER(Base_Cobranzas!$AC$2:$AC$814))))>0),--((--ISNUMBER(SEARCH("ESTACION",UPPER(Base_Cobranzas!$E$2:$E$814)))+--ISNUMBER(SEARCH("ESTACION",UPPER(Base_Cobranzas!$M$2:$M$814)))+--ISNUMBER(SEARCH("ESTACION",UPPER(Base_Cobranzas!$U$2:$U$814)))+--ISNUMBER(SEARCH("ESTACION",UPPER(Base_Cobranzas!$AC$2:$AC$814))))=0),--ISNUMBER(SEARCH("VENCIDO",UPPER(TRIM(Base_Cobranzas!$BK$2:$BK$814)))),Base_Cobranzas!$AZ$2:$AZ$814),0) -> 1438430 | J12: =IF(C12=0,0,I12/C12) -> 0.087703264 | K12: 4 | L12: 93
B13: Departamento + Estacionamiento | C13: 7817500 | D13: 27 | F13: =IF(C13=0,0,G13/C13) -> 0.88177166 | G13: =IFERROR(SUMPRODUCT(--ISNUMBER(SEARCH($B$6,Base_Cobranzas!$A$2:$A$814)),--((--ISNUMBER(SEARCH("DEPART",UPPER(Base_Cobranzas!$E$2:$E$814)))+--ISNUMBER(SEARCH("DEPART",UPPER(Base_Cobranzas!$M$2:$M$814)))+--ISNUMBER(SEARCH("DEPART",UPPER(Base_Cobranzas!$U$2:$U$814)))+--ISNUMBER(SEARCH("DEPART",UPPER(Base_Cobranzas!$AC$2:$AC$814))))>0),--((--ISNUMBER(SEARCH("ESTACION",UPPER(Base_Cobranzas!$E$2:$E$814)))+--ISNUMBER(SEARCH("ESTACION",UPPER(Base_Cobranzas!$M$2:$M$814)))+--ISNUMBER(SEARCH("ESTACION",UPPER(Base_Cobranzas!$U$2:$U$814)))+--ISNUMBER(SEARCH("ESTACION",UPPER(Base_Cobranzas!$AC$2:$AC$814))))>0),--(Base_Cobranzas!$AY$2:$AY$814>0),Base_Cobranzas!$AY$2:$AY$814),0) -> 6893250 | H13: =IFERROR(SUMPRODUCT(--ISNUMBER(SEARCH($B$6,Base_Cobranzas!$A$2:$A$814)),--((--ISNUMBER(SEARCH("DEPART",UPPER(Base_Cobranzas!$E$2:$E$814)))+--ISNUMBER(SEARCH("DEPART",UPPER(Base_Cobranzas!$M$2:$M$814)))+--ISNUMBER(SEARCH("DEPART",UPPER(Base_Cobranzas!$U$2:$U$814)))+--ISNUMBER(SEARCH("DEPART",UPPER(Base_Cobranzas!$AC$2:$AC$814))))>0),--((--ISNUMBER(SEARCH("ESTACION",UPPER(Base_Cobranzas!$E$2:$E$814)))+--ISNUMBER(SEARCH("ESTACION",UPPER(Base_Cobranzas!$M$2:$M$814)))+--ISNUMBER(SEARCH("ESTACION",UPPER(Base_Cobranzas!$U$2:$U$814)))+--ISNUMBER(SEARCH("ESTACION",UPPER(Base_Cobranzas!$AC$2:$AC$814))))>0),--ISNUMBER(SEARCH("PENDIENTE",UPPER(TRIM(Base_Cobranzas!$BK$2:$BK$814)))),Base_Cobranzas!$AZ$2:$AZ$814),0) -> 460800 | I13: =IFERROR(SUMPRODUCT(--ISNUMBER(SEARCH($B$6,Base_Cobranzas!$A$2:$A$814)),--((--ISNUMBER(SEARCH("DEPART",UPPER(Base_Cobranzas!$E$2:$E$814)))+--ISNUMBER(SEARCH("DEPART",UPPER(Base_Cobranzas!$M$2:$M$814)))+--ISNUMBER(SEARCH("DEPART",UPPER(Base_Cobranzas!$U$2:$U$814)))+--ISNUMBER(SEARCH("DEPART",UPPER(Base_Cobranzas!$AC$2:$AC$814))))>0),--((--ISNUMBER(SEARCH("ESTACION",UPPER(Base_Cobranzas!$E$2:$E$814)))+--ISNUMBER(SEARCH("ESTACION",UPPER(Base_Cobranzas!$M$2:$M$814)))+--ISNUMBER(SEARCH("ESTACION",UPPER(Base_Cobranzas!$U$2:$U$814)))+--ISNUMBER(SEARCH("ESTACION",UPPER(Base_Cobranzas!$AC$2:$AC$814))))>0),--ISNUMBER(SEARCH("VENCIDO",UPPER(TRIM(Base_Cobranzas!$BK$2:$BK$814)))),Base_Cobranzas!$AZ$2:$AZ$814),0) -> 463450 | J13: =IF(C13=0,0,I13/C13) -> 0.059283658 | K13: 2 | L13: 19
B15: Estacionamientos | C15: 807100 | D15: 15 | F15: =IF(C15=0,0,G15/C15) -> 0.79099269 | G15: =IFERROR(SUMPRODUCT(--ISNUMBER(SEARCH($B$6,Base_Cobranzas!$A$2:$A$814)),--((--ISNUMBER(SEARCH("DEPART",UPPER(Base_Cobranzas!$E$2:$E$814)))+--ISNUMBER(SEARCH("DEPART",UPPER(Base_Cobranzas!$M$2:$M$814)))+--ISNUMBER(SEARCH("DEPART",UPPER(Base_Cobranzas!$U$2:$U$814)))+--ISNUMBER(SEARCH("DEPART",UPPER(Base_Cobranzas!$AC$2:$AC$814))))=0),--((--ISNUMBER(SEARCH("ESTACION",UPPER(Base_Cobranzas!$E$2:$E$814)))+--ISNUMBER(SEARCH("ESTACION",UPPER(Base_Cobranzas!$M$2:$M$814)))+--ISNUMBER(SEARCH("ESTACION",UPPER(Base_Cobranzas!$U$2:$U$814)))+--ISNUMBER(SEARCH("ESTACION",UPPER(Base_Cobranzas!$AC$2:$AC$814))))>0),--(Base_Cobranzas!$AY$2:$AY$814>0),Base_Cobranzas!$AY$2:$AY$814),0) -> 638410.2 | H15: =IFERROR(SUMPRODUCT(--ISNUMBER(SEARCH($B$6,Base_Cobranzas!$A$2:$A$814)),--((--ISNUMBER(SEARCH("DEPART",UPPER(Base_Cobranzas!$E$2:$E$814)))+--ISNUMBER(SEARCH("DEPART",UPPER(Base_Cobranzas!$M$2:$M$814)))+--ISNUMBER(SEARCH("DEPART",UPPER(Base_Cobranzas!$U$2:$U$814)))+--ISNUMBER(SEARCH("DEPART",UPPER(Base_Cobranzas!$AC$2:$AC$814))))=0),--((--ISNUMBER(SEARCH("ESTACION",UPPER(Base_Cobranzas!$E$2:$E$814)))+--ISNUMBER(SEARCH("ESTACION",UPPER(Base_Cobranzas!$M$2:$M$814)))+--ISNUMBER(SEARCH("ESTACION",UPPER(Base_Cobranzas!$U$2:$U$814)))+--ISNUMBER(SEARCH("ESTACION",UPPER(Base_Cobranzas!$AC$2:$AC$814))))>0),--ISNUMBER(SEARCH("PENDIENTE",UPPER(TRIM(Base_Cobranzas!$BK$2:$BK$814)))),Base_Cobranzas!$AZ$2:$AZ$814),0) -> 73889.8 | I15: =IFERROR(SUMPRODUCT(--ISNUMBER(SEARCH($B$6,Base_Cobranzas!$A$2:$A$814)),--((--ISNUMBER(SEARCH("DEPART",UPPER(Base_Cobranzas!$E$2:$E$814)))+--ISNUMBER(SEARCH("DEPART",UPPER(Base_Cobranzas!$M$2:$M$814)))+--ISNUMBER(SEARCH("DEPART",UPPER(Base_Cobranzas!$U$2:$U$814)))+--ISNUMBER(SEARCH("DEPART",UPPER(Base_Cobranzas!$AC$2:$AC$814))))=0),--((--ISNUMBER(SEARCH("ESTACION",UPPER(Base_Cobranzas!$E$2:$E$814)))+--ISNUMBER(SEARCH("ESTACION",UPPER(Base_Cobranzas!$M$2:$M$814)))+--ISNUMBER(SEARCH("ESTACION",UPPER(Base_Cobranzas!$U$2:$U$814)))+--ISNUMBER(SEARCH("ESTACION",UPPER(Base_Cobranzas!$AC$2:$AC$814))))>0),--ISNUMBER(SEARCH("VENCIDO",UPPER(TRIM(Base_Cobranzas!$BK$2:$BK$814)))),Base_Cobranzas!$AZ$2:$AZ$814),0) -> 94800 | J15: =IF(C15=0,0,I15/C15) -> 0.11745756 | K15: 5 | L15: 40
B17: Depositos | C17: 0 | D17: 0 | F17: =IF(C17=0,0,G17/C17) -> 0 | G17: =IFERROR(SUMPRODUCT(--ISNUMBER(SEARCH($B$6,Base_Cobranzas!$A$2:$A$814)),--((--ISNUMBER(SEARCH("DEPART",UPPER(Base_Cobranzas!$E$2:$E$814)))+--ISNUMBER(SEARCH("DEPART",UPPER(Base_Cobranzas!$M$2:$M$814)))+--ISNUMBER(SEARCH("DEPART",UPPER(Base_Cobranzas!$U$2:$U$814)))+--ISNUMBER(SEARCH("DEPART",UPPER(Base_Cobranzas!$AC$2:$AC$814))))=0),--((--ISNUMBER(SEARCH("ESTACION",UPPER(Base_Cobranzas!$E$2:$E$814)))+--ISNUMBER(SEARCH("ESTACION",UPPER(Base_Cobranzas!$M$2:$M$814)))+--ISNUMBER(SEARCH("ESTACION",UPPER(Base_Cobranzas!$U$2:$U$814)))+--ISNUMBER(SEARCH("ESTACION",UPPER(Base_Cobranzas!$AC$2:$AC$814))))=0),--((--ISNUMBER(SEARCH("DEPOS",UPPER(Base_Cobranzas!$E$2:$E$814)))+--ISNUMBER(SEARCH("DEPOS",UPPER(Base_Cobranzas!$M$2:$M$814)))+--ISNUMBER(SEARCH("DEPOS",UPPER(Base_Cobranzas!$U$2:$U$814)))+--ISNUMBER(SEARCH("DEPOS",UPPER(Base_Cobranzas!$AC$2:$AC$814))))>0),--(Base_Cobranzas!$AY$2:$AY$814>0),Base_Cobranzas!$AY$2:$AY$814),0) -> 0 | H17: =IFERROR(SUMPRODUCT(--ISNUMBER(SEARCH($B$6,Base_Cobranzas!$A$2:$A$814)),--((--ISNUMBER(SEARCH("DEPART",UPPER(Base_Cobranzas!$E$2:$E$814)))+--ISNUMBER(SEARCH("DEPART",UPPER(Base_Cobranzas!$M$2:$M$814)))+--ISNUMBER(SEARCH("DEPART",UPPER(Base_Cobranzas!$U$2:$U$814)))+--ISNUMBER(SEARCH("DEPART",UPPER(Base_Cobranzas!$AC$2:$AC$814))))=0),--((--ISNUMBER(SEARCH("ESTACION",UPPER(Base_Cobranzas!$E$2:$E$814)))+--ISNUMBER(SEARCH("ESTACION",UPPER(Base_Cobranzas!$M$2:$M$814)))+--ISNUMBER(SEARCH("ESTACION",UPPER(Base_Cobranzas!$U$2:$U$814)))+--ISNUMBER(SEARCH("ESTACION",UPPER(Base_Cobranzas!$AC$2:$AC$814))))=0),--((--ISNUMBER(SEARCH("DEPOS",UPPER(Base_Cobranzas!$E$2:$E$814)))+--ISNUMBER(SEARCH("DEPOS",UPPER(Base_Cobranzas!$M$2:$M$814)))+--ISNUMBER(SEARCH("DEPOS",UPPER(Base_Cobranzas!$U$2:$U$814)))+--ISNUMBER(SEARCH("DEPOS",UPPER(Base_Cobranzas!$AC$2:$AC$814))))>0),--ISNUMBER(SEARCH("PENDIENTE",UPPER(TRIM(Base_Cobranzas!$BK$2:$BK$814)))),Base_Cobranzas!$AZ$2:$AZ$814),0) -> 0 | I17: =IFERROR(SUMPRODUCT(--ISNUMBER(SEARCH($B$6,Base_Cobranzas!$A$2:$A$814)),--((--ISNUMBER(SEARCH("DEPART",UPPER(Base_Cobranzas!$E$2:$E$814)))+--ISNUMBER(SEARCH("DEPART",UPPER(Base_Cobranzas!$M$2:$M$814)))+--ISNUMBER(SEARCH("DEPART",UPPER(Base_Cobranzas!$U$2:$U$814)))+--ISNUMBER(SEARCH("DEPART",UPPER(Base_Cobranzas!$AC$2:$AC$814))))=0),--((--ISNUMBER(SEARCH("ESTACION",UPPER(Base_Cobranzas!$E$2:$E$814)))+--ISNUMBER(SEARCH("ESTACION",UPPER(Base_Cobranzas!$M$2:$M$814)))+--ISNUMBER(SEARCH("ESTACION",UPPER(Base_Cobranzas!$U$2:$U$814)))+--ISNUMBER(SEARCH("ESTACION",UPPER(Base_Cobranzas!$AC$2:$AC$814))))=0),--((--ISNUMBER(SEARCH("DEPOS",UPPER(Base_Cobranzas!$E$2:$E$814)))+--ISNUMBER(SEARCH("DEPOS",UPPER(Base_Cobranzas!$M$2:$M$814)))+--ISNUMBER(SEARCH("DEPOS",UPPER(Base_Cobranzas!$U$2:$U$814)))+--ISNUMBER(SEARCH("DEPOS",UPPER(Base_Cobranzas!$AC$2:$AC$814))))>0),--ISNUMBER(SEARCH("VENCIDO",UPPER(TRIM(Base_Cobranzas!$BK$2:$BK$814)))),Base_Cobranzas!$AZ$2:$AZ$814),0) -> 0 | J17: =IF(C17=0,0,I17/C17) -> 0 | K17: 0 | L17: 0
B19: Local Comercial | C19: 0 | D19: 0 | F19: =IF(C19=0,0,G19/C19) -> 0 | G19: =IFERROR(SUMPRODUCT(--ISNUMBER(SEARCH($B$6,Base_Cobranzas!$A$2:$A$814)),--(((--ISNUMBER(SEARCH("LOCAL",UPPER(Base_Cobranzas!$E$2:$E$814)))+--ISNUMBER(SEARCH("LOCAL",UPPER(Base_Cobranzas!$M$2:$M$814)))+--ISNUMBER(SEARCH("LOCAL",UPPER(Base_Cobranzas!$U$2:$U$814)))+--ISNUMBER(SEARCH("LOCAL",UPPER(Base_Cobranzas!$AC$2:$AC$814))))+(--ISNUMBER(SEARCH("COMERCIAL",UPPER(Base_Cobranzas!$E$2:$E$814)))+--ISNUMBER(SEARCH("COMERCIAL",UPPER(Base_Cobranzas!$M$2:$M$814)))+--ISNUMBER(SEARCH("COMERCIAL",UPPER(Base_Cobranzas!$U$2:$U$814)))+--ISNUMBER(SEARCH("COMERCIAL",UPPER(Base_Cobranzas!$AC$2:$AC$814)))))>0),--(Base_Cobranzas!$AY$2:$AY$814>0),Base_Cobranzas!$AY$2:$AY$814),0) -> 0 | H19: =IFERROR(SUMPRODUCT(--ISNUMBER(SEARCH($B$6,Base_Cobranzas!$A$2:$A$814)),--(((--ISNUMBER(SEARCH("LOCAL",UPPER(Base_Cobranzas!$E$2:$E$814)))+--ISNUMBER(SEARCH("LOCAL",UPPER(Base_Cobranzas!$M$2:$M$814)))+--ISNUMBER(SEARCH("LOCAL",UPPER(Base_Cobranzas!$U$2:$U$814)))+--ISNUMBER(SEARCH("LOCAL",UPPER(Base_Cobranzas!$AC$2:$AC$814))))+(--ISNUMBER(SEARCH("COMERCIAL",UPPER(Base_Cobranzas!$E$2:$E$814)))+--ISNUMBER(SEARCH("COMERCIAL",UPPER(Base_Cobranzas!$M$2:$M$814)))+--ISNUMBER(SEARCH("COMERCIAL",UPPER(Base_Cobranzas!$U$2:$U$814)))+--ISNUMBER(SEARCH("COMERCIAL",UPPER(Base_Cobranzas!$AC$2:$AC$814)))))>0),--ISNUMBER(SEARCH("PENDIENTE",UPPER(TRIM(Base_Cobranzas!$BK$2:$BK$814)))),Base_Cobranzas!$AZ$2:$AZ$814),0) -> 0 | I19: =IFERROR(SUMPRODUCT(--ISNUMBER(SEARCH($B$6,Base_Cobranzas!$A$2:$A$814)),--(((--ISNUMBER(SEARCH("LOCAL",UPPER(Base_Cobranzas!$E$2:$E$814)))+--ISNUMBER(SEARCH("LOCAL",UPPER(Base_Cobranzas!$M$2:$M$814)))+--ISNUMBER(SEARCH("LOCAL",UPPER(Base_Cobranzas!$U$2:$U$814)))+--ISNUMBER(SEARCH("LOCAL",UPPER(Base_Cobranzas!$AC$2:$AC$814))))+(--ISNUMBER(SEARCH("COMERCIAL",UPPER(Base_Cobranzas!$E$2:$E$814)))+--ISNUMBER(SEARCH("COMERCIAL",UPPER(Base_Cobranzas!$M$2:$M$814)))+--ISNUMBER(SEARCH("COMERCIAL",UPPER(Base_Cobranzas!$U$2:$U$814)))+--ISNUMBER(SEARCH("COMERCIAL",UPPER(Base_Cobranzas!$AC$2:$AC$814)))))>0),--ISNUMBER(SEARCH("VENCIDO",UPPER(TRIM(Base_Cobranzas!$BK$2:$BK$814)))),Base_Cobranzas!$AZ$2:$AZ$814),0) -> 0 | J19: =IF(C19=0,0,I19/C19) -> 0 | K19: 0 | L19: 0
A21: =+IF(ROUND(C21,0)=ROUND(G21+H21+I21,0),"OK","REVISAR") -> OK | B21: Total | C21: 25025700 | D21: 73 | F21: =IF(C21=0,0,G21/C21) -> 0.89884919 | G21: =G11+G15+G17+G19 -> 22494330 | H21: =H11+H15+H17+H19 -> 534689.8 | I21: =I11+I15+I17+I19 -> 1996680 | J21: =IF(C21=0,0,I21/C21) -> 0.079785181 | K21: 11 | L21: 58
B31: COBRANZA REAL
B33: Tipo de Credito | C33: 2024 | D33: 2025 | E33: 46023 | F33: 46054 | G33: 46082 | H33: 46113 | I33: 46143 | J33: 46174 | K33: 46204 | L33: 46235 | M33: Total
B34: Crédito Directo | C34: =IFERROR(SUMPRODUCT(--ISNUMBER(SEARCH($B$6,Base_Cobranzas!$A$2:$A$814)),--(Base_Cobranzas!$AR$2:$AR$814>=IF(C$33<3000,DATE(C$33,1,1),C$33)),--(Base_Cobranzas!$AR$2:$AR$814<IF(C$33<3000,DATE(C$33+1,1,1),EDATE(C$33,1))),--ISNUMBER(SEARCH(IF(ISNUMBER(SEARCH("DIRECTO",UPPER($B34))),"DIRECTO",IF(ISNUMBER(SEARCH("HIPOT",UPPER($B34))),"HIPOT",IF(ISNUMBER(SEARCH("AHORRO",UPPER($B34))),"AHORRO",UPPER($B34)))),UPPER(Base_Cobranzas!$BB$2:$BB$814))),--(Base_Cobranzas!$AY$2:$AY$814>0),Base_Cobranzas!$AY$2:$AY$814),0) -> 542725 | D34: =IFERROR(SUMPRODUCT(--ISNUMBER(SEARCH($B$6,Base_Cobranzas!$A$2:$A$814)),--(Base_Cobranzas!$AR$2:$AR$814>=IF(D$33<3000,DATE(D$33,1,1),D$33)),--(Base_Cobranzas!$AR$2:$AR$814<IF(D$33<3000,DATE(D$33+1,1,1),EDATE(D$33,1))),--ISNUMBER(SEARCH(IF(ISNUMBER(SEARCH("DIRECTO",UPPER($B34))),"DIRECTO",IF(ISNUMBER(SEARCH("HIPOT",UPPER($B34))),"HIPOT",IF(ISNUMBER(SEARCH("AHORRO",UPPER($B34))),"AHORRO",UPPER($B34)))),UPPER(Base_Cobranzas!$BB$2:$BB$814))),--(Base_Cobranzas!$AY$2:$AY$814>0),Base_Cobranzas!$AY$2:$AY$814),0) -> 2280048.6 | E34: =IFERROR(SUMPRODUCT(--ISNUMBER(SEARCH($B$6,Base_Cobranzas!$A$2:$A$814)),--(Base_Cobranzas!$AR$2:$AR$814>=IF(E$33<3000,DATE(E$33,1,1),E$33)),--(Base_Cobranzas!$AR$2:$AR$814<IF(E$33<3000,DATE(E$33+1,1,1),EDATE(E$33,1))),--ISNUMBER(SEARCH(IF(ISNUMBER(SEARCH("DIRECTO",UPPER($B34))),"DIRECTO",IF(ISNUMBER(SEARCH("HIPOT",UPPER($B34))),"HIPOT",IF(ISNUMBER(SEARCH("AHORRO",UPPER($B34))),"AHORRO",UPPER($B34)))),UPPER(Base_Cobranzas!$BB$2:$BB$814))),--(Base_Cobranzas!$AY$2:$AY$814>0),Base_Cobranzas!$AY$2:$AY$814),0) -> 202837.5 | F34: =IFERROR(SUMPRODUCT(--ISNUMBER(SEARCH($B$6,Base_Cobranzas!$A$2:$A$814)),--(Base_Cobranzas!$AR$2:$AR$814>=IF(F$33<3000,DATE(F$33,1,1),F$33)),--(Base_Cobranzas!$AR$2:$AR$814<IF(F$33<3000,DATE(F$33+1,1,1),EDATE(F$33,1))),--ISNUMBER(SEARCH(IF(ISNUMBER(SEARCH("DIRECTO",UPPER($B34))),"DIRECTO",IF(ISNUMBER(SEARCH("HIPOT",UPPER($B34))),"HIPOT",IF(ISNUMBER(SEARCH("AHORRO",UPPER($B34))),"AHORRO",UPPER($B34)))),UPPER(Base_Cobranzas!$BB$2:$BB$814))),--(Base_Cobranzas!$AY$2:$AY$814>0),Base_Cobranzas!$AY$2:$AY$814),0) -> 302117.48 | G34: =IFERROR(SUMPRODUCT(--ISNUMBER(SEARCH($B$6,Base_Cobranzas!$A$2:$A$814)),--(Base_Cobranzas!$AR$2:$AR$814>=IF(G$33<3000,DATE(G$33,1,1),G$33)),--(Base_Cobranzas!$AR$2:$AR$814<IF(G$33<3000,DATE(G$33+1,1,1),EDATE(G$33,1))),--ISNUMBER(SEARCH(IF(ISNUMBER(SEARCH("DIRECTO",UPPER($B34))),"DIRECTO",IF(ISNUMBER(SEARCH("HIPOT",UPPER($B34))),"HIPOT",IF(ISNUMBER(SEARCH("AHORRO",UPPER($B34))),"AHORRO",UPPER($B34)))),UPPER(Base_Cobranzas!$BB$2:$BB$814))),--(Base_Cobranzas!$AY$2:$AY$814>0),Base_Cobranzas!$AY$2:$AY$814),0) -> 311500 | H34: =IFERROR(SUMPRODUCT(--ISNUMBER(SEARCH($B$6,Base_Cobranzas!$A$2:$A$814)),--(Base_Cobranzas!$AR$2:$AR$814>=IF(H$33<3000,DATE(H$33,1,1),H$33)),--(Base_Cobranzas!$AR$2:$AR$814<IF(H$33<3000,DATE(H$33+1,1,1),EDATE(H$33,1))),--ISNUMBER(SEARCH(IF(ISNUMBER(SEARCH("DIRECTO",UPPER($B34))),"DIRECTO",IF(ISNUMBER(SEARCH("HIPOT",UPPER($B34))),"HIPOT",IF(ISNUMBER(SEARCH("AHORRO",UPPER($B34))),"AHORRO",UPPER($B34)))),UPPER(Base_Cobranzas!$BB$2:$BB$814))),--(Base_Cobranzas!$AY$2:$AY$814>0),Base_Cobranzas!$AY$2:$AY$814),0) -> 25000 | I34: =IFERROR(SUMPRODUCT(--ISNUMBER(SEARCH($B$6,Base_Cobranzas!$A$2:$A$814)),--(Base_Cobranzas!$AR$2:$AR$814>=IF(I$33<3000,DATE(I$33,1,1),I$33)),--(Base_Cobranzas!$AR$2:$AR$814<IF(I$33<3000,DATE(I$33+1,1,1),EDATE(I$33,1))),--ISNUMBER(SEARCH(IF(ISNUMBER(SEARCH("DIRECTO",UPPER($B34))),"DIRECTO",IF(ISNUMBER(SEARCH("HIPOT",UPPER($B34))),"HIPOT",IF(ISNUMBER(SEARCH("AHORRO",UPPER($B34))),"AHORRO",UPPER($B34)))),UPPER(Base_Cobranzas!$BB$2:$BB$814))),--(Base_Cobranzas!$AY$2:$AY$814>0),Base_Cobranzas!$AY$2:$AY$814),0) -> 204171.42 | J34: =IFERROR(SUMPRODUCT(--ISNUMBER(SEARCH($B$6,Base_Cobranzas!$A$2:$A$814)),--(Base_Cobranzas!$AR$2:$AR$814>=IF(J$33<3000,DATE(J$33,1,1),J$33)),--(Base_Cobranzas!$AR$2:$AR$814<IF(J$33<3000,DATE(J$33+1,1,1),EDATE(J$33,1))),--ISNUMBER(SEARCH(IF(ISNUMBER(SEARCH("DIRECTO",UPPER($B34))),"DIRECTO",IF(ISNUMBER(SEARCH("HIPOT",UPPER($B34))),"HIPOT",IF(ISNUMBER(SEARCH("AHORRO",UPPER($B34))),"AHORRO",UPPER($B34)))),UPPER(Base_Cobranzas!$BB$2:$BB$814))),--(Base_Cobranzas!$AY$2:$AY$814>0),Base_Cobranzas!$AY$2:$AY$814),0) -> 472110.2 | ... L34: =IFERROR(SUMPRODUCT(--ISNUMBER(SEARCH($B$6,Base_Cobranzas!$A$2:$A$814)),--(Base_Cobranzas!$AR$2:$AR$814>=IF(L$33<3000,DATE(L$33,1,1),L$33)),--(Base_Cobranzas!$AR$2:$AR$814<IF(L$33<3000,DATE(L$33+1,1,1),EDATE(L$33,1))),--ISNUMBER(SEARCH(IF(ISNUMBER(SEARCH("DIRECTO",UPPER($B34))),"DIRECTO",IF(ISNUMBER(SEARCH("HIPOT",UPPER($B34))),"HIPOT",IF(ISNUMBER(SEARCH("AHORRO",UPPER($B34))),"AHORRO",UPPER($B34)))),UPPER(Base_Cobranzas!$BB$2:$BB$814))),--(Base_Cobranzas!$AY$2:$AY$814>0),Base_Cobranzas!$AY$2:$AY$814),0) -> 100900 | M34: =SUM(C34:L34) -> 4458910.2
B35: Crédito Hipotecario | C35: =IFERROR(SUMPRODUCT(--ISNUMBER(SEARCH($B$6,Base_Cobranzas!$A$2:$A$814)),--(Base_Cobranzas!$AR$2:$AR$814>=IF(C$33<3000,DATE(C$33,1,1),C$33)),--(Base_Cobranzas!$AR$2:$AR$814<IF(C$33<3000,DATE(C$33+1,1,1),EDATE(C$33,1))),--ISNUMBER(SEARCH(IF(ISNUMBER(SEARCH("DIRECTO",UPPER($B35))),"DIRECTO",IF(ISNUMBER(SEARCH("HIPOT",UPPER($B35))),"HIPOT",IF(ISNUMBER(SEARCH("AHORRO",UPPER($B35))),"AHORRO",UPPER($B35)))),UPPER(Base_Cobranzas!$BB$2:$BB$814))),--(Base_Cobranzas!$AY$2:$AY$814>0),Base_Cobranzas!$AY$2:$AY$814),0) -> 468490 | D35: =IFERROR(SUMPRODUCT(--ISNUMBER(SEARCH($B$6,Base_Cobranzas!$A$2:$A$814)),--(Base_Cobranzas!$AR$2:$AR$814>=IF(D$33<3000,DATE(D$33,1,1),D$33)),--(Base_Cobranzas!$AR$2:$AR$814<IF(D$33<3000,DATE(D$33+1,1,1),EDATE(D$33,1))),--ISNUMBER(SEARCH(IF(ISNUMBER(SEARCH("DIRECTO",UPPER($B35))),"DIRECTO",IF(ISNUMBER(SEARCH("HIPOT",UPPER($B35))),"HIPOT",IF(ISNUMBER(SEARCH("AHORRO",UPPER($B35))),"AHORRO",UPPER($B35)))),UPPER(Base_Cobranzas!$BB$2:$BB$814))),--(Base_Cobranzas!$AY$2:$AY$814>0),Base_Cobranzas!$AY$2:$AY$814),0) -> 9286060 | E35: =IFERROR(SUMPRODUCT(--ISNUMBER(SEARCH($B$6,Base_Cobranzas!$A$2:$A$814)),--(Base_Cobranzas!$AR$2:$AR$814>=IF(E$33<3000,DATE(E$33,1,1),E$33)),--(Base_Cobranzas!$AR$2:$AR$814<IF(E$33<3000,DATE(E$33+1,1,1),EDATE(E$33,1))),--ISNUMBER(SEARCH(IF(ISNUMBER(SEARCH("DIRECTO",UPPER($B35))),"DIRECTO",IF(ISNUMBER(SEARCH("HIPOT",UPPER($B35))),"HIPOT",IF(ISNUMBER(SEARCH("AHORRO",UPPER($B35))),"AHORRO",UPPER($B35)))),UPPER(Base_Cobranzas!$BB$2:$BB$814))),--(Base_Cobranzas!$AY$2:$AY$814>0),Base_Cobranzas!$AY$2:$AY$814),0) -> 1005350 | F35: =IFERROR(SUMPRODUCT(--ISNUMBER(SEARCH($B$6,Base_Cobranzas!$A$2:$A$814)),--(Base_Cobranzas!$AR$2:$AR$814>=IF(F$33<3000,DATE(F$33,1,1),F$33)),--(Base_Cobranzas!$AR$2:$AR$814<IF(F$33<3000,DATE(F$33+1,1,1),EDATE(F$33,1))),--ISNUMBER(SEARCH(IF(ISNUMBER(SEARCH("DIRECTO",UPPER($B35))),"DIRECTO",IF(ISNUMBER(SEARCH("HIPOT",UPPER($B35))),"HIPOT",IF(ISNUMBER(SEARCH("AHORRO",UPPER($B35))),"AHORRO",UPPER($B35)))),UPPER(Base_Cobranzas!$BB$2:$BB$814))),--(Base_Cobranzas!$AY$2:$AY$814>0),Base_Cobranzas!$AY$2:$AY$814),0) -> 117514 | G35: =IFERROR(SUMPRODUCT(--ISNUMBER(SEARCH($B$6,Base_Cobranzas!$A$2:$A$814)),--(Base_Cobranzas!$AR$2:$AR$814>=IF(G$33<3000,DATE(G$33,1,1),G$33)),--(Base_Cobranzas!$AR$2:$AR$814<IF(G$33<3000,DATE(G$33+1,1,1),EDATE(G$33,1))),--ISNUMBER(SEARCH(IF(ISNUMBER(SEARCH("DIRECTO",UPPER($B35))),"DIRECTO",IF(ISNUMBER(SEARCH("HIPOT",UPPER($B35))),"HIPOT",IF(ISNUMBER(SEARCH("AHORRO",UPPER($B35))),"AHORRO",UPPER($B35)))),UPPER(Base_Cobranzas!$BB$2:$BB$814))),--(Base_Cobranzas!$AY$2:$AY$814>0),Base_Cobranzas!$AY$2:$AY$814),0) -> 909875.7 | H35: =IFERROR(SUMPRODUCT(--ISNUMBER(SEARCH($B$6,Base_Cobranzas!$A$2:$A$814)),--(Base_Cobranzas!$AR$2:$AR$814>=IF(H$33<3000,DATE(H$33,1,1),H$33)),--(Base_Cobranzas!$AR$2:$AR$814<IF(H$33<3000,DATE(H$33+1,1,1),EDATE(H$33,1))),--ISNUMBER(SEARCH(IF(ISNUMBER(SEARCH("DIRECTO",UPPER($B35))),"DIRECTO",IF(ISNUMBER(SEARCH("HIPOT",UPPER($B35))),"HIPOT",IF(ISNUMBER(SEARCH("AHORRO",UPPER($B35))),"AHORRO",UPPER($B35)))),UPPER(Base_Cobranzas!$BB$2:$BB$814))),--(Base_Cobranzas!$AY$2:$AY$814>0),Base_Cobranzas!$AY$2:$AY$814),0) -> 170810.3 | I35: =IFERROR(SUMPRODUCT(--ISNUMBER(SEARCH($B$6,Base_Cobranzas!$A$2:$A$814)),--(Base_Cobranzas!$AR$2:$AR$814>=IF(I$33<3000,DATE(I$33,1,1),I$33)),--(Base_Cobranzas!$AR$2:$AR$814<IF(I$33<3000,DATE(I$33+1,1,1),EDATE(I$33,1))),--ISNUMBER(SEARCH(IF(ISNUMBER(SEARCH("DIRECTO",UPPER($B35))),"DIRECTO",IF(ISNUMBER(SEARCH("HIPOT",UPPER($B35))),"HIPOT",IF(ISNUMBER(SEARCH("AHORRO",UPPER($B35))),"AHORRO",UPPER($B35)))),UPPER(Base_Cobranzas!$BB$2:$BB$814))),--(Base_Cobranzas!$AY$2:$AY$814>0),Base_Cobranzas!$AY$2:$AY$814),0) -> 850400 | J35: =IFERROR(SUMPRODUCT(--ISNUMBER(SEARCH($B$6,Base_Cobranzas!$A$2:$A$814)),--(Base_Cobranzas!$AR$2:$AR$814>=IF(J$33<3000,DATE(J$33,1,1),J$33)),--(Base_Cobranzas!$AR$2:$AR$814<IF(J$33<3000,DATE(J$33+1,1,1),EDATE(J$33,1))),--ISNUMBER(SEARCH(IF(ISNUMBER(SEARCH("DIRECTO",UPPER($B35))),"DIRECTO",IF(ISNUMBER(SEARCH("HIPOT",UPPER($B35))),"HIPOT",IF(ISNUMBER(SEARCH("AHORRO",UPPER($B35))),"AHORRO",UPPER($B35)))),UPPER(Base_Cobranzas!$BB$2:$BB$814))),--(Base_Cobranzas!$AY$2:$AY$814>0),Base_Cobranzas!$AY$2:$AY$814),0) -> 273650 | ... L35: =IFERROR(SUMPRODUCT(--ISNUMBER(SEARCH($B$6,Base_Cobranzas!$A$2:$A$814)),--(Base_Cobranzas!$AR$2:$AR$814>=IF(L$33<3000,DATE(L$33,1,1),L$33)),--(Base_Cobranzas!$AR$2:$AR$814<IF(L$33<3000,DATE(L$33+1,1,1),EDATE(L$33,1))),--ISNUMBER(SEARCH(IF(ISNUMBER(SEARCH("DIRECTO",UPPER($B35))),"DIRECTO",IF(ISNUMBER(SEARCH("HIPOT",UPPER($B35))),"HIPOT",IF(ISNUMBER(SEARCH("AHORRO",UPPER($B35))),"AHORRO",UPPER($B35)))),UPPER(Base_Cobranzas!$BB$2:$BB$814))),--(Base_Cobranzas!$AY$2:$AY$814>0),Base_Cobranzas!$AY$2:$AY$814),0) -> 200000 | M35: =SUM(C35:L35) -> 13679150
B36: Ahorro | C36: =IFERROR(SUMPRODUCT(--ISNUMBER(SEARCH($B$6,Base_Cobranzas!$A$2:$A$814)),--(Base_Cobranzas!$AR$2:$AR$814>=IF(C$33<3000,DATE(C$33,1,1),C$33)),--(Base_Cobranzas!$AR$2:$AR$814<IF(C$33<3000,DATE(C$33+1,1,1),EDATE(C$33,1))),--ISNUMBER(SEARCH(IF(ISNUMBER(SEARCH("DIRECTO",UPPER($B36))),"DIRECTO",IF(ISNUMBER(SEARCH("HIPOT",UPPER($B36))),"HIPOT",IF(ISNUMBER(SEARCH("AHORRO",UPPER($B36))),"AHORRO",UPPER($B36)))),UPPER(Base_Cobranzas!$BB$2:$BB$814))),--(Base_Cobranzas!$AY$2:$AY$814>0),Base_Cobranzas!$AY$2:$AY$814),0) -> 86500 | D36: =IFERROR(SUMPRODUCT(--ISNUMBER(SEARCH($B$6,Base_Cobranzas!$A$2:$A$814)),--(Base_Cobranzas!$AR$2:$AR$814>=IF(D$33<3000,DATE(D$33,1,1),D$33)),--(Base_Cobranzas!$AR$2:$AR$814<IF(D$33<3000,DATE(D$33+1,1,1),EDATE(D$33,1))),--ISNUMBER(SEARCH(IF(ISNUMBER(SEARCH("DIRECTO",UPPER($B36))),"DIRECTO",IF(ISNUMBER(SEARCH("HIPOT",UPPER($B36))),"HIPOT",IF(ISNUMBER(SEARCH("AHORRO",UPPER($B36))),"AHORRO",UPPER($B36)))),UPPER(Base_Cobranzas!$BB$2:$BB$814))),--(Base_Cobranzas!$AY$2:$AY$814>0),Base_Cobranzas!$AY$2:$AY$814),0) -> 2520500 | E36: =IFERROR(SUMPRODUCT(--ISNUMBER(SEARCH($B$6,Base_Cobranzas!$A$2:$A$814)),--(Base_Cobranzas!$AR$2:$AR$814>=IF(E$33<3000,DATE(E$33,1,1),E$33)),--(Base_Cobranzas!$AR$2:$AR$814<IF(E$33<3000,DATE(E$33+1,1,1),EDATE(E$33,1))),--ISNUMBER(SEARCH(IF(ISNUMBER(SEARCH("DIRECTO",UPPER($B36))),"DIRECTO",IF(ISNUMBER(SEARCH("HIPOT",UPPER($B36))),"HIPOT",IF(ISNUMBER(SEARCH("AHORRO",UPPER($B36))),"AHORRO",UPPER($B36)))),UPPER(Base_Cobranzas!$BB$2:$BB$814))),--(Base_Cobranzas!$AY$2:$AY$814>0),Base_Cobranzas!$AY$2:$AY$814),0) -> 536650 | F36: =IFERROR(SUMPRODUCT(--ISNUMBER(SEARCH($B$6,Base_Cobranzas!$A$2:$A$814)),--(Base_Cobranzas!$AR$2:$AR$814>=IF(F$33<3000,DATE(F$33,1,1),F$33)),--(Base_Cobranzas!$AR$2:$AR$814<IF(F$33<3000,DATE(F$33+1,1,1),EDATE(F$33,1))),--ISNUMBER(SEARCH(IF(ISNUMBER(SEARCH("DIRECTO",UPPER($B36))),"DIRECTO",IF(ISNUMBER(SEARCH("HIPOT",UPPER($B36))),"HIPOT",IF(ISNUMBER(SEARCH("AHORRO",UPPER($B36))),"AHORRO",UPPER($B36)))),UPPER(Base_Cobranzas!$BB$2:$BB$814))),--(Base_Cobranzas!$AY$2:$AY$814>0),Base_Cobranzas!$AY$2:$AY$814),0) -> 350 | G36: =IFERROR(SUMPRODUCT(--ISNUMBER(SEARCH($B$6,Base_Cobranzas!$A$2:$A$814)),--(Base_Cobranzas!$AR$2:$AR$814>=IF(G$33<3000,DATE(G$33,1,1),G$33)),--(Base_Cobranzas!$AR$2:$AR$814<IF(G$33<3000,DATE(G$33+1,1,1),EDATE(G$33,1))),--ISNUMBER(SEARCH(IF(ISNUMBER(SEARCH("DIRECTO",UPPER($B36))),"DIRECTO",IF(ISNUMBER(SEARCH("HIPOT",UPPER($B36))),"HIPOT",IF(ISNUMBER(SEARCH("AHORRO",UPPER($B36))),"AHORRO",UPPER($B36)))),UPPER(Base_Cobranzas!$BB$2:$BB$814))),--(Base_Cobranzas!$AY$2:$AY$814>0),Base_Cobranzas!$AY$2:$AY$814),0) -> 3000 | H36: =IFERROR(SUMPRODUCT(--ISNUMBER(SEARCH($B$6,Base_Cobranzas!$A$2:$A$814)),--(Base_Cobranzas!$AR$2:$AR$814>=IF(H$33<3000,DATE(H$33,1,1),H$33)),--(Base_Cobranzas!$AR$2:$AR$814<IF(H$33<3000,DATE(H$33+1,1,1),EDATE(H$33,1))),--ISNUMBER(SEARCH(IF(ISNUMBER(SEARCH("DIRECTO",UPPER($B36))),"DIRECTO",IF(ISNUMBER(SEARCH("HIPOT",UPPER($B36))),"HIPOT",IF(ISNUMBER(SEARCH("AHORRO",UPPER($B36))),"AHORRO",UPPER($B36)))),UPPER(Base_Cobranzas!$BB$2:$BB$814))),--(Base_Cobranzas!$AY$2:$AY$814>0),Base_Cobranzas!$AY$2:$AY$814),0) -> 150270 | I36: =IFERROR(SUMPRODUCT(--ISNUMBER(SEARCH($B$6,Base_Cobranzas!$A$2:$A$814)),--(Base_Cobranzas!$AR$2:$AR$814>=IF(I$33<3000,DATE(I$33,1,1),I$33)),--(Base_Cobranzas!$AR$2:$AR$814<IF(I$33<3000,DATE(I$33+1,1,1),EDATE(I$33,1))),--ISNUMBER(SEARCH(IF(ISNUMBER(SEARCH("DIRECTO",UPPER($B36))),"DIRECTO",IF(ISNUMBER(SEARCH("HIPOT",UPPER($B36))),"HIPOT",IF(ISNUMBER(SEARCH("AHORRO",UPPER($B36))),"AHORRO",UPPER($B36)))),UPPER(Base_Cobranzas!$BB$2:$BB$814))),--(Base_Cobranzas!$AY$2:$AY$814>0),Base_Cobranzas!$AY$2:$AY$814),0) -> 430300 | J36: =IFERROR(SUMPRODUCT(--ISNUMBER(SEARCH($B$6,Base_Cobranzas!$A$2:$A$814)),--(Base_Cobranzas!$AR$2:$AR$814>=IF(J$33<3000,DATE(J$33,1,1),J$33)),--(Base_Cobranzas!$AR$2:$AR$814<IF(J$33<3000,DATE(J$33+1,1,1),EDATE(J$33,1))),--ISNUMBER(SEARCH(IF(ISNUMBER(SEARCH("DIRECTO",UPPER($B36))),"DIRECTO",IF(ISNUMBER(SEARCH("HIPOT",UPPER($B36))),"HIPOT",IF(ISNUMBER(SEARCH("AHORRO",UPPER($B36))),"AHORRO",UPPER($B36)))),UPPER(Base_Cobranzas!$BB$2:$BB$814))),--(Base_Cobranzas!$AY$2:$AY$814>0),Base_Cobranzas!$AY$2:$AY$814),0) -> 278700 | ... L36: =IFERROR(SUMPRODUCT(--ISNUMBER(SEARCH($B$6,Base_Cobranzas!$A$2:$A$814)),--(Base_Cobranzas!$AR$2:$AR$814>=IF(L$33<3000,DATE(L$33,1,1),L$33)),--(Base_Cobranzas!$AR$2:$AR$814<IF(L$33<3000,DATE(L$33+1,1,1),EDATE(L$33,1))),--ISNUMBER(SEARCH(IF(ISNUMBER(SEARCH("DIRECTO",UPPER($B36))),"DIRECTO",IF(ISNUMBER(SEARCH("HIPOT",UPPER($B36))),"HIPOT",IF(ISNUMBER(SEARCH("AHORRO",UPPER($B36))),"AHORRO",UPPER($B36)))),UPPER(Base_Cobranzas!$BB$2:$BB$814))),--(Base_Cobranzas!$AY$2:$AY$814>0),Base_Cobranzas!$AY$2:$AY$814),0) -> 350000 | M36: =SUM(C36:L36) -> 4356270
B37: Total | C37: =SUM(C34:C36) -> 1097715 | D37: =SUM(D34:D36) -> 14086609 | E37: =SUM(E34:E36) -> 1744837.5 | F37: =SUM(F34:F36) -> 419981.48 | G37: =SUM(G34:G36) -> 1224375.7 | H37: =SUM(H34:H36) -> 346080.3 | I37: =SUM(I34:I36) -> 1484871.4 | J37: =SUM(J34:J36) -> 1024460.2 | ... L37: =SUM(L34:L36) -> 650900 | M37: =SUM(C37:L37) -> 22494330 | N37: =IF($G$21=M37,"OK","REVISAR") -> OK
B39: Acumulado | C39: =C37 -> 1097715 | D39: =C39+D37 -> 15184324 | E39: =D39+E37 -> 16929161 | F39: =E39+F37 -> 17349143 | G39: =F39+G37 -> 18573518 | H39: =G39+H37 -> 18919599 | I39: =H39+I37 -> 20404470 | J39: =I39+J37 -> 21428930 | K39: =J39+K37 -> 21843430 | L39: =K39+L37 -> 22494330
B43: COBRANZA PROYECTADA
B45: Tipo de Credito | C45: 46266 | D45: 46296 | E45: 46327 | F45: 46357 | G45: Total
B46: Crédito Directo | C46: =IFERROR(SUMPRODUCT(--ISNUMBER(SEARCH($B$6,Base_Cobranzas!$A$2:$A$814)),--(Base_Cobranzas!$AQ$2:$AQ$814>=IF(C$45<3000,DATE(C$45,1,1),C$45)),--(Base_Cobranzas!$AQ$2:$AQ$814<IF(C$45<3000,DATE(C$45+1,1,1),EDATE(C$45,1))),--ISNUMBER(SEARCH(IF(ISNUMBER(SEARCH("DIRECTO",UPPER($B46))),"DIRECTO",IF(ISNUMBER(SEARCH("HIPOT",UPPER($B46))),"HIPOT",IF(ISNUMBER(SEARCH("AHORRO",UPPER($B46))),"AHORRO",UPPER($B46)))),UPPER(Base_Cobranzas!$BB$2:$BB$814))),--ISNUMBER(SEARCH("PENDIENTE",UPPER(TRIM(Base_Cobranzas!$BK$2:$BK$814)))),Base_Cobranzas!$AZ$2:$AZ$814),0) -> 43889.8 | D46: =IFERROR(SUMPRODUCT(--ISNUMBER(SEARCH($B$6,Base_Cobranzas!$A$2:$A$814)),--(Base_Cobranzas!$AQ$2:$AQ$814>=IF(D$45<3000,DATE(D$45,1,1),D$45)),--(Base_Cobranzas!$AQ$2:$AQ$814<IF(D$45<3000,DATE(D$45+1,1,1),EDATE(D$45,1))),--ISNUMBER(SEARCH(IF(ISNUMBER(SEARCH("DIRECTO",UPPER($B46))),"DIRECTO",IF(ISNUMBER(SEARCH("HIPOT",UPPER($B46))),"HIPOT",IF(ISNUMBER(SEARCH("AHORRO",UPPER($B46))),"AHORRO",UPPER($B46)))),UPPER(Base_Cobranzas!$BB$2:$BB$814))),--ISNUMBER(SEARCH("PENDIENTE",UPPER(TRIM(Base_Cobranzas!$BK$2:$BK$814)))),Base_Cobranzas!$AZ$2:$AZ$814),0) -> 20000 | E46: =IFERROR(SUMPRODUCT(--ISNUMBER(SEARCH($B$6,Base_Cobranzas!$A$2:$A$814)),--(Base_Cobranzas!$AQ$2:$AQ$814>=IF(E$45<3000,DATE(E$45,1,1),E$45)),--(Base_Cobranzas!$AQ$2:$AQ$814<IF(E$45<3000,DATE(E$45+1,1,1),EDATE(E$45,1))),--ISNUMBER(SEARCH(IF(ISNUMBER(SEARCH("DIRECTO",UPPER($B46))),"DIRECTO",IF(ISNUMBER(SEARCH("HIPOT",UPPER($B46))),"HIPOT",IF(ISNUMBER(SEARCH("AHORRO",UPPER($B46))),"AHORRO",UPPER($B46)))),UPPER(Base_Cobranzas!$BB$2:$BB$814))),--ISNUMBER(SEARCH("PENDIENTE",UPPER(TRIM(Base_Cobranzas!$BK$2:$BK$814)))),Base_Cobranzas!$AZ$2:$AZ$814),0) -> 0 | F46: =IFERROR(SUMPRODUCT(--ISNUMBER(SEARCH($B$6,Base_Cobranzas!$A$2:$A$814)),--(Base_Cobranzas!$AQ$2:$AQ$814>=IF(F$45<3000,DATE(F$45,1,1),F$45)),--(Base_Cobranzas!$AQ$2:$AQ$814<IF(F$45<3000,DATE(F$45+1,1,1),EDATE(F$45,1))),--ISNUMBER(SEARCH(IF(ISNUMBER(SEARCH("DIRECTO",UPPER($B46))),"DIRECTO",IF(ISNUMBER(SEARCH("HIPOT",UPPER($B46))),"HIPOT",IF(ISNUMBER(SEARCH("AHORRO",UPPER($B46))),"AHORRO",UPPER($B46)))),UPPER(Base_Cobranzas!$BB$2:$BB$814))),--ISNUMBER(SEARCH("PENDIENTE",UPPER(TRIM(Base_Cobranzas!$BK$2:$BK$814)))),Base_Cobranzas!$AZ$2:$AZ$814),0) -> 10000 | G46: =SUM(C46:F46) -> 73889.8
B47: Crédito Hipotecario | C47: =IFERROR(SUMPRODUCT(--ISNUMBER(SEARCH($B$6,Base_Cobranzas!$A$2:$A$814)),--(Base_Cobranzas!$AQ$2:$AQ$814>=IF(C$45<3000,DATE(C$45,1,1),C$45)),--(Base_Cobranzas!$AQ$2:$AQ$814<IF(C$45<3000,DATE(C$45+1,1,1),EDATE(C$45,1))),--ISNUMBER(SEARCH(IF(ISNUMBER(SEARCH("DIRECTO",UPPER($B47))),"DIRECTO",IF(ISNUMBER(SEARCH("HIPOT",UPPER($B47))),"HIPOT",IF(ISNUMBER(SEARCH("AHORRO",UPPER($B47))),"AHORRO",UPPER($B47)))),UPPER(Base_Cobranzas!$BB$2:$BB$814))),--ISNUMBER(SEARCH("PENDIENTE",UPPER(TRIM(Base_Cobranzas!$BK$2:$BK$814)))),Base_Cobranzas!$AZ$2:$AZ$814),0) -> 0 | D47: =IFERROR(SUMPRODUCT(--ISNUMBER(SEARCH($B$6,Base_Cobranzas!$A$2:$A$814)),--(Base_Cobranzas!$AQ$2:$AQ$814>=IF(D$45<3000,DATE(D$45,1,1),D$45)),--(Base_Cobranzas!$AQ$2:$AQ$814<IF(D$45<3000,DATE(D$45+1,1,1),EDATE(D$45,1))),--ISNUMBER(SEARCH(IF(ISNUMBER(SEARCH("DIRECTO",UPPER($B47))),"DIRECTO",IF(ISNUMBER(SEARCH("HIPOT",UPPER($B47))),"HIPOT",IF(ISNUMBER(SEARCH("AHORRO",UPPER($B47))),"AHORRO",UPPER($B47)))),UPPER(Base_Cobranzas!$BB$2:$BB$814))),--ISNUMBER(SEARCH("PENDIENTE",UPPER(TRIM(Base_Cobranzas!$BK$2:$BK$814)))),Base_Cobranzas!$AZ$2:$AZ$814),0) -> 0 | E47: =IFERROR(SUMPRODUCT(--ISNUMBER(SEARCH($B$6,Base_Cobranzas!$A$2:$A$814)),--(Base_Cobranzas!$AQ$2:$AQ$814>=IF(E$45<3000,DATE(E$45,1,1),E$45)),--(Base_Cobranzas!$AQ$2:$AQ$814<IF(E$45<3000,DATE(E$45+1,1,1),EDATE(E$45,1))),--ISNUMBER(SEARCH(IF(ISNUMBER(SEARCH("DIRECTO",UPPER($B47))),"DIRECTO",IF(ISNUMBER(SEARCH("HIPOT",UPPER($B47))),"HIPOT",IF(ISNUMBER(SEARCH("AHORRO",UPPER($B47))),"AHORRO",UPPER($B47)))),UPPER(Base_Cobranzas!$BB$2:$BB$814))),--ISNUMBER(SEARCH("PENDIENTE",UPPER(TRIM(Base_Cobranzas!$BK$2:$BK$814)))),Base_Cobranzas!$AZ$2:$AZ$814),0) -> 0 | F47: =IFERROR(SUMPRODUCT(--ISNUMBER(SEARCH($B$6,Base_Cobranzas!$A$2:$A$814)),--(Base_Cobranzas!$AQ$2:$AQ$814>=IF(F$45<3000,DATE(F$45,1,1),F$45)),--(Base_Cobranzas!$AQ$2:$AQ$814<IF(F$45<3000,DATE(F$45+1,1,1),EDATE(F$45,1))),--ISNUMBER(SEARCH(IF(ISNUMBER(SEARCH("DIRECTO",UPPER($B47))),"DIRECTO",IF(ISNUMBER(SEARCH("HIPOT",UPPER($B47))),"HIPOT",IF(ISNUMBER(SEARCH("AHORRO",UPPER($B47))),"AHORRO",UPPER($B47)))),UPPER(Base_Cobranzas!$BB$2:$BB$814))),--ISNUMBER(SEARCH("PENDIENTE",UPPER(TRIM(Base_Cobranzas!$BK$2:$BK$814)))),Base_Cobranzas!$AZ$2:$AZ$814),0) -> 0 | G47: =SUM(C47:F47) -> 0
B48: Ahorro | C48: =IFERROR(SUMPRODUCT(--ISNUMBER(SEARCH($B$6,Base_Cobranzas!$A$2:$A$814)),--(Base_Cobranzas!$AQ$2:$AQ$814>=IF(C$45<3000,DATE(C$45,1,1),C$45)),--(Base_Cobranzas!$AQ$2:$AQ$814<IF(C$45<3000,DATE(C$45+1,1,1),EDATE(C$45,1))),--ISNUMBER(SEARCH(IF(ISNUMBER(SEARCH("DIRECTO",UPPER($B48))),"DIRECTO",IF(ISNUMBER(SEARCH("HIPOT",UPPER($B48))),"HIPOT",IF(ISNUMBER(SEARCH("AHORRO",UPPER($B48))),"AHORRO",UPPER($B48)))),UPPER(Base_Cobranzas!$BB$2:$BB$814))),--ISNUMBER(SEARCH("PENDIENTE",UPPER(TRIM(Base_Cobranzas!$BK$2:$BK$814)))),Base_Cobranzas!$AZ$2:$AZ$814),0) -> 460800 | D48: =IFERROR(SUMPRODUCT(--ISNUMBER(SEARCH($B$6,Base_Cobranzas!$A$2:$A$814)),--(Base_Cobranzas!$AQ$2:$AQ$814>=IF(D$45<3000,DATE(D$45,1,1),D$45)),--(Base_Cobranzas!$AQ$2:$AQ$814<IF(D$45<3000,DATE(D$45+1,1,1),EDATE(D$45,1))),--ISNUMBER(SEARCH(IF(ISNUMBER(SEARCH("DIRECTO",UPPER($B48))),"DIRECTO",IF(ISNUMBER(SEARCH("HIPOT",UPPER($B48))),"HIPOT",IF(ISNUMBER(SEARCH("AHORRO",UPPER($B48))),"AHORRO",UPPER($B48)))),UPPER(Base_Cobranzas!$BB$2:$BB$814))),--ISNUMBER(SEARCH("PENDIENTE",UPPER(TRIM(Base_Cobranzas!$BK$2:$BK$814)))),Base_Cobranzas!$AZ$2:$AZ$814),0) -> 0 | E48: =IFERROR(SUMPRODUCT(--ISNUMBER(SEARCH($B$6,Base_Cobranzas!$A$2:$A$814)),--(Base_Cobranzas!$AQ$2:$AQ$814>=IF(E$45<3000,DATE(E$45,1,1),E$45)),--(Base_Cobranzas!$AQ$2:$AQ$814<IF(E$45<3000,DATE(E$45+1,1,1),EDATE(E$45,1))),--ISNUMBER(SEARCH(IF(ISNUMBER(SEARCH("DIRECTO",UPPER($B48))),"DIRECTO",IF(ISNUMBER(SEARCH("HIPOT",UPPER($B48))),"HIPOT",IF(ISNUMBER(SEARCH("AHORRO",UPPER($B48))),"AHORRO",UPPER($B48)))),UPPER(Base_Cobranzas!$BB$2:$BB$814))),--ISNUMBER(SEARCH("PENDIENTE",UPPER(TRIM(Base_Cobranzas!$BK$2:$BK$814)))),Base_Cobranzas!$AZ$2:$AZ$814),0) -> 0 | F48: =IFERROR(SUMPRODUCT(--ISNUMBER(SEARCH($B$6,Base_Cobranzas!$A$2:$A$814)),--(Base_Cobranzas!$AQ$2:$AQ$814>=IF(F$45<3000,DATE(F$45,1,1),F$45)),--(Base_Cobranzas!$AQ$2:$AQ$814<IF(F$45<3000,DATE(F$45+1,1,1),EDATE(F$45,1))),--ISNUMBER(SEARCH(IF(ISNUMBER(SEARCH("DIRECTO",UPPER($B48))),"DIRECTO",IF(ISNUMBER(SEARCH("HIPOT",UPPER($B48))),"HIPOT",IF(ISNUMBER(SEARCH("AHORRO",UPPER($B48))),"AHORRO",UPPER($B48)))),UPPER(Base_Cobranzas!$BB$2:$BB$814))),--ISNUMBER(SEARCH("PENDIENTE",UPPER(TRIM(Base_Cobranzas!$BK$2:$BK$814)))),Base_Cobranzas!$AZ$2:$AZ$814),0) -> 0 | G48: =SUM(C48:F48) -> 460800
B49: Total | C49: =SUM(C46:C48) -> 504689.8 | D49: =SUM(D46:D48) -> 20000 | E49: =SUM(E46:E48) -> 0 | F49: =SUM(F46:F48) -> 10000 | G49: =SUM(C49:F49) -> 534689.8 | H49: =IF($H$21=G49,"OK","REVISAR") -> OK
B51: Acumulado | C51: =C49 -> 504689.8 | D51: =C51+D49 -> 524689.8 | E51: =D51+E49 -> 524689.8 | F51: =E51+F49 -> 534689.8
B55: COBRANZA MOROSA
B57: Tipo de Credito | C57: 45901 | D57: 45931 | E57: 45962 | F57: 45992 | G57: 46023 | H57: 46054 | I57: 46082 | J57: 46113 | K57: 46143 | L57: 46174 | M57: 46204 | N57: 46235 | O57: Total
B58: Crédito Directo | C58: =IFERROR(SUMPRODUCT(--ISNUMBER(SEARCH($B$6,Base_Cobranzas!$A$2:$A$814)),--(Base_Cobranzas!$AQ$2:$AQ$814>=IF(C$57<3000,DATE(C$57,1,1),C$57)),--(Base_Cobranzas!$AQ$2:$AQ$814<IF(C$57<3000,DATE(C$57+1,1,1),EDATE(C$57,1))),--ISNUMBER(SEARCH(IF(ISNUMBER(SEARCH("DIRECTO",UPPER($B58))),"DIRECTO",IF(ISNUMBER(SEARCH("HIPOT",UPPER($B58))),"HIPOT",IF(ISNUMBER(SEARCH("AHORRO",UPPER($B58))),"AHORRO",UPPER($B58)))),UPPER(Base_Cobranzas!$BB$2:$BB$814))),--ISNUMBER(SEARCH("VENCIDO",UPPER(TRIM(Base_Cobranzas!$BK$2:$BK$814)))),Base_Cobranzas!$AZ$2:$AZ$814),0) -> 0 | D58: =IFERROR(SUMPRODUCT(--ISNUMBER(SEARCH($B$6,Base_Cobranzas!$A$2:$A$814)),--(Base_Cobranzas!$AQ$2:$AQ$814>=IF(D$57<3000,DATE(D$57,1,1),D$57)),--(Base_Cobranzas!$AQ$2:$AQ$814<IF(D$57<3000,DATE(D$57+1,1,1),EDATE(D$57,1))),--ISNUMBER(SEARCH(IF(ISNUMBER(SEARCH("DIRECTO",UPPER($B58))),"DIRECTO",IF(ISNUMBER(SEARCH("HIPOT",UPPER($B58))),"HIPOT",IF(ISNUMBER(SEARCH("AHORRO",UPPER($B58))),"AHORRO",UPPER($B58)))),UPPER(Base_Cobranzas!$BB$2:$BB$814))),--ISNUMBER(SEARCH("VENCIDO",UPPER(TRIM(Base_Cobranzas!$BK$2:$BK$814)))),Base_Cobranzas!$AZ$2:$AZ$814),0) -> 0 | E58: =IFERROR(SUMPRODUCT(--ISNUMBER(SEARCH($B$6,Base_Cobranzas!$A$2:$A$814)),--(Base_Cobranzas!$AQ$2:$AQ$814>=IF(E$57<3000,DATE(E$57,1,1),E$57)),--(Base_Cobranzas!$AQ$2:$AQ$814<IF(E$57<3000,DATE(E$57+1,1,1),EDATE(E$57,1))),--ISNUMBER(SEARCH(IF(ISNUMBER(SEARCH("DIRECTO",UPPER($B58))),"DIRECTO",IF(ISNUMBER(SEARCH("HIPOT",UPPER($B58))),"HIPOT",IF(ISNUMBER(SEARCH("AHORRO",UPPER($B58))),"AHORRO",UPPER($B58)))),UPPER(Base_Cobranzas!$BB$2:$BB$814))),--ISNUMBER(SEARCH("VENCIDO",UPPER(TRIM(Base_Cobranzas!$BK$2:$BK$814)))),Base_Cobranzas!$AZ$2:$AZ$814),0) -> 0 | F58: =IFERROR(SUMPRODUCT(--ISNUMBER(SEARCH($B$6,Base_Cobranzas!$A$2:$A$814)),--(Base_Cobranzas!$AQ$2:$AQ$814>=IF(F$57<3000,DATE(F$57,1,1),F$57)),--(Base_Cobranzas!$AQ$2:$AQ$814<IF(F$57<3000,DATE(F$57+1,1,1),EDATE(F$57,1))),--ISNUMBER(SEARCH(IF(ISNUMBER(SEARCH("DIRECTO",UPPER($B58))),"DIRECTO",IF(ISNUMBER(SEARCH("HIPOT",UPPER($B58))),"HIPOT",IF(ISNUMBER(SEARCH("AHORRO",UPPER($B58))),"AHORRO",UPPER($B58)))),UPPER(Base_Cobranzas!$BB$2:$BB$814))),--ISNUMBER(SEARCH("VENCIDO",UPPER(TRIM(Base_Cobranzas!$BK$2:$BK$814)))),Base_Cobranzas!$AZ$2:$AZ$814),0) -> 0 | G58: =IFERROR(SUMPRODUCT(--ISNUMBER(SEARCH($B$6,Base_Cobranzas!$A$2:$A$814)),--(Base_Cobranzas!$AQ$2:$AQ$814>=IF(G$57<3000,DATE(G$57,1,1),G$57)),--(Base_Cobranzas!$AQ$2:$AQ$814<IF(G$57<3000,DATE(G$57+1,1,1),EDATE(G$57,1))),--ISNUMBER(SEARCH(IF(ISNUMBER(SEARCH("DIRECTO",UPPER($B58))),"DIRECTO",IF(ISNUMBER(SEARCH("HIPOT",UPPER($B58))),"HIPOT",IF(ISNUMBER(SEARCH("AHORRO",UPPER($B58))),"AHORRO",UPPER($B58)))),UPPER(Base_Cobranzas!$BB$2:$BB$814))),--ISNUMBER(SEARCH("VENCIDO",UPPER(TRIM(Base_Cobranzas!$BK$2:$BK$814)))),Base_Cobranzas!$AZ$2:$AZ$814),0) -> 0 | H58: =IFERROR(SUMPRODUCT(--ISNUMBER(SEARCH($B$6,Base_Cobranzas!$A$2:$A$814)),--(Base_Cobranzas!$AQ$2:$AQ$814>=IF(H$57<3000,DATE(H$57,1,1),H$57)),--(Base_Cobranzas!$AQ$2:$AQ$814<IF(H$57<3000,DATE(H$57+1,1,1),EDATE(H$57,1))),--ISNUMBER(SEARCH(IF(ISNUMBER(SEARCH("DIRECTO",UPPER($B58))),"DIRECTO",IF(ISNUMBER(SEARCH("HIPOT",UPPER($B58))),"HIPOT",IF(ISNUMBER(SEARCH("AHORRO",UPPER($B58))),"AHORRO",UPPER($B58)))),UPPER(Base_Cobranzas!$BB$2:$BB$814))),--ISNUMBER(SEARCH("VENCIDO",UPPER(TRIM(Base_Cobranzas!$BK$2:$BK$814)))),Base_Cobranzas!$AZ$2:$AZ$814),0) -> 0 | I58: =IFERROR(SUMPRODUCT(--ISNUMBER(SEARCH($B$6,Base_Cobranzas!$A$2:$A$814)),--(Base_Cobranzas!$AQ$2:$AQ$814>=IF(I$57<3000,DATE(I$57,1,1),I$57)),--(Base_Cobranzas!$AQ$2:$AQ$814<IF(I$57<3000,DATE(I$57+1,1,1),EDATE(I$57,1))),--ISNUMBER(SEARCH(IF(ISNUMBER(SEARCH("DIRECTO",UPPER($B58))),"DIRECTO",IF(ISNUMBER(SEARCH("HIPOT",UPPER($B58))),"HIPOT",IF(ISNUMBER(SEARCH("AHORRO",UPPER($B58))),"AHORRO",UPPER($B58)))),UPPER(Base_Cobranzas!$BB$2:$BB$814))),--ISNUMBER(SEARCH("VENCIDO",UPPER(TRIM(Base_Cobranzas!$BK$2:$BK$814)))),Base_Cobranzas!$AZ$2:$AZ$814),0) -> 160000 | J58: =IFERROR(SUMPRODUCT(--ISNUMBER(SEARCH($B$6,Base_Cobranzas!$A$2:$A$814)),--(Base_Cobranzas!$AQ$2:$AQ$814>=IF(J$57<3000,DATE(J$57,1,1),J$57)),--(Base_Cobranzas!$AQ$2:$AQ$814<IF(J$57<3000,DATE(J$57+1,1,1),EDATE(J$57,1))),--ISNUMBER(SEARCH(IF(ISNUMBER(SEARCH("DIRECTO",UPPER($B58))),"DIRECTO",IF(ISNUMBER(SEARCH("HIPOT",UPPER($B58))),"HIPOT",IF(ISNUMBER(SEARCH("AHORRO",UPPER($B58))),"AHORRO",UPPER($B58)))),UPPER(Base_Cobranzas!$BB$2:$BB$814))),--ISNUMBER(SEARCH("VENCIDO",UPPER(TRIM(Base_Cobranzas!$BK$2:$BK$814)))),Base_Cobranzas!$AZ$2:$AZ$814),0) -> 0 | ... N58: =IFERROR(SUMPRODUCT(--ISNUMBER(SEARCH($B$6,Base_Cobranzas!$A$2:$A$814)),--(Base_Cobranzas!$AQ$2:$AQ$814>=IF(N$57<3000,DATE(N$57,1,1),N$57)),--(Base_Cobranzas!$AQ$2:$AQ$814<IF(N$57<3000,DATE(N$57+1,1,1),EDATE(N$57,1))),--ISNUMBER(SEARCH(IF(ISNUMBER(SEARCH("DIRECTO",UPPER($B58))),"DIRECTO",IF(ISNUMBER(SEARCH("HIPOT",UPPER($B58))),"HIPOT",IF(ISNUMBER(SEARCH("AHORRO",UPPER($B58))),"AHORRO",UPPER($B58)))),UPPER(Base_Cobranzas!$BB$2:$BB$814))),--ISNUMBER(SEARCH("VENCIDO",UPPER(TRIM(Base_Cobranzas!$BK$2:$BK$814)))),Base_Cobranzas!$AZ$2:$AZ$814),0) -> 16000 | O58: =SUM(C58:N58) -> 254800
B59: Crédito Hipotecario | C59: =IFERROR(SUMPRODUCT(--ISNUMBER(SEARCH($B$6,Base_Cobranzas!$A$2:$A$814)),--(Base_Cobranzas!$AQ$2:$AQ$814>=IF(C$57<3000,DATE(C$57,1,1),C$57)),--(Base_Cobranzas!$AQ$2:$AQ$814<IF(C$57<3000,DATE(C$57+1,1,1),EDATE(C$57,1))),--ISNUMBER(SEARCH(IF(ISNUMBER(SEARCH("DIRECTO",UPPER($B59))),"DIRECTO",IF(ISNUMBER(SEARCH("HIPOT",UPPER($B59))),"HIPOT",IF(ISNUMBER(SEARCH("AHORRO",UPPER($B59))),"AHORRO",UPPER($B59)))),UPPER(Base_Cobranzas!$BB$2:$BB$814))),--ISNUMBER(SEARCH("VENCIDO",UPPER(TRIM(Base_Cobranzas!$BK$2:$BK$814)))),Base_Cobranzas!$AZ$2:$AZ$814),0) -> 0 | D59: =IFERROR(SUMPRODUCT(--ISNUMBER(SEARCH($B$6,Base_Cobranzas!$A$2:$A$814)),--(Base_Cobranzas!$AQ$2:$AQ$814>=IF(D$57<3000,DATE(D$57,1,1),D$57)),--(Base_Cobranzas!$AQ$2:$AQ$814<IF(D$57<3000,DATE(D$57+1,1,1),EDATE(D$57,1))),--ISNUMBER(SEARCH(IF(ISNUMBER(SEARCH("DIRECTO",UPPER($B59))),"DIRECTO",IF(ISNUMBER(SEARCH("HIPOT",UPPER($B59))),"HIPOT",IF(ISNUMBER(SEARCH("AHORRO",UPPER($B59))),"AHORRO",UPPER($B59)))),UPPER(Base_Cobranzas!$BB$2:$BB$814))),--ISNUMBER(SEARCH("VENCIDO",UPPER(TRIM(Base_Cobranzas!$BK$2:$BK$814)))),Base_Cobranzas!$AZ$2:$AZ$814),0) -> 0 | E59: =IFERROR(SUMPRODUCT(--ISNUMBER(SEARCH($B$6,Base_Cobranzas!$A$2:$A$814)),--(Base_Cobranzas!$AQ$2:$AQ$814>=IF(E$57<3000,DATE(E$57,1,1),E$57)),--(Base_Cobranzas!$AQ$2:$AQ$814<IF(E$57<3000,DATE(E$57+1,1,1),EDATE(E$57,1))),--ISNUMBER(SEARCH(IF(ISNUMBER(SEARCH("DIRECTO",UPPER($B59))),"DIRECTO",IF(ISNUMBER(SEARCH("HIPOT",UPPER($B59))),"HIPOT",IF(ISNUMBER(SEARCH("AHORRO",UPPER($B59))),"AHORRO",UPPER($B59)))),UPPER(Base_Cobranzas!$BB$2:$BB$814))),--ISNUMBER(SEARCH("VENCIDO",UPPER(TRIM(Base_Cobranzas!$BK$2:$BK$814)))),Base_Cobranzas!$AZ$2:$AZ$814),0) -> 0 | F59: =IFERROR(SUMPRODUCT(--ISNUMBER(SEARCH($B$6,Base_Cobranzas!$A$2:$A$814)),--(Base_Cobranzas!$AQ$2:$AQ$814>=IF(F$57<3000,DATE(F$57,1,1),F$57)),--(Base_Cobranzas!$AQ$2:$AQ$814<IF(F$57<3000,DATE(F$57+1,1,1),EDATE(F$57,1))),--ISNUMBER(SEARCH(IF(ISNUMBER(SEARCH("DIRECTO",UPPER($B59))),"DIRECTO",IF(ISNUMBER(SEARCH("HIPOT",UPPER($B59))),"HIPOT",IF(ISNUMBER(SEARCH("AHORRO",UPPER($B59))),"AHORRO",UPPER($B59)))),UPPER(Base_Cobranzas!$BB$2:$BB$814))),--ISNUMBER(SEARCH("VENCIDO",UPPER(TRIM(Base_Cobranzas!$BK$2:$BK$814)))),Base_Cobranzas!$AZ$2:$AZ$814),0) -> 0 | G59: =IFERROR(SUMPRODUCT(--ISNUMBER(SEARCH($B$6,Base_Cobranzas!$A$2:$A$814)),--(Base_Cobranzas!$AQ$2:$AQ$814>=IF(G$57<3000,DATE(G$57,1,1),G$57)),--(Base_Cobranzas!$AQ$2:$AQ$814<IF(G$57<3000,DATE(G$57+1,1,1),EDATE(G$57,1))),--ISNUMBER(SEARCH(IF(ISNUMBER(SEARCH("DIRECTO",UPPER($B59))),"DIRECTO",IF(ISNUMBER(SEARCH("HIPOT",UPPER($B59))),"HIPOT",IF(ISNUMBER(SEARCH("AHORRO",UPPER($B59))),"AHORRO",UPPER($B59)))),UPPER(Base_Cobranzas!$BB$2:$BB$814))),--ISNUMBER(SEARCH("VENCIDO",UPPER(TRIM(Base_Cobranzas!$BK$2:$BK$814)))),Base_Cobranzas!$AZ$2:$AZ$814),0) -> 0 | H59: =IFERROR(SUMPRODUCT(--ISNUMBER(SEARCH($B$6,Base_Cobranzas!$A$2:$A$814)),--(Base_Cobranzas!$AQ$2:$AQ$814>=IF(H$57<3000,DATE(H$57,1,1),H$57)),--(Base_Cobranzas!$AQ$2:$AQ$814<IF(H$57<3000,DATE(H$57+1,1,1),EDATE(H$57,1))),--ISNUMBER(SEARCH(IF(ISNUMBER(SEARCH("DIRECTO",UPPER($B59))),"DIRECTO",IF(ISNUMBER(SEARCH("HIPOT",UPPER($B59))),"HIPOT",IF(ISNUMBER(SEARCH("AHORRO",UPPER($B59))),"AHORRO",UPPER($B59)))),UPPER(Base_Cobranzas!$BB$2:$BB$814))),--ISNUMBER(SEARCH("VENCIDO",UPPER(TRIM(Base_Cobranzas!$BK$2:$BK$814)))),Base_Cobranzas!$AZ$2:$AZ$814),0) -> 0 | I59: =IFERROR(SUMPRODUCT(--ISNUMBER(SEARCH($B$6,Base_Cobranzas!$A$2:$A$814)),--(Base_Cobranzas!$AQ$2:$AQ$814>=IF(I$57<3000,DATE(I$57,1,1),I$57)),--(Base_Cobranzas!$AQ$2:$AQ$814<IF(I$57<3000,DATE(I$57+1,1,1),EDATE(I$57,1))),--ISNUMBER(SEARCH(IF(ISNUMBER(SEARCH("DIRECTO",UPPER($B59))),"DIRECTO",IF(ISNUMBER(SEARCH("HIPOT",UPPER($B59))),"HIPOT",IF(ISNUMBER(SEARCH("AHORRO",UPPER($B59))),"AHORRO",UPPER($B59)))),UPPER(Base_Cobranzas!$BB$2:$BB$814))),--ISNUMBER(SEARCH("VENCIDO",UPPER(TRIM(Base_Cobranzas!$BK$2:$BK$814)))),Base_Cobranzas!$AZ$2:$AZ$814),0) -> 0 | J59: =IFERROR(SUMPRODUCT(--ISNUMBER(SEARCH($B$6,Base_Cobranzas!$A$2:$A$814)),--(Base_Cobranzas!$AQ$2:$AQ$814>=IF(J$57<3000,DATE(J$57,1,1),J$57)),--(Base_Cobranzas!$AQ$2:$AQ$814<IF(J$57<3000,DATE(J$57+1,1,1),EDATE(J$57,1))),--ISNUMBER(SEARCH(IF(ISNUMBER(SEARCH("DIRECTO",UPPER($B59))),"DIRECTO",IF(ISNUMBER(SEARCH("HIPOT",UPPER($B59))),"HIPOT",IF(ISNUMBER(SEARCH("AHORRO",UPPER($B59))),"AHORRO",UPPER($B59)))),UPPER(Base_Cobranzas!$BB$2:$BB$814))),--ISNUMBER(SEARCH("VENCIDO",UPPER(TRIM(Base_Cobranzas!$BK$2:$BK$814)))),Base_Cobranzas!$AZ$2:$AZ$814),0) -> 0 | ... N59: =IFERROR(SUMPRODUCT(--ISNUMBER(SEARCH($B$6,Base_Cobranzas!$A$2:$A$814)),--(Base_Cobranzas!$AQ$2:$AQ$814>=IF(N$57<3000,DATE(N$57,1,1),N$57)),--(Base_Cobranzas!$AQ$2:$AQ$814<IF(N$57<3000,DATE(N$57+1,1,1),EDATE(N$57,1))),--ISNUMBER(SEARCH(IF(ISNUMBER(SEARCH("DIRECTO",UPPER($B59))),"DIRECTO",IF(ISNUMBER(SEARCH("HIPOT",UPPER($B59))),"HIPOT",IF(ISNUMBER(SEARCH("AHORRO",UPPER($B59))),"AHORRO",UPPER($B59)))),UPPER(Base_Cobranzas!$BB$2:$BB$814))),--ISNUMBER(SEARCH("VENCIDO",UPPER(TRIM(Base_Cobranzas!$BK$2:$BK$814)))),Base_Cobranzas!$AZ$2:$AZ$814),0) -> 338000 | O59: =SUM(C59:N59) -> 893850
B60: Ahorro | C60: =IFERROR(SUMPRODUCT(--ISNUMBER(SEARCH($B$6,Base_Cobranzas!$A$2:$A$814)),--(Base_Cobranzas!$AQ$2:$AQ$814>=IF(C$57<3000,DATE(C$57,1,1),C$57)),--(Base_Cobranzas!$AQ$2:$AQ$814<IF(C$57<3000,DATE(C$57+1,1,1),EDATE(C$57,1))),--ISNUMBER(SEARCH(IF(ISNUMBER(SEARCH("DIRECTO",UPPER($B60))),"DIRECTO",IF(ISNUMBER(SEARCH("HIPOT",UPPER($B60))),"HIPOT",IF(ISNUMBER(SEARCH("AHORRO",UPPER($B60))),"AHORRO",UPPER($B60)))),UPPER(Base_Cobranzas!$BB$2:$BB$814))),--ISNUMBER(SEARCH("VENCIDO",UPPER(TRIM(Base_Cobranzas!$BK$2:$BK$814)))),Base_Cobranzas!$AZ$2:$AZ$814),0) -> 58000 | D60: =IFERROR(SUMPRODUCT(--ISNUMBER(SEARCH($B$6,Base_Cobranzas!$A$2:$A$814)),--(Base_Cobranzas!$AQ$2:$AQ$814>=IF(D$57<3000,DATE(D$57,1,1),D$57)),--(Base_Cobranzas!$AQ$2:$AQ$814<IF(D$57<3000,DATE(D$57+1,1,1),EDATE(D$57,1))),--ISNUMBER(SEARCH(IF(ISNUMBER(SEARCH("DIRECTO",UPPER($B60))),"DIRECTO",IF(ISNUMBER(SEARCH("HIPOT",UPPER($B60))),"HIPOT",IF(ISNUMBER(SEARCH("AHORRO",UPPER($B60))),"AHORRO",UPPER($B60)))),UPPER(Base_Cobranzas!$BB$2:$BB$814))),--ISNUMBER(SEARCH("VENCIDO",UPPER(TRIM(Base_Cobranzas!$BK$2:$BK$814)))),Base_Cobranzas!$AZ$2:$AZ$814),0) -> 0 | E60: =IFERROR(SUMPRODUCT(--ISNUMBER(SEARCH($B$6,Base_Cobranzas!$A$2:$A$814)),--(Base_Cobranzas!$AQ$2:$AQ$814>=IF(E$57<3000,DATE(E$57,1,1),E$57)),--(Base_Cobranzas!$AQ$2:$AQ$814<IF(E$57<3000,DATE(E$57+1,1,1),EDATE(E$57,1))),--ISNUMBER(SEARCH(IF(ISNUMBER(SEARCH("DIRECTO",UPPER($B60))),"DIRECTO",IF(ISNUMBER(SEARCH("HIPOT",UPPER($B60))),"HIPOT",IF(ISNUMBER(SEARCH("AHORRO",UPPER($B60))),"AHORRO",UPPER($B60)))),UPPER(Base_Cobranzas!$BB$2:$BB$814))),--ISNUMBER(SEARCH("VENCIDO",UPPER(TRIM(Base_Cobranzas!$BK$2:$BK$814)))),Base_Cobranzas!$AZ$2:$AZ$814),0) -> 0 | F60: =IFERROR(SUMPRODUCT(--ISNUMBER(SEARCH($B$6,Base_Cobranzas!$A$2:$A$814)),--(Base_Cobranzas!$AQ$2:$AQ$814>=IF(F$57<3000,DATE(F$57,1,1),F$57)),--(Base_Cobranzas!$AQ$2:$AQ$814<IF(F$57<3000,DATE(F$57+1,1,1),EDATE(F$57,1))),--ISNUMBER(SEARCH(IF(ISNUMBER(SEARCH("DIRECTO",UPPER($B60))),"DIRECTO",IF(ISNUMBER(SEARCH("HIPOT",UPPER($B60))),"HIPOT",IF(ISNUMBER(SEARCH("AHORRO",UPPER($B60))),"AHORRO",UPPER($B60)))),UPPER(Base_Cobranzas!$BB$2:$BB$814))),--ISNUMBER(SEARCH("VENCIDO",UPPER(TRIM(Base_Cobranzas!$BK$2:$BK$814)))),Base_Cobranzas!$AZ$2:$AZ$814),0) -> 0 | G60: =IFERROR(SUMPRODUCT(--ISNUMBER(SEARCH($B$6,Base_Cobranzas!$A$2:$A$814)),--(Base_Cobranzas!$AQ$2:$AQ$814>=IF(G$57<3000,DATE(G$57,1,1),G$57)),--(Base_Cobranzas!$AQ$2:$AQ$814<IF(G$57<3000,DATE(G$57+1,1,1),EDATE(G$57,1))),--ISNUMBER(SEARCH(IF(ISNUMBER(SEARCH("DIRECTO",UPPER($B60))),"DIRECTO",IF(ISNUMBER(SEARCH("HIPOT",UPPER($B60))),"HIPOT",IF(ISNUMBER(SEARCH("AHORRO",UPPER($B60))),"AHORRO",UPPER($B60)))),UPPER(Base_Cobranzas!$BB$2:$BB$814))),--ISNUMBER(SEARCH("VENCIDO",UPPER(TRIM(Base_Cobranzas!$BK$2:$BK$814)))),Base_Cobranzas!$AZ$2:$AZ$814),0) -> 0 | H60: =IFERROR(SUMPRODUCT(--ISNUMBER(SEARCH($B$6,Base_Cobranzas!$A$2:$A$814)),--(Base_Cobranzas!$AQ$2:$AQ$814>=IF(H$57<3000,DATE(H$57,1,1),H$57)),--(Base_Cobranzas!$AQ$2:$AQ$814<IF(H$57<3000,DATE(H$57+1,1,1),EDATE(H$57,1))),--ISNUMBER(SEARCH(IF(ISNUMBER(SEARCH("DIRECTO",UPPER($B60))),"DIRECTO",IF(ISNUMBER(SEARCH("HIPOT",UPPER($B60))),"HIPOT",IF(ISNUMBER(SEARCH("AHORRO",UPPER($B60))),"AHORRO",UPPER($B60)))),UPPER(Base_Cobranzas!$BB$2:$BB$814))),--ISNUMBER(SEARCH("VENCIDO",UPPER(TRIM(Base_Cobranzas!$BK$2:$BK$814)))),Base_Cobranzas!$AZ$2:$AZ$814),0) -> 0 | I60: =IFERROR(SUMPRODUCT(--ISNUMBER(SEARCH($B$6,Base_Cobranzas!$A$2:$A$814)),--(Base_Cobranzas!$AQ$2:$AQ$814>=IF(I$57<3000,DATE(I$57,1,1),I$57)),--(Base_Cobranzas!$AQ$2:$AQ$814<IF(I$57<3000,DATE(I$57+1,1,1),EDATE(I$57,1))),--ISNUMBER(SEARCH(IF(ISNUMBER(SEARCH("DIRECTO",UPPER($B60))),"DIRECTO",IF(ISNUMBER(SEARCH("HIPOT",UPPER($B60))),"HIPOT",IF(ISNUMBER(SEARCH("AHORRO",UPPER($B60))),"AHORRO",UPPER($B60)))),UPPER(Base_Cobranzas!$BB$2:$BB$814))),--ISNUMBER(SEARCH("VENCIDO",UPPER(TRIM(Base_Cobranzas!$BK$2:$BK$814)))),Base_Cobranzas!$AZ$2:$AZ$814),0) -> 0 | J60: =IFERROR(SUMPRODUCT(--ISNUMBER(SEARCH($B$6,Base_Cobranzas!$A$2:$A$814)),--(Base_Cobranzas!$AQ$2:$AQ$814>=IF(J$57<3000,DATE(J$57,1,1),J$57)),--(Base_Cobranzas!$AQ$2:$AQ$814<IF(J$57<3000,DATE(J$57+1,1,1),EDATE(J$57,1))),--ISNUMBER(SEARCH(IF(ISNUMBER(SEARCH("DIRECTO",UPPER($B60))),"DIRECTO",IF(ISNUMBER(SEARCH("HIPOT",UPPER($B60))),"HIPOT",IF(ISNUMBER(SEARCH("AHORRO",UPPER($B60))),"AHORRO",UPPER($B60)))),UPPER(Base_Cobranzas!$BB$2:$BB$814))),--ISNUMBER(SEARCH("VENCIDO",UPPER(TRIM(Base_Cobranzas!$BK$2:$BK$814)))),Base_Cobranzas!$AZ$2:$AZ$814),0) -> 0 | ... N60: =IFERROR(SUMPRODUCT(--ISNUMBER(SEARCH($B$6,Base_Cobranzas!$A$2:$A$814)),--(Base_Cobranzas!$AQ$2:$AQ$814>=IF(N$57<3000,DATE(N$57,1,1),N$57)),--(Base_Cobranzas!$AQ$2:$AQ$814<IF(N$57<3000,DATE(N$57+1,1,1),EDATE(N$57,1))),--ISNUMBER(SEARCH(IF(ISNUMBER(SEARCH("DIRECTO",UPPER($B60))),"DIRECTO",IF(ISNUMBER(SEARCH("HIPOT",UPPER($B60))),"HIPOT",IF(ISNUMBER(SEARCH("AHORRO",UPPER($B60))),"AHORRO",UPPER($B60)))),UPPER(Base_Cobranzas!$BB$2:$BB$814))),--ISNUMBER(SEARCH("VENCIDO",UPPER(TRIM(Base_Cobranzas!$BK$2:$BK$814)))),Base_Cobranzas!$AZ$2:$AZ$814),0) -> 399530 | O60: =SUM(C60:N60) -> 848030
B61: Total | C61: =SUM(C58:C60) -> 58000 | D61: =SUM(D58:D60) -> 0 | E61: =SUM(E58:E60) -> 0 | F61: =SUM(F58:F60) -> 0 | G61: =SUM(G58:G60) -> 0 | H61: =SUM(H58:H60) -> 0 | I61: =SUM(I58:I60) -> 160000 | J61: =SUM(J58:J60) -> 0 | ... N61: =SUM(N58:N60) -> 753530 | O61: =SUM(C61:N61) -> 1996680 | P61: =IF($I$21=O61,"OK","REVISAR") -> OK
B63: Acumulado | C63: =C61 -> 58000 | D63: =C63+D61 -> 58000 | E63: =D63+E61 -> 58000 | F63: =E63+F61 -> 58000 | G63: =F63+G61 -> 58000 | H63: =G63+H61 -> 58000 | I63: =H63+I61 -> 218000 | J63: =I63+J61 -> 218000 | K63: =J63+K61 -> 223000 | ... N63: =M63+N61 -> 1996680

Sheet Beyond
C5: REPORTE DE COBRANZAS
B6: Beyond
C8: Vendido | F8: Cobranzas
C9: Monto | D9: Unidades | F9: Avance | G9: Cobrado | H9: Por Cobrar | I9: Vencido | J9: Tasa de Morosidad | K9: Clientes Morosos (unidades) | L9: Dias de Atraso (Promedio)
B11: Departamentos | C11: 20403900 | D11: 64 | F11: =IF(C11=0,0,G11/C11) -> 0.2171117 | G11: =SUM(G12:G13) -> 4429925.5 | H11: =SUM(H12:H13) -> 8949397.2 | I11: =SUM(I12:I13) -> 7024577.3 | J11: =IF(C11=0,0,I11/C11) -> 0.34427621 | K11: 25 | L11: 143
B12: Departamento | C12: 11272900 | D12: 25 | F12: =IF(C12=0,0,G12/C12) -> 0.13675505 | G12: =IFERROR(SUMPRODUCT(--ISNUMBER(SEARCH($B$6,Base_Cobranzas!$A$2:$A$814)),--((--ISNUMBER(SEARCH("DEPART",UPPER(Base_Cobranzas!$E$2:$E$814)))+--ISNUMBER(SEARCH("DEPART",UPPER(Base_Cobranzas!$M$2:$M$814)))+--ISNUMBER(SEARCH("DEPART",UPPER(Base_Cobranzas!$U$2:$U$814)))+--ISNUMBER(SEARCH("DEPART",UPPER(Base_Cobranzas!$AC$2:$AC$814))))>0),--((--ISNUMBER(SEARCH("ESTACION",UPPER(Base_Cobranzas!$E$2:$E$814)))+--ISNUMBER(SEARCH("ESTACION",UPPER(Base_Cobranzas!$M$2:$M$814)))+--ISNUMBER(SEARCH("ESTACION",UPPER(Base_Cobranzas!$U$2:$U$814)))+--ISNUMBER(SEARCH("ESTACION",UPPER(Base_Cobranzas!$AC$2:$AC$814))))=0),--(Base_Cobranzas!$AY$2:$AY$814>0),Base_Cobranzas!$AY$2:$AY$814),0) -> 1541626 | H12: =IFERROR(SUMPRODUCT(--ISNUMBER(SEARCH($B$6,Base_Cobranzas!$A$2:$A$814)),--((--ISNUMBER(SEARCH("DEPART",UPPER(Base_Cobranzas!$E$2:$E$814)))+--ISNUMBER(SEARCH("DEPART",UPPER(Base_Cobranzas!$M$2:$M$814)))+--ISNUMBER(SEARCH("DEPART",UPPER(Base_Cobranzas!$U$2:$U$814)))+--ISNUMBER(SEARCH("DEPART",UPPER(Base_Cobranzas!$AC$2:$AC$814))))>0),--((--ISNUMBER(SEARCH("ESTACION",UPPER(Base_Cobranzas!$E$2:$E$814)))+--ISNUMBER(SEARCH("ESTACION",UPPER(Base_Cobranzas!$M$2:$M$814)))+--ISNUMBER(SEARCH("ESTACION",UPPER(Base_Cobranzas!$U$2:$U$814)))+--ISNUMBER(SEARCH("ESTACION",UPPER(Base_Cobranzas!$AC$2:$AC$814))))=0),--ISNUMBER(SEARCH("PENDIENTE",UPPER(TRIM(Base_Cobranzas!$BK$2:$BK$814)))),Base_Cobranzas!$AZ$2:$AZ$814),0) -> 4215249 | I12: =IFERROR(SUMPRODUCT(--ISNUMBER(SEARCH($B$6,Base_Cobranzas!$A$2:$A$814)),--((--ISNUMBER(SEARCH("DEPART",UPPER(Base_Cobranzas!$E$2:$E$814)))+--ISNUMBER(SEARCH("DEPART",UPPER(Base_Cobranzas!$M$2:$M$814)))+--ISNUMBER(SEARCH("DEPART",UPPER(Base_Cobranzas!$U$2:$U$814)))+--ISNUMBER(SEARCH("DEPART",UPPER(Base_Cobranzas!$AC$2:$AC$814))))>0),--((--ISNUMBER(SEARCH("ESTACION",UPPER(Base_Cobranzas!$E$2:$E$814)))+--ISNUMBER(SEARCH("ESTACION",UPPER(Base_Cobranzas!$M$2:$M$814)))+--ISNUMBER(SEARCH("ESTACION",UPPER(Base_Cobranzas!$U$2:$U$814)))+--ISNUMBER(SEARCH("ESTACION",UPPER(Base_Cobranzas!$AC$2:$AC$814))))=0),--ISNUMBER(SEARCH("VENCIDO",UPPER(TRIM(Base_Cobranzas!$BK$2:$BK$814)))),Base_Cobranzas!$AZ$2:$AZ$814),0) -> 5516025 | J12: =IF(C12=0,0,I12/C12) -> 0.4893173 | K12: 17 | L12: 78
B13: Departamento + Estacionamiento | C13: 9131000 | D13: 39 | F13: =IF(C13=0,0,G13/C13) -> 0.31631798 | G13: =IFERROR(SUMPRODUCT(--ISNUMBER(SEARCH($B$6,Base_Cobranzas!$A$2:$A$814)),--((--ISNUMBER(SEARCH("DEPART",UPPER(Base_Cobranzas!$E$2:$E$814)))+--ISNUMBER(SEARCH("DEPART",UPPER(Base_Cobranzas!$M$2:$M$814)))+--ISNUMBER(SEARCH("DEPART",UPPER(Base_Cobranzas!$U$2:$U$814)))+--ISNUMBER(SEARCH("DEPART",UPPER(Base_Cobranzas!$AC$2:$AC$814))))>0),--((--ISNUMBER(SEARCH("ESTACION",UPPER(Base_Cobranzas!$E$2:$E$814)))+--ISNUMBER(SEARCH("ESTACION",UPPER(Base_Cobranzas!$M$2:$M$814)))+--ISNUMBER(SEARCH("ESTACION",UPPER(Base_Cobranzas!$U$2:$U$814)))+--ISNUMBER(SEARCH("ESTACION",UPPER(Base_Cobranzas!$AC$2:$AC$814))))>0),--(Base_Cobranzas!$AY$2:$AY$814>0),Base_Cobranzas!$AY$2:$AY$814),0) -> 2888299.5 | H13: =IFERROR(SUMPRODUCT(--ISNUMBER(SEARCH($B$6,Base_Cobranzas!$A$2:$A$814)),--((--ISNUMBER(SEARCH("DEPART",UPPER(Base_Cobranzas!$E$2:$E$814)))+--ISNUMBER(SEARCH("DEPART",UPPER(Base_Cobranzas!$M$2:$M$814)))+--ISNUMBER(SEARCH("DEPART",UPPER(Base_Cobranzas!$U$2:$U$814)))+--ISNUMBER(SEARCH("DEPART",UPPER(Base_Cobranzas!$AC$2:$AC$814))))>0),--((--ISNUMBER(SEARCH("ESTACION",UPPER(Base_Cobranzas!$E$2:$E$814)))+--ISNUMBER(SEARCH("ESTACION",UPPER(Base_Cobranzas!$M$2:$M$814)))+--ISNUMBER(SEARCH("ESTACION",UPPER(Base_Cobranzas!$U$2:$U$814)))+--ISNUMBER(SEARCH("ESTACION",UPPER(Base_Cobranzas!$AC$2:$AC$814))))>0),--ISNUMBER(SEARCH("PENDIENTE",UPPER(TRIM(Base_Cobranzas!$BK$2:$BK$814)))),Base_Cobranzas!$AZ$2:$AZ$814),0) -> 4734148.2 | I13: =IFERROR(SUMPRODUCT(--ISNUMBER(SEARCH($B$6,Base_Cobranzas!$A$2:$A$814)),--((--ISNUMBER(SEARCH("DEPART",UPPER(Base_Cobranzas!$E$2:$E$814)))+--ISNUMBER(SEARCH("DEPART",UPPER(Base_Cobranzas!$M$2:$M$814)))+--ISNUMBER(SEARCH("DEPART",UPPER(Base_Cobranzas!$U$2:$U$814)))+--ISNUMBER(SEARCH("DEPART",UPPER(Base_Cobranzas!$AC$2:$AC$814))))>0),--((--ISNUMBER(SEARCH("ESTACION",UPPER(Base_Cobranzas!$E$2:$E$814)))+--ISNUMBER(SEARCH("ESTACION",UPPER(Base_Cobranzas!$M$2:$M$814)))+--ISNUMBER(SEARCH("ESTACION",UPPER(Base_Cobranzas!$U$2:$U$814)))+--ISNUMBER(SEARCH("ESTACION",UPPER(Base_Cobranzas!$AC$2:$AC$814))))>0),--ISNUMBER(SEARCH("VENCIDO",UPPER(TRIM(Base_Cobranzas!$BK$2:$BK$814)))),Base_Cobranzas!$AZ$2:$AZ$814),0) -> 1508552.3 | J13: =IF(C13=0,0,I13/C13) -> 0.16521217 | K13: 8 | L13: 204
B15: Estacionamientos | C15: 47500 | D15: 1 | F15: =IF(C15=0,0,G15/C15) -> 0.2 | G15: =IFERROR(SUMPRODUCT(--ISNUMBER(SEARCH($B$6,Base_Cobranzas!$A$2:$A$814)),--((--ISNUMBER(SEARCH("DEPART",UPPER(Base_Cobranzas!$E$2:$E$814)))+--ISNUMBER(SEARCH("DEPART",UPPER(Base_Cobranzas!$M$2:$M$814)))+--ISNUMBER(SEARCH("DEPART",UPPER(Base_Cobranzas!$U$2:$U$814)))+--ISNUMBER(SEARCH("DEPART",UPPER(Base_Cobranzas!$AC$2:$AC$814))))=0),--((--ISNUMBER(SEARCH("ESTACION",UPPER(Base_Cobranzas!$E$2:$E$814)))+--ISNUMBER(SEARCH("ESTACION",UPPER(Base_Cobranzas!$M$2:$M$814)))+--ISNUMBER(SEARCH("ESTACION",UPPER(Base_Cobranzas!$U$2:$U$814)))+--ISNUMBER(SEARCH("ESTACION",UPPER(Base_Cobranzas!$AC$2:$AC$814))))>0),--(Base_Cobranzas!$AY$2:$AY$814>0),Base_Cobranzas!$AY$2:$AY$814),0) -> 9500 | H15: =IFERROR(SUMPRODUCT(--ISNUMBER(SEARCH($B$6,Base_Cobranzas!$A$2:$A$814)),--((--ISNUMBER(SEARCH("DEPART",UPPER(Base_Cobranzas!$E$2:$E$814)))+--ISNUMBER(SEARCH("DEPART",UPPER(Base_Cobranzas!$M$2:$M$814)))+--ISNUMBER(SEARCH("DEPART",UPPER(Base_Cobranzas!$U$2:$U$814)))+--ISNUMBER(SEARCH("DEPART",UPPER(Base_Cobranzas!$AC$2:$AC$814))))=0),--((--ISNUMBER(SEARCH("ESTACION",UPPER(Base_Cobranzas!$E$2:$E$814)))+--ISNUMBER(SEARCH("ESTACION",UPPER(Base_Cobranzas!$M$2:$M$814)))+--ISNUMBER(SEARCH("ESTACION",UPPER(Base_Cobranzas!$U$2:$U$814)))+--ISNUMBER(SEARCH("ESTACION",UPPER(Base_Cobranzas!$AC$2:$AC$814))))>0),--ISNUMBER(SEARCH("PENDIENTE",UPPER(TRIM(Base_Cobranzas!$BK$2:$BK$814)))),Base_Cobranzas!$AZ$2:$AZ$814),0) -> 38000 | I15: =IFERROR(SUMPRODUCT(--ISNUMBER(SEARCH($B$6,Base_Cobranzas!$A$2:$A$814)),--((--ISNUMBER(SEARCH("DEPART",UPPER(Base_Cobranzas!$E$2:$E$814)))+--ISNUMBER(SEARCH("DEPART",UPPER(Base_Cobranzas!$M$2:$M$814)))+--ISNUMBER(SEARCH("DEPART",UPPER(Base_Cobranzas!$U$2:$U$814)))+--ISNUMBER(SEARCH("DEPART",UPPER(Base_Cobranzas!$AC$2:$AC$814))))=0),--((--ISNUMBER(SEARCH("ESTACION",UPPER(Base_Cobranzas!$E$2:$E$814)))+--ISNUMBER(SEARCH("ESTACION",UPPER(Base_Cobranzas!$M$2:$M$814)))+--ISNUMBER(SEARCH("ESTACION",UPPER(Base_Cobranzas!$U$2:$U$814)))+--ISNUMBER(SEARCH("ESTACION",UPPER(Base_Cobranzas!$AC$2:$AC$814))))>0),--ISNUMBER(SEARCH("VENCIDO",UPPER(TRIM(Base_Cobranzas!$BK$2:$BK$814)))),Base_Cobranzas!$AZ$2:$AZ$814),0) -> 0 | J15: =IF(C15=0,0,I15/C15) -> 0 | K15: 0 | L15: 0
B17: Depositos | C17: 0 | D17: 0 | F17: =IF(C17=0,0,G17/C17) -> 0 | G17: =IFERROR(SUMPRODUCT(--ISNUMBER(SEARCH($B$6,Base_Cobranzas!$A$2:$A$814)),--((--ISNUMBER(SEARCH("DEPART",UPPER(Base_Cobranzas!$E$2:$E$814)))+--ISNUMBER(SEARCH("DEPART",UPPER(Base_Cobranzas!$M$2:$M$814)))+--ISNUMBER(SEARCH("DEPART",UPPER(Base_Cobranzas!$U$2:$U$814)))+--ISNUMBER(SEARCH("DEPART",UPPER(Base_Cobranzas!$AC$2:$AC$814))))=0),--((--ISNUMBER(SEARCH("ESTACION",UPPER(Base_Cobranzas!$E$2:$E$814)))+--ISNUMBER(SEARCH("ESTACION",UPPER(Base_Cobranzas!$M$2:$M$814)))+--ISNUMBER(SEARCH("ESTACION",UPPER(Base_Cobranzas!$U$2:$U$814)))+--ISNUMBER(SEARCH("ESTACION",UPPER(Base_Cobranzas!$AC$2:$AC$814))))=0),--((--ISNUMBER(SEARCH("DEPOS",UPPER(Base_Cobranzas!$E$2:$E$814)))+--ISNUMBER(SEARCH("DEPOS",UPPER(Base_Cobranzas!$M$2:$M$814)))+--ISNUMBER(SEARCH("DEPOS",UPPER(Base_Cobranzas!$U$2:$U$814)))+--ISNUMBER(SEARCH("DEPOS",UPPER(Base_Cobranzas!$AC$2:$AC$814))))>0),--(Base_Cobranzas!$AY$2:$AY$814>0),Base_Cobranzas!$AY$2:$AY$814),0) -> 0 | H17: =IFERROR(SUMPRODUCT(--ISNUMBER(SEARCH($B$6,Base_Cobranzas!$A$2:$A$814)),--((--ISNUMBER(SEARCH("DEPART",UPPER(Base_Cobranzas!$E$2:$E$814)))+--ISNUMBER(SEARCH("DEPART",UPPER(Base_Cobranzas!$M$2:$M$814)))+--ISNUMBER(SEARCH("DEPART",UPPER(Base_Cobranzas!$U$2:$U$814)))+--ISNUMBER(SEARCH("DEPART",UPPER(Base_Cobranzas!$AC$2:$AC$814))))=0),--((--ISNUMBER(SEARCH("ESTACION",UPPER(Base_Cobranzas!$E$2:$E$814)))+--ISNUMBER(SEARCH("ESTACION",UPPER(Base_Cobranzas!$M$2:$M$814)))+--ISNUMBER(SEARCH("ESTACION",UPPER(Base_Cobranzas!$U$2:$U$814)))+--ISNUMBER(SEARCH("ESTACION",UPPER(Base_Cobranzas!$AC$2:$AC$814))))=0),--((--ISNUMBER(SEARCH("DEPOS",UPPER(Base_Cobranzas!$E$2:$E$814)))+--ISNUMBER(SEARCH("DEPOS",UPPER(Base_Cobranzas!$M$2:$M$814)))+--ISNUMBER(SEARCH("DEPOS",UPPER(Base_Cobranzas!$U$2:$U$814)))+--ISNUMBER(SEARCH("DEPOS",UPPER(Base_Cobranzas!$AC$2:$AC$814))))>0),--ISNUMBER(SEARCH("PENDIENTE",UPPER(TRIM(Base_Cobranzas!$BK$2:$BK$814)))),Base_Cobranzas!$AZ$2:$AZ$814),0) -> 0 | I17: =IFERROR(SUMPRODUCT(--ISNUMBER(SEARCH($B$6,Base_Cobranzas!$A$2:$A$814)),--((--ISNUMBER(SEARCH("DEPART",UPPER(Base_Cobranzas!$E$2:$E$814)))+--ISNUMBER(SEARCH("DEPART",UPPER(Base_Cobranzas!$M$2:$M$814)))+--ISNUMBER(SEARCH("DEPART",UPPER(Base_Cobranzas!$U$2:$U$814)))+--ISNUMBER(SEARCH("DEPART",UPPER(Base_Cobranzas!$AC$2:$AC$814))))=0),--((--ISNUMBER(SEARCH("ESTACION",UPPER(Base_Cobranzas!$E$2:$E$814)))+--ISNUMBER(SEARCH("ESTACION",UPPER(Base_Cobranzas!$M$2:$M$814)))+--ISNUMBER(SEARCH("ESTACION",UPPER(Base_Cobranzas!$U$2:$U$814)))+--ISNUMBER(SEARCH("ESTACION",UPPER(Base_Cobranzas!$AC$2:$AC$814))))=0),--((--ISNUMBER(SEARCH("DEPOS",UPPER(Base_Cobranzas!$E$2:$E$814)))+--ISNUMBER(SEARCH("DEPOS",UPPER(Base_Cobranzas!$M$2:$M$814)))+--ISNUMBER(SEARCH("DEPOS",UPPER(Base_Cobranzas!$U$2:$U$814)))+--ISNUMBER(SEARCH("DEPOS",UPPER(Base_Cobranzas!$AC$2:$AC$814))))>0),--ISNUMBER(SEARCH("VENCIDO",UPPER(TRIM(Base_Cobranzas!$BK$2:$BK$814)))),Base_Cobranzas!$AZ$2:$AZ$814),0) -> 0 | J17: =IF(C17=0,0,I17/C17) -> 0 | K17: 0 | L17: 0
B19: Local Comercial | C19: 0 | D19: 0 | F19: =IF(C19=0,0,G19/C19) -> 0 | G19: =IFERROR(SUMPRODUCT(--ISNUMBER(SEARCH($B$6,Base_Cobranzas!$A$2:$A$814)),--(((--ISNUMBER(SEARCH("LOCAL",UPPER(Base_Cobranzas!$E$2:$E$814)))+--ISNUMBER(SEARCH("LOCAL",UPPER(Base_Cobranzas!$M$2:$M$814)))+--ISNUMBER(SEARCH("LOCAL",UPPER(Base_Cobranzas!$U$2:$U$814)))+--ISNUMBER(SEARCH("LOCAL",UPPER(Base_Cobranzas!$AC$2:$AC$814))))+(--ISNUMBER(SEARCH("COMERCIAL",UPPER(Base_Cobranzas!$E$2:$E$814)))+--ISNUMBER(SEARCH("COMERCIAL",UPPER(Base_Cobranzas!$M$2:$M$814)))+--ISNUMBER(SEARCH("COMERCIAL",UPPER(Base_Cobranzas!$U$2:$U$814)))+--ISNUMBER(SEARCH("COMERCIAL",UPPER(Base_Cobranzas!$AC$2:$AC$814)))))>0),--(Base_Cobranzas!$AY$2:$AY$814>0),Base_Cobranzas!$AY$2:$AY$814),0) -> 0 | H19: =IFERROR(SUMPRODUCT(--ISNUMBER(SEARCH($B$6,Base_Cobranzas!$A$2:$A$814)),--(((--ISNUMBER(SEARCH("LOCAL",UPPER(Base_Cobranzas!$E$2:$E$814)))+--ISNUMBER(SEARCH("LOCAL",UPPER(Base_Cobranzas!$M$2:$M$814)))+--ISNUMBER(SEARCH("LOCAL",UPPER(Base_Cobranzas!$U$2:$U$814)))+--ISNUMBER(SEARCH("LOCAL",UPPER(Base_Cobranzas!$AC$2:$AC$814))))+(--ISNUMBER(SEARCH("COMERCIAL",UPPER(Base_Cobranzas!$E$2:$E$814)))+--ISNUMBER(SEARCH("COMERCIAL",UPPER(Base_Cobranzas!$M$2:$M$814)))+--ISNUMBER(SEARCH("COMERCIAL",UPPER(Base_Cobranzas!$U$2:$U$814)))+--ISNUMBER(SEARCH("COMERCIAL",UPPER(Base_Cobranzas!$AC$2:$AC$814)))))>0),--ISNUMBER(SEARCH("PENDIENTE",UPPER(TRIM(Base_Cobranzas!$BK$2:$BK$814)))),Base_Cobranzas!$AZ$2:$AZ$814),0) -> 0 | I19: =IFERROR(SUMPRODUCT(--ISNUMBER(SEARCH($B$6,Base_Cobranzas!$A$2:$A$814)),--(((--ISNUMBER(SEARCH("LOCAL",UPPER(Base_Cobranzas!$E$2:$E$814)))+--ISNUMBER(SEARCH("LOCAL",UPPER(Base_Cobranzas!$M$2:$M$814)))+--ISNUMBER(SEARCH("LOCAL",UPPER(Base_Cobranzas!$U$2:$U$814)))+--ISNUMBER(SEARCH("LOCAL",UPPER(Base_Cobranzas!$AC$2:$AC$814))))+(--ISNUMBER(SEARCH("COMERCIAL",UPPER(Base_Cobranzas!$E$2:$E$814)))+--ISNUMBER(SEARCH("COMERCIAL",UPPER(Base_Cobranzas!$M$2:$M$814)))+--ISNUMBER(SEARCH("COMERCIAL",UPPER(Base_Cobranzas!$U$2:$U$814)))+--ISNUMBER(SEARCH("COMERCIAL",UPPER(Base_Cobranzas!$AC$2:$AC$814)))))>0),--ISNUMBER(SEARCH("VENCIDO",UPPER(TRIM(Base_Cobranzas!$BK$2:$BK$814)))),Base_Cobranzas!$AZ$2:$AZ$814),0) -> 0 | J19: =IF(C19=0,0,I19/C19) -> 0 | K19: 0 | L19: 0
A21: =+IF(ROUND(C21,0)=ROUND(G21+H21+I21,0),"OK","REVISAR") -> OK | B21: Total | C21: 20451400 | D21: 65 | F21: =IF(C21=0,0,G21/C21) -> 0.21707196 | G21: =G11+G15+G17+G19 -> 4439425.5 | H21: =H11+H15+H17+H19 -> 8987397.2 | I21: =I11+I15+I17+I19 -> 7024577.3 | J21: =IF(C21=0,0,I21/C21) -> 0.3434766 | K21: 25 | L21: 143
B31: COBRANZA REAL
B33: Tipo de Credito | C33: 2024 | D33: 2025 | E33: 46023 | F33: 46054 | G33: 46082 | H33: 46113 | I33: 46143 | J33: 46174 | K33: 46204 | L33: 46235 | M33: Total
B34: Crédito Directo | C34: =IFERROR(SUMPRODUCT(--ISNUMBER(SEARCH($B$6,Base_Cobranzas!$A$2:$A$814)),--(Base_Cobranzas!$AR$2:$AR$814>=IF(C$33<3000,DATE(C$33,1,1),C$33)),--(Base_Cobranzas!$AR$2:$AR$814<IF(C$33<3000,DATE(C$33+1,1,1),EDATE(C$33,1))),--ISNUMBER(SEARCH(IF(ISNUMBER(SEARCH("DIRECTO",UPPER($B34))),"DIRECTO",IF(ISNUMBER(SEARCH("HIPOT",UPPER($B34))),"HIPOT",IF(ISNUMBER(SEARCH("AHORRO",UPPER($B34))),"AHORRO",UPPER($B34)))),UPPER(Base_Cobranzas!$BB$2:$BB$814))),--(Base_Cobranzas!$AY$2:$AY$814>0),Base_Cobranzas!$AY$2:$AY$814),0) -> 3000 | D34: =IFERROR(SUMPRODUCT(--ISNUMBER(SEARCH($B$6,Base_Cobranzas!$A$2:$A$814)),--(Base_Cobranzas!$AR$2:$AR$814>=IF(D$33<3000,DATE(D$33,1,1),D$33)),--(Base_Cobranzas!$AR$2:$AR$814<IF(D$33<3000,DATE(D$33+1,1,1),EDATE(D$33,1))),--ISNUMBER(SEARCH(IF(ISNUMBER(SEARCH("DIRECTO",UPPER($B34))),"DIRECTO",IF(ISNUMBER(SEARCH("HIPOT",UPPER($B34))),"HIPOT",IF(ISNUMBER(SEARCH("AHORRO",UPPER($B34))),"AHORRO",UPPER($B34)))),UPPER(Base_Cobranzas!$BB$2:$BB$814))),--(Base_Cobranzas!$AY$2:$AY$814>0),Base_Cobranzas!$AY$2:$AY$814),0) -> 1009316.9 | E34: =IFERROR(SUMPRODUCT(--ISNUMBER(SEARCH($B$6,Base_Cobranzas!$A$2:$A$814)),--(Base_Cobranzas!$AR$2:$AR$814>=IF(E$33<3000,DATE(E$33,1,1),E$33)),--(Base_Cobranzas!$AR$2:$AR$814<IF(E$33<3000,DATE(E$33+1,1,1),EDATE(E$33,1))),--ISNUMBER(SEARCH(IF(ISNUMBER(SEARCH("DIRECTO",UPPER($B34))),"DIRECTO",IF(ISNUMBER(SEARCH("HIPOT",UPPER($B34))),"HIPOT",IF(ISNUMBER(SEARCH("AHORRO",UPPER($B34))),"AHORRO",UPPER($B34)))),UPPER(Base_Cobranzas!$BB$2:$BB$814))),--(Base_Cobranzas!$AY$2:$AY$814>0),Base_Cobranzas!$AY$2:$AY$814),0) -> 158000 | F34: =IFERROR(SUMPRODUCT(--ISNUMBER(SEARCH($B$6,Base_Cobranzas!$A$2:$A$814)),--(Base_Cobranzas!$AR$2:$AR$814>=IF(F$33<3000,DATE(F$33,1,1),F$33)),--(Base_Cobranzas!$AR$2:$AR$814<IF(F$33<3000,DATE(F$33+1,1,1),EDATE(F$33,1))),--ISNUMBER(SEARCH(IF(ISNUMBER(SEARCH("DIRECTO",UPPER($B34))),"DIRECTO",IF(ISNUMBER(SEARCH("HIPOT",UPPER($B34))),"HIPOT",IF(ISNUMBER(SEARCH("AHORRO",UPPER($B34))),"AHORRO",UPPER($B34)))),UPPER(Base_Cobranzas!$BB$2:$BB$814))),--(Base_Cobranzas!$AY$2:$AY$814>0),Base_Cobranzas!$AY$2:$AY$814),0) -> 51470 | G34: =IFERROR(SUMPRODUCT(--ISNUMBER(SEARCH($B$6,Base_Cobranzas!$A$2:$A$814)),--(Base_Cobranzas!$AR$2:$AR$814>=IF(G$33<3000,DATE(G$33,1,1),G$33)),--(Base_Cobranzas!$AR$2:$AR$814<IF(G$33<3000,DATE(G$33+1,1,1),EDATE(G$33,1))),--ISNUMBER(SEARCH(IF(ISNUMBER(SEARCH("DIRECTO",UPPER($B34))),"DIRECTO",IF(ISNUMBER(SEARCH("HIPOT",UPPER($B34))),"HIPOT",IF(ISNUMBER(SEARCH("AHORRO",UPPER($B34))),"AHORRO",UPPER($B34)))),UPPER(Base_Cobranzas!$BB$2:$BB$814))),--(Base_Cobranzas!$AY$2:$AY$814>0),Base_Cobranzas!$AY$2:$AY$814),0) -> 187590 | H34: =IFERROR(SUMPRODUCT(--ISNUMBER(SEARCH($B$6,Base_Cobranzas!$A$2:$A$814)),--(Base_Cobranzas!$AR$2:$AR$814>=IF(H$33<3000,DATE(H$33,1,1),H$33)),--(Base_Cobranzas!$AR$2:$AR$814<IF(H$33<3000,DATE(H$33+1,1,1),EDATE(H$33,1))),--ISNUMBER(SEARCH(IF(ISNUMBER(SEARCH("DIRECTO",UPPER($B34))),"DIRECTO",IF(ISNUMBER(SEARCH("HIPOT",UPPER($B34))),"HIPOT",IF(ISNUMBER(SEARCH("AHORRO",UPPER($B34))),"AHORRO",UPPER($B34)))),UPPER(Base_Cobranzas!$BB$2:$BB$814))),--(Base_Cobranzas!$AY$2:$AY$814>0),Base_Cobranzas!$AY$2:$AY$814),0) -> 512279.21 | I34: =IFERROR(SUMPRODUCT(--ISNUMBER(SEARCH($B$6,Base_Cobranzas!$A$2:$A$814)),--(Base_Cobranzas!$AR$2:$AR$814>=IF(I$33<3000,DATE(I$33,1,1),I$33)),--(Base_Cobranzas!$AR$2:$AR$814<IF(I$33<3000,DATE(I$33+1,1,1),EDATE(I$33,1))),--ISNUMBER(SEARCH(IF(ISNUMBER(SEARCH("DIRECTO",UPPER($B34))),"DIRECTO",IF(ISNUMBER(SEARCH("HIPOT",UPPER($B34))),"HIPOT",IF(ISNUMBER(SEARCH("AHORRO",UPPER($B34))),"AHORRO",UPPER($B34)))),UPPER(Base_Cobranzas!$BB$2:$BB$814))),--(Base_Cobranzas!$AY$2:$AY$814>0),Base_Cobranzas!$AY$2:$AY$814),0) -> 72000 | J34: =IFERROR(SUMPRODUCT(--ISNUMBER(SEARCH($B$6,Base_Cobranzas!$A$2:$A$814)),--(Base_Cobranzas!$AR$2:$AR$814>=IF(J$33<3000,DATE(J$33,1,1),J$33)),--(Base_Cobranzas!$AR$2:$AR$814<IF(J$33<3000,DATE(J$33+1,1,1),EDATE(J$33,1))),--ISNUMBER(SEARCH(IF(ISNUMBER(SEARCH("DIRECTO",UPPER($B34))),"DIRECTO",IF(ISNUMBER(SEARCH("HIPOT",UPPER($B34))),"HIPOT",IF(ISNUMBER(SEARCH("AHORRO",UPPER($B34))),"AHORRO",UPPER($B34)))),UPPER(Base_Cobranzas!$BB$2:$BB$814))),--(Base_Cobranzas!$AY$2:$AY$814>0),Base_Cobranzas!$AY$2:$AY$814),0) -> 47250 | ... L34: =IFERROR(SUMPRODUCT(--ISNUMBER(SEARCH($B$6,Base_Cobranzas!$A$2:$A$814)),--(Base_Cobranzas!$AR$2:$AR$814>=IF(L$33<3000,DATE(L$33,1,1),L$33)),--(Base_Cobranzas!$AR$2:$AR$814<IF(L$33<3000,DATE(L$33+1,1,1),EDATE(L$33,1))),--ISNUMBER(SEARCH(IF(ISNUMBER(SEARCH("DIRECTO",UPPER($B34))),"DIRECTO",IF(ISNUMBER(SEARCH("HIPOT",UPPER($B34))),"HIPOT",IF(ISNUMBER(SEARCH("AHORRO",UPPER($B34))),"AHORRO",UPPER($B34)))),UPPER(Base_Cobranzas!$BB$2:$BB$814))),--(Base_Cobranzas!$AY$2:$AY$814>0),Base_Cobranzas!$AY$2:$AY$814),0) -> 88432.49 | M34: =SUM(C34:L34) -> 2188609.5
B35: Crédito Hipotecario | C35: =IFERROR(SUMPRODUCT(--ISNUMBER(SEARCH($B$6,Base_Cobranzas!$A$2:$A$814)),--(Base_Cobranzas!$AR$2:$AR$814>=IF(C$33<3000,DATE(C$33,1,1),C$33)),--(Base_Cobranzas!$AR$2:$AR$814<IF(C$33<3000,DATE(C$33+1,1,1),EDATE(C$33,1))),--ISNUMBER(SEARCH(IF(ISNUMBER(SEARCH("DIRECTO",UPPER($B35))),"DIRECTO",IF(ISNUMBER(SEARCH("HIPOT",UPPER($B35))),"HIPOT",IF(ISNUMBER(SEARCH("AHORRO",UPPER($B35))),"AHORRO",UPPER($B35)))),UPPER(Base_Cobranzas!$BB$2:$BB$814))),--(Base_Cobranzas!$AY$2:$AY$814>0),Base_Cobranzas!$AY$2:$AY$814),0) -> 0 | D35: =IFERROR(SUMPRODUCT(--ISNUMBER(SEARCH($B$6,Base_Cobranzas!$A$2:$A$814)),--(Base_Cobranzas!$AR$2:$AR$814>=IF(D$33<3000,DATE(D$33,1,1),D$33)),--(Base_Cobranzas!$AR$2:$AR$814<IF(D$33<3000,DATE(D$33+1,1,1),EDATE(D$33,1))),--ISNUMBER(SEARCH(IF(ISNUMBER(SEARCH("DIRECTO",UPPER($B35))),"DIRECTO",IF(ISNUMBER(SEARCH("HIPOT",UPPER($B35))),"HIPOT",IF(ISNUMBER(SEARCH("AHORRO",UPPER($B35))),"AHORRO",UPPER($B35)))),UPPER(Base_Cobranzas!$BB$2:$BB$814))),--(Base_Cobranzas!$AY$2:$AY$814>0),Base_Cobranzas!$AY$2:$AY$814),0) -> 84500 | E35: =IFERROR(SUMPRODUCT(--ISNUMBER(SEARCH($B$6,Base_Cobranzas!$A$2:$A$814)),--(Base_Cobranzas!$AR$2:$AR$814>=IF(E$33<3000,DATE(E$33,1,1),E$33)),--(Base_Cobranzas!$AR$2:$AR$814<IF(E$33<3000,DATE(E$33+1,1,1),EDATE(E$33,1))),--ISNUMBER(SEARCH(IF(ISNUMBER(SEARCH("DIRECTO",UPPER($B35))),"DIRECTO",IF(ISNUMBER(SEARCH("HIPOT",UPPER($B35))),"HIPOT",IF(ISNUMBER(SEARCH("AHORRO",UPPER($B35))),"AHORRO",UPPER($B35)))),UPPER(Base_Cobranzas!$BB$2:$BB$814))),--(Base_Cobranzas!$AY$2:$AY$814>0),Base_Cobranzas!$AY$2:$AY$814),0) -> 148300 | F35: =IFERROR(SUMPRODUCT(--ISNUMBER(SEARCH($B$6,Base_Cobranzas!$A$2:$A$814)),--(Base_Cobranzas!$AR$2:$AR$814>=IF(F$33<3000,DATE(F$33,1,1),F$33)),--(Base_Cobranzas!$AR$2:$AR$814<IF(F$33<3000,DATE(F$33+1,1,1),EDATE(F$33,1))),--ISNUMBER(SEARCH(IF(ISNUMBER(SEARCH("DIRECTO",UPPER($B35))),"DIRECTO",IF(ISNUMBER(SEARCH("HIPOT",UPPER($B35))),"HIPOT",IF(ISNUMBER(SEARCH("AHORRO",UPPER($B35))),"AHORRO",UPPER($B35)))),UPPER(Base_Cobranzas!$BB$2:$BB$814))),--(Base_Cobranzas!$AY$2:$AY$814>0),Base_Cobranzas!$AY$2:$AY$814),0) -> 15000 | G35: =IFERROR(SUMPRODUCT(--ISNUMBER(SEARCH($B$6,Base_Cobranzas!$A$2:$A$814)),--(Base_Cobranzas!$AR$2:$AR$814>=IF(G$33<3000,DATE(G$33,1,1),G$33)),--(Base_Cobranzas!$AR$2:$AR$814<IF(G$33<3000,DATE(G$33+1,1,1),EDATE(G$33,1))),--ISNUMBER(SEARCH(IF(ISNUMBER(SEARCH("DIRECTO",UPPER($B35))),"DIRECTO",IF(ISNUMBER(SEARCH("HIPOT",UPPER($B35))),"HIPOT",IF(ISNUMBER(SEARCH("AHORRO",UPPER($B35))),"AHORRO",UPPER($B35)))),UPPER(Base_Cobranzas!$BB$2:$BB$814))),--(Base_Cobranzas!$AY$2:$AY$814>0),Base_Cobranzas!$AY$2:$AY$814),0) -> 49135 | H35: =IFERROR(SUMPRODUCT(--ISNUMBER(SEARCH($B$6,Base_Cobranzas!$A$2:$A$814)),--(Base_Cobranzas!$AR$2:$AR$814>=IF(H$33<3000,DATE(H$33,1,1),H$33)),--(Base_Cobranzas!$AR$2:$AR$814<IF(H$33<3000,DATE(H$33+1,1,1),EDATE(H$33,1))),--ISNUMBER(SEARCH(IF(ISNUMBER(SEARCH("DIRECTO",UPPER($B35))),"DIRECTO",IF(ISNUMBER(SEARCH("HIPOT",UPPER($B35))),"HIPOT",IF(ISNUMBER(SEARCH("AHORRO",UPPER($B35))),"AHORRO",UPPER($B35)))),UPPER(Base_Cobranzas!$BB$2:$BB$814))),--(Base_Cobranzas!$AY$2:$AY$814>0),Base_Cobranzas!$AY$2:$AY$814),0) -> 62135 | I35: =IFERROR(SUMPRODUCT(--ISNUMBER(SEARCH($B$6,Base_Cobranzas!$A$2:$A$814)),--(Base_Cobranzas!$AR$2:$AR$814>=IF(I$33<3000,DATE(I$33,1,1),I$33)),--(Base_Cobranzas!$AR$2:$AR$814<IF(I$33<3000,DATE(I$33+1,1,1),EDATE(I$33,1))),--ISNUMBER(SEARCH(IF(ISNUMBER(SEARCH("DIRECTO",UPPER($B35))),"DIRECTO",IF(ISNUMBER(SEARCH("HIPOT",UPPER($B35))),"HIPOT",IF(ISNUMBER(SEARCH("AHORRO",UPPER($B35))),"AHORRO",UPPER($B35)))),UPPER(Base_Cobranzas!$BB$2:$BB$814))),--(Base_Cobranzas!$AY$2:$AY$814>0),Base_Cobranzas!$AY$2:$AY$814),0) -> 8200 | J35: =IFERROR(SUMPRODUCT(--ISNUMBER(SEARCH($B$6,Base_Cobranzas!$A$2:$A$814)),--(Base_Cobranzas!$AR$2:$AR$814>=IF(J$33<3000,DATE(J$33,1,1),J$33)),--(Base_Cobranzas!$AR$2:$AR$814<IF(J$33<3000,DATE(J$33+1,1,1),EDATE(J$33,1))),--ISNUMBER(SEARCH(IF(ISNUMBER(SEARCH("DIRECTO",UPPER($B35))),"DIRECTO",IF(ISNUMBER(SEARCH("HIPOT",UPPER($B35))),"HIPOT",IF(ISNUMBER(SEARCH("AHORRO",UPPER($B35))),"AHORRO",UPPER($B35)))),UPPER(Base_Cobranzas!$BB$2:$BB$814))),--(Base_Cobranzas!$AY$2:$AY$814>0),Base_Cobranzas!$AY$2:$AY$814),0) -> 0 | ... L35: =IFERROR(SUMPRODUCT(--ISNUMBER(SEARCH($B$6,Base_Cobranzas!$A$2:$A$814)),--(Base_Cobranzas!$AR$2:$AR$814>=IF(L$33<3000,DATE(L$33,1,1),L$33)),--(Base_Cobranzas!$AR$2:$AR$814<IF(L$33<3000,DATE(L$33+1,1,1),EDATE(L$33,1))),--ISNUMBER(SEARCH(IF(ISNUMBER(SEARCH("DIRECTO",UPPER($B35))),"DIRECTO",IF(ISNUMBER(SEARCH("HIPOT",UPPER($B35))),"HIPOT",IF(ISNUMBER(SEARCH("AHORRO",UPPER($B35))),"AHORRO",UPPER($B35)))),UPPER(Base_Cobranzas!$BB$2:$BB$814))),--(Base_Cobranzas!$AY$2:$AY$814>0),Base_Cobranzas!$AY$2:$AY$814),0) -> 46000 | M35: =SUM(C35:L35) -> 423270
B36: Ahorro | C36: =IFERROR(SUMPRODUCT(--ISNUMBER(SEARCH($B$6,Base_Cobranzas!$A$2:$A$814)),--(Base_Cobranzas!$AR$2:$AR$814>=IF(C$33<3000,DATE(C$33,1,1),C$33)),--(Base_Cobranzas!$AR$2:$AR$814<IF(C$33<3000,DATE(C$33+1,1,1),EDATE(C$33,1))),--ISNUMBER(SEARCH(IF(ISNUMBER(SEARCH("DIRECTO",UPPER($B36))),"DIRECTO",IF(ISNUMBER(SEARCH("HIPOT",UPPER($B36))),"HIPOT",IF(ISNUMBER(SEARCH("AHORRO",UPPER($B36))),"AHORRO",UPPER($B36)))),UPPER(Base_Cobranzas!$BB$2:$BB$814))),--(Base_Cobranzas!$AY$2:$AY$814>0),Base_Cobranzas!$AY$2:$AY$814),0) -> 3000 | D36: =IFERROR(SUMPRODUCT(--ISNUMBER(SEARCH($B$6,Base_Cobranzas!$A$2:$A$814)),--(Base_Cobranzas!$AR$2:$AR$814>=IF(D$33<3000,DATE(D$33,1,1),D$33)),--(Base_Cobranzas!$AR$2:$AR$814<IF(D$33<3000,DATE(D$33+1,1,1),EDATE(D$33,1))),--ISNUMBER(SEARCH(IF(ISNUMBER(SEARCH("DIRECTO",UPPER($B36))),"DIRECTO",IF(ISNUMBER(SEARCH("HIPOT",UPPER($B36))),"HIPOT",IF(ISNUMBER(SEARCH("AHORRO",UPPER($B36))),"AHORRO",UPPER($B36)))),UPPER(Base_Cobranzas!$BB$2:$BB$814))),--(Base_Cobranzas!$AY$2:$AY$814>0),Base_Cobranzas!$AY$2:$AY$814),0) -> 456315 | E36: =IFERROR(SUMPRODUCT(--ISNUMBER(SEARCH($B$6,Base_Cobranzas!$A$2:$A$814)),--(Base_Cobranzas!$AR$2:$AR$814>=IF(E$33<3000,DATE(E$33,1,1),E$33)),--(Base_Cobranzas!$AR$2:$AR$814<IF(E$33<3000,DATE(E$33+1,1,1),EDATE(E$33,1))),--ISNUMBER(SEARCH(IF(ISNUMBER(SEARCH("DIRECTO",UPPER($B36))),"DIRECTO",IF(ISNUMBER(SEARCH("HIPOT",UPPER($B36))),"HIPOT",IF(ISNUMBER(SEARCH("AHORRO",UPPER($B36))),"AHORRO",UPPER($B36)))),UPPER(Base_Cobranzas!$BB$2:$BB$814))),--(Base_Cobranzas!$AY$2:$AY$814>0),Base_Cobranzas!$AY$2:$AY$814),0) -> 0 | F36: =IFERROR(SUMPRODUCT(--ISNUMBER(SEARCH($B$6,Base_Cobranzas!$A$2:$A$814)),--(Base_Cobranzas!$AR$2:$AR$814>=IF(F$33<3000,DATE(F$33,1,1),F$33)),--(Base_Cobranzas!$AR$2:$AR$814<IF(F$33<3000,DATE(F$33+1,1,1),EDATE(F$33,1))),--ISNUMBER(SEARCH(IF(ISNUMBER(SEARCH("DIRECTO",UPPER($B36))),"DIRECTO",IF(ISNUMBER(SEARCH("HIPOT",UPPER($B36))),"HIPOT",IF(ISNUMBER(SEARCH("AHORRO",UPPER($B36))),"AHORRO",UPPER($B36)))),UPPER(Base_Cobranzas!$BB$2:$BB$814))),--(Base_Cobranzas!$AY$2:$AY$814>0),Base_Cobranzas!$AY$2:$AY$814),0) -> 74400 | G36: =IFERROR(SUMPRODUCT(--ISNUMBER(SEARCH($B$6,Base_Cobranzas!$A$2:$A$814)),--(Base_Cobranzas!$AR$2:$AR$814>=IF(G$33<3000,DATE(G$33,1,1),G$33)),--(Base_Cobranzas!$AR$2:$AR$814<IF(G$33<3000,DATE(G$33+1,1,1),EDATE(G$33,1))),--ISNUMBER(SEARCH(IF(ISNUMBER(SEARCH("DIRECTO",UPPER($B36))),"DIRECTO",IF(ISNUMBER(SEARCH("HIPOT",UPPER($B36))),"HIPOT",IF(ISNUMBER(SEARCH("AHORRO",UPPER($B36))),"AHORRO",UPPER($B36)))),UPPER(Base_Cobranzas!$BB$2:$BB$814))),--(Base_Cobranzas!$AY$2:$AY$814>0),Base_Cobranzas!$AY$2:$AY$814),0) -> 151688 | H36: =IFERROR(SUMPRODUCT(--ISNUMBER(SEARCH($B$6,Base_Cobranzas!$A$2:$A$814)),--(Base_Cobranzas!$AR$2:$AR$814>=IF(H$33<3000,DATE(H$33,1,1),H$33)),--(Base_Cobranzas!$AR$2:$AR$814<IF(H$33<3000,DATE(H$33+1,1,1),EDATE(H$33,1))),--ISNUMBER(SEARCH(IF(ISNUMBER(SEARCH("DIRECTO",UPPER($B36))),"DIRECTO",IF(ISNUMBER(SEARCH("HIPOT",UPPER($B36))),"HIPOT",IF(ISNUMBER(SEARCH("AHORRO",UPPER($B36))),"AHORRO",UPPER($B36)))),UPPER(Base_Cobranzas!$BB$2:$BB$814))),--(Base_Cobranzas!$AY$2:$AY$814>0),Base_Cobranzas!$AY$2:$AY$814),0) -> 382388 | I36: =IFERROR(SUMPRODUCT(--ISNUMBER(SEARCH($B$6,Base_Cobranzas!$A$2:$A$814)),--(Base_Cobranzas!$AR$2:$AR$814>=IF(I$33<3000,DATE(I$33,1,1),I$33)),--(Base_Cobranzas!$AR$2:$AR$814<IF(I$33<3000,DATE(I$33+1,1,1),EDATE(I$33,1))),--ISNUMBER(SEARCH(IF(ISNUMBER(SEARCH("DIRECTO",UPPER($B36))),"DIRECTO",IF(ISNUMBER(SEARCH("HIPOT",UPPER($B36))),"HIPOT",IF(ISNUMBER(SEARCH("AHORRO",UPPER($B36))),"AHORRO",UPPER($B36)))),UPPER(Base_Cobranzas!$BB$2:$BB$814))),--(Base_Cobranzas!$AY$2:$AY$814>0),Base_Cobranzas!$AY$2:$AY$814),0) -> 470520 | J36: =IFERROR(SUMPRODUCT(--ISNUMBER(SEARCH($B$6,Base_Cobranzas!$A$2:$A$814)),--(Base_Cobranzas!$AR$2:$AR$814>=IF(J$33<3000,DATE(J$33,1,1),J$33)),--(Base_Cobranzas!$AR$2:$AR$814<IF(J$33<3000,DATE(J$33+1,1,1),EDATE(J$33,1))),--ISNUMBER(SEARCH(IF(ISNUMBER(SEARCH("DIRECTO",UPPER($B36))),"DIRECTO",IF(ISNUMBER(SEARCH("HIPOT",UPPER($B36))),"HIPOT",IF(ISNUMBER(SEARCH("AHORRO",UPPER($B36))),"AHORRO",UPPER($B36)))),UPPER(Base_Cobranzas!$BB$2:$BB$814))),--(Base_Cobranzas!$AY$2:$AY$814>0),Base_Cobranzas!$AY$2:$AY$814),0) -> 173165 | ... L36: =IFERROR(SUMPRODUCT(--ISNUMBER(SEARCH($B$6,Base_Cobranzas!$A$2:$A$814)),--(Base_Cobranzas!$AR$2:$AR$814>=IF(L$33<3000,DATE(L$33,1,1),L$33)),--(Base_Cobranzas!$AR$2:$AR$814<IF(L$33<3000,DATE(L$33+1,1,1),EDATE(L$33,1))),--ISNUMBER(SEARCH(IF(ISNUMBER(SEARCH("DIRECTO",UPPER($B36))),"DIRECTO",IF(ISNUMBER(SEARCH("HIPOT",UPPER($B36))),"HIPOT",IF(ISNUMBER(SEARCH("AHORRO",UPPER($B36))),"AHORRO",UPPER($B36)))),UPPER(Base_Cobranzas!$BB$2:$BB$814))),--(Base_Cobranzas!$AY$2:$AY$814>0),Base_Cobranzas!$AY$2:$AY$814),0) -> 65120 | M36: =SUM(C36:L36) -> 1827546
B37: Total | C37: =SUM(C34:C36) -> 6000 | D37: =SUM(D34:D36) -> 1550131.9 | E37: =SUM(E34:E36) -> 306300 | F37: =SUM(F34:F36) -> 140870 | G37: =SUM(G34:G36) -> 388413 | H37: =SUM(H34:H36) -> 956802.21 | I37: =SUM(I34:I36) -> 550720 | J37: =SUM(J34:J36) -> 220415 | ... L37: =SUM(L34:L36) -> 199552.49 | M37: =SUM(C37:L37) -> 4439425.5 | N37: =IF($G$21=M37,"OK","REVISAR") -> OK
B39: Acumulado | C39: =C37 -> 6000 | D39: =C39+D37 -> 1556131.9 | E39: =D39+E37 -> 1862431.9 | F39: =E39+F37 -> 2003301.9 | G39: =F39+G37 -> 2391714.9 | H39: =G39+H37 -> 3348517.1 | I39: =H39+I37 -> 3899237.1 | J39: =I39+J37 -> 4119652.1 | K39: =J39+K37 -> 4239873 | L39: =K39+L37 -> 4439425.5
B43: COBRANZA PROYECTADA
B45: Tipo de Credito | C45: 46266 | D45: 46296 | E45: 46327 | F45: 46357 | G45: 46388 | H45: 46419 | I45: 46447 | J45: 46478 | K45: 46508 | L45: 46539 | M45: 46569 | N45: 46600 | O45: 46631 | P45: 46661 | Q45: 46692 | R45: Total
B46: Crédito Directo | C46: =IFERROR(SUMPRODUCT(--ISNUMBER(SEARCH($B$6,Base_Cobranzas!$A$2:$A$814)),--(Base_Cobranzas!$AQ$2:$AQ$814>=IF(C$45<3000,DATE(C$45,1,1),C$45)),--(Base_Cobranzas!$AQ$2:$AQ$814<IF(C$45<3000,DATE(C$45+1,1,1),EDATE(C$45,1))),--ISNUMBER(SEARCH(IF(ISNUMBER(SEARCH("DIRECTO",UPPER($B46))),"DIRECTO",IF(ISNUMBER(SEARCH("HIPOT",UPPER($B46))),"HIPOT",IF(ISNUMBER(SEARCH("AHORRO",UPPER($B46))),"AHORRO",UPPER($B46)))),UPPER(Base_Cobranzas!$BB$2:$BB$814))),--ISNUMBER(SEARCH("PENDIENTE",UPPER(TRIM(Base_Cobranzas!$BK$2:$BK$814)))),Base_Cobranzas!$AZ$2:$AZ$814),0) -> 361279.66 | D46: =IFERROR(SUMPRODUCT(--ISNUMBER(SEARCH($B$6,Base_Cobranzas!$A$2:$A$814)),--(Base_Cobranzas!$AQ$2:$AQ$814>=IF(D$45<3000,DATE(D$45,1,1),D$45)),--(Base_Cobranzas!$AQ$2:$AQ$814<IF(D$45<3000,DATE(D$45+1,1,1),EDATE(D$45,1))),--ISNUMBER(SEARCH(IF(ISNUMBER(SEARCH("DIRECTO",UPPER($B46))),"DIRECTO",IF(ISNUMBER(SEARCH("HIPOT",UPPER($B46))),"HIPOT",IF(ISNUMBER(SEARCH("AHORRO",UPPER($B46))),"AHORRO",UPPER($B46)))),UPPER(Base_Cobranzas!$BB$2:$BB$814))),--ISNUMBER(SEARCH("PENDIENTE",UPPER(TRIM(Base_Cobranzas!$BK$2:$BK$814)))),Base_Cobranzas!$AZ$2:$AZ$814),0) -> 79279.66 | E46: =IFERROR(SUMPRODUCT(--ISNUMBER(SEARCH($B$6,Base_Cobranzas!$A$2:$A$814)),--(Base_Cobranzas!$AQ$2:$AQ$814>=IF(E$45<3000,DATE(E$45,1,1),E$45)),--(Base_Cobranzas!$AQ$2:$AQ$814<IF(E$45<3000,DATE(E$45+1,1,1),EDATE(E$45,1))),--ISNUMBER(SEARCH(IF(ISNUMBER(SEARCH("DIRECTO",UPPER($B46))),"DIRECTO",IF(ISNUMBER(SEARCH("HIPOT",UPPER($B46))),"HIPOT",IF(ISNUMBER(SEARCH("AHORRO",UPPER($B46))),"AHORRO",UPPER($B46)))),UPPER(Base_Cobranzas!$BB$2:$BB$814))),--ISNUMBER(SEARCH("PENDIENTE",UPPER(TRIM(Base_Cobranzas!$BK$2:$BK$814)))),Base_Cobranzas!$AZ$2:$AZ$814),0) -> 79279.66 | F46: =IFERROR(SUMPRODUCT(--ISNUMBER(SEARCH($B$6,Base_Cobranzas!$A$2:$A$814)),--(Base_Cobranzas!$AQ$2:$AQ$814>=IF(F$45<3000,DATE(F$45,1,1),F$45)),--(Base_Cobranzas!$AQ$2:$AQ$814<IF(F$45<3000,DATE(F$45+1,1,1),EDATE(F$45,1))),--ISNUMBER(SEARCH(IF(ISNUMBER(SEARCH("DIRECTO",UPPER($B46))),"DIRECTO",IF(ISNUMBER(SEARCH("HIPOT",UPPER($B46))),"HIPOT",IF(ISNUMBER(SEARCH("AHORRO",UPPER($B46))),"AHORRO",UPPER($B46)))),UPPER(Base_Cobranzas!$BB$2:$BB$814))),--ISNUMBER(SEARCH("PENDIENTE",UPPER(TRIM(Base_Cobranzas!$BK$2:$BK$814)))),Base_Cobranzas!$AZ$2:$AZ$814),0) -> 209339.66 | G46: =IFERROR(SUMPRODUCT(--ISNUMBER(SEARCH($B$6,Base_Cobranzas!$A$2:$A$814)),--(Base_Cobranzas!$AQ$2:$AQ$814>=IF(G$45<3000,DATE(G$45,1,1),G$45)),--(Base_Cobranzas!$AQ$2:$AQ$814<IF(G$45<3000,DATE(G$45+1,1,1),EDATE(G$45,1))),--ISNUMBER(SEARCH(IF(ISNUMBER(SEARCH("DIRECTO",UPPER($B46))),"DIRECTO",IF(ISNUMBER(SEARCH("HIPOT",UPPER($B46))),"HIPOT",IF(ISNUMBER(SEARCH("AHORRO",UPPER($B46))),"AHORRO",UPPER($B46)))),UPPER(Base_Cobranzas!$BB$2:$BB$814))),--ISNUMBER(SEARCH("PENDIENTE",UPPER(TRIM(Base_Cobranzas!$BK$2:$BK$814)))),Base_Cobranzas!$AZ$2:$AZ$814),0) -> 79279.66 | H46: =IFERROR(SUMPRODUCT(--ISNUMBER(SEARCH($B$6,Base_Cobranzas!$A$2:$A$814)),--(Base_Cobranzas!$AQ$2:$AQ$814>=IF(H$45<3000,DATE(H$45,1,1),H$45)),--(Base_Cobranzas!$AQ$2:$AQ$814<IF(H$45<3000,DATE(H$45+1,1,1),EDATE(H$45,1))),--ISNUMBER(SEARCH(IF(ISNUMBER(SEARCH("DIRECTO",UPPER($B46))),"DIRECTO",IF(ISNUMBER(SEARCH("HIPOT",UPPER($B46))),"HIPOT",IF(ISNUMBER(SEARCH("AHORRO",UPPER($B46))),"AHORRO",UPPER($B46)))),UPPER(Base_Cobranzas!$BB$2:$BB$814))),--ISNUMBER(SEARCH("PENDIENTE",UPPER(TRIM(Base_Cobranzas!$BK$2:$BK$814)))),Base_Cobranzas!$AZ$2:$AZ$814),0) -> 129279.66 | I46: =IFERROR(SUMPRODUCT(--ISNUMBER(SEARCH($B$6,Base_Cobranzas!$A$2:$A$814)),--(Base_Cobranzas!$AQ$2:$AQ$814>=IF(I$45<3000,DATE(I$45,1,1),I$45)),--(Base_Cobranzas!$AQ$2:$AQ$814<IF(I$45<3000,DATE(I$45+1,1,1),EDATE(I$45,1))),--ISNUMBER(SEARCH(IF(ISNUMBER(SEARCH("DIRECTO",UPPER($B46))),"DIRECTO",IF(ISNUMBER(SEARCH("HIPOT",UPPER($B46))),"HIPOT",IF(ISNUMBER(SEARCH("AHORRO",UPPER($B46))),"AHORRO",UPPER($B46)))),UPPER(Base_Cobranzas!$BB$2:$BB$814))),--ISNUMBER(SEARCH("PENDIENTE",UPPER(TRIM(Base_Cobranzas!$BK$2:$BK$814)))),Base_Cobranzas!$AZ$2:$AZ$814),0) -> 79279.66 | J46: =IFERROR(SUMPRODUCT(--ISNUMBER(SEARCH($B$6,Base_Cobranzas!$A$2:$A$814)),--(Base_Cobranzas!$AQ$2:$AQ$814>=IF(J$45<3000,DATE(J$45,1,1),J$45)),--(Base_Cobranzas!$AQ$2:$AQ$814<IF(J$45<3000,DATE(J$45+1,1,1),EDATE(J$45,1))),--ISNUMBER(SEARCH(IF(ISNUMBER(SEARCH("DIRECTO",UPPER($B46))),"DIRECTO",IF(ISNUMBER(SEARCH("HIPOT",UPPER($B46))),"HIPOT",IF(ISNUMBER(SEARCH("AHORRO",UPPER($B46))),"AHORRO",UPPER($B46)))),UPPER(Base_Cobranzas!$BB$2:$BB$814))),--ISNUMBER(SEARCH("PENDIENTE",UPPER(TRIM(Base_Cobranzas!$BK$2:$BK$814)))),Base_Cobranzas!$AZ$2:$AZ$814),0) -> 79279.7 | ... Q46: =IFERROR(SUMPRODUCT(--ISNUMBER(SEARCH($B$6,Base_Cobranzas!$A$2:$A$814)),--(Base_Cobranzas!$AQ$2:$AQ$814>=IF(Q$45<3000,DATE(Q$45,1,1),Q$45)),--(Base_Cobranzas!$AQ$2:$AQ$814<IF(Q$45<3000,DATE(Q$45+1,1,1),EDATE(Q$45,1))),--ISNUMBER(SEARCH(IF(ISNUMBER(SEARCH("DIRECTO",UPPER($B46))),"DIRECTO",IF(ISNUMBER(SEARCH("HIPOT",UPPER($B46))),"HIPOT",IF(ISNUMBER(SEARCH("AHORRO",UPPER($B46))),"AHORRO",UPPER($B46)))),UPPER(Base_Cobranzas!$BB$2:$BB$814))),--ISNUMBER(SEARCH("PENDIENTE",UPPER(TRIM(Base_Cobranzas!$BK$2:$BK$814)))),Base_Cobranzas!$AZ$2:$AZ$814),0) -> 38000 | R46: =SUM(C46:Q46) -> 2378528.2
B47: Crédito Hipotecario | C47: =IFERROR(SUMPRODUCT(--ISNUMBER(SEARCH($B$6,Base_Cobranzas!$A$2:$A$814)),--(Base_Cobranzas!$AQ$2:$AQ$814>=IF(C$45<3000,DATE(C$45,1,1),C$45)),--(Base_Cobranzas!$AQ$2:$AQ$814<IF(C$45<3000,DATE(C$45+1,1,1),EDATE(C$45,1))),--ISNUMBER(SEARCH(IF(ISNUMBER(SEARCH("DIRECTO",UPPER($B47))),"DIRECTO",IF(ISNUMBER(SEARCH("HIPOT",UPPER($B47))),"HIPOT",IF(ISNUMBER(SEARCH("AHORRO",UPPER($B47))),"AHORRO",UPPER($B47)))),UPPER(Base_Cobranzas!$BB$2:$BB$814))),--ISNUMBER(SEARCH("PENDIENTE",UPPER(TRIM(Base_Cobranzas!$BK$2:$BK$814)))),Base_Cobranzas!$AZ$2:$AZ$814),0) -> 0 | D47: =IFERROR(SUMPRODUCT(--ISNUMBER(SEARCH($B$6,Base_Cobranzas!$A$2:$A$814)),--(Base_Cobranzas!$AQ$2:$AQ$814>=IF(D$45<3000,DATE(D$45,1,1),D$45)),--(Base_Cobranzas!$AQ$2:$AQ$814<IF(D$45<3000,DATE(D$45+1,1,1),EDATE(D$45,1))),--ISNUMBER(SEARCH(IF(ISNUMBER(SEARCH("DIRECTO",UPPER($B47))),"DIRECTO",IF(ISNUMBER(SEARCH("HIPOT",UPPER($B47))),"HIPOT",IF(ISNUMBER(SEARCH("AHORRO",UPPER($B47))),"AHORRO",UPPER($B47)))),UPPER(Base_Cobranzas!$BB$2:$BB$814))),--ISNUMBER(SEARCH("PENDIENTE",UPPER(TRIM(Base_Cobranzas!$BK$2:$BK$814)))),Base_Cobranzas!$AZ$2:$AZ$814),0) -> 478800 | E47: =IFERROR(SUMPRODUCT(--ISNUMBER(SEARCH($B$6,Base_Cobranzas!$A$2:$A$814)),--(Base_Cobranzas!$AQ$2:$AQ$814>=IF(E$45<3000,DATE(E$45,1,1),E$45)),--(Base_Cobranzas!$AQ$2:$AQ$814<IF(E$45<3000,DATE(E$45+1,1,1),EDATE(E$45,1))),--ISNUMBER(SEARCH(IF(ISNUMBER(SEARCH("DIRECTO",UPPER($B47))),"DIRECTO",IF(ISNUMBER(SEARCH("HIPOT",UPPER($B47))),"HIPOT",IF(ISNUMBER(SEARCH("AHORRO",UPPER($B47))),"AHORRO",UPPER($B47)))),UPPER(Base_Cobranzas!$BB$2:$BB$814))),--ISNUMBER(SEARCH("PENDIENTE",UPPER(TRIM(Base_Cobranzas!$BK$2:$BK$814)))),Base_Cobranzas!$AZ$2:$AZ$814),0) -> 0 | F47: =IFERROR(SUMPRODUCT(--ISNUMBER(SEARCH($B$6,Base_Cobranzas!$A$2:$A$814)),--(Base_Cobranzas!$AQ$2:$AQ$814>=IF(F$45<3000,DATE(F$45,1,1),F$45)),--(Base_Cobranzas!$AQ$2:$AQ$814<IF(F$45<3000,DATE(F$45+1,1,1),EDATE(F$45,1))),--ISNUMBER(SEARCH(IF(ISNUMBER(SEARCH("DIRECTO",UPPER($B47))),"DIRECTO",IF(ISNUMBER(SEARCH("HIPOT",UPPER($B47))),"HIPOT",IF(ISNUMBER(SEARCH("AHORRO",UPPER($B47))),"AHORRO",UPPER($B47)))),UPPER(Base_Cobranzas!$BB$2:$BB$814))),--ISNUMBER(SEARCH("PENDIENTE",UPPER(TRIM(Base_Cobranzas!$BK$2:$BK$814)))),Base_Cobranzas!$AZ$2:$AZ$814),0) -> 107750 | G47: =IFERROR(SUMPRODUCT(--ISNUMBER(SEARCH($B$6,Base_Cobranzas!$A$2:$A$814)),--(Base_Cobranzas!$AQ$2:$AQ$814>=IF(G$45<3000,DATE(G$45,1,1),G$45)),--(Base_Cobranzas!$AQ$2:$AQ$814<IF(G$45<3000,DATE(G$45+1,1,1),EDATE(G$45,1))),--ISNUMBER(SEARCH(IF(ISNUMBER(SEARCH("DIRECTO",UPPER($B47))),"DIRECTO",IF(ISNUMBER(SEARCH("HIPOT",UPPER($B47))),"HIPOT",IF(ISNUMBER(SEARCH("AHORRO",UPPER($B47))),"AHORRO",UPPER($B47)))),UPPER(Base_Cobranzas!$BB$2:$BB$814))),--ISNUMBER(SEARCH("PENDIENTE",UPPER(TRIM(Base_Cobranzas!$BK$2:$BK$814)))),Base_Cobranzas!$AZ$2:$AZ$814),0) -> 0 | H47: =IFERROR(SUMPRODUCT(--ISNUMBER(SEARCH($B$6,Base_Cobranzas!$A$2:$A$814)),--(Base_Cobranzas!$AQ$2:$AQ$814>=IF(H$45<3000,DATE(H$45,1,1),H$45)),--(Base_Cobranzas!$AQ$2:$AQ$814<IF(H$45<3000,DATE(H$45+1,1,1),EDATE(H$45,1))),--ISNUMBER(SEARCH(IF(ISNUMBER(SEARCH("DIRECTO",UPPER($B47))),"DIRECTO",IF(ISNUMBER(SEARCH("HIPOT",UPPER($B47))),"HIPOT",IF(ISNUMBER(SEARCH("AHORRO",UPPER($B47))),"AHORRO",UPPER($B47)))),UPPER(Base_Cobranzas!$BB$2:$BB$814))),--ISNUMBER(SEARCH("PENDIENTE",UPPER(TRIM(Base_Cobranzas!$BK$2:$BK$814)))),Base_Cobranzas!$AZ$2:$AZ$814),0) -> 0 | I47: =IFERROR(SUMPRODUCT(--ISNUMBER(SEARCH($B$6,Base_Cobranzas!$A$2:$A$814)),--(Base_Cobranzas!$AQ$2:$AQ$814>=IF(I$45<3000,DATE(I$45,1,1),I$45)),--(Base_Cobranzas!$AQ$2:$AQ$814<IF(I$45<3000,DATE(I$45+1,1,1),EDATE(I$45,1))),--ISNUMBER(SEARCH(IF(ISNUMBER(SEARCH("DIRECTO",UPPER($B47))),"DIRECTO",IF(ISNUMBER(SEARCH("HIPOT",UPPER($B47))),"HIPOT",IF(ISNUMBER(SEARCH("AHORRO",UPPER($B47))),"AHORRO",UPPER($B47)))),UPPER(Base_Cobranzas!$BB$2:$BB$814))),--ISNUMBER(SEARCH("PENDIENTE",UPPER(TRIM(Base_Cobranzas!$BK$2:$BK$814)))),Base_Cobranzas!$AZ$2:$AZ$814),0) -> 107750 | J47: =IFERROR(SUMPRODUCT(--ISNUMBER(SEARCH($B$6,Base_Cobranzas!$A$2:$A$814)),--(Base_Cobranzas!$AQ$2:$AQ$814>=IF(J$45<3000,DATE(J$45,1,1),J$45)),--(Base_Cobranzas!$AQ$2:$AQ$814<IF(J$45<3000,DATE(J$45+1,1,1),EDATE(J$45,1))),--ISNUMBER(SEARCH(IF(ISNUMBER(SEARCH("DIRECTO",UPPER($B47))),"DIRECTO",IF(ISNUMBER(SEARCH("HIPOT",UPPER($B47))),"HIPOT",IF(ISNUMBER(SEARCH("AHORRO",UPPER($B47))),"AHORRO",UPPER($B47)))),UPPER(Base_Cobranzas!$BB$2:$BB$814))),--ISNUMBER(SEARCH("PENDIENTE",UPPER(TRIM(Base_Cobranzas!$BK$2:$BK$814)))),Base_Cobranzas!$AZ$2:$AZ$814),0) -> 0 | ... Q47: =IFERROR(SUMPRODUCT(--ISNUMBER(SEARCH($B$6,Base_Cobranzas!$A$2:$A$814)),--(Base_Cobranzas!$AQ$2:$AQ$814>=IF(Q$45<3000,DATE(Q$45,1,1),Q$45)),--(Base_Cobranzas!$AQ$2:$AQ$814<IF(Q$45<3000,DATE(Q$45+1,1,1),EDATE(Q$45,1))),--ISNUMBER(SEARCH(IF(ISNUMBER(SEARCH("DIRECTO",UPPER($B47))),"DIRECTO",IF(ISNUMBER(SEARCH("HIPOT",UPPER($B47))),"HIPOT",IF(ISNUMBER(SEARCH("AHORRO",UPPER($B47))),"AHORRO",UPPER($B47)))),UPPER(Base_Cobranzas!$BB$2:$BB$814))),--ISNUMBER(SEARCH("PENDIENTE",UPPER(TRIM(Base_Cobranzas!$BK$2:$BK$814)))),Base_Cobranzas!$AZ$2:$AZ$814),0) -> 0 | R47: =SUM(C47:Q47) -> 802050
B48: Ahorro | C48: =IFERROR(SUMPRODUCT(--ISNUMBER(SEARCH($B$6,Base_Cobranzas!$A$2:$A$814)),--(Base_Cobranzas!$AQ$2:$AQ$814>=IF(C$45<3000,DATE(C$45,1,1),C$45)),--(Base_Cobranzas!$AQ$2:$AQ$814<IF(C$45<3000,DATE(C$45+1,1,1),EDATE(C$45,1))),--ISNUMBER(SEARCH(IF(ISNUMBER(SEARCH("DIRECTO",UPPER($B48))),"DIRECTO",IF(ISNUMBER(SEARCH("HIPOT",UPPER($B48))),"HIPOT",IF(ISNUMBER(SEARCH("AHORRO",UPPER($B48))),"AHORRO",UPPER($B48)))),UPPER(Base_Cobranzas!$BB$2:$BB$814))),--ISNUMBER(SEARCH("PENDIENTE",UPPER(TRIM(Base_Cobranzas!$BK$2:$BK$814)))),Base_Cobranzas!$AZ$2:$AZ$814),0) -> 1066649 | D48: =IFERROR(SUMPRODUCT(--ISNUMBER(SEARCH($B$6,Base_Cobranzas!$A$2:$A$814)),--(Base_Cobranzas!$AQ$2:$AQ$814>=IF(D$45<3000,DATE(D$45,1,1),D$45)),--(Base_Cobranzas!$AQ$2:$AQ$814<IF(D$45<3000,DATE(D$45+1,1,1),EDATE(D$45,1))),--ISNUMBER(SEARCH(IF(ISNUMBER(SEARCH("DIRECTO",UPPER($B48))),"DIRECTO",IF(ISNUMBER(SEARCH("HIPOT",UPPER($B48))),"HIPOT",IF(ISNUMBER(SEARCH("AHORRO",UPPER($B48))),"AHORRO",UPPER($B48)))),UPPER(Base_Cobranzas!$BB$2:$BB$814))),--ISNUMBER(SEARCH("PENDIENTE",UPPER(TRIM(Base_Cobranzas!$BK$2:$BK$814)))),Base_Cobranzas!$AZ$2:$AZ$814),0) -> 105880 | E48: =IFERROR(SUMPRODUCT(--ISNUMBER(SEARCH($B$6,Base_Cobranzas!$A$2:$A$814)),--(Base_Cobranzas!$AQ$2:$AQ$814>=IF(E$45<3000,DATE(E$45,1,1),E$45)),--(Base_Cobranzas!$AQ$2:$AQ$814<IF(E$45<3000,DATE(E$45+1,1,1),EDATE(E$45,1))),--ISNUMBER(SEARCH(IF(ISNUMBER(SEARCH("DIRECTO",UPPER($B48))),"DIRECTO",IF(ISNUMBER(SEARCH("HIPOT",UPPER($B48))),"HIPOT",IF(ISNUMBER(SEARCH("AHORRO",UPPER($B48))),"AHORRO",UPPER($B48)))),UPPER(Base_Cobranzas!$BB$2:$BB$814))),--ISNUMBER(SEARCH("PENDIENTE",UPPER(TRIM(Base_Cobranzas!$BK$2:$BK$814)))),Base_Cobranzas!$AZ$2:$AZ$814),0) -> 914385 | F48: =IFERROR(SUMPRODUCT(--ISNUMBER(SEARCH($B$6,Base_Cobranzas!$A$2:$A$814)),--(Base_Cobranzas!$AQ$2:$AQ$814>=IF(F$45<3000,DATE(F$45,1,1),F$45)),--(Base_Cobranzas!$AQ$2:$AQ$814<IF(F$45<3000,DATE(F$45+1,1,1),EDATE(F$45,1))),--ISNUMBER(SEARCH(IF(ISNUMBER(SEARCH("DIRECTO",UPPER($B48))),"DIRECTO",IF(ISNUMBER(SEARCH("HIPOT",UPPER($B48))),"HIPOT",IF(ISNUMBER(SEARCH("AHORRO",UPPER($B48))),"AHORRO",UPPER($B48)))),UPPER(Base_Cobranzas!$BB$2:$BB$814))),--ISNUMBER(SEARCH("PENDIENTE",UPPER(TRIM(Base_Cobranzas!$BK$2:$BK$814)))),Base_Cobranzas!$AZ$2:$AZ$814),0) -> 711425 | G48: =IFERROR(SUMPRODUCT(--ISNUMBER(SEARCH($B$6,Base_Cobranzas!$A$2:$A$814)),--(Base_Cobranzas!$AQ$2:$AQ$814>=IF(G$45<3000,DATE(G$45,1,1),G$45)),--(Base_Cobranzas!$AQ$2:$AQ$814<IF(G$45<3000,DATE(G$45+1,1,1),EDATE(G$45,1))),--ISNUMBER(SEARCH(IF(ISNUMBER(SEARCH("DIRECTO",UPPER($B48))),"DIRECTO",IF(ISNUMBER(SEARCH("HIPOT",UPPER($B48))),"HIPOT",IF(ISNUMBER(SEARCH("AHORRO",UPPER($B48))),"AHORRO",UPPER($B48)))),UPPER(Base_Cobranzas!$BB$2:$BB$814))),--ISNUMBER(SEARCH("PENDIENTE",UPPER(TRIM(Base_Cobranzas!$BK$2:$BK$814)))),Base_Cobranzas!$AZ$2:$AZ$814),0) -> 1247430 | H48: =IFERROR(SUMPRODUCT(--ISNUMBER(SEARCH($B$6,Base_Cobranzas!$A$2:$A$814)),--(Base_Cobranzas!$AQ$2:$AQ$814>=IF(H$45<3000,DATE(H$45,1,1),H$45)),--(Base_Cobranzas!$AQ$2:$AQ$814<IF(H$45<3000,DATE(H$45+1,1,1),EDATE(H$45,1))),--ISNUMBER(SEARCH(IF(ISNUMBER(SEARCH("DIRECTO",UPPER($B48))),"DIRECTO",IF(ISNUMBER(SEARCH("HIPOT",UPPER($B48))),"HIPOT",IF(ISNUMBER(SEARCH("AHORRO",UPPER($B48))),"AHORRO",UPPER($B48)))),UPPER(Base_Cobranzas!$BB$2:$BB$814))),--ISNUMBER(SEARCH("PENDIENTE",UPPER(TRIM(Base_Cobranzas!$BK$2:$BK$814)))),Base_Cobranzas!$AZ$2:$AZ$814),0) -> 816935 | I48: =IFERROR(SUMPRODUCT(--ISNUMBER(SEARCH($B$6,Base_Cobranzas!$A$2:$A$814)),--(Base_Cobranzas!$AQ$2:$AQ$814>=IF(I$45<3000,DATE(I$45,1,1),I$45)),--(Base_Cobranzas!$AQ$2:$AQ$814<IF(I$45<3000,DATE(I$45+1,1,1),EDATE(I$45,1))),--ISNUMBER(SEARCH(IF(ISNUMBER(SEARCH("DIRECTO",UPPER($B48))),"DIRECTO",IF(ISNUMBER(SEARCH("HIPOT",UPPER($B48))),"HIPOT",IF(ISNUMBER(SEARCH("AHORRO",UPPER($B48))),"AHORRO",UPPER($B48)))),UPPER(Base_Cobranzas!$BB$2:$BB$814))),--ISNUMBER(SEARCH("PENDIENTE",UPPER(TRIM(Base_Cobranzas!$BK$2:$BK$814)))),Base_Cobranzas!$AZ$2:$AZ$814),0) -> 549365 | J48: =IFERROR(SUMPRODUCT(--ISNUMBER(SEARCH($B$6,Base_Cobranzas!$A$2:$A$814)),--(Base_Cobranzas!$AQ$2:$AQ$814>=IF(J$45<3000,DATE(J$45,1,1),J$45)),--(Base_Cobranzas!$AQ$2:$AQ$814<IF(J$45<3000,DATE(J$45+1,1,1),EDATE(J$45,1))),--ISNUMBER(SEARCH(IF(ISNUMBER(SEARCH("DIRECTO",UPPER($B48))),"DIRECTO",IF(ISNUMBER(SEARCH("HIPOT",UPPER($B48))),"HIPOT",IF(ISNUMBER(SEARCH("AHORRO",UPPER($B48))),"AHORRO",UPPER($B48)))),UPPER(Base_Cobranzas!$BB$2:$BB$814))),--ISNUMBER(SEARCH("PENDIENTE",UPPER(TRIM(Base_Cobranzas!$BK$2:$BK$814)))),Base_Cobranzas!$AZ$2:$AZ$814),0) -> 0 | ... Q48: =IFERROR(SUMPRODUCT(--ISNUMBER(SEARCH($B$6,Base_Cobranzas!$A$2:$A$814)),--(Base_Cobranzas!$AQ$2:$AQ$814>=IF(Q$45<3000,DATE(Q$45,1,1),Q$45)),--(Base_Cobranzas!$AQ$2:$AQ$814<IF(Q$45<3000,DATE(Q$45+1,1,1),EDATE(Q$45,1))),--ISNUMBER(SEARCH(IF(ISNUMBER(SEARCH("DIRECTO",UPPER($B48))),"DIRECTO",IF(ISNUMBER(SEARCH("HIPOT",UPPER($B48))),"HIPOT",IF(ISNUMBER(SEARCH("AHORRO",UPPER($B48))),"AHORRO",UPPER($B48)))),UPPER(Base_Cobranzas!$BB$2:$BB$814))),--ISNUMBER(SEARCH("PENDIENTE",UPPER(TRIM(Base_Cobranzas!$BK$2:$BK$814)))),Base_Cobranzas!$AZ$2:$AZ$814),0) -> 0 | R48: =SUM(C48:Q48) -> 5806819
B49: Total | C49: =SUM(C46:C48) -> 1427928.7 | D49: =SUM(D46:D48) -> 663959.66 | E49: =SUM(E46:E48) -> 993664.66 | F49: =SUM(F46:F48) -> 1028514.7 | G49: =SUM(G46:G48) -> 1326709.7 | H49: =SUM(H46:H48) -> 946214.66 | I49: =SUM(I46:I48) -> 736394.66 | J49: =SUM(J46:J48) -> 79279.7 | ... Q49: =SUM(Q46:Q48) -> 38000 | R49: =SUM(C49:Q49) -> 8987397.2 | S49: =IF($H$21=R49,"OK","REVISAR") -> OK
B51: Acumulado | C51: =C49 -> 1427928.7 | D51: =C51+D49 -> 2091888.3 | E51: =D51+E49 -> 3085553 | F51: =E51+F49 -> 4114067.6 | G51: =F51+G49 -> 5440777.3 | H51: =G51+H49 -> 6386992 | I51: =H51+I49 -> 7123386.6 | J51: =I51+J49 -> 7202666.3 | K51: =J51+K49 -> 7327937.2 | ... Q51: =P51+Q49 -> 8987397.2
B55: COBRANZA MOROSA
B57: Tipo de Credito | C57: 45717 | D57: 45748 | E57: 45778 | F57: 45809 | G57: 45839 | H57: 45870 | I57: 45901 | J57: 45931 | K57: 45962 | L57: 45992 | M57: 46023 | N57: 46054 | O57: 46082 | P57: 46113 | Q57: 46143 | R57: 46174 | S57: 46204 | T57: 46235 | U57: Total
B58: Crédito Directo | C58: =IFERROR(SUMPRODUCT(--ISNUMBER(SEARCH($B$6,Base_Cobranzas!$A$2:$A$814)),--(Base_Cobranzas!$AQ$2:$AQ$814>=IF(C$57<3000,DATE(C$57,1,1),C$57)),--(Base_Cobranzas!$AQ$2:$AQ$814<IF(C$57<3000,DATE(C$57+1,1,1),EDATE(C$57,1))),--ISNUMBER(SEARCH(IF(ISNUMBER(SEARCH("DIRECTO",UPPER($B58))),"DIRECTO",IF(ISNUMBER(SEARCH("HIPOT",UPPER($B58))),"HIPOT",IF(ISNUMBER(SEARCH("AHORRO",UPPER($B58))),"AHORRO",UPPER($B58)))),UPPER(Base_Cobranzas!$BB$2:$BB$814))),--ISNUMBER(SEARCH("VENCIDO",UPPER(TRIM(Base_Cobranzas!$BK$2:$BK$814)))),Base_Cobranzas!$AZ$2:$AZ$814),0) -> 1502.5 | D58: =IFERROR(SUMPRODUCT(--ISNUMBER(SEARCH($B$6,Base_Cobranzas!$A$2:$A$814)),--(Base_Cobranzas!$AQ$2:$AQ$814>=IF(D$57<3000,DATE(D$57,1,1),D$57)),--(Base_Cobranzas!$AQ$2:$AQ$814<IF(D$57<3000,DATE(D$57+1,1,1),EDATE(D$57,1))),--ISNUMBER(SEARCH(IF(ISNUMBER(SEARCH("DIRECTO",UPPER($B58))),"DIRECTO",IF(ISNUMBER(SEARCH("HIPOT",UPPER($B58))),"HIPOT",IF(ISNUMBER(SEARCH("AHORRO",UPPER($B58))),"AHORRO",UPPER($B58)))),UPPER(Base_Cobranzas!$BB$2:$BB$814))),--ISNUMBER(SEARCH("VENCIDO",UPPER(TRIM(Base_Cobranzas!$BK$2:$BK$814)))),Base_Cobranzas!$AZ$2:$AZ$814),0) -> 188.42 | E58: =IFERROR(SUMPRODUCT(--ISNUMBER(SEARCH($B$6,Base_Cobranzas!$A$2:$A$814)),--(Base_Cobranzas!$AQ$2:$AQ$814>=IF(E$57<3000,DATE(E$57,1,1),E$57)),--(Base_Cobranzas!$AQ$2:$AQ$814<IF(E$57<3000,DATE(E$57+1,1,1),EDATE(E$57,1))),--ISNUMBER(SEARCH(IF(ISNUMBER(SEARCH("DIRECTO",UPPER($B58))),"DIRECTO",IF(ISNUMBER(SEARCH("HIPOT",UPPER($B58))),"HIPOT",IF(ISNUMBER(SEARCH("AHORRO",UPPER($B58))),"AHORRO",UPPER($B58)))),UPPER(Base_Cobranzas!$BB$2:$BB$814))),--ISNUMBER(SEARCH("VENCIDO",UPPER(TRIM(Base_Cobranzas!$BK$2:$BK$814)))),Base_Cobranzas!$AZ$2:$AZ$814),0) -> 188.46 | F58: =IFERROR(SUMPRODUCT(--ISNUMBER(SEARCH($B$6,Base_Cobranzas!$A$2:$A$814)),--(Base_Cobranzas!$AQ$2:$AQ$814>=IF(F$57<3000,DATE(F$57,1,1),F$57)),--(Base_Cobranzas!$AQ$2:$AQ$814<IF(F$57<3000,DATE(F$57+1,1,1),EDATE(F$57,1))),--ISNUMBER(SEARCH(IF(ISNUMBER(SEARCH("DIRECTO",UPPER($B58))),"DIRECTO",IF(ISNUMBER(SEARCH("HIPOT",UPPER($B58))),"HIPOT",IF(ISNUMBER(SEARCH("AHORRO",UPPER($B58))),"AHORRO",UPPER($B58)))),UPPER(Base_Cobranzas!$BB$2:$BB$814))),--ISNUMBER(SEARCH("VENCIDO",UPPER(TRIM(Base_Cobranzas!$BK$2:$BK$814)))),Base_Cobranzas!$AZ$2:$AZ$814),0) -> 188.6 | G58: =IFERROR(SUMPRODUCT(--ISNUMBER(SEARCH($B$6,Base_Cobranzas!$A$2:$A$814)),--(Base_Cobranzas!$AQ$2:$AQ$814>=IF(G$57<3000,DATE(G$57,1,1),G$57)),--(Base_Cobranzas!$AQ$2:$AQ$814<IF(G$57<3000,DATE(G$57+1,1,1),EDATE(G$57,1))),--ISNUMBER(SEARCH(IF(ISNUMBER(SEARCH("DIRECTO",UPPER($B58))),"DIRECTO",IF(ISNUMBER(SEARCH("HIPOT",UPPER($B58))),"HIPOT",IF(ISNUMBER(SEARCH("AHORRO",UPPER($B58))),"AHORRO",UPPER($B58)))),UPPER(Base_Cobranzas!$BB$2:$BB$814))),--ISNUMBER(SEARCH("VENCIDO",UPPER(TRIM(Base_Cobranzas!$BK$2:$BK$814)))),Base_Cobranzas!$AZ$2:$AZ$814),0) -> 188.64 | H58: =IFERROR(SUMPRODUCT(--ISNUMBER(SEARCH($B$6,Base_Cobranzas!$A$2:$A$814)),--(Base_Cobranzas!$AQ$2:$AQ$814>=IF(H$57<3000,DATE(H$57,1,1),H$57)),--(Base_Cobranzas!$AQ$2:$AQ$814<IF(H$57<3000,DATE(H$57+1,1,1),EDATE(H$57,1))),--ISNUMBER(SEARCH(IF(ISNUMBER(SEARCH("DIRECTO",UPPER($B58))),"DIRECTO",IF(ISNUMBER(SEARCH("HIPOT",UPPER($B58))),"HIPOT",IF(ISNUMBER(SEARCH("AHORRO",UPPER($B58))),"AHORRO",UPPER($B58)))),UPPER(Base_Cobranzas!$BB$2:$BB$814))),--ISNUMBER(SEARCH("VENCIDO",UPPER(TRIM(Base_Cobranzas!$BK$2:$BK$814)))),Base_Cobranzas!$AZ$2:$AZ$814),0) -> 188.68 | I58: =IFERROR(SUMPRODUCT(--ISNUMBER(SEARCH($B$6,Base_Cobranzas!$A$2:$A$814)),--(Base_Cobranzas!$AQ$2:$AQ$814>=IF(I$57<3000,DATE(I$57,1,1),I$57)),--(Base_Cobranzas!$AQ$2:$AQ$814<IF(I$57<3000,DATE(I$57+1,1,1),EDATE(I$57,1))),--ISNUMBER(SEARCH(IF(ISNUMBER(SEARCH("DIRECTO",UPPER($B58))),"DIRECTO",IF(ISNUMBER(SEARCH("HIPOT",UPPER($B58))),"HIPOT",IF(ISNUMBER(SEARCH("AHORRO",UPPER($B58))),"AHORRO",UPPER($B58)))),UPPER(Base_Cobranzas!$BB$2:$BB$814))),--ISNUMBER(SEARCH("VENCIDO",UPPER(TRIM(Base_Cobranzas!$BK$2:$BK$814)))),Base_Cobranzas!$AZ$2:$AZ$814),0) -> 188.75 | J58: =IFERROR(SUMPRODUCT(--ISNUMBER(SEARCH($B$6,Base_Cobranzas!$A$2:$A$814)),--(Base_Cobranzas!$AQ$2:$AQ$814>=IF(J$57<3000,DATE(J$57,1,1),J$57)),--(Base_Cobranzas!$AQ$2:$AQ$814<IF(J$57<3000,DATE(J$57+1,1,1),EDATE(J$57,1))),--ISNUMBER(SEARCH(IF(ISNUMBER(SEARCH("DIRECTO",UPPER($B58))),"DIRECTO",IF(ISNUMBER(SEARCH("HIPOT",UPPER($B58))),"HIPOT",IF(ISNUMBER(SEARCH("AHORRO",UPPER($B58))),"AHORRO",UPPER($B58)))),UPPER(Base_Cobranzas!$BB$2:$BB$814))),--ISNUMBER(SEARCH("VENCIDO",UPPER(TRIM(Base_Cobranzas!$BK$2:$BK$814)))),Base_Cobranzas!$AZ$2:$AZ$814),0) -> 189 | ... T58: =IFERROR(SUMPRODUCT(--ISNUMBER(SEARCH($B$6,Base_Cobranzas!$A$2:$A$814)),--(Base_Cobranzas!$AQ$2:$AQ$814>=IF(T$57<3000,DATE(T$57,1,1),T$57)),--(Base_Cobranzas!$AQ$2:$AQ$814<IF(T$57<3000,DATE(T$57+1,1,1),EDATE(T$57,1))),--ISNUMBER(SEARCH(IF(ISNUMBER(SEARCH("DIRECTO",UPPER($B58))),"DIRECTO",IF(ISNUMBER(SEARCH("HIPOT",UPPER($B58))),"HIPOT",IF(ISNUMBER(SEARCH("AHORRO",UPPER($B58))),"AHORRO",UPPER($B58)))),UPPER(Base_Cobranzas!$BB$2:$BB$814))),--ISNUMBER(SEARCH("VENCIDO",UPPER(TRIM(Base_Cobranzas!$BK$2:$BK$814)))),Base_Cobranzas!$AZ$2:$AZ$814),0) -> 43168 | U58: =SUM(C58:T58) -> 337562.3
B59: Crédito Hipotecario | C59: =IFERROR(SUMPRODUCT(--ISNUMBER(SEARCH($B$6,Base_Cobranzas!$A$2:$A$814)),--(Base_Cobranzas!$AQ$2:$AQ$814>=IF(C$57<3000,DATE(C$57,1,1),C$57)),--(Base_Cobranzas!$AQ$2:$AQ$814<IF(C$57<3000,DATE(C$57+1,1,1),EDATE(C$57,1))),--ISNUMBER(SEARCH(IF(ISNUMBER(SEARCH("DIRECTO",UPPER($B59))),"DIRECTO",IF(ISNUMBER(SEARCH("HIPOT",UPPER($B59))),"HIPOT",IF(ISNUMBER(SEARCH("AHORRO",UPPER($B59))),"AHORRO",UPPER($B59)))),UPPER(Base_Cobranzas!$BB$2:$BB$814))),--ISNUMBER(SEARCH("VENCIDO",UPPER(TRIM(Base_Cobranzas!$BK$2:$BK$814)))),Base_Cobranzas!$AZ$2:$AZ$814),0) -> 0 | D59: =IFERROR(SUMPRODUCT(--ISNUMBER(SEARCH($B$6,Base_Cobranzas!$A$2:$A$814)),--(Base_Cobranzas!$AQ$2:$AQ$814>=IF(D$57<3000,DATE(D$57,1,1),D$57)),--(Base_Cobranzas!$AQ$2:$AQ$814<IF(D$57<3000,DATE(D$57+1,1,1),EDATE(D$57,1))),--ISNUMBER(SEARCH(IF(ISNUMBER(SEARCH("DIRECTO",UPPER($B59))),"DIRECTO",IF(ISNUMBER(SEARCH("HIPOT",UPPER($B59))),"HIPOT",IF(ISNUMBER(SEARCH("AHORRO",UPPER($B59))),"AHORRO",UPPER($B59)))),UPPER(Base_Cobranzas!$BB$2:$BB$814))),--ISNUMBER(SEARCH("VENCIDO",UPPER(TRIM(Base_Cobranzas!$BK$2:$BK$814)))),Base_Cobranzas!$AZ$2:$AZ$814),0) -> 0 | E59: =IFERROR(SUMPRODUCT(--ISNUMBER(SEARCH($B$6,Base_Cobranzas!$A$2:$A$814)),--(Base_Cobranzas!$AQ$2:$AQ$814>=IF(E$57<3000,DATE(E$57,1,1),E$57)),--(Base_Cobranzas!$AQ$2:$AQ$814<IF(E$57<3000,DATE(E$57+1,1,1),EDATE(E$57,1))),--ISNUMBER(SEARCH(IF(ISNUMBER(SEARCH("DIRECTO",UPPER($B59))),"DIRECTO",IF(ISNUMBER(SEARCH("HIPOT",UPPER($B59))),"HIPOT",IF(ISNUMBER(SEARCH("AHORRO",UPPER($B59))),"AHORRO",UPPER($B59)))),UPPER(Base_Cobranzas!$BB$2:$BB$814))),--ISNUMBER(SEARCH("VENCIDO",UPPER(TRIM(Base_Cobranzas!$BK$2:$BK$814)))),Base_Cobranzas!$AZ$2:$AZ$814),0) -> 0 | F59: =IFERROR(SUMPRODUCT(--ISNUMBER(SEARCH($B$6,Base_Cobranzas!$A$2:$A$814)),--(Base_Cobranzas!$AQ$2:$AQ$814>=IF(F$57<3000,DATE(F$57,1,1),F$57)),--(Base_Cobranzas!$AQ$2:$AQ$814<IF(F$57<3000,DATE(F$57+1,1,1),EDATE(F$57,1))),--ISNUMBER(SEARCH(IF(ISNUMBER(SEARCH("DIRECTO",UPPER($B59))),"DIRECTO",IF(ISNUMBER(SEARCH("HIPOT",UPPER($B59))),"HIPOT",IF(ISNUMBER(SEARCH("AHORRO",UPPER($B59))),"AHORRO",UPPER($B59)))),UPPER(Base_Cobranzas!$BB$2:$BB$814))),--ISNUMBER(SEARCH("VENCIDO",UPPER(TRIM(Base_Cobranzas!$BK$2:$BK$814)))),Base_Cobranzas!$AZ$2:$AZ$814),0) -> 0 | G59: =IFERROR(SUMPRODUCT(--ISNUMBER(SEARCH($B$6,Base_Cobranzas!$A$2:$A$814)),--(Base_Cobranzas!$AQ$2:$AQ$814>=IF(G$57<3000,DATE(G$57,1,1),G$57)),--(Base_Cobranzas!$AQ$2:$AQ$814<IF(G$57<3000,DATE(G$57+1,1,1),EDATE(G$57,1))),--ISNUMBER(SEARCH(IF(ISNUMBER(SEARCH("DIRECTO",UPPER($B59))),"DIRECTO",IF(ISNUMBER(SEARCH("HIPOT",UPPER($B59))),"HIPOT",IF(ISNUMBER(SEARCH("AHORRO",UPPER($B59))),"AHORRO",UPPER($B59)))),UPPER(Base_Cobranzas!$BB$2:$BB$814))),--ISNUMBER(SEARCH("VENCIDO",UPPER(TRIM(Base_Cobranzas!$BK$2:$BK$814)))),Base_Cobranzas!$AZ$2:$AZ$814),0) -> 0 | H59: =IFERROR(SUMPRODUCT(--ISNUMBER(SEARCH($B$6,Base_Cobranzas!$A$2:$A$814)),--(Base_Cobranzas!$AQ$2:$AQ$814>=IF(H$57<3000,DATE(H$57,1,1),H$57)),--(Base_Cobranzas!$AQ$2:$AQ$814<IF(H$57<3000,DATE(H$57+1,1,1),EDATE(H$57,1))),--ISNUMBER(SEARCH(IF(ISNUMBER(SEARCH("DIRECTO",UPPER($B59))),"DIRECTO",IF(ISNUMBER(SEARCH("HIPOT",UPPER($B59))),"HIPOT",IF(ISNUMBER(SEARCH("AHORRO",UPPER($B59))),"AHORRO",UPPER($B59)))),UPPER(Base_Cobranzas!$BB$2:$BB$814))),--ISNUMBER(SEARCH("VENCIDO",UPPER(TRIM(Base_Cobranzas!$BK$2:$BK$814)))),Base_Cobranzas!$AZ$2:$AZ$814),0) -> 0 | I59: =IFERROR(SUMPRODUCT(--ISNUMBER(SEARCH($B$6,Base_Cobranzas!$A$2:$A$814)),--(Base_Cobranzas!$AQ$2:$AQ$814>=IF(I$57<3000,DATE(I$57,1,1),I$57)),--(Base_Cobranzas!$AQ$2:$AQ$814<IF(I$57<3000,DATE(I$57+1,1,1),EDATE(I$57,1))),--ISNUMBER(SEARCH(IF(ISNUMBER(SEARCH("DIRECTO",UPPER($B59))),"DIRECTO",IF(ISNUMBER(SEARCH("HIPOT",UPPER($B59))),"HIPOT",IF(ISNUMBER(SEARCH("AHORRO",UPPER($B59))),"AHORRO",UPPER($B59)))),UPPER(Base_Cobranzas!$BB$2:$BB$814))),--ISNUMBER(SEARCH("VENCIDO",UPPER(TRIM(Base_Cobranzas!$BK$2:$BK$814)))),Base_Cobranzas!$AZ$2:$AZ$814),0) -> 0 | J59: =IFERROR(SUMPRODUCT(--ISNUMBER(SEARCH($B$6,Base_Cobranzas!$A$2:$A$814)),--(Base_Cobranzas!$AQ$2:$AQ$814>=IF(J$57<3000,DATE(J$57,1,1),J$57)),--(Base_Cobranzas!$AQ$2:$AQ$814<IF(J$57<3000,DATE(J$57+1,1,1),EDATE(J$57,1))),--ISNUMBER(SEARCH(IF(ISNUMBER(SEARCH("DIRECTO",UPPER($B59))),"DIRECTO",IF(ISNUMBER(SEARCH("HIPOT",UPPER($B59))),"HIPOT",IF(ISNUMBER(SEARCH("AHORRO",UPPER($B59))),"AHORRO",UPPER($B59)))),UPPER(Base_Cobranzas!$BB$2:$BB$814))),--ISNUMBER(SEARCH("VENCIDO",UPPER(TRIM(Base_Cobranzas!$BK$2:$BK$814)))),Base_Cobranzas!$AZ$2:$AZ$814),0) -> 0 | ... T59: =IFERROR(SUMPRODUCT(--ISNUMBER(SEARCH($B$6,Base_Cobranzas!$A$2:$A$814)),--(Base_Cobranzas!$AQ$2:$AQ$814>=IF(T$57<3000,DATE(T$57,1,1),T$57)),--(Base_Cobranzas!$AQ$2:$AQ$814<IF(T$57<3000,DATE(T$57+1,1,1),EDATE(T$57,1))),--ISNUMBER(SEARCH(IF(ISNUMBER(SEARCH("DIRECTO",UPPER($B59))),"DIRECTO",IF(ISNUMBER(SEARCH("HIPOT",UPPER($B59))),"HIPOT",IF(ISNUMBER(SEARCH("AHORRO",UPPER($B59))),"AHORRO",UPPER($B59)))),UPPER(Base_Cobranzas!$BB$2:$BB$814))),--ISNUMBER(SEARCH("VENCIDO",UPPER(TRIM(Base_Cobranzas!$BK$2:$BK$814)))),Base_Cobranzas!$AZ$2:$AZ$814),0) -> 0 | U59: =SUM(C59:T59) -> 2567980
B60: Ahorro | C60: =IFERROR(SUMPRODUCT(--ISNUMBER(SEARCH($B$6,Base_Cobranzas!$A$2:$A$814)),--(Base_Cobranzas!$AQ$2:$AQ$814>=IF(C$57<3000,DATE(C$57,1,1),C$57)),--(Base_Cobranzas!$AQ$2:$AQ$814<IF(C$57<3000,DATE(C$57+1,1,1),EDATE(C$57,1))),--ISNUMBER(SEARCH(IF(ISNUMBER(SEARCH("DIRECTO",UPPER($B60))),"DIRECTO",IF(ISNUMBER(SEARCH("HIPOT",UPPER($B60))),"HIPOT",IF(ISNUMBER(SEARCH("AHORRO",UPPER($B60))),"AHORRO",UPPER($B60)))),UPPER(Base_Cobranzas!$BB$2:$BB$814))),--ISNUMBER(SEARCH("VENCIDO",UPPER(TRIM(Base_Cobranzas!$BK$2:$BK$814)))),Base_Cobranzas!$AZ$2:$AZ$814),0) -> 0 | D60: =IFERROR(SUMPRODUCT(--ISNUMBER(SEARCH($B$6,Base_Cobranzas!$A$2:$A$814)),--(Base_Cobranzas!$AQ$2:$AQ$814>=IF(D$57<3000,DATE(D$57,1,1),D$57)),--(Base_Cobranzas!$AQ$2:$AQ$814<IF(D$57<3000,DATE(D$57+1,1,1),EDATE(D$57,1))),--ISNUMBER(SEARCH(IF(ISNUMBER(SEARCH("DIRECTO",UPPER($B60))),"DIRECTO",IF(ISNUMBER(SEARCH("HIPOT",UPPER($B60))),"HIPOT",IF(ISNUMBER(SEARCH("AHORRO",UPPER($B60))),"AHORRO",UPPER($B60)))),UPPER(Base_Cobranzas!$BB$2:$BB$814))),--ISNUMBER(SEARCH("VENCIDO",UPPER(TRIM(Base_Cobranzas!$BK$2:$BK$814)))),Base_Cobranzas!$AZ$2:$AZ$814),0) -> 0 | E60: =IFERROR(SUMPRODUCT(--ISNUMBER(SEARCH($B$6,Base_Cobranzas!$A$2:$A$814)),--(Base_Cobranzas!$AQ$2:$AQ$814>=IF(E$57<3000,DATE(E$57,1,1),E$57)),--(Base_Cobranzas!$AQ$2:$AQ$814<IF(E$57<3000,DATE(E$57+1,1,1),EDATE(E$57,1))),--ISNUMBER(SEARCH(IF(ISNUMBER(SEARCH("DIRECTO",UPPER($B60))),"DIRECTO",IF(ISNUMBER(SEARCH("HIPOT",UPPER($B60))),"HIPOT",IF(ISNUMBER(SEARCH("AHORRO",UPPER($B60))),"AHORRO",UPPER($B60)))),UPPER(Base_Cobranzas!$BB$2:$BB$814))),--ISNUMBER(SEARCH("VENCIDO",UPPER(TRIM(Base_Cobranzas!$BK$2:$BK$814)))),Base_Cobranzas!$AZ$2:$AZ$814),0) -> 0 | F60: =IFERROR(SUMPRODUCT(--ISNUMBER(SEARCH($B$6,Base_Cobranzas!$A$2:$A$814)),--(Base_Cobranzas!$AQ$2:$AQ$814>=IF(F$57<3000,DATE(F$57,1,1),F$57)),--(Base_Cobranzas!$AQ$2:$AQ$814<IF(F$57<3000,DATE(F$57+1,1,1),EDATE(F$57,1))),--ISNUMBER(SEARCH(IF(ISNUMBER(SEARCH("DIRECTO",UPPER($B60))),"DIRECTO",IF(ISNUMBER(SEARCH("HIPOT",UPPER($B60))),"HIPOT",IF(ISNUMBER(SEARCH("AHORRO",UPPER($B60))),"AHORRO",UPPER($B60)))),UPPER(Base_Cobranzas!$BB$2:$BB$814))),--ISNUMBER(SEARCH("VENCIDO",UPPER(TRIM(Base_Cobranzas!$BK$2:$BK$814)))),Base_Cobranzas!$AZ$2:$AZ$814),0) -> 0 | G60: =IFERROR(SUMPRODUCT(--ISNUMBER(SEARCH($B$6,Base_Cobranzas!$A$2:$A$814)),--(Base_Cobranzas!$AQ$2:$AQ$814>=IF(G$57<3000,DATE(G$57,1,1),G$57)),--(Base_Cobranzas!$AQ$2:$AQ$814<IF(G$57<3000,DATE(G$57+1,1,1),EDATE(G$57,1))),--ISNUMBER(SEARCH(IF(ISNUMBER(SEARCH("DIRECTO",UPPER($B60))),"DIRECTO",IF(ISNUMBER(SEARCH("HIPOT",UPPER($B60))),"HIPOT",IF(ISNUMBER(SEARCH("AHORRO",UPPER($B60))),"AHORRO",UPPER($B60)))),UPPER(Base_Cobranzas!$BB$2:$BB$814))),--ISNUMBER(SEARCH("VENCIDO",UPPER(TRIM(Base_Cobranzas!$BK$2:$BK$814)))),Base_Cobranzas!$AZ$2:$AZ$814),0) -> 0 | H60: =IFERROR(SUMPRODUCT(--ISNUMBER(SEARCH($B$6,Base_Cobranzas!$A$2:$A$814)),--(Base_Cobranzas!$AQ$2:$AQ$814>=IF(H$57<3000,DATE(H$57,1,1),H$57)),--(Base_Cobranzas!$AQ$2:$AQ$814<IF(H$57<3000,DATE(H$57+1,1,1),EDATE(H$57,1))),--ISNUMBER(SEARCH(IF(ISNUMBER(SEARCH("DIRECTO",UPPER($B60))),"DIRECTO",IF(ISNUMBER(SEARCH("HIPOT",UPPER($B60))),"HIPOT",IF(ISNUMBER(SEARCH("AHORRO",UPPER($B60))),"AHORRO",UPPER($B60)))),UPPER(Base_Cobranzas!$BB$2:$BB$814))),--ISNUMBER(SEARCH("VENCIDO",UPPER(TRIM(Base_Cobranzas!$BK$2:$BK$814)))),Base_Cobranzas!$AZ$2:$AZ$814),0) -> 0 | I60: =IFERROR(SUMPRODUCT(--ISNUMBER(SEARCH($B$6,Base_Cobranzas!$A$2:$A$814)),--(Base_Cobranzas!$AQ$2:$AQ$814>=IF(I$57<3000,DATE(I$57,1,1),I$57)),--(Base_Cobranzas!$AQ$2:$AQ$814<IF(I$57<3000,DATE(I$57+1,1,1),EDATE(I$57,1))),--ISNUMBER(SEARCH(IF(ISNUMBER(SEARCH("DIRECTO",UPPER($B60))),"DIRECTO",IF(ISNUMBER(SEARCH("HIPOT",UPPER($B60))),"HIPOT",IF(ISNUMBER(SEARCH("AHORRO",UPPER($B60))),"AHORRO",UPPER($B60)))),UPPER(Base_Cobranzas!$BB$2:$BB$814))),--ISNUMBER(SEARCH("VENCIDO",UPPER(TRIM(Base_Cobranzas!$BK$2:$BK$814)))),Base_Cobranzas!$AZ$2:$AZ$814),0) -> 0 | J60: =IFERROR(SUMPRODUCT(--ISNUMBER(SEARCH($B$6,Base_Cobranzas!$A$2:$A$814)),--(Base_Cobranzas!$AQ$2:$AQ$814>=IF(J$57<3000,DATE(J$57,1,1),J$57)),--(Base_Cobranzas!$AQ$2:$AQ$814<IF(J$57<3000,DATE(J$57+1,1,1),EDATE(J$57,1))),--ISNUMBER(SEARCH(IF(ISNUMBER(SEARCH("DIRECTO",UPPER($B60))),"DIRECTO",IF(ISNUMBER(SEARCH("HIPOT",UPPER($B60))),"HIPOT",IF(ISNUMBER(SEARCH("AHORRO",UPPER($B60))),"AHORRO",UPPER($B60)))),UPPER(Base_Cobranzas!$BB$2:$BB$814))),--ISNUMBER(SEARCH("VENCIDO",UPPER(TRIM(Base_Cobranzas!$BK$2:$BK$814)))),Base_Cobranzas!$AZ$2:$AZ$814),0) -> 0 | ... T60: =IFERROR(SUMPRODUCT(--ISNUMBER(SEARCH($B$6,Base_Cobranzas!$A$2:$A$814)),--(Base_Cobranzas!$AQ$2:$AQ$814>=IF(T$57<3000,DATE(T$57,1,1),T$57)),--(Base_Cobranzas!$AQ$2:$AQ$814<IF(T$57<3000,DATE(T$57+1,1,1),EDATE(T$57,1))),--ISNUMBER(SEARCH(IF(ISNUMBER(SEARCH("DIRECTO",UPPER($B60))),"DIRECTO",IF(ISNUMBER(SEARCH("HIPOT",UPPER($B60))),"HIPOT",IF(ISNUMBER(SEARCH("AHORRO",UPPER($B60))),"AHORRO",UPPER($B60)))),UPPER(Base_Cobranzas!$BB$2:$BB$814))),--ISNUMBER(SEARCH("VENCIDO",UPPER(TRIM(Base_Cobranzas!$BK$2:$BK$814)))),Base_Cobranzas!$AZ$2:$AZ$814),0) -> 435800 | U60: =SUM(C60:T60) -> 4119035
B61: Total | C61: =SUM(C58:C60) -> 1502.5 | D61: =SUM(D58:D60) -> 188.42 | E61: =SUM(E58:E60) -> 188.46 | F61: =SUM(F58:F60) -> 188.6 | G61: =SUM(G58:G60) -> 188.64 | H61: =SUM(H58:H60) -> 188.68 | I61: =SUM(I58:I60) -> 188.75 | J61: =SUM(J58:J60) -> 189 | ... T61: =SUM(T58:T60) -> 478968 | U61: =SUM(C61:T61) -> 7024577.3 | V61: =IF($I$21=U61,"OK","REVISAR") -> OK
B63: Acumulado | C63: =C61 -> 1502.5 | D63: =C63+D61 -> 1690.92 | E63: =D63+E61 -> 1879.38 | F63: =E63+F61 -> 2067.98 | G63: =F63+G61 -> 2256.62 | H63: =G63+H61 -> 2445.3 | I63: =H63+I61 -> 2634.05 | J63: =I63+J61 -> 2823.05 | K63: =J63+K61 -> 24164.3 | ... T63: =S63+T61 -> 7024577.3

Sheet Venecia
C5: REPORTE DE COBRANZAS
B6: Venecia
C8: Vendido | F8: Cobranzas
C9: Monto | D9: Unidades | F9: Avance | G9: Cobrado | H9: Por Cobrar | I9: Vencido | J9: Tasa de Morosidad | K9: Clientes Morosos (unidades) | L9: Dias de Atraso (Promedio)
B11: Departamentos | C11: 8411400 | D11: 24 | F11: =IF(C11=0,0,G11/C11) -> 0.52823311 | G11: =SUM(G12:G13) -> 4443180 | H11: =SUM(H12:H13) -> 3268046.7 | I11: =SUM(I12:I13) -> 700173.34 | J11: =IF(C11=0,0,I11/C11) -> 0.083240999 | K11: 6 | L11: 47
